Workbook
Name bb: LANÇAMENTO[[#Headers],[OBRA]]
Name bb: LANÇAMENTO[[#Headers],[OBRA]]
Name FORNECEDORES: FORNECEDOR[]
Name FORNECEDORES: FORNECEDOR[]
Name FORNECEDORES: FORNECEDOR[]
Name FORNECEDORES: FORNECEDOR[]
Name FORNECEDORES: FORNECEDOR[]
Name FORNECEDORES: FORNECEDOR[]
Name OBRA: LANÇAMENTO[[#Headers],[OBRA]]
Name OBRA: LANÇAMENTO[[#Headers],[OBRA]]
Name OBRA: LANÇAMENTO[[#Headers],[OBRA]]
Name OBRA: LANÇAMENTO[[#Headers],[OBRA]]
Name OBRA: LANÇAMENTO[[#Headers],[OBRA]]
Name OBRA: LANÇAMENTO[[#Headers],[OBRA]]
Name OBRA: LANÇAMENTO[[#Headers],[OBRA]]

Sheet LANÇAMENTO
E1: =TODAY() -> 46129
A2: DATA SOLICITAÇÃO | B2: OBRA | C2: FATURAMENTO | D2: ITEM | E2: MATERIAL SOLICITADO | F2: QTDADE | G2: UNID | H2: PEDIDO | I2: FORNECEDOR | J2: DESCRIÇÃO MATERIAL | K2: VALOR UNITARIO | L2: VALOR TOTAL | M2: DATA PEDIDO | N2: MÊS/ANO PEDIDO | O2: CONDIÇÃO PAGAMENTO | P2: FORMA DE PAGAMENTO | Q2: RETIRA OU ENTREGA | R2: PRAZO | S2: PREVISÃO ENTREGA OBRA | T2: RESTA | U2: OBRA COM MATERIAL | V2: OBSERVAÇÃO
A3: 45795 | B3: SYLVIA DE MELLO | C3: =VLOOKUP(LANÇAMENTO[[#This Row],[OBRA]],OBRAS[],2,FALSE) -> B&B | D3: ELETRICA | E3: PLACA 4X4 CEGA BR SIENA | F3: 2 | G3: UNID. | H3: 1846 | I3: AREA ELETRICOS | J3: PLACA 4X4 CEGA BR SIENA | K3: 5.5 | L3: =LANÇAMENTO[[#This Row],[VALOR UNITARIO]]*LANÇAMENTO[[#This Row],[QTDADE]] -> 11 | M3: 45887 | N3: =TEXT(LANÇAMENTO[[#This Row],[DATA PEDIDO]],"MMM")&"-"&TEXT(M3,"AAAA") -> ago-2025 | O3: 30/60/90 | P3: BOLETO | Q3: RETIRA | R3: 0 | S3: =IF(LANÇAMENTO[[#This Row],[DATA PEDIDO]]="","",LANÇAMENTO[[#This Row],[DATA PEDIDO]]+LANÇAMENTO[[#This Row],[PRAZO]]) -> 45887 | T3: =IF(LANÇAMENTO[[#This Row],[OBRA COM MATERIAL]]="OK","ENTREGUE",IF(LANÇAMENTO[[#This Row],[PRAZO]]="","",LANÇAMENTO[[#This Row],[PREVISÃO ENTREGA OBRA]]-$E$1)) -> ENTREGUE | U3: OK
A4: 45795 | B4: SYLVIA DE MELLO | C4: =VLOOKUP(LANÇAMENTO[[#This Row],[OBRA]],OBRAS[],2,FALSE) -> B&B | D4: ELETRICA | E4: PLACA 4X4 2MOD BR SIENA | F4: 1 | G4: UNID. | H4: 1846 | I4: AREA ELETRICOS | J4: PLACA 4X4 2MOD BR SIENA | K4: 5.5 | L4: =LANÇAMENTO[[#This Row],[VALOR UNITARIO]]*LANÇAMENTO[[#This Row],[QTDADE]] -> 5.5 | M4: 45887 | N4: =TEXT(LANÇAMENTO[[#This Row],[DATA PEDIDO]],"MMM")&"-"&TEXT(M4,"AAAA") -> ago-2025 | O4: 30/60/90 | P4: BOLETO | Q4: RETIRA | R4: 0 | S4: =IF(LANÇAMENTO[[#This Row],[DATA PEDIDO]]="","",LANÇAMENTO[[#This Row],[DATA PEDIDO]]+LANÇAMENTO[[#This Row],[PRAZO]]) -> 45887 | T4: =IF(LANÇAMENTO[[#This Row],[OBRA COM MATERIAL]]="OK","ENTREGUE",IF(LANÇAMENTO[[#This Row],[PRAZO]]="","",LANÇAMENTO[[#This Row],[PREVISÃO ENTREGA OBRA]]-$E$1)) -> ENTREGUE | U4: OK
A5: 45795 | B5: SYLVIA DE MELLO | C5: =VLOOKUP(LANÇAMENTO[[#This Row],[OBRA]],OBRAS[],2,FALSE) -> B&B | D5: ELETRICA | E5: MODULO INT BIPOLAR SIMP 10A BR SIENA | F5: 1 | G5: UNID. | H5: 1846 | I5: AREA ELETRICOS | J5: MODULO INT BIPOLAR SIMP 10A BR SIENA | K5: 24.9 | L5: =LANÇAMENTO[[#This Row],[VALOR UNITARIO]]*LANÇAMENTO[[#This Row],[QTDADE]] -> 24.9 | M5: 45887 | N5: =TEXT(LANÇAMENTO[[#This Row],[DATA PEDIDO]],"MMM")&"-"&TEXT(M5,"AAAA") -> ago-2025 | O5: 30/60/90 | P5: BOLETO | Q5: RETIRA | R5: 0 | S5: =IF(LANÇAMENTO[[#This Row],[DATA PEDIDO]]="","",LANÇAMENTO[[#This Row],[DATA PEDIDO]]+LANÇAMENTO[[#This Row],[PRAZO]]) -> 45887 | T5: =IF(LANÇAMENTO[[#This Row],[OBRA COM MATERIAL]]="OK","ENTREGUE",IF(LANÇAMENTO[[#This Row],[PRAZO]]="","",LANÇAMENTO[[#This Row],[PREVISÃO ENTREGA OBRA]]-$E$1)) -> ENTREGUE | U5: OK
A6: 45795 | B6: SYLVIA DE MELLO | C6: =VLOOKUP(LANÇAMENTO[[#This Row],[OBRA]],OBRAS[],2,FALSE) -> B&B | D6: ELETRICA | E6: MODULO CEGO BR SIENA | F6: 1 | G6: UNID. | H6: 1846 | I6: AREA ELETRICOS | J6: MODULO CEGO BR SIENA | K6: 1.1 | L6: =LANÇAMENTO[[#This Row],[VALOR UNITARIO]]*LANÇAMENTO[[#This Row],[QTDADE]] -> 1.1 | M6: 45887 | N6: =TEXT(LANÇAMENTO[[#This Row],[DATA PEDIDO]],"MMM")&"-"&TEXT(M6,"AAAA") -> ago-2025 | O6: 30/60/90 | P6: BOLETO | Q6: RETIRA | R6: 0 | S6: =IF(LANÇAMENTO[[#This Row],[DATA PEDIDO]]="","",LANÇAMENTO[[#This Row],[DATA PEDIDO]]+LANÇAMENTO[[#This Row],[PRAZO]]) -> 45887 | T6: =IF(LANÇAMENTO[[#This Row],[OBRA COM MATERIAL]]="OK","ENTREGUE",IF(LANÇAMENTO[[#This Row],[PRAZO]]="","",LANÇAMENTO[[#This Row],[PREVISÃO ENTREGA OBRA]]-$E$1)) -> ENTREGUE | U6: OK
A7: 45795 | B7: SYLVIA DE MELLO | C7: =VLOOKUP(LANÇAMENTO[[#This Row],[OBRA]],OBRAS[],2,FALSE) -> B&B | D7: ELETRICA | E7: PLACA 4X2 1MOD HORIZONTA BR SIENA | F7: 1 | G7: UNID. | H7: 1846 | I7: AREA ELETRICOS | J7: PLACA 4X2 1MOD HORIZONTA BR SIENA | K7: 2.8 | L7: =LANÇAMENTO[[#This Row],[VALOR UNITARIO]]*LANÇAMENTO[[#This Row],[QTDADE]] -> 2.8 | M7: 45887 | N7: =TEXT(LANÇAMENTO[[#This Row],[DATA PEDIDO]],"MMM")&"-"&TEXT(M7,"AAAA") -> ago-2025 | O7: 30/60/90 | P7: BOLETO | Q7: RETIRA | R7: 0 | S7: =IF(LANÇAMENTO[[#This Row],[DATA PEDIDO]]="","",LANÇAMENTO[[#This Row],[DATA PEDIDO]]+LANÇAMENTO[[#This Row],[PRAZO]]) -> 45887 | T7: =IF(LANÇAMENTO[[#This Row],[OBRA COM MATERIAL]]="OK","ENTREGUE",IF(LANÇAMENTO[[#This Row],[PRAZO]]="","",LANÇAMENTO[[#This Row],[PREVISÃO ENTREGA OBRA]]-$E$1)) -> ENTREGUE | U7: OK
A8: 45795 | B8: SYLVIA DE MELLO | C8: =VLOOKUP(LANÇAMENTO[[#This Row],[OBRA]],OBRAS[],2,FALSE) -> B&B | D8: ELETRICA | E8: MODULO INT BIPOLAR SIMP 10A BR SIENA | F8: 1 | G8: UNID. | H8: 1846 | I8: AREA ELETRICOS | J8: MODULO INT BIPOLAR SIMP 10A BR SIENA | K8: 26 | L8: =LANÇAMENTO[[#This Row],[VALOR UNITARIO]]*LANÇAMENTO[[#This Row],[QTDADE]] -> 26 | M8: 45887 | N8: =TEXT(LANÇAMENTO[[#This Row],[DATA PEDIDO]],"MMM")&"-"&TEXT(M8,"AAAA") -> ago-2025 | O8: 30/60/90 | P8: BOLETO | Q8: RETIRA | R8: 0 | S8: =IF(LANÇAMENTO[[#This Row],[DATA PEDIDO]]="","",LANÇAMENTO[[#This Row],[DATA PEDIDO]]+LANÇAMENTO[[#This Row],[PRAZO]]) -> 45887 | T8: =IF(LANÇAMENTO[[#This Row],[OBRA COM MATERIAL]]="OK","ENTREGUE",IF(LANÇAMENTO[[#This Row],[PRAZO]]="","",LANÇAMENTO[[#This Row],[PREVISÃO ENTREGA OBRA]]-$E$1)) -> ENTREGUE | U8: OK
A9: 45795 | B9: SYLVIA DE MELLO | C9: =VLOOKUP(LANÇAMENTO[[#This Row],[OBRA]],OBRAS[],2,FALSE) -> B&B | D9: ELETRICA | E9: PLACA 4X2 CEGA BR SIENA | F9: 1 | G9: UNID. | H9: 1846 | I9: AREA ELETRICOS | J9: PLACA 4X2 CEGA BR SIENA | K9: 2.8 | L9: =LANÇAMENTO[[#This Row],[VALOR UNITARIO]]*LANÇAMENTO[[#This Row],[QTDADE]] -> 2.8 | M9: 45887 | N9: =TEXT(LANÇAMENTO[[#This Row],[DATA PEDIDO]],"MMM")&"-"&TEXT(M9,"AAAA") -> ago-2025 | O9: 30/60/90 | P9: BOLETO | Q9: RETIRA | R9: 0 | S9: =IF(LANÇAMENTO[[#This Row],[DATA PEDIDO]]="","",LANÇAMENTO[[#This Row],[DATA PEDIDO]]+LANÇAMENTO[[#This Row],[PRAZO]]) -> 45887 | T9: =IF(LANÇAMENTO[[#This Row],[OBRA COM MATERIAL]]="OK","ENTREGUE",IF(LANÇAMENTO[[#This Row],[PRAZO]]="","",LANÇAMENTO[[#This Row],[PREVISÃO ENTREGA OBRA]]-$E$1)) -> ENTREGUE | U9: OK
A10: 45795 | B10: SYLVIA DE MELLO | C10: =VLOOKUP(LANÇAMENTO[[#This Row],[OBRA]],OBRAS[],2,FALSE) -> B&B | D10: ELETRICA | E10: PLACA 4X2 SAIDA DE FIO BR SIENA | F10: 1 | G10: UNID. | H10: 1846 | I10: AREA ELETRICOS | J10: PLACA 4X2 SAIDA DE FIO BR SIENA | K10: 2.8 | L10: =LANÇAMENTO[[#This Row],[VALOR UNITARIO]]*LANÇAMENTO[[#This Row],[QTDADE]] -> 2.8 | M10: 45887 | N10: =TEXT(LANÇAMENTO[[#This Row],[DATA PEDIDO]],"MMM")&"-"&TEXT(M10,"AAAA") -> ago-2025 | O10: 30/60/90 | P10: BOLETO | Q10: RETIRA | R10: 0 | S10: =IF(LANÇAMENTO[[#This Row],[DATA PEDIDO]]="","",LANÇAMENTO[[#This Row],[DATA PEDIDO]]+LANÇAMENTO[[#This Row],[PRAZO]]) -> 45887 | T10: =IF(LANÇAMENTO[[#This Row],[OBRA COM MATERIAL]]="OK","ENTREGUE",IF(LANÇAMENTO[[#This Row],[PRAZO]]="","",LANÇAMENTO[[#This Row],[PREVISÃO ENTREGA OBRA]]-$E$1)) -> ENTREGUE | U10: OK
A11: 45795 | B11: SYLVIA DE MELLO | C11: =VLOOKUP(LANÇAMENTO[[#This Row],[OBRA]],OBRAS[],2,FALSE) -> B&B | D11: ELETRICA | E11: PARAFUSO SEXTAVADO 3/16X60MM P/BUCHA S08 | F11: 500 | G11: UNID. | H11: 1846 | I11: AREA ELETRICOS | J11: PARAFUSO SEXTAVADO 3/16X60MM P/BUCHA S08 | K11: 0.1 | L11: =LANÇAMENTO[[#This Row],[VALOR UNITARIO]]*LANÇAMENTO[[#This Row],[QTDADE]] -> 50 | M11: 45887 | N11: =TEXT(LANÇAMENTO[[#This Row],[DATA PEDIDO]],"MMM")&"-"&TEXT(M11,"AAAA") -> ago-2025 | O11: 30/60/90 | P11: BOLETO | Q11: RETIRA | R11: 0 | S11: =IF(LANÇAMENTO[[#This Row],[DATA PEDIDO]]="","",LANÇAMENTO[[#This Row],[DATA PEDIDO]]+LANÇAMENTO[[#This Row],[PRAZO]]) -> 45887 | T11: =IF(LANÇAMENTO[[#This Row],[OBRA COM MATERIAL]]="OK","ENTREGUE",IF(LANÇAMENTO[[#This Row],[PRAZO]]="","",LANÇAMENTO[[#This Row],[PREVISÃO ENTREGA OBRA]]-$E$1)) -> ENTREGUE | U11: OK
A12: 45795 | B12: SYLVIA DE MELLO | C12: =VLOOKUP(LANÇAMENTO[[#This Row],[OBRA]],OBRAS[],2,FALSE) -> B&B | D12: ELETRICA | E12: BUCHA FUS-8 P/ PARAFUSO PVC BLOCO | F12: 500 | G12: UNID. | H12: 1846 | I12: AREA ELETRICOS | J12: BUCHA FUS-8 P/ PARAFUSO PVC BLOCO | K12: 0.2 | L12: =LANÇAMENTO[[#This Row],[VALOR UNITARIO]]*LANÇAMENTO[[#This Row],[QTDADE]] -> 100 | M12: 45887 | N12: =TEXT(LANÇAMENTO[[#This Row],[DATA PEDIDO]],"MMM")&"-"&TEXT(M12,"AAAA") -> ago-2025 | O12: 30/60/90 | P12: BOLETO | Q12: RETIRA | R12: 0 | S12: =IF(LANÇAMENTO[[#This Row],[DATA PEDIDO]]="","",LANÇAMENTO[[#This Row],[DATA PEDIDO]]+LANÇAMENTO[[#This Row],[PRAZO]]) -> 45887 | T12: =IF(LANÇAMENTO[[#This Row],[OBRA COM MATERIAL]]="OK","ENTREGUE",IF(LANÇAMENTO[[#This Row],[PRAZO]]="","",LANÇAMENTO[[#This Row],[PREVISÃO ENTREGA OBRA]]-$E$1)) -> ENTREGUE | U12: OK
A13: 45795 | B13: SYLVIA DE MELLO | C13: =VLOOKUP(LANÇAMENTO[[#This Row],[OBRA]],OBRAS[],2,FALSE) -> B&B | D13: ELETRICA | E13: PARAFUSO SEXTAVADO AUTO BROCANTE 1/4X1 | F13: 200 | G13: UNID. | H13: 1846 | I13: AREA ELETRICOS | J13: PARAFUSO SEXTAVADO AUTO BROCANTE 1/4X1 | K13: 0.7 | L13: =LANÇAMENTO[[#This Row],[VALOR UNITARIO]]*LANÇAMENTO[[#This Row],[QTDADE]] -> 140 | M13: 45887 | N13: =TEXT(LANÇAMENTO[[#This Row],[DATA PEDIDO]],"MMM")&"-"&TEXT(M13,"AAAA") -> ago-2025 | O13: 30/60/90 | P13: BOLETO | Q13: RETIRA | R13: 0 | S13: =IF(LANÇAMENTO[[#This Row],[DATA PEDIDO]]="","",LANÇAMENTO[[#This Row],[DATA PEDIDO]]+LANÇAMENTO[[#This Row],[PRAZO]]) -> 45887 | T13: =IF(LANÇAMENTO[[#This Row],[OBRA COM MATERIAL]]="OK","ENTREGUE",IF(LANÇAMENTO[[#This Row],[PRAZO]]="","",LANÇAMENTO[[#This Row],[PREVISÃO ENTREGA OBRA]]-$E$1)) -> ENTREGUE | U13: OK
A14: 45795 | B14: SYLVIA DE MELLO | C14: =VLOOKUP(LANÇAMENTO[[#This Row],[OBRA]],OBRAS[],2,FALSE) -> B&B | D14: ELETRICA | E14: CABO FLEX750V 2,5MM2 PT | F14: 14 | G14: ROLO | H14: 1846 | I14: AREA ELETRICOS | J14: CABO FLEX750V 2,5MM2 PT | K14: 192 | L14: =LANÇAMENTO[[#This Row],[VALOR UNITARIO]]*LANÇAMENTO[[#This Row],[QTDADE]] -> 2688 | M14: 45887 | N14: =TEXT(LANÇAMENTO[[#This Row],[DATA PEDIDO]],"MMM")&"-"&TEXT(M14,"AAAA") -> ago-2025 | O14: 30/60/90 | P14: BOLETO | Q14: RETIRA | R14: 0 | S14: =IF(LANÇAMENTO[[#This Row],[DATA PEDIDO]]="","",LANÇAMENTO[[#This Row],[DATA PEDIDO]]+LANÇAMENTO[[#This Row],[PRAZO]]) -> 45887 | T14: =IF(LANÇAMENTO[[#This Row],[OBRA COM MATERIAL]]="OK","ENTREGUE",IF(LANÇAMENTO[[#This Row],[PRAZO]]="","",LANÇAMENTO[[#This Row],[PREVISÃO ENTREGA OBRA]]-$E$1)) -> ENTREGUE | U14: OK
... A31: 45874 | B31: DAGOBERTO SALLES FILHO | C31: =VLOOKUP(LANÇAMENTO[[#This Row],[OBRA]],OBRAS[],2,FALSE) -> INTERIORANA | D31: OUTROS | E31: 64 pçs c/ 1.150mm(Sup) x 1.000mm(Inf) - dir/esq | F31: 73.6 | G31: M | H31: 1774 | I31: BIG TELHAS | J31: 64 pçs c/ 1.150mm(Sup) x 1.000mm(Inf) - dir/esq | K31: 118.9 | L31: =LANÇAMENTO[[#This Row],[VALOR UNITARIO]]*LANÇAMENTO[[#This Row],[QTDADE]] -> 8751.04 | M31: 45874 | N31: =TEXT(LANÇAMENTO[[#This Row],[DATA PEDIDO]],"MMM")&"-"&TEXT(M31,"AAAA") -> ago-2025 | O31: 30/60/90 | P31: BOLETO | Q31: ENTREGA | R31: 10 | S31: =IF(LANÇAMENTO[[#This Row],[DATA PEDIDO]]="","",LANÇAMENTO[[#This Row],[DATA PEDIDO]]+LANÇAMENTO[[#This Row],[PRAZO]]) -> 45884 | T31: =IF(LANÇAMENTO[[#This Row],[OBRA COM MATERIAL]]="OK","ENTREGUE",IF(LANÇAMENTO[[#This Row],[PRAZO]]="","",LANÇAMENTO[[#This Row],[PREVISÃO ENTREGA OBRA]]-$E$1)) -> ENTREGUE | U31: OK
A32: 45874 | B32: JOSE DE ALMEIDA PINHEIRO | C32: =VLOOKUP(LANÇAMENTO[[#This Row],[OBRA]],OBRAS[],2,FALSE) -> B&B | D32: HIDRAULICA | E32: LEVE BARRA APOIO RETA 80CM PCD POL | F32: 2 | G32: UNID. | H32: 1775 | I32: CASA MIMOSA | J32: LEVE BARRA APOIO RETA 80CM PCD POL | K32: 164.98 | L32: =LANÇAMENTO[[#This Row],[VALOR UNITARIO]]*LANÇAMENTO[[#This Row],[QTDADE]] -> 329.96 | M32: 45874 | N32: =TEXT(LANÇAMENTO[[#This Row],[DATA PEDIDO]],"MMM")&"-"&TEXT(M32,"AAAA") -> ago-2025 | O32: 28 | P32: BOLETO | Q32: RETIRA | R32: 1 | S32: =IF(LANÇAMENTO[[#This Row],[DATA PEDIDO]]="","",LANÇAMENTO[[#This Row],[DATA PEDIDO]]+LANÇAMENTO[[#This Row],[PRAZO]]) -> 45875 | T32: =IF(LANÇAMENTO[[#This Row],[OBRA COM MATERIAL]]="OK","ENTREGUE",IF(LANÇAMENTO[[#This Row],[PRAZO]]="","",LANÇAMENTO[[#This Row],[PREVISÃO ENTREGA OBRA]]-$E$1)) -> ENTREGUE | U32: OK | V32: MATERIAL PARA OBRA PEI CRISTIANE CHAVES, FATURAR PARA A B&B
A33: 45874 | B33: JOSE DE ALMEIDA PINHEIRO | C33: =VLOOKUP(LANÇAMENTO[[#This Row],[OBRA]],OBRAS[],2,FALSE) -> B&B | D33: HIDRAULICA | E33: LEVE BARRA APOIO RETA 40CM PCD POL | F33: 3 | G33: UNID. | H33: 1775 | I33: CASA MIMOSA | J33: LEVE BARRA APOIO RETA 40CM PCD POL | K33: 128.23 | L33: =LANÇAMENTO[[#This Row],[VALOR UNITARIO]]*LANÇAMENTO[[#This Row],[QTDADE]] -> 384.69 | M33: 45874 | N33: =TEXT(LANÇAMENTO[[#This Row],[DATA PEDIDO]],"MMM")&"-"&TEXT(M33,"AAAA") -> ago-2025 | O33: 28 | P33: BOLETO | Q33: RETIRA | R33: 1 | S33: =IF(LANÇAMENTO[[#This Row],[DATA PEDIDO]]="","",LANÇAMENTO[[#This Row],[DATA PEDIDO]]+LANÇAMENTO[[#This Row],[PRAZO]]) -> 45875 | T33: =IF(LANÇAMENTO[[#This Row],[OBRA COM MATERIAL]]="OK","ENTREGUE",IF(LANÇAMENTO[[#This Row],[PRAZO]]="","",LANÇAMENTO[[#This Row],[PREVISÃO ENTREGA OBRA]]-$E$1)) -> ENTREGUE | U33: OK | V33: MATERIAL PARA OBRA PEI CRISTIANE CHAVES, FATURAR PARA A B&B
A34: 45874 | B34: JOSE DE ALMEIDA PINHEIRO | C34: =VLOOKUP(LANÇAMENTO[[#This Row],[OBRA]],OBRAS[],2,FALSE) -> B&B | D34: HIDRAULICA | E34: CENSI TUBO EXTENS.CROMADO 7154 | F34: 1 | G34: UNID. | H34: 1775 | I34: CASA MIMOSA | J34: CENSI TUBO EXTENS.CROMADO 7154 | K34: 28.13 | L34: =LANÇAMENTO[[#This Row],[VALOR UNITARIO]]*LANÇAMENTO[[#This Row],[QTDADE]] -> 28.13 | M34: 45874 | N34: =TEXT(LANÇAMENTO[[#This Row],[DATA PEDIDO]],"MMM")&"-"&TEXT(M34,"AAAA") -> ago-2025 | O34: 28 | P34: BOLETO | Q34: RETIRA | R34: 1 | S34: =IF(LANÇAMENTO[[#This Row],[DATA PEDIDO]]="","",LANÇAMENTO[[#This Row],[DATA PEDIDO]]+LANÇAMENTO[[#This Row],[PRAZO]]) -> 45875 | T34: =IF(LANÇAMENTO[[#This Row],[OBRA COM MATERIAL]]="OK","ENTREGUE",IF(LANÇAMENTO[[#This Row],[PRAZO]]="","",LANÇAMENTO[[#This Row],[PREVISÃO ENTREGA OBRA]]-$E$1)) -> ENTREGUE | U34: OK | V34: MATERIAL PARA OBRA PEI CRISTIANE CHAVES, FATURAR PARA A B&B
A35: 45874 | B35: JOSE DE ALMEIDA PINHEIRO | C35: =VLOOKUP(LANÇAMENTO[[#This Row],[OBRA]],OBRAS[],2,FALSE) -> B&B | D35: HIDRAULICA | E35: TORALF PARAFUSO B-10 LAT. 75MM C/2 P/BACIA 1070 | F35: 1 | G35: UNID. | H35: 1775 | I35: CASA MIMOSA | J35: TORALF PARAFUSO B-10 LAT. 75MM C/2 P/BACIA 1070 | K35: 10.9 | L35: =LANÇAMENTO[[#This Row],[VALOR UNITARIO]]*LANÇAMENTO[[#This Row],[QTDADE]] -> 10.9 | M35: 45874 | N35: =TEXT(LANÇAMENTO[[#This Row],[DATA PEDIDO]],"MMM")&"-"&TEXT(M35,"AAAA") -> ago-2025 | O35: 28 | P35: BOLETO | Q35: RETIRA | R35: 1 | S35: =IF(LANÇAMENTO[[#This Row],[DATA PEDIDO]]="","",LANÇAMENTO[[#This Row],[DATA PEDIDO]]+LANÇAMENTO[[#This Row],[PRAZO]]) -> 45875 | T35: =IF(LANÇAMENTO[[#This Row],[OBRA COM MATERIAL]]="OK","ENTREGUE",IF(LANÇAMENTO[[#This Row],[PRAZO]]="","",LANÇAMENTO[[#This Row],[PREVISÃO ENTREGA OBRA]]-$E$1)) -> ENTREGUE | U35: OK | V35: MATERIAL PARA OBRA PEI CRISTIANE CHAVES, FATURAR PARA A B&B
A36: 45874 | B36: JOSE DE ALMEIDA PINHEIRO | C36: =VLOOKUP(LANÇAMENTO[[#This Row],[OBRA]],OBRAS[],2,FALSE) -> B&B | D36: HIDRAULICA | E36: TORALF PARAFUSO B-12 LAT. 90MM C/2 P/TANQUE | F36: 1 | G36: UNID. | H36: 1775 | I36: CASA MIMOSA | J36: TORALF PARAFUSO B-12 LAT. 90MM C/2 P/TANQUE | K36: 15.31 | L36: =LANÇAMENTO[[#This Row],[VALOR UNITARIO]]*LANÇAMENTO[[#This Row],[QTDADE]] -> 15.31 | M36: 45874 | N36: =TEXT(LANÇAMENTO[[#This Row],[DATA PEDIDO]],"MMM")&"-"&TEXT(M36,"AAAA") -> ago-2025 | O36: 28 | P36: BOLETO | Q36: RETIRA | R36: 1 | S36: =IF(LANÇAMENTO[[#This Row],[DATA PEDIDO]]="","",LANÇAMENTO[[#This Row],[DATA PEDIDO]]+LANÇAMENTO[[#This Row],[PRAZO]]) -> 45875 | T36: =IF(LANÇAMENTO[[#This Row],[OBRA COM MATERIAL]]="OK","ENTREGUE",IF(LANÇAMENTO[[#This Row],[PRAZO]]="","",LANÇAMENTO[[#This Row],[PREVISÃO ENTREGA OBRA]]-$E$1)) -> ENTREGUE | U36: OK | V36: MATERIAL PARA OBRA PEI CRISTIANE CHAVES, FATURAR PARA A B&B
A37: 45874 | B37: JOSE DE ALMEIDA PINHEIRO | C37: =VLOOKUP(LANÇAMENTO[[#This Row],[OBRA]],OBRAS[],2,FALSE) -> B&B | D37: HIDRAULICA | E37: TUPAN ASS.UNIV PP PREMIUM CONV BR | F37: 1 | G37: UNID. | H37: 1775 | I37: CASA MIMOSA | J37: TUPAN ASS.UNIV PP PREMIUM CONV BR | K37: 34.33 | L37: =LANÇAMENTO[[#This Row],[VALOR UNITARIO]]*LANÇAMENTO[[#This Row],[QTDADE]] -> 34.33 | M37: 45874 | N37: =TEXT(LANÇAMENTO[[#This Row],[DATA PEDIDO]],"MMM")&"-"&TEXT(M37,"AAAA") -> ago-2025 | O37: 28 | P37: BOLETO | Q37: RETIRA | R37: 1 | S37: =IF(LANÇAMENTO[[#This Row],[DATA PEDIDO]]="","",LANÇAMENTO[[#This Row],[DATA PEDIDO]]+LANÇAMENTO[[#This Row],[PRAZO]]) -> 45875 | T37: =IF(LANÇAMENTO[[#This Row],[OBRA COM MATERIAL]]="OK","ENTREGUE",IF(LANÇAMENTO[[#This Row],[PRAZO]]="","",LANÇAMENTO[[#This Row],[PREVISÃO ENTREGA OBRA]]-$E$1)) -> ENTREGUE | U37: OK | V37: MATERIAL PARA OBRA PEI CRISTIANE CHAVES, FATURAR PARA A B&B
A38: 45874 | B38: JOSE DE ALMEIDA PINHEIRO | C38: =VLOOKUP(LANÇAMENTO[[#This Row],[OBRA]],OBRAS[],2,FALSE) -> B&B | D38: HIDRAULICA | E38: DECA CANOPLA VALV.HYDRA MAX C | F38: 1 | G38: UNID. | H38: 1775 | I38: CASA MIMOSA | J38: DECA CANOPLA VALV.HYDRA MAX C | K38: 122.26 | L38: =LANÇAMENTO[[#This Row],[VALOR UNITARIO]]*LANÇAMENTO[[#This Row],[QTDADE]] -> 122.26 | M38: 45874 | N38: =TEXT(LANÇAMENTO[[#This Row],[DATA PEDIDO]],"MMM")&"-"&TEXT(M38,"AAAA") -> ago-2025 | O38: 28 | P38: BOLETO | Q38: RETIRA | R38: 1 | S38: =IF(LANÇAMENTO[[#This Row],[DATA PEDIDO]]="","",LANÇAMENTO[[#This Row],[DATA PEDIDO]]+LANÇAMENTO[[#This Row],[PRAZO]]) -> 45875 | T38: =IF(LANÇAMENTO[[#This Row],[OBRA COM MATERIAL]]="OK","ENTREGUE",IF(LANÇAMENTO[[#This Row],[PRAZO]]="","",LANÇAMENTO[[#This Row],[PREVISÃO ENTREGA OBRA]]-$E$1)) -> ENTREGUE | U38: OK | V38: MATERIAL PARA OBRA PEI CRISTIANE CHAVES, FATURAR PARA A B&B
A39: 45874 | B39: JOSE DE ALMEIDA PINHEIRO | C39: =VLOOKUP(LANÇAMENTO[[#This Row],[OBRA]],OBRAS[],2,FALSE) -> B&B | D39: HIDRAULICA | E39: CEMIX ACABAMENTO C50 3/4 F | F39: 1 | G39: UNID. | H39: 1775 | I39: CASA MIMOSA | J39: CEMIX ACABAMENTO C50 3/4 F | K39: 13.81 | L39: =LANÇAMENTO[[#This Row],[VALOR UNITARIO]]*LANÇAMENTO[[#This Row],[QTDADE]] -> 13.81 | M39: 45874 | N39: =TEXT(LANÇAMENTO[[#This Row],[DATA PEDIDO]],"MMM")&"-"&TEXT(M39,"AAAA") -> ago-2025 | O39: 28 | P39: BOLETO | Q39: RETIRA | R39: 1 | S39: =IF(LANÇAMENTO[[#This Row],[DATA PEDIDO]]="","",LANÇAMENTO[[#This Row],[DATA PEDIDO]]+LANÇAMENTO[[#This Row],[PRAZO]]) -> 45875 | T39: =IF(LANÇAMENTO[[#This Row],[OBRA COM MATERIAL]]="OK","ENTREGUE",IF(LANÇAMENTO[[#This Row],[PRAZO]]="","",LANÇAMENTO[[#This Row],[PREVISÃO ENTREGA OBRA]]-$E$1)) -> ENTREGUE | U39: OK | V39: MATERIAL PARA OBRA PEI CRISTIANE CHAVES, FATURAR PARA A B&B
A40: 45874 | B40: JOSE DE ALMEIDA PINHEIRO | C40: =VLOOKUP(LANÇAMENTO[[#This Row],[OBRA]],OBRAS[],2,FALSE) -> B&B | D40: HIDRAULICA | E40: CEMIX ACABAMENTO C50 1.1/2 | F40: 1 | G40: UNID. | H40: 1775 | I40: CASA MIMOSA | J40: CEMIX ACABAMENTO C50 1.1/2 | K40: 15.34 | L40: =LANÇAMENTO[[#This Row],[VALOR UNITARIO]]*LANÇAMENTO[[#This Row],[QTDADE]] -> 15.34 | M40: 45874 | N40: =TEXT(LANÇAMENTO[[#This Row],[DATA PEDIDO]],"MMM")&"-"&TEXT(M40,"AAAA") -> ago-2025 | O40: 28 | P40: BOLETO | Q40: RETIRA | R40: 1 | S40: =IF(LANÇAMENTO[[#This Row],[DATA PEDIDO]]="","",LANÇAMENTO[[#This Row],[DATA PEDIDO]]+LANÇAMENTO[[#This Row],[PRAZO]]) -> 45875 | T40: =IF(LANÇAMENTO[[#This Row],[OBRA COM MATERIAL]]="OK","ENTREGUE",IF(LANÇAMENTO[[#This Row],[PRAZO]]="","",LANÇAMENTO[[#This Row],[PREVISÃO ENTREGA OBRA]]-$E$1)) -> ENTREGUE | U40: OK | V40: MATERIAL PARA OBRA PEI CRISTIANE CHAVES, FATURAR PARA A B&B
A41: 45874 | B41: JOSE DE ALMEIDA PINHEIRO | C41: =VLOOKUP(LANÇAMENTO[[#This Row],[OBRA]],OBRAS[],2,FALSE) -> B&B | D41: HIDRAULICA | E41: EMMETI DUCHA HIG.ECO.1/2 GAT.ABS BR RG.MET. | F41: 1 | G41: UNID. | H41: 1775 | I41: CASA MIMOSA | J41: EMMETI DUCHA HIG.ECO.1/2 GAT.ABS BR RG.MET. | K41: 66.73 | L41: =LANÇAMENTO[[#This Row],[VALOR UNITARIO]]*LANÇAMENTO[[#This Row],[QTDADE]] -> 66.73 | M41: 45874 | N41: =TEXT(LANÇAMENTO[[#This Row],[DATA PEDIDO]],"MMM")&"-"&TEXT(M41,"AAAA") -> ago-2025 | O41: 28 | P41: BOLETO | Q41: RETIRA | R41: 1 | S41: =IF(LANÇAMENTO[[#This Row],[DATA PEDIDO]]="","",LANÇAMENTO[[#This Row],[DATA PEDIDO]]+LANÇAMENTO[[#This Row],[PRAZO]]) -> 45875 | T41: =IF(LANÇAMENTO[[#This Row],[OBRA COM MATERIAL]]="OK","ENTREGUE",IF(LANÇAMENTO[[#This Row],[PRAZO]]="","",LANÇAMENTO[[#This Row],[PREVISÃO ENTREGA OBRA]]-$E$1)) -> ENTREGUE | U41: OK | V41: MATERIAL PARA OBRA PEI CRISTIANE CHAVES, FATURAR PARA A B&B
A42: 45874 | B42: JOSE DE ALMEIDA PINHEIRO | C42: =VLOOKUP(LANÇAMENTO[[#This Row],[OBRA]],OBRAS[],2,FALSE) -> B&B | D42: HIDRAULICA | E42: EMMETI FLEX.1/2X60CM MF C/CANOPLA H0524600 | F42: 1 | G42: UNID. | H42: 1775 | I42: CASA MIMOSA | J42: EMMETI FLEX.1/2X60CM MF C/CANOPLA H0524600 | K42: 20.69 | L42: =LANÇAMENTO[[#This Row],[VALOR UNITARIO]]*LANÇAMENTO[[#This Row],[QTDADE]] -> 20.69 | M42: 45874 | N42: =TEXT(LANÇAMENTO[[#This Row],[DATA PEDIDO]],"MMM")&"-"&TEXT(M42,"AAAA") -> ago-2025 | O42: 28 | P42: BOLETO | Q42: RETIRA | R42: 1 | S42: =IF(LANÇAMENTO[[#This Row],[DATA PEDIDO]]="","",LANÇAMENTO[[#This Row],[DATA PEDIDO]]+LANÇAMENTO[[#This Row],[PRAZO]]) -> 45875 | T42: =IF(LANÇAMENTO[[#This Row],[OBRA COM MATERIAL]]="OK","ENTREGUE",IF(LANÇAMENTO[[#This Row],[PRAZO]]="","",LANÇAMENTO[[#This Row],[PREVISÃO ENTREGA OBRA]]-$E$1)) -> ENTREGUE | U42: OK | V42: MATERIAL PARA OBRA PEI CRISTIANE CHAVES, FATURAR PARA A B&B
A43: 45874 | B43: LEA APARECIDA | C43: =VLOOKUP(LANÇAMENTO[[#This Row],[OBRA]],OBRAS[],2,FALSE) -> INTERIORANA | D43: OUTROS | E43: TELA POP | F43: 44 | G43: UNID. | H43: 1776 | I43: RISATEC | J43: TELA SOLDADA TOP PA Q45 2X3 M LEVE CD | K43: 30.99 | L43: =LANÇAMENTO[[#This Row],[VALOR UNITARIO]]*LANÇAMENTO[[#This Row],[QTDADE]] -> 1363.56 | M43: 45874 | N43: =TEXT(LANÇAMENTO[[#This Row],[DATA PEDIDO]],"MMM")&"-"&TEXT(M43,"AAAA") -> ago-2025 | O43: 28 | P43: BOLETO | Q43: RETIRA | R43: 2 | S43: =IF(LANÇAMENTO[[#This Row],[DATA PEDIDO]]="","",LANÇAMENTO[[#This Row],[DATA PEDIDO]]+LANÇAMENTO[[#This Row],[PRAZO]]) -> 45876 | T43: =IF(LANÇAMENTO[[#This Row],[OBRA COM MATERIAL]]="OK","ENTREGUE",IF(LANÇAMENTO[[#This Row],[PRAZO]]="","",LANÇAMENTO[[#This Row],[PREVISÃO ENTREGA OBRA]]-$E$1)) -> ENTREGUE | U43: OK
A44: 45874 | B44: ERICO VERISSIMO | C44: =VLOOKUP(LANÇAMENTO[[#This Row],[OBRA]],OBRAS[],2,FALSE) -> INTERIORANA | D44: PINTURA | E44: ADERE FITA CREPE 24X50M | F44: 25 | G44: PACOTE | H44: 1777 | I44: OLD RIVER | J44: ADERE FITA CREPE 24X50M | K44: 5.99 | L44: =LANÇAMENTO[[#This Row],[VALOR UNITARIO]]*LANÇAMENTO[[#This Row],[QTDADE]] -> 149.75 | M44: 45874 | N44: =TEXT(LANÇAMENTO[[#This Row],[DATA PEDIDO]],"MMM")&"-"&TEXT(M44,"AAAA") -> ago-2025 | O44: 28/56/84 | P44: BOLETO | Q44: ENTREGA | R44: 1 | S44: =IF(LANÇAMENTO[[#This Row],[DATA PEDIDO]]="","",LANÇAMENTO[[#This Row],[DATA PEDIDO]]+LANÇAMENTO[[#This Row],[PRAZO]]) -> 45875 | T44: =IF(LANÇAMENTO[[#This Row],[OBRA COM MATERIAL]]="OK","ENTREGUE",IF(LANÇAMENTO[[#This Row],[PRAZO]]="","",LANÇAMENTO[[#This Row],[PREVISÃO ENTREGA OBRA]]-$E$1)) -> ENTREGUE | U44: OK
A45: 45874 | B45: ERICO VERISSIMO | C45: =VLOOKUP(LANÇAMENTO[[#This Row],[OBRA]],OBRAS[],2,FALSE) -> INTERIORANA | D45: PINTURA | E45: COMPEL 1423 ROLO DE LA RESPINGO ZERO ECONOMICO 23CM | F45: 6 | G45: PACOTE | H45: 1777 | I45: OLD RIVER | J45: COMPEL 1423 ROLO DE LA RESPINGO ZERO ECONOMICO 23CM | K45: 8.99 | L45: =LANÇAMENTO[[#This Row],[VALOR UNITARIO]]*LANÇAMENTO[[#This Row],[QTDADE]] -> 53.94 | M45: 45874 | N45: =TEXT(LANÇAMENTO[[#This Row],[DATA PEDIDO]],"MMM")&"-"&TEXT(M45,"AAAA") -> ago-2025 | O45: 28/56/84 | P45: BOLETO | Q45: ENTREGA | R45: 1 | S45: =IF(LANÇAMENTO[[#This Row],[DATA PEDIDO]]="","",LANÇAMENTO[[#This Row],[DATA PEDIDO]]+LANÇAMENTO[[#This Row],[PRAZO]]) -> 45875 | T45: =IF(LANÇAMENTO[[#This Row],[OBRA COM MATERIAL]]="OK","ENTREGUE",IF(LANÇAMENTO[[#This Row],[PRAZO]]="","",LANÇAMENTO[[#This Row],[PREVISÃO ENTREGA OBRA]]-$E$1)) -> ENTREGUE | U45: OK
A46: 45874 | B46: ERICO VERISSIMO | C46: =VLOOKUP(LANÇAMENTO[[#This Row],[OBRA]],OBRAS[],2,FALSE) -> INTERIORANA | D46: PINTURA | E46: COMPEL 2072 SUPORTE DE PRESSAO 23CM | F46: 6 | G46: PACOTE | H46: 1777 | I46: OLD RIVER | J46: COMPEL 2072 SUPORTE DE PRESSAO 23CM | K46: 4.99 | L46: =LANÇAMENTO[[#This Row],[VALOR UNITARIO]]*LANÇAMENTO[[#This Row],[QTDADE]] -> 29.94 | M46: 45874 | N46: =TEXT(LANÇAMENTO[[#This Row],[DATA PEDIDO]],"MMM")&"-"&TEXT(M46,"AAAA") -> ago-2025 | O46: 28/56/84 | P46: BOLETO | Q46: ENTREGA | R46: 1 | S46: =IF(LANÇAMENTO[[#This Row],[DATA PEDIDO]]="","",LANÇAMENTO[[#This Row],[DATA PEDIDO]]+LANÇAMENTO[[#This Row],[PRAZO]]) -> 45875 | T46: =IF(LANÇAMENTO[[#This Row],[OBRA COM MATERIAL]]="OK","ENTREGUE",IF(LANÇAMENTO[[#This Row],[PRAZO]]="","",LANÇAMENTO[[#This Row],[PREVISÃO ENTREGA OBRA]]-$E$1)) -> ENTREGUE | U46: OK
A47: 45874 | B47: ERICO VERISSIMO | C47: =VLOOKUP(LANÇAMENTO[[#This Row],[OBRA]],OBRAS[],2,FALSE) -> INTERIORANA | D47: PINTURA | E47: FUTURA PREMIUM TINTA PARA PISO AMARELO 3,6L | F47: 1 | G47: GALÃO | H47: 1777 | I47: OLD RIVER | J47: FUTURA PREMIUM TINTA PARA PISO AMARELO 3,6L | K47: 69.9 | L47: =LANÇAMENTO[[#This Row],[VALOR UNITARIO]]*LANÇAMENTO[[#This Row],[QTDADE]] -> 69.9 | M47: 45874 | N47: =TEXT(LANÇAMENTO[[#This Row],[DATA PEDIDO]],"MMM")&"-"&TEXT(M47,"AAAA") -> ago-2025 | O47: 28/56/84 | P47: BOLETO | Q47: ENTREGA | R47: 1 | S47: =IF(LANÇAMENTO[[#This Row],[DATA PEDIDO]]="","",LANÇAMENTO[[#This Row],[DATA PEDIDO]]+LANÇAMENTO[[#This Row],[PRAZO]]) -> 45875 | T47: =IF(LANÇAMENTO[[#This Row],[OBRA COM MATERIAL]]="OK","ENTREGUE",IF(LANÇAMENTO[[#This Row],[PRAZO]]="","",LANÇAMENTO[[#This Row],[PREVISÃO ENTREGA OBRA]]-$E$1)) -> ENTREGUE | U47: OK
A48: 45874 | B48: ERICO VERISSIMO | C48: =VLOOKUP(LANÇAMENTO[[#This Row],[OBRA]],OBRAS[],2,FALSE) -> INTERIORANA | D48: PINTURA | E48: FUTURA PREMIUM TINTA PARA PISO AZUL 18L | F48: 6 | G48: LATA | H48: 1777 | I48: OLD RIVER | J48: FUTURA PREMIUM TINTA PARA PISO AZUL 18L | K48: 249.9 | L48: =LANÇAMENTO[[#This Row],[VALOR UNITARIO]]*LANÇAMENTO[[#This Row],[QTDADE]] -> 1499.4 | M48: 45874 | N48: =TEXT(LANÇAMENTO[[#This Row],[DATA PEDIDO]],"MMM")&"-"&TEXT(M48,"AAAA") -> ago-2025 | O48: 28/56/84 | P48: BOLETO | Q48: ENTREGA | R48: 1 | S48: =IF(LANÇAMENTO[[#This Row],[DATA PEDIDO]]="","",LANÇAMENTO[[#This Row],[DATA PEDIDO]]+LANÇAMENTO[[#This Row],[PRAZO]]) -> 45875 | T48: =IF(LANÇAMENTO[[#This Row],[OBRA COM MATERIAL]]="OK","ENTREGUE",IF(LANÇAMENTO[[#This Row],[PRAZO]]="","",LANÇAMENTO[[#This Row],[PREVISÃO ENTREGA OBRA]]-$E$1)) -> ENTREGUE | U48: OK
A49: 45874 | B49: ERICO VERISSIMO | C49: =VLOOKUP(LANÇAMENTO[[#This Row],[OBRA]],OBRAS[],2,FALSE) -> INTERIORANA | D49: PINTURA | E49: FUTURA PREMIUM TINTA PARA PISO BRANCO 3,6L | F49: 1 | G49: GALÃO | H49: 1777 | I49: OLD RIVER | J49: FUTURA PREMIUM TINTA PARA PISO BRANCO 3,6L | K49: 69.9 | L49: =LANÇAMENTO[[#This Row],[VALOR UNITARIO]]*LANÇAMENTO[[#This Row],[QTDADE]] -> 69.9 | M49: 45874 | N49: =TEXT(LANÇAMENTO[[#This Row],[DATA PEDIDO]],"MMM")&"-"&TEXT(M49,"AAAA") -> ago-2025 | O49: 28/56/84 | P49: BOLETO | Q49: ENTREGA | R49: 1 | S49: =IF(LANÇAMENTO[[#This Row],[DATA PEDIDO]]="","",LANÇAMENTO[[#This Row],[DATA PEDIDO]]+LANÇAMENTO[[#This Row],[PRAZO]]) -> 45875 | T49: =IF(LANÇAMENTO[[#This Row],[OBRA COM MATERIAL]]="OK","ENTREGUE",IF(LANÇAMENTO[[#This Row],[PRAZO]]="","",LANÇAMENTO[[#This Row],[PREVISÃO ENTREGA OBRA]]-$E$1)) -> ENTREGUE | U49: OK
A50: 45874 | B50: ERICO VERISSIMO | C50: =VLOOKUP(LANÇAMENTO[[#This Row],[OBRA]],OBRAS[],2,FALSE) -> INTERIORANA | D50: PINTURA | E50: FUTURA PREMIUM TINTA PARA PISO VERDE 3,6L | F50: 1 | G50: GALÃO | H50: 1777 | I50: OLD RIVER | J50: FUTURA PREMIUM TINTA PARA PISO VERDE 3,6L | K50: 69.9 | L50: =LANÇAMENTO[[#This Row],[VALOR UNITARIO]]*LANÇAMENTO[[#This Row],[QTDADE]] -> 69.9 | M50: 45874 | N50: =TEXT(LANÇAMENTO[[#This Row],[DATA PEDIDO]],"MMM")&"-"&TEXT(M50,"AAAA") -> ago-2025 | O50: 28/56/84 | P50: BOLETO | Q50: ENTREGA | R50: 1 | S50: =IF(LANÇAMENTO[[#This Row],[DATA PEDIDO]]="","",LANÇAMENTO[[#This Row],[DATA PEDIDO]]+LANÇAMENTO[[#This Row],[PRAZO]]) -> 45875 | T50: =IF(LANÇAMENTO[[#This Row],[OBRA COM MATERIAL]]="OK","ENTREGUE",IF(LANÇAMENTO[[#This Row],[PRAZO]]="","",LANÇAMENTO[[#This Row],[PREVISÃO ENTREGA OBRA]]-$E$1)) -> ENTREGUE | U50: OK
A51: 45874 | B51: ERICO VERISSIMO | C51: =VLOOKUP(LANÇAMENTO[[#This Row],[OBRA]],OBRAS[],2,FALSE) -> INTERIORANA | D51: PINTURA | E51: FUTURA PREMIUM TINTA PARA PISO VERMELHO SEGURANÇA 18L | F51: 2 | G51: LATA | H51: 1777 | I51: OLD RIVER | J51: FUTURA PREMIUM TINTA PARA PISO VERMELHO SEGURANÇA 18L | K51: 249.9 | L51: =LANÇAMENTO[[#This Row],[VALOR UNITARIO]]*LANÇAMENTO[[#This Row],[QTDADE]] -> 499.8 | M51: 45874 | N51: =TEXT(LANÇAMENTO[[#This Row],[DATA PEDIDO]],"MMM")&"-"&TEXT(M51,"AAAA") -> ago-2025 | O51: 28/56/84 | P51: BOLETO | Q51: ENTREGA | R51: 1 | S51: =IF(LANÇAMENTO[[#This Row],[DATA PEDIDO]]="","",LANÇAMENTO[[#This Row],[DATA PEDIDO]]+LANÇAMENTO[[#This Row],[PRAZO]]) -> 45875 | T51: =IF(LANÇAMENTO[[#This Row],[OBRA COM MATERIAL]]="OK","ENTREGUE",IF(LANÇAMENTO[[#This Row],[PRAZO]]="","",LANÇAMENTO[[#This Row],[PREVISÃO ENTREGA OBRA]]-$E$1)) -> ENTREGUE | U51: OK
A52: 45874 | B52: ERICO VERISSIMO | C52: =VLOOKUP(LANÇAMENTO[[#This Row],[OBRA]],OBRAS[],2,FALSE) -> INTERIORANA | D52: PINTURA | E52: ROMA 301/005 TRINCHA CABO PRETO/CERDA GRIS 301 2" | F52: 6 | G52: PACOTE | H52: 1777 | I52: OLD RIVER | J52: ROMA 301/005 TRINCHA CABO PRETO/CERDA GRIS 301 2" | K52: 4.99 | L52: =LANÇAMENTO[[#This Row],[VALOR UNITARIO]]*LANÇAMENTO[[#This Row],[QTDADE]] -> 29.94 | M52: 45874 | N52: =TEXT(LANÇAMENTO[[#This Row],[DATA PEDIDO]],"MMM")&"-"&TEXT(M52,"AAAA") -> ago-2025 | O52: 28/56/84 | P52: BOLETO | Q52: ENTREGA | R52: 1 | S52: =IF(LANÇAMENTO[[#This Row],[DATA PEDIDO]]="","",LANÇAMENTO[[#This Row],[DATA PEDIDO]]+LANÇAMENTO[[#This Row],[PRAZO]]) -> 45875 | T52: =IF(LANÇAMENTO[[#This Row],[OBRA COM MATERIAL]]="OK","ENTREGUE",IF(LANÇAMENTO[[#This Row],[PRAZO]]="","",LANÇAMENTO[[#This Row],[PREVISÃO ENTREGA OBRA]]-$E$1)) -> ENTREGUE | U52: OK
A53: 45874 | B53: ERICO VERISSIMO | C53: =VLOOKUP(LANÇAMENTO[[#This Row],[OBRA]],OBRAS[],2,FALSE) -> INTERIORANA | D53: PINTURA | E53: RESINA ACRILICA EUCATEX 18 LTS | F53: 6 | G53: LATA | H53: 1778 | I53: DEPOSITO PADRÃO | J53: RESINA ACRILICA EUCATEX 18 LTS | K53: 450 | L53: =LANÇAMENTO[[#This Row],[VALOR UNITARIO]]*LANÇAMENTO[[#This Row],[QTDADE]] -> 2700 | M53: 45874 | N53: =TEXT(LANÇAMENTO[[#This Row],[DATA PEDIDO]],"MMM")&"-"&TEXT(M53,"AAAA") -> ago-2025 | O53: 28/35/42 | P53: BOLETO | Q53: ENTREGA | R53: 1 | S53: =IF(LANÇAMENTO[[#This Row],[DATA PEDIDO]]="","",LANÇAMENTO[[#This Row],[DATA PEDIDO]]+LANÇAMENTO[[#This Row],[PRAZO]]) -> 45875 | T53: =IF(LANÇAMENTO[[#This Row],[OBRA COM MATERIAL]]="OK","ENTREGUE",IF(LANÇAMENTO[[#This Row],[PRAZO]]="","",LANÇAMENTO[[#This Row],[PREVISÃO ENTREGA OBRA]]-$E$1)) -> ENTREGUE | U53: OK
A54: 45874 | B54: ERICO VERISSIMO | C54: =VLOOKUP(LANÇAMENTO[[#This Row],[OBRA]],OBRAS[],2,FALSE) -> INTERIORANA | D54: PINTURA | E54: FITA DUPLAFACE 3M FORTE TRANSP.19MMX2MT | F54: 1 | G54: UNID. | H54: 1778 | I54: DEPOSITO PADRÃO | J54: FITA DUPLAFACE 3M FORTE TRANSP.19MMX2MT | K54: 18.88 | L54: =LANÇAMENTO[[#This Row],[VALOR UNITARIO]]*LANÇAMENTO[[#This Row],[QTDADE]] -> 18.88 | M54: 45874 | N54: =TEXT(LANÇAMENTO[[#This Row],[DATA PEDIDO]],"MMM")&"-"&TEXT(M54,"AAAA") -> ago-2025 | O54: 28/35/42 | P54: BOLETO | Q54: ENTREGA | R54: 1 | S54: =IF(LANÇAMENTO[[#This Row],[DATA PEDIDO]]="","",LANÇAMENTO[[#This Row],[DATA PEDIDO]]+LANÇAMENTO[[#This Row],[PRAZO]]) -> 45875 | T54: =IF(LANÇAMENTO[[#This Row],[OBRA COM MATERIAL]]="OK","ENTREGUE",IF(LANÇAMENTO[[#This Row],[PRAZO]]="","",LANÇAMENTO[[#This Row],[PREVISÃO ENTREGA OBRA]]-$E$1)) -> ENTREGUE | U54: OK
... A87: 45875 | B87: SYLVIA DE MELLO | C87: =VLOOKUP(LANÇAMENTO[[#This Row],[OBRA]],OBRAS[],2,FALSE) -> B&B | D87: OUTROS | E87: CAMARA P PNEU CARRINHO | F87: 2 | G87: UNID. | H87: 1784 | I87: DEPOSITO PADRÃO | J87: CAMARA P/CARRI.PEDR 3,25X8 MOLDADA FERTAK | K87: 18.29 | L87: =LANÇAMENTO[[#This Row],[VALOR UNITARIO]]*LANÇAMENTO[[#This Row],[QTDADE]] -> 36.58 | M87: 45875 | N87: =TEXT(LANÇAMENTO[[#This Row],[DATA PEDIDO]],"MMM")&"-"&TEXT(M87,"AAAA") -> ago-2025 | O87: 14 | P87: BOLETO | Q87: RETIRA | R87: 0 | S87: =IF(LANÇAMENTO[[#This Row],[DATA PEDIDO]]="","",LANÇAMENTO[[#This Row],[DATA PEDIDO]]+LANÇAMENTO[[#This Row],[PRAZO]]) -> 45875 | T87: =IF(LANÇAMENTO[[#This Row],[OBRA COM MATERIAL]]="OK","ENTREGUE",IF(LANÇAMENTO[[#This Row],[PRAZO]]="","",LANÇAMENTO[[#This Row],[PREVISÃO ENTREGA OBRA]]-$E$1)) -> ENTREGUE | U87: OK
A88: 45875 | B88: JOSE DE ALMEIDA PINHEIRO | C88: =VLOOKUP(LANÇAMENTO[[#This Row],[OBRA]],OBRAS[],2,FALSE) -> B&B | D88: OUTROS | E88: TB RD 50,80 X 1,55 MM (2") GALV | F88: 2 | G88: BARRA | H88: 1785 | I88: IMPERIO AÇO | J88: TB RD 50,80 X 1,55 MM (2") GALV | K88: 105 | L88: =LANÇAMENTO[[#This Row],[VALOR UNITARIO]]*LANÇAMENTO[[#This Row],[QTDADE]] -> 210 | M88: 45875 | N88: =TEXT(LANÇAMENTO[[#This Row],[DATA PEDIDO]],"MMM")&"-"&TEXT(M88,"AAAA") -> ago-2025 | O88: 30/45 | P88: BOLETO | Q88: RETIRA | R88: 0 | S88: =IF(LANÇAMENTO[[#This Row],[DATA PEDIDO]]="","",LANÇAMENTO[[#This Row],[DATA PEDIDO]]+LANÇAMENTO[[#This Row],[PRAZO]]) -> 45875 | T88: =IF(LANÇAMENTO[[#This Row],[OBRA COM MATERIAL]]="OK","ENTREGUE",IF(LANÇAMENTO[[#This Row],[PRAZO]]="","",LANÇAMENTO[[#This Row],[PREVISÃO ENTREGA OBRA]]-$E$1)) -> ENTREGUE | U88: OK | V88: MATERIAL PARA OBRA EE ANDRE FRANCO MONTORO
A89: 45875 | B89: JOSE DE ALMEIDA PINHEIRO | C89: =VLOOKUP(LANÇAMENTO[[#This Row],[OBRA]],OBRAS[],2,FALSE) -> B&B | D89: OUTROS | E89: TB RD 31,75 X 1,55 MM (1.1/4") GALV | F89: 12 | G89: BARRA | H89: 1785 | I89: IMPERIO AÇO | J89: TB RD 31,75 X 1,55 MM (1.1/4") GALV | K89: 66 | L89: =LANÇAMENTO[[#This Row],[VALOR UNITARIO]]*LANÇAMENTO[[#This Row],[QTDADE]] -> 792 | M89: 45875 | N89: =TEXT(LANÇAMENTO[[#This Row],[DATA PEDIDO]],"MMM")&"-"&TEXT(M89,"AAAA") -> ago-2025 | O89: 30/45 | P89: BOLETO | Q89: RETIRA | R89: 0 | S89: =IF(LANÇAMENTO[[#This Row],[DATA PEDIDO]]="","",LANÇAMENTO[[#This Row],[DATA PEDIDO]]+LANÇAMENTO[[#This Row],[PRAZO]]) -> 45875 | T89: =IF(LANÇAMENTO[[#This Row],[OBRA COM MATERIAL]]="OK","ENTREGUE",IF(LANÇAMENTO[[#This Row],[PRAZO]]="","",LANÇAMENTO[[#This Row],[PREVISÃO ENTREGA OBRA]]-$E$1)) -> ENTREGUE | U89: OK | V89: MATERIAL PARA OBRA EE ANDRE FRANCO MONTORO
A90: 45875 | B90: JOSE DE ALMEIDA PINHEIRO | C90: =VLOOKUP(LANÇAMENTO[[#This Row],[OBRA]],OBRAS[],2,FALSE) -> B&B | D90: OUTROS | E90: IMPOSTO (IPI E ICMSST) | F90: 1 | G90: VERBA | H90: 1785 | I90: IMPERIO AÇO | J90: IMPOSTO (IPI E ICMSST) | K90: 32.57 | L90: =LANÇAMENTO[[#This Row],[VALOR UNITARIO]]*LANÇAMENTO[[#This Row],[QTDADE]] -> 32.57 | M90: 45875 | N90: =TEXT(LANÇAMENTO[[#This Row],[DATA PEDIDO]],"MMM")&"-"&TEXT(M90,"AAAA") -> ago-2025 | O90: 30/45 | P90: BOLETO | Q90: RETIRA | R90: 0 | S90: =IF(LANÇAMENTO[[#This Row],[DATA PEDIDO]]="","",LANÇAMENTO[[#This Row],[DATA PEDIDO]]+LANÇAMENTO[[#This Row],[PRAZO]]) -> 45875 | T90: =IF(LANÇAMENTO[[#This Row],[OBRA COM MATERIAL]]="OK","ENTREGUE",IF(LANÇAMENTO[[#This Row],[PRAZO]]="","",LANÇAMENTO[[#This Row],[PREVISÃO ENTREGA OBRA]]-$E$1)) -> ENTREGUE | U90: OK | V90: MATERIAL PARA OBRA EE ANDRE FRANCO MONTORO
A91: 45875 | B91: SYLVIA DE MELLO | C91: =VLOOKUP(LANÇAMENTO[[#This Row],[OBRA]],OBRAS[],2,FALSE) -> B&B | D91: OUTROS | E91: TB RD 50,80 X 1,55 MM (2") GALV | F91: 5 | G91: BARRA | H91: 1786 | I91: IMPERIO AÇO | J91: TB RD 50,80 X 1,55 MM (2") GALV | K91: 105 | L91: =LANÇAMENTO[[#This Row],[VALOR UNITARIO]]*LANÇAMENTO[[#This Row],[QTDADE]] -> 525 | M91: 45875 | N91: =TEXT(LANÇAMENTO[[#This Row],[DATA PEDIDO]],"MMM")&"-"&TEXT(M91,"AAAA") -> ago-2025 | O91: 30/45 | P91: BOLETO | Q91: RETIRA | R91: 0 | S91: =IF(LANÇAMENTO[[#This Row],[DATA PEDIDO]]="","",LANÇAMENTO[[#This Row],[DATA PEDIDO]]+LANÇAMENTO[[#This Row],[PRAZO]]) -> 45875 | T91: =IF(LANÇAMENTO[[#This Row],[OBRA COM MATERIAL]]="OK","ENTREGUE",IF(LANÇAMENTO[[#This Row],[PRAZO]]="","",LANÇAMENTO[[#This Row],[PREVISÃO ENTREGA OBRA]]-$E$1)) -> ENTREGUE | U91: OK | V91: MATERIAL PARA OBRA EE DAGOBERTTO SALES FILHO
A92: 45875 | B92: SYLVIA DE MELLO | C92: =VLOOKUP(LANÇAMENTO[[#This Row],[OBRA]],OBRAS[],2,FALSE) -> B&B | D92: OUTROS | E92: TB RD 31,75 X 1,55 MM (1.1/4") GALV] | F92: 10 | G92: BARRA | H92: 1786 | I92: IMPERIO AÇO | J92: TB RD 31,75 X 1,55 MM (1.1/4") GALV] | K92: 66 | L92: =LANÇAMENTO[[#This Row],[VALOR UNITARIO]]*LANÇAMENTO[[#This Row],[QTDADE]] -> 660 | M92: 45875 | N92: =TEXT(LANÇAMENTO[[#This Row],[DATA PEDIDO]],"MMM")&"-"&TEXT(M92,"AAAA") -> ago-2025 | O92: 30/45 | P92: BOLETO | Q92: RETIRA | R92: 0 | S92: =IF(LANÇAMENTO[[#This Row],[DATA PEDIDO]]="","",LANÇAMENTO[[#This Row],[DATA PEDIDO]]+LANÇAMENTO[[#This Row],[PRAZO]]) -> 45875 | T92: =IF(LANÇAMENTO[[#This Row],[OBRA COM MATERIAL]]="OK","ENTREGUE",IF(LANÇAMENTO[[#This Row],[PRAZO]]="","",LANÇAMENTO[[#This Row],[PREVISÃO ENTREGA OBRA]]-$E$1)) -> ENTREGUE | U92: OK | V92: MATERIAL PARA OBRA EE DAGOBERTTO SALES FILHO
A93: 45875 | B93: SYLVIA DE MELLO | C93: =VLOOKUP(LANÇAMENTO[[#This Row],[OBRA]],OBRAS[],2,FALSE) -> B&B | D93: OUTROS | E93: IMPOSTO (IPI E ICMSST) | F93: 1 | G93: VERBA | H93: 1786 | I93: IMPERIO AÇO | J93: IMPOSTO (IPI E ICMSST) | K93: 38.51 | L93: =LANÇAMENTO[[#This Row],[VALOR UNITARIO]]*LANÇAMENTO[[#This Row],[QTDADE]] -> 38.51 | M93: 45875 | N93: =TEXT(LANÇAMENTO[[#This Row],[DATA PEDIDO]],"MMM")&"-"&TEXT(M93,"AAAA") -> ago-2025 | O93: 30/45 | P93: BOLETO | Q93: RETIRA | R93: 0 | S93: =IF(LANÇAMENTO[[#This Row],[DATA PEDIDO]]="","",LANÇAMENTO[[#This Row],[DATA PEDIDO]]+LANÇAMENTO[[#This Row],[PRAZO]]) -> 45875 | T93: =IF(LANÇAMENTO[[#This Row],[OBRA COM MATERIAL]]="OK","ENTREGUE",IF(LANÇAMENTO[[#This Row],[PRAZO]]="","",LANÇAMENTO[[#This Row],[PREVISÃO ENTREGA OBRA]]-$E$1)) -> ENTREGUE | U93: OK | V93: MATERIAL PARA OBRA EE DAGOBERTTO SALES FILHO
A94: 45875 | B94: JOSE DE ALMEIDA PINHEIRO | C94: =VLOOKUP(LANÇAMENTO[[#This Row],[OBRA]],OBRAS[],2,FALSE) -> B&B | D94: HIDRAULICA | E94: AMANCO TUBO 6M ESG. 100MM | F94: 12 | G94: BARRA | H94: 1787 | I94: CASA MIMOSA | J94: AMANCO TUBO 6M ESG. 100MM | K94: 70.97 | L94: =LANÇAMENTO[[#This Row],[VALOR UNITARIO]]*LANÇAMENTO[[#This Row],[QTDADE]] -> 851.64 | M94: 45875 | N94: =TEXT(LANÇAMENTO[[#This Row],[DATA PEDIDO]],"MMM")&"-"&TEXT(M94,"AAAA") -> ago-2025 | O94: 28 | P94: BOLETO | Q94: RETIRA | R94: 1 | S94: =IF(LANÇAMENTO[[#This Row],[DATA PEDIDO]]="","",LANÇAMENTO[[#This Row],[DATA PEDIDO]]+LANÇAMENTO[[#This Row],[PRAZO]]) -> 45876 | T94: =IF(LANÇAMENTO[[#This Row],[OBRA COM MATERIAL]]="OK","ENTREGUE",IF(LANÇAMENTO[[#This Row],[PRAZO]]="","",LANÇAMENTO[[#This Row],[PREVISÃO ENTREGA OBRA]]-$E$1)) -> ENTREGUE | U94: OK | V94: MATERIAL PARA OBRA EE DAGOBERTTO SALES FILHO
A95: 45875 | B95: JOSE DE ALMEIDA PINHEIRO | C95: =VLOOKUP(LANÇAMENTO[[#This Row],[OBRA]],OBRAS[],2,FALSE) -> B&B | D95: HIDRAULICA | E95: AMANCO JOELHO 45 ESG. 100MM | F95: 24 | G95: UNID. | H95: 1787 | I95: CASA MIMOSA | J95: AMANCO JOELHO 45 ESG. 100MM | K95: 5.39 | L95: =LANÇAMENTO[[#This Row],[VALOR UNITARIO]]*LANÇAMENTO[[#This Row],[QTDADE]] -> 129.36 | M95: 45875 | N95: =TEXT(LANÇAMENTO[[#This Row],[DATA PEDIDO]],"MMM")&"-"&TEXT(M95,"AAAA") -> ago-2025 | O95: 28 | P95: BOLETO | Q95: RETIRA | R95: 1 | S95: =IF(LANÇAMENTO[[#This Row],[DATA PEDIDO]]="","",LANÇAMENTO[[#This Row],[DATA PEDIDO]]+LANÇAMENTO[[#This Row],[PRAZO]]) -> 45876 | T95: =IF(LANÇAMENTO[[#This Row],[OBRA COM MATERIAL]]="OK","ENTREGUE",IF(LANÇAMENTO[[#This Row],[PRAZO]]="","",LANÇAMENTO[[#This Row],[PREVISÃO ENTREGA OBRA]]-$E$1)) -> ENTREGUE | U95: OK | V95: MATERIAL PARA OBRA EE ANDRE FRANCO MONTORO
A96: 45875 | B96: JOSE DE ALMEIDA PINHEIRO | C96: =VLOOKUP(LANÇAMENTO[[#This Row],[OBRA]],OBRAS[],2,FALSE) -> B&B | D96: HIDRAULICA | E96: AMANCO LUVA SIMPLES ESG. 100MM | F96: 24 | G96: UNID. | H96: 1787 | I96: CASA MIMOSA | J96: AMANCO LUVA SIMPLES ESG. 100MM | K96: 3.88 | L96: =LANÇAMENTO[[#This Row],[VALOR UNITARIO]]*LANÇAMENTO[[#This Row],[QTDADE]] -> 93.12 | M96: 45875 | N96: =TEXT(LANÇAMENTO[[#This Row],[DATA PEDIDO]],"MMM")&"-"&TEXT(M96,"AAAA") -> ago-2025 | O96: 28 | P96: BOLETO | Q96: RETIRA | R96: 1 | S96: =IF(LANÇAMENTO[[#This Row],[DATA PEDIDO]]="","",LANÇAMENTO[[#This Row],[DATA PEDIDO]]+LANÇAMENTO[[#This Row],[PRAZO]]) -> 45876 | T96: =IF(LANÇAMENTO[[#This Row],[OBRA COM MATERIAL]]="OK","ENTREGUE",IF(LANÇAMENTO[[#This Row],[PRAZO]]="","",LANÇAMENTO[[#This Row],[PREVISÃO ENTREGA OBRA]]-$E$1)) -> ENTREGUE | U96: OK | V96: MATERIAL PARA OBRA EE ANDRE FRANCO MONTORO
A97: 45875 | B97: JOSE DE ALMEIDA PINHEIRO | C97: =VLOOKUP(LANÇAMENTO[[#This Row],[OBRA]],OBRAS[],2,FALSE) -> B&B | D97: HIDRAULICA | E97: ABRACADEIRA TIPO U GALV.OMEGA 4 | F97: 36 | G97: UNID. | H97: 1787 | I97: CASA MIMOSA | J97: ABRACADEIRA TIPO U GALV.OMEGA 4 | K97: 1.83 | L97: =LANÇAMENTO[[#This Row],[VALOR UNITARIO]]*LANÇAMENTO[[#This Row],[QTDADE]] -> 65.88 | M97: 45875 | N97: =TEXT(LANÇAMENTO[[#This Row],[DATA PEDIDO]],"MMM")&"-"&TEXT(M97,"AAAA") -> ago-2025 | O97: 28 | P97: BOLETO | Q97: RETIRA | R97: 1 | S97: =IF(LANÇAMENTO[[#This Row],[DATA PEDIDO]]="","",LANÇAMENTO[[#This Row],[DATA PEDIDO]]+LANÇAMENTO[[#This Row],[PRAZO]]) -> 45876 | T97: =IF(LANÇAMENTO[[#This Row],[OBRA COM MATERIAL]]="OK","ENTREGUE",IF(LANÇAMENTO[[#This Row],[PRAZO]]="","",LANÇAMENTO[[#This Row],[PREVISÃO ENTREGA OBRA]]-$E$1)) -> ENTREGUE | U97: OK | V97: MATERIAL PARA OBRA EE ANDRE FRANCO MONTORO
A98: 45875 | B98: JOSE DE ALMEIDA PINHEIRO | C98: =VLOOKUP(LANÇAMENTO[[#This Row],[OBRA]],OBRAS[],2,FALSE) -> B&B | D98: HIDRAULICA | E98: CMD BUCHA FIXACAO S-08 | F98: 100 | G98: UNID. | H98: 1787 | I98: CASA MIMOSA | J98: CMD BUCHA FIXACAO S-08 | K98: 0.06 | L98: =LANÇAMENTO[[#This Row],[VALOR UNITARIO]]*LANÇAMENTO[[#This Row],[QTDADE]] -> 6 | M98: 45875 | N98: =TEXT(LANÇAMENTO[[#This Row],[DATA PEDIDO]],"MMM")&"-"&TEXT(M98,"AAAA") -> ago-2025 | O98: 28 | P98: BOLETO | Q98: RETIRA | R98: 1 | S98: =IF(LANÇAMENTO[[#This Row],[DATA PEDIDO]]="","",LANÇAMENTO[[#This Row],[DATA PEDIDO]]+LANÇAMENTO[[#This Row],[PRAZO]]) -> 45876 | T98: =IF(LANÇAMENTO[[#This Row],[OBRA COM MATERIAL]]="OK","ENTREGUE",IF(LANÇAMENTO[[#This Row],[PRAZO]]="","",LANÇAMENTO[[#This Row],[PREVISÃO ENTREGA OBRA]]-$E$1)) -> ENTREGUE | U98: OK | V98: MATERIAL PARA OBRA EE ANDRE FRANCO MONTORO
A99: 45875 | B99: JOSE DE ALMEIDA PINHEIRO | C99: =VLOOKUP(LANÇAMENTO[[#This Row],[OBRA]],OBRAS[],2,FALSE) -> B&B | D99: HIDRAULICA | E99: CMD PARAF.A.ATARR.C/PHILLIPS P/B8 4,8X38 | F99: 100 | G99: UNID. | H99: 1787 | I99: CASA MIMOSA | J99: CMD PARAF.A.ATARR.C/PHILLIPS P/B8 4,8X38 | K99: 0.21 | L99: =LANÇAMENTO[[#This Row],[VALOR UNITARIO]]*LANÇAMENTO[[#This Row],[QTDADE]] -> 21 | M99: 45875 | N99: =TEXT(LANÇAMENTO[[#This Row],[DATA PEDIDO]],"MMM")&"-"&TEXT(M99,"AAAA") -> ago-2025 | O99: 28 | P99: BOLETO | Q99: RETIRA | R99: 1 | S99: =IF(LANÇAMENTO[[#This Row],[DATA PEDIDO]]="","",LANÇAMENTO[[#This Row],[DATA PEDIDO]]+LANÇAMENTO[[#This Row],[PRAZO]]) -> 45876 | T99: =IF(LANÇAMENTO[[#This Row],[OBRA COM MATERIAL]]="OK","ENTREGUE",IF(LANÇAMENTO[[#This Row],[PRAZO]]="","",LANÇAMENTO[[#This Row],[PREVISÃO ENTREGA OBRA]]-$E$1)) -> ENTREGUE | U99: OK | V99: MATERIAL PARA OBRA EE ANDRE FRANCO MONTORO
A100: 45875 | B100: JOSE DE ALMEIDA PINHEIRO | C100: =VLOOKUP(LANÇAMENTO[[#This Row],[OBRA]],OBRAS[],2,FALSE) -> B&B | D100: HIDRAULICA | E100: AMANCO ADESIVO PVC 850G | F100: 1 | G100: UNID. | H100: 1787 | I100: CASA MIMOSA | J100: AMANCO ADESIVO PVC 850G | K100: 35.76 | L100: =LANÇAMENTO[[#This Row],[VALOR UNITARIO]]*LANÇAMENTO[[#This Row],[QTDADE]] -> 35.76 | M100: 45875 | N100: =TEXT(LANÇAMENTO[[#This Row],[DATA PEDIDO]],"MMM")&"-"&TEXT(M100,"AAAA") -> ago-2025 | O100: 28 | P100: BOLETO | Q100: RETIRA | R100: 1 | S100: =IF(LANÇAMENTO[[#This Row],[DATA PEDIDO]]="","",LANÇAMENTO[[#This Row],[DATA PEDIDO]]+LANÇAMENTO[[#This Row],[PRAZO]]) -> 45876 | T100: =IF(LANÇAMENTO[[#This Row],[OBRA COM MATERIAL]]="OK","ENTREGUE",IF(LANÇAMENTO[[#This Row],[PRAZO]]="","",LANÇAMENTO[[#This Row],[PREVISÃO ENTREGA OBRA]]-$E$1)) -> ENTREGUE | U100: OK | V100: MATERIAL PARA OBRA EE ANDRE FRANCO MONTORO
A101: 45876 | B101: LEA APARECIDA | C101: =VLOOKUP(LANÇAMENTO[[#This Row],[OBRA]],OBRAS[],2,FALSE) -> INTERIORANA | D101: ELETRICA | E101: BARRA CHATA ALUMINIO 7/8 X 1/8 - 6MTS | F101: 10 | G101: BARRA | H101: 1788 | I101: AREA ELETRICOS | J101: BARRA CHATA ALUMINIO 7/8 X 1/8 - 6MTS | K101: 54.6 | L101: =LANÇAMENTO[[#This Row],[VALOR UNITARIO]]*LANÇAMENTO[[#This Row],[QTDADE]] -> 546 | M101: 45876 | N101: =TEXT(LANÇAMENTO[[#This Row],[DATA PEDIDO]],"MMM")&"-"&TEXT(M101,"AAAA") -> ago-2025 | O101: 30/60/90 | P101: BOLETO | Q101: ENTREGA | R101: 1 | S101: =IF(LANÇAMENTO[[#This Row],[DATA PEDIDO]]="","",LANÇAMENTO[[#This Row],[DATA PEDIDO]]+LANÇAMENTO[[#This Row],[PRAZO]]) -> 45877 | T101: =IF(LANÇAMENTO[[#This Row],[OBRA COM MATERIAL]]="OK","ENTREGUE",IF(LANÇAMENTO[[#This Row],[PRAZO]]="","",LANÇAMENTO[[#This Row],[PREVISÃO ENTREGA OBRA]]-$E$1)) -> ENTREGUE | U101: OK
A102: 45876 | B102: LEA APARECIDA | C102: =VLOOKUP(LANÇAMENTO[[#This Row],[OBRA]],OBRAS[],2,FALSE) -> INTERIORANA | D102: ELETRICA | E102: TERMINAL PRESSAO REFORCADO 50MM | F102: 8 | G102: UNID. | H102: 1788 | I102: AREA ELETRICOS | J102: TERMINAL PRESSAO REFORCADO 50MM | K102: 9.8 | L102: =LANÇAMENTO[[#This Row],[VALOR UNITARIO]]*LANÇAMENTO[[#This Row],[QTDADE]] -> 78.4 | M102: 45876 | N102: =TEXT(LANÇAMENTO[[#This Row],[DATA PEDIDO]],"MMM")&"-"&TEXT(M102,"AAAA") -> ago-2025 | O102: 30/60/90 | P102: BOLETO | Q102: ENTREGA | R102: 1 | S102: =IF(LANÇAMENTO[[#This Row],[DATA PEDIDO]]="","",LANÇAMENTO[[#This Row],[DATA PEDIDO]]+LANÇAMENTO[[#This Row],[PRAZO]]) -> 45877 | T102: =IF(LANÇAMENTO[[#This Row],[OBRA COM MATERIAL]]="OK","ENTREGUE",IF(LANÇAMENTO[[#This Row],[PRAZO]]="","",LANÇAMENTO[[#This Row],[PREVISÃO ENTREGA OBRA]]-$E$1)) -> ENTREGUE | U102: OK
A103: 45876 | B103: LEA APARECIDA | C103: =VLOOKUP(LANÇAMENTO[[#This Row],[OBRA]],OBRAS[],2,FALSE) -> INTERIORANA | D103: ELETRICA | E103: ELETRODUTO GALV LEVE 1 (0,50) C/LV | F103: 15 | G103: UNID. | H103: 1788 | I103: AREA ELETRICOS | J103: ELETRODUTO GALV LEVE 1 (0,50) C/LV | K103: 20 | L103: =LANÇAMENTO[[#This Row],[VALOR UNITARIO]]*LANÇAMENTO[[#This Row],[QTDADE]] -> 300 | M103: 45876 | N103: =TEXT(LANÇAMENTO[[#This Row],[DATA PEDIDO]],"MMM")&"-"&TEXT(M103,"AAAA") -> ago-2025 | O103: 30/60/90 | P103: BOLETO | Q103: ENTREGA | R103: 1 | S103: =IF(LANÇAMENTO[[#This Row],[DATA PEDIDO]]="","",LANÇAMENTO[[#This Row],[DATA PEDIDO]]+LANÇAMENTO[[#This Row],[PRAZO]]) -> 45877 | T103: =IF(LANÇAMENTO[[#This Row],[OBRA COM MATERIAL]]="OK","ENTREGUE",IF(LANÇAMENTO[[#This Row],[PRAZO]]="","",LANÇAMENTO[[#This Row],[PREVISÃO ENTREGA OBRA]]-$E$1)) -> ENTREGUE | U103: OK
A104: 45876 | B104: LEA APARECIDA | C104: =VLOOKUP(LANÇAMENTO[[#This Row],[OBRA]],OBRAS[],2,FALSE) -> INTERIORANA | D104: ELETRICA | E104: ABRACADEIRA GALV D C/CUNHA 1 | F104: 40 | G104: UNID. | H104: 1788 | I104: AREA ELETRICOS | J104: ABRACADEIRA GALV D C/CUNHA 1 | K104: 0.7 | L104: =LANÇAMENTO[[#This Row],[VALOR UNITARIO]]*LANÇAMENTO[[#This Row],[QTDADE]] -> 28 | M104: 45876 | N104: =TEXT(LANÇAMENTO[[#This Row],[DATA PEDIDO]],"MMM")&"-"&TEXT(M104,"AAAA") -> ago-2025 | O104: 30/60/90 | P104: BOLETO | Q104: ENTREGA | R104: 1 | S104: =IF(LANÇAMENTO[[#This Row],[DATA PEDIDO]]="","",LANÇAMENTO[[#This Row],[DATA PEDIDO]]+LANÇAMENTO[[#This Row],[PRAZO]]) -> 45877 | T104: =IF(LANÇAMENTO[[#This Row],[OBRA COM MATERIAL]]="OK","ENTREGUE",IF(LANÇAMENTO[[#This Row],[PRAZO]]="","",LANÇAMENTO[[#This Row],[PREVISÃO ENTREGA OBRA]]-$E$1)) -> ENTREGUE | U104: OK
A105: 45876 | B105: LEA APARECIDA | C105: =VLOOKUP(LANÇAMENTO[[#This Row],[OBRA]],OBRAS[],2,FALSE) -> INTERIORANA | D105: ELETRICA | E105: CONDULETE ALUM MULTIPLO X 1 S/T | F105: 5 | G105: UNID. | H105: 1788 | I105: AREA ELETRICOS | J105: CONDULETE ALUM MULTIPLO X 1 S/T | K105: 11.4 | L105: =LANÇAMENTO[[#This Row],[VALOR UNITARIO]]*LANÇAMENTO[[#This Row],[QTDADE]] -> 57 | M105: 45876 | N105: =TEXT(LANÇAMENTO[[#This Row],[DATA PEDIDO]],"MMM")&"-"&TEXT(M105,"AAAA") -> ago-2025 | O105: 30/60/90 | P105: BOLETO | Q105: ENTREGA | R105: 1 | S105: =IF(LANÇAMENTO[[#This Row],[DATA PEDIDO]]="","",LANÇAMENTO[[#This Row],[DATA PEDIDO]]+LANÇAMENTO[[#This Row],[PRAZO]]) -> 45877 | T105: =IF(LANÇAMENTO[[#This Row],[OBRA COM MATERIAL]]="OK","ENTREGUE",IF(LANÇAMENTO[[#This Row],[PRAZO]]="","",LANÇAMENTO[[#This Row],[PREVISÃO ENTREGA OBRA]]-$E$1)) -> ENTREGUE | U105: OK
A106: 45876 | B106: LEA APARECIDA | C106: =VLOOKUP(LANÇAMENTO[[#This Row],[OBRA]],OBRAS[],2,FALSE) -> INTERIORANA | D106: ELETRICA | E106: UNIDUT MULTIPLO ALUM 1 | F106: 10 | G106: UNID. | H106: 1788 | I106: AREA ELETRICOS | J106: UNIDUT MULTIPLO ALUM 1 | K106: 2.8 | L106: =LANÇAMENTO[[#This Row],[VALOR UNITARIO]]*LANÇAMENTO[[#This Row],[QTDADE]] -> 28 | M106: 45876 | N106: =TEXT(LANÇAMENTO[[#This Row],[DATA PEDIDO]],"MMM")&"-"&TEXT(M106,"AAAA") -> ago-2025 | O106: 30/60/90 | P106: BOLETO | Q106: ENTREGA | R106: 1 | S106: =IF(LANÇAMENTO[[#This Row],[DATA PEDIDO]]="","",LANÇAMENTO[[#This Row],[DATA PEDIDO]]+LANÇAMENTO[[#This Row],[PRAZO]]) -> 45877 | T106: =IF(LANÇAMENTO[[#This Row],[OBRA COM MATERIAL]]="OK","ENTREGUE",IF(LANÇAMENTO[[#This Row],[PRAZO]]="","",LANÇAMENTO[[#This Row],[PREVISÃO ENTREGA OBRA]]-$E$1)) -> ENTREGUE | U106: OK
A107: 45876 | B107: LEA APARECIDA | C107: =VLOOKUP(LANÇAMENTO[[#This Row],[OBRA]],OBRAS[],2,FALSE) -> INTERIORANA | D107: ELETRICA | E107: UNIDUT RETO ALUM 1 | F107: 6 | G107: UNID. | H107: 1788 | I107: AREA ELETRICOS | J107: UNIDUT RETO ALUM 1 | K107: 3 | L107: =LANÇAMENTO[[#This Row],[VALOR UNITARIO]]*LANÇAMENTO[[#This Row],[QTDADE]] -> 18 | M107: 45876 | N107: =TEXT(LANÇAMENTO[[#This Row],[DATA PEDIDO]],"MMM")&"-"&TEXT(M107,"AAAA") -> ago-2025 | O107: 30/60/90 | P107: BOLETO | Q107: ENTREGA | R107: 1 | S107: =IF(LANÇAMENTO[[#This Row],[DATA PEDIDO]]="","",LANÇAMENTO[[#This Row],[DATA PEDIDO]]+LANÇAMENTO[[#This Row],[PRAZO]]) -> 45877 | T107: =IF(LANÇAMENTO[[#This Row],[OBRA COM MATERIAL]]="OK","ENTREGUE",IF(LANÇAMENTO[[#This Row],[PRAZO]]="","",LANÇAMENTO[[#This Row],[PREVISÃO ENTREGA OBRA]]-$E$1)) -> ENTREGUE | U107: OK
A108: 45876 | B108: LEA APARECIDA | C108: =VLOOKUP(LANÇAMENTO[[#This Row],[OBRA]],OBRAS[],2,FALSE) -> INTERIORANA | D108: ELETRICA | E108: ELETRODUTO GALV LEVE 3/4 (0,50) C/LV | F108: 30 | G108: UNID. | H108: 1788 | I108: AREA ELETRICOS | J108: ELETRODUTO GALV LEVE 3/4 (0,50) C/LV | K108: 14 | L108: =LANÇAMENTO[[#This Row],[VALOR UNITARIO]]*LANÇAMENTO[[#This Row],[QTDADE]] -> 420 | M108: 45876 | N108: =TEXT(LANÇAMENTO[[#This Row],[DATA PEDIDO]],"MMM")&"-"&TEXT(M108,"AAAA") -> ago-2025 | O108: 30/60/90 | P108: BOLETO | Q108: ENTREGA | R108: 1 | S108: =IF(LANÇAMENTO[[#This Row],[DATA PEDIDO]]="","",LANÇAMENTO[[#This Row],[DATA PEDIDO]]+LANÇAMENTO[[#This Row],[PRAZO]]) -> 45877 | T108: =IF(LANÇAMENTO[[#This Row],[OBRA COM MATERIAL]]="OK","ENTREGUE",IF(LANÇAMENTO[[#This Row],[PRAZO]]="","",LANÇAMENTO[[#This Row],[PREVISÃO ENTREGA OBRA]]-$E$1)) -> ENTREGUE | U108: OK
A109: 45876 | B109: LEA APARECIDA | C109: =VLOOKUP(LANÇAMENTO[[#This Row],[OBRA]],OBRAS[],2,FALSE) -> INTERIORANA | D109: ELETRICA | E109: CONDULETE ALUM MULTI X 3/4 S/T | F109: 15 | G109: UNID. | H109: 1788 | I109: AREA ELETRICOS | J109: CONDULETE ALUM MULTI X 3/4 S/T | K109: 6.9 | L109: =LANÇAMENTO[[#This Row],[VALOR UNITARIO]]*LANÇAMENTO[[#This Row],[QTDADE]] -> 103.5 | M109: 45876 | N109: =TEXT(LANÇAMENTO[[#This Row],[DATA PEDIDO]],"MMM")&"-"&TEXT(M109,"AAAA") -> ago-2025 | O109: 30/60/90 | P109: BOLETO | Q109: ENTREGA | R109: 1 | S109: =IF(LANÇAMENTO[[#This Row],[DATA PEDIDO]]="","",LANÇAMENTO[[#This Row],[DATA PEDIDO]]+LANÇAMENTO[[#This Row],[PRAZO]]) -> 45877 | T109: =IF(LANÇAMENTO[[#This Row],[OBRA COM MATERIAL]]="OK","ENTREGUE",IF(LANÇAMENTO[[#This Row],[PRAZO]]="","",LANÇAMENTO[[#This Row],[PREVISÃO ENTREGA OBRA]]-$E$1)) -> ENTREGUE | U109: OK
A110: 45876 | B110: LEA APARECIDA | C110: =VLOOKUP(LANÇAMENTO[[#This Row],[OBRA]],OBRAS[],2,FALSE) -> INTERIORANA | D110: ELETRICA | E110: UNIDUT MULTIPLO ALUM 3/4 | F110: 45 | G110: UNID. | H110: 1788 | I110: AREA ELETRICOS | J110: UNIDUT MULTIPLO ALUM 3/4 | K110: 2.2 | L110: =LANÇAMENTO[[#This Row],[VALOR UNITARIO]]*LANÇAMENTO[[#This Row],[QTDADE]] -> 99 | M110: 45876 | N110: =TEXT(LANÇAMENTO[[#This Row],[DATA PEDIDO]],"MMM")&"-"&TEXT(M110,"AAAA") -> ago-2025 | O110: 30/60/90 | P110: BOLETO | Q110: ENTREGA | R110: 1 | S110: =IF(LANÇAMENTO[[#This Row],[DATA PEDIDO]]="","",LANÇAMENTO[[#This Row],[DATA PEDIDO]]+LANÇAMENTO[[#This Row],[PRAZO]]) -> 45877 | T110: =IF(LANÇAMENTO[[#This Row],[OBRA COM MATERIAL]]="OK","ENTREGUE",IF(LANÇAMENTO[[#This Row],[PRAZO]]="","",LANÇAMENTO[[#This Row],[PREVISÃO ENTREGA OBRA]]-$E$1)) -> ENTREGUE | U110: OK
A111: 45876 | B111: LEA APARECIDA | C111: =VLOOKUP(LANÇAMENTO[[#This Row],[OBRA]],OBRAS[],2,FALSE) -> INTERIORANA | D111: ELETRICA | E111: UNIDUT RETO ALUM 3/4 | F111: 25 | G111: UNID. | H111: 1788 | I111: AREA ELETRICOS | J111: UNIDUT RETO ALUM 3/4 | K111: 2.4 | L111: =LANÇAMENTO[[#This Row],[VALOR UNITARIO]]*LANÇAMENTO[[#This Row],[QTDADE]] -> 60 | M111: 45876 | N111: =TEXT(LANÇAMENTO[[#This Row],[DATA PEDIDO]],"MMM")&"-"&TEXT(M111,"AAAA") -> ago-2025 | O111: 30/60/90 | P111: BOLETO | Q111: ENTREGA | R111: 1 | S111: =IF(LANÇAMENTO[[#This Row],[DATA PEDIDO]]="","",LANÇAMENTO[[#This Row],[DATA PEDIDO]]+LANÇAMENTO[[#This Row],[PRAZO]]) -> 45877 | T111: =IF(LANÇAMENTO[[#This Row],[OBRA COM MATERIAL]]="OK","ENTREGUE",IF(LANÇAMENTO[[#This Row],[PRAZO]]="","",LANÇAMENTO[[#This Row],[PREVISÃO ENTREGA OBRA]]-$E$1)) -> ENTREGUE | U111: OK
A112: 45876 | B112: LEA APARECIDA | C112: =VLOOKUP(LANÇAMENTO[[#This Row],[OBRA]],OBRAS[],2,FALSE) -> INTERIORANA | D112: ELETRICA | E112: ABRACADEIRA GALV D C/CUNHA 3/4 | F112: 50 | G112: UNID. | H112: 1788 | I112: AREA ELETRICOS | J112: ABRACADEIRA GALV D C/CUNHA 3/4 | K112: 0.7 | L112: =LANÇAMENTO[[#This Row],[VALOR UNITARIO]]*LANÇAMENTO[[#This Row],[QTDADE]] -> 35 | M112: 45876 | N112: =TEXT(LANÇAMENTO[[#This Row],[DATA PEDIDO]],"MMM")&"-"&TEXT(M112,"AAAA") -> ago-2025 | O112: 30/60/90 | P112: BOLETO | Q112: ENTREGA | R112: 1 | S112: =IF(LANÇAMENTO[[#This Row],[DATA PEDIDO]]="","",LANÇAMENTO[[#This Row],[DATA PEDIDO]]+LANÇAMENTO[[#This Row],[PRAZO]]) -> 45877 | T112: =IF(LANÇAMENTO[[#This Row],[OBRA COM MATERIAL]]="OK","ENTREGUE",IF(LANÇAMENTO[[#This Row],[PRAZO]]="","",LANÇAMENTO[[#This Row],[PREVISÃO ENTREGA OBRA]]-$E$1)) -> ENTREGUE | U112: OK
... A145: 45876 | B145: JOSE DE ALMEIDA PINHEIRO | C145: =VLOOKUP(LANÇAMENTO[[#This Row],[OBRA]],OBRAS[],2,FALSE) -> B&B | D145: PINTURA | E145: ROMA 301/005 TRINCHA CABO PRETO/CERDA GRIS 301 2" | F145: 2 | G145: UNID. | H145: 1792 | I145: OLD RIVER | J145: ROMA 301/005 TRINCHA CABO PRETO/CERDA GRIS 301 2" | K145: 4.99 | L145: =LANÇAMENTO[[#This Row],[VALOR UNITARIO]]*LANÇAMENTO[[#This Row],[QTDADE]] -> 9.98 | M145: 45876 | N145: =TEXT(LANÇAMENTO[[#This Row],[DATA PEDIDO]],"MMM")&"-"&TEXT(M145,"AAAA") -> ago-2025 | O145: 28/42 | P145: BOLETO | Q145: RETIRA | R145: 0 | S145: =IF(LANÇAMENTO[[#This Row],[DATA PEDIDO]]="","",LANÇAMENTO[[#This Row],[DATA PEDIDO]]+LANÇAMENTO[[#This Row],[PRAZO]]) -> 45876 | T145: =IF(LANÇAMENTO[[#This Row],[OBRA COM MATERIAL]]="OK","ENTREGUE",IF(LANÇAMENTO[[#This Row],[PRAZO]]="","",LANÇAMENTO[[#This Row],[PREVISÃO ENTREGA OBRA]]-$E$1)) -> ENTREGUE | U145: OK
A146: 45876 | B146: SYLVIA DE MELLO | C146: =VLOOKUP(LANÇAMENTO[[#This Row],[OBRA]],OBRAS[],2,FALSE) -> B&B | D146: HIDRAULICA | E146: APOLO TUBO 6M GALV.NBR 5580 L 3/4" 26,9X2,25MM | F146: 18 | G146: M | H146: 1793 | I146: CASA MIMOSA | J146: APOLO TUBO 6M GALV.NBR 5580 L 3/4" 26,9X2,25MM | K146: 20.56 | L146: =LANÇAMENTO[[#This Row],[VALOR UNITARIO]]*LANÇAMENTO[[#This Row],[QTDADE]] -> 370.08 | M146: 45876 | N146: =TEXT(LANÇAMENTO[[#This Row],[DATA PEDIDO]],"MMM")&"-"&TEXT(M146,"AAAA") -> ago-2025 | O146: 28 | P146: BOLETO | Q146: RETIRA | R146: 1 | S146: =IF(LANÇAMENTO[[#This Row],[DATA PEDIDO]]="","",LANÇAMENTO[[#This Row],[DATA PEDIDO]]+LANÇAMENTO[[#This Row],[PRAZO]]) -> 45877 | T146: =IF(LANÇAMENTO[[#This Row],[OBRA COM MATERIAL]]="OK","ENTREGUE",IF(LANÇAMENTO[[#This Row],[PRAZO]]="","",LANÇAMENTO[[#This Row],[PREVISÃO ENTREGA OBRA]]-$E$1)) -> ENTREGUE | U146: OK | V146: MATERIA PARA OBRA WADIH JORGE FATURADO B&B
A147: 45876 | B147: SYLVIA DE MELLO | C147: =VLOOKUP(LANÇAMENTO[[#This Row],[OBRA]],OBRAS[],2,FALSE) -> B&B | D147: HIDRAULICA | E147: TUPY COTOVELO 90 GALV. 3/4 | F147: 5 | G147: UNID. | H147: 1793 | I147: CASA MIMOSA | J147: TUPY COTOVELO 90 GALV. 3/4 | K147: 11.1 | L147: =LANÇAMENTO[[#This Row],[VALOR UNITARIO]]*LANÇAMENTO[[#This Row],[QTDADE]] -> 55.5 | M147: 45876 | N147: =TEXT(LANÇAMENTO[[#This Row],[DATA PEDIDO]],"MMM")&"-"&TEXT(M147,"AAAA") -> ago-2025 | O147: 28 | P147: BOLETO | Q147: RETIRA | R147: 1 | S147: =IF(LANÇAMENTO[[#This Row],[DATA PEDIDO]]="","",LANÇAMENTO[[#This Row],[DATA PEDIDO]]+LANÇAMENTO[[#This Row],[PRAZO]]) -> 45877 | T147: =IF(LANÇAMENTO[[#This Row],[OBRA COM MATERIAL]]="OK","ENTREGUE",IF(LANÇAMENTO[[#This Row],[PRAZO]]="","",LANÇAMENTO[[#This Row],[PREVISÃO ENTREGA OBRA]]-$E$1)) -> ENTREGUE | U147: OK | V147: MATERIA PARA OBRA WADIH JORGE FATURADO B&B
A148: 45876 | B148: SYLVIA DE MELLO | C148: =VLOOKUP(LANÇAMENTO[[#This Row],[OBRA]],OBRAS[],2,FALSE) -> B&B | D148: HIDRAULICA | E148: TUPY LUVA GALV. 3/4 | F148: 3 | G148: UNID. | H148: 1793 | I148: CASA MIMOSA | J148: TUPY LUVA GALV. 3/4 | K148: 9.32 | L148: =LANÇAMENTO[[#This Row],[VALOR UNITARIO]]*LANÇAMENTO[[#This Row],[QTDADE]] -> 27.96 | M148: 45876 | N148: =TEXT(LANÇAMENTO[[#This Row],[DATA PEDIDO]],"MMM")&"-"&TEXT(M148,"AAAA") -> ago-2025 | O148: 28 | P148: BOLETO | Q148: RETIRA | R148: 1 | S148: =IF(LANÇAMENTO[[#This Row],[DATA PEDIDO]]="","",LANÇAMENTO[[#This Row],[DATA PEDIDO]]+LANÇAMENTO[[#This Row],[PRAZO]]) -> 45877 | T148: =IF(LANÇAMENTO[[#This Row],[OBRA COM MATERIAL]]="OK","ENTREGUE",IF(LANÇAMENTO[[#This Row],[PRAZO]]="","",LANÇAMENTO[[#This Row],[PREVISÃO ENTREGA OBRA]]-$E$1)) -> ENTREGUE | U148: OK | V148: MATERIA PARA OBRA WADIH JORGE FATURADO B&B
A149: 45876 | B149: SYLVIA DE MELLO | C149: =VLOOKUP(LANÇAMENTO[[#This Row],[OBRA]],OBRAS[],2,FALSE) -> B&B | D149: HIDRAULICA | E149: SCOPO VEDA ROSCA 18MM X 50 MT | F149: 2 | G149: ROLO | H149: 1793 | I149: CASA MIMOSA | J149: SCOPO VEDA ROSCA 18MM X 50 MT | K149: 6.03 | L149: =LANÇAMENTO[[#This Row],[VALOR UNITARIO]]*LANÇAMENTO[[#This Row],[QTDADE]] -> 12.06 | M149: 45876 | N149: =TEXT(LANÇAMENTO[[#This Row],[DATA PEDIDO]],"MMM")&"-"&TEXT(M149,"AAAA") -> ago-2025 | O149: 28 | P149: BOLETO | Q149: RETIRA | R149: 1 | S149: =IF(LANÇAMENTO[[#This Row],[DATA PEDIDO]]="","",LANÇAMENTO[[#This Row],[DATA PEDIDO]]+LANÇAMENTO[[#This Row],[PRAZO]]) -> 45877 | T149: =IF(LANÇAMENTO[[#This Row],[OBRA COM MATERIAL]]="OK","ENTREGUE",IF(LANÇAMENTO[[#This Row],[PRAZO]]="","",LANÇAMENTO[[#This Row],[PREVISÃO ENTREGA OBRA]]-$E$1)) -> ENTREGUE | U149: OK | V149: MATERIA PARA OBRA WADIH JORGE FATURADO B&B
A150: 45876 | B150: SYLVIA DE MELLO | C150: =VLOOKUP(LANÇAMENTO[[#This Row],[OBRA]],OBRAS[],2,FALSE) -> B&B | D150: HIDRAULICA | E150: VEDACIT NEUTROL 900ML | F150: 1 | G150: LATA | H150: 1793 | I150: CASA MIMOSA | J150: VEDACIT NEUTROL 900ML | K150: 42.09 | L150: =LANÇAMENTO[[#This Row],[VALOR UNITARIO]]*LANÇAMENTO[[#This Row],[QTDADE]] -> 42.09 | M150: 45876 | N150: =TEXT(LANÇAMENTO[[#This Row],[DATA PEDIDO]],"MMM")&"-"&TEXT(M150,"AAAA") -> ago-2025 | O150: 28 | P150: BOLETO | Q150: RETIRA | R150: 1 | S150: =IF(LANÇAMENTO[[#This Row],[DATA PEDIDO]]="","",LANÇAMENTO[[#This Row],[DATA PEDIDO]]+LANÇAMENTO[[#This Row],[PRAZO]]) -> 45877 | T150: =IF(LANÇAMENTO[[#This Row],[OBRA COM MATERIAL]]="OK","ENTREGUE",IF(LANÇAMENTO[[#This Row],[PRAZO]]="","",LANÇAMENTO[[#This Row],[PREVISÃO ENTREGA OBRA]]-$E$1)) -> ENTREGUE | U150: OK | V150: MATERIA PARA OBRA WADIH JORGE FATURADO B&B
A151: 45877 | B151: CRISTIANE CHAVES | C151: =VLOOKUP(LANÇAMENTO[[#This Row],[OBRA]],OBRAS[],2,FALSE) -> INTERIORANA | D151: LOCAÇÃO | E151: BANHEIRO QUIMICO STANDARD COM 2 LIMPEZAS SEMANAIS | F151: 1 | G151: VERBA | H151: 1794 | I151: RENT MAX | J151: BANHEIRO QUIMICO STANDARD COM 2 LIMPEZAS SEMANAIS | K151: 1300 | L151: =LANÇAMENTO[[#This Row],[VALOR UNITARIO]]*LANÇAMENTO[[#This Row],[QTDADE]] -> 1300 | M151: 45877 | N151: =TEXT(LANÇAMENTO[[#This Row],[DATA PEDIDO]],"MMM")&"-"&TEXT(M151,"AAAA") -> ago-2025 | O151: 28 | P151: BOLETO | Q151: ENTREGA | R151: 0 | S151: =IF(LANÇAMENTO[[#This Row],[DATA PEDIDO]]="","",LANÇAMENTO[[#This Row],[DATA PEDIDO]]+LANÇAMENTO[[#This Row],[PRAZO]]) -> 45877 | T151: =IF(LANÇAMENTO[[#This Row],[OBRA COM MATERIAL]]="OK","ENTREGUE",IF(LANÇAMENTO[[#This Row],[PRAZO]]="","",LANÇAMENTO[[#This Row],[PREVISÃO ENTREGA OBRA]]-$E$1)) -> ENTREGUE | U151: OK
A152: 45877 | B152: MARIA DE LOURDES | C152: =VLOOKUP(LANÇAMENTO[[#This Row],[OBRA]],OBRAS[],2,FALSE) -> INTERIORANA | D152: LOCAÇÃO | E152: ANDAIME 1,5 | F152: 16 | G152: UNID. | H152: 1795 | I152: GALIETA LOCAÇÕES | J152: ANDAIME 1,5 | K152: 10.5 | L152: =LANÇAMENTO[[#This Row],[VALOR UNITARIO]]*LANÇAMENTO[[#This Row],[QTDADE]] -> 168 | M152: 45877 | N152: =TEXT(LANÇAMENTO[[#This Row],[DATA PEDIDO]],"MMM")&"-"&TEXT(M152,"AAAA") -> ago-2025 | O152: 28 | P152: BOLETO | Q152: ENTREGA | R152: 0 | S152: =IF(LANÇAMENTO[[#This Row],[DATA PEDIDO]]="","",LANÇAMENTO[[#This Row],[DATA PEDIDO]]+LANÇAMENTO[[#This Row],[PRAZO]]) -> 45877 | T152: =IF(LANÇAMENTO[[#This Row],[OBRA COM MATERIAL]]="OK","ENTREGUE",IF(LANÇAMENTO[[#This Row],[PRAZO]]="","",LANÇAMENTO[[#This Row],[PREVISÃO ENTREGA OBRA]]-$E$1)) -> ENTREGUE | U152: OK
A153: 45877 | B153: MARIA DE LOURDES | C153: =VLOOKUP(LANÇAMENTO[[#This Row],[OBRA]],OBRAS[],2,FALSE) -> INTERIORANA | D153: LOCAÇÃO | E153: PLATAFORMA 1,5 | F153: 8 | G153: UNID. | H153: 1795 | I153: GALIETA LOCAÇÕES | J153: PLATAFORMA 1,5 | K153: 21 | L153: =LANÇAMENTO[[#This Row],[VALOR UNITARIO]]*LANÇAMENTO[[#This Row],[QTDADE]] -> 168 | M153: 45877 | N153: =TEXT(LANÇAMENTO[[#This Row],[DATA PEDIDO]],"MMM")&"-"&TEXT(M153,"AAAA") -> ago-2025 | O153: 28 | P153: BOLETO | Q153: ENTREGA | R153: 0 | S153: =IF(LANÇAMENTO[[#This Row],[DATA PEDIDO]]="","",LANÇAMENTO[[#This Row],[DATA PEDIDO]]+LANÇAMENTO[[#This Row],[PRAZO]]) -> 45877 | T153: =IF(LANÇAMENTO[[#This Row],[OBRA COM MATERIAL]]="OK","ENTREGUE",IF(LANÇAMENTO[[#This Row],[PRAZO]]="","",LANÇAMENTO[[#This Row],[PREVISÃO ENTREGA OBRA]]-$E$1)) -> ENTREGUE | U153: OK
A154: 45877 | B154: MARIA DE LOURDES | C154: =VLOOKUP(LANÇAMENTO[[#This Row],[OBRA]],OBRAS[],2,FALSE) -> INTERIORANA | D154: LOCAÇÃO | E154: DIAGONAL 1,5 | F154: 2 | G154: UNID. | H154: 1795 | I154: GALIETA LOCAÇÕES | J154: DIAGONAL 1,5 | K154: 0 | L154: =LANÇAMENTO[[#This Row],[VALOR UNITARIO]]*LANÇAMENTO[[#This Row],[QTDADE]] -> 0 | M154: 45877 | N154: =TEXT(LANÇAMENTO[[#This Row],[DATA PEDIDO]],"MMM")&"-"&TEXT(M154,"AAAA") -> ago-2025 | O154: 28 | P154: BOLETO | Q154: ENTREGA | R154: 0 | S154: =IF(LANÇAMENTO[[#This Row],[DATA PEDIDO]]="","",LANÇAMENTO[[#This Row],[DATA PEDIDO]]+LANÇAMENTO[[#This Row],[PRAZO]]) -> 45877 | T154: =IF(LANÇAMENTO[[#This Row],[OBRA COM MATERIAL]]="OK","ENTREGUE",IF(LANÇAMENTO[[#This Row],[PRAZO]]="","",LANÇAMENTO[[#This Row],[PREVISÃO ENTREGA OBRA]]-$E$1)) -> ENTREGUE | U154: OK
A155: 45877 | B155: ERICO VERISSIMO | C155: =VLOOKUP(LANÇAMENTO[[#This Row],[OBRA]],OBRAS[],2,FALSE) -> INTERIORANA | D155: LOCAÇÃO | E155: 40 PÇAS DE ANDAIMES 1 X 1,500 | F155: 30 | G155: VERBA | H155: 1796 | I155: ASAP | J155: 40 PÇAS DE ANDAIMES 1 X 1,500 | K155: 16 | L155: =LANÇAMENTO[[#This Row],[VALOR UNITARIO]]*LANÇAMENTO[[#This Row],[QTDADE]] -> 480 | M155: 45877 | N155: =TEXT(LANÇAMENTO[[#This Row],[DATA PEDIDO]],"MMM")&"-"&TEXT(M155,"AAAA") -> ago-2025 | O155: 28 | P155: BOLETO | Q155: ENTREGA | R155: 0 | S155: =IF(LANÇAMENTO[[#This Row],[DATA PEDIDO]]="","",LANÇAMENTO[[#This Row],[DATA PEDIDO]]+LANÇAMENTO[[#This Row],[PRAZO]]) -> 45877 | T155: =IF(LANÇAMENTO[[#This Row],[OBRA COM MATERIAL]]="OK","ENTREGUE",IF(LANÇAMENTO[[#This Row],[PRAZO]]="","",LANÇAMENTO[[#This Row],[PREVISÃO ENTREGA OBRA]]-$E$1)) -> ENTREGUE | U155: OK
A156: 45877 | B156: ERICO VERISSIMO | C156: =VLOOKUP(LANÇAMENTO[[#This Row],[OBRA]],OBRAS[],2,FALSE) -> INTERIORANA | D156: LOCAÇÃO | E156: 08 PISOS METALICO 1500 X 370 | F156: 30 | G156: VERBA | H156: 1796 | I156: ASAP | J156: 08 PISOS METALICO 1500 X 370 | K156: 4.4 | L156: =LANÇAMENTO[[#This Row],[VALOR UNITARIO]]*LANÇAMENTO[[#This Row],[QTDADE]] -> 132 | M156: 45877 | N156: =TEXT(LANÇAMENTO[[#This Row],[DATA PEDIDO]],"MMM")&"-"&TEXT(M156,"AAAA") -> ago-2025 | O156: 28 | P156: BOLETO | Q156: ENTREGA | R156: 0 | S156: =IF(LANÇAMENTO[[#This Row],[DATA PEDIDO]]="","",LANÇAMENTO[[#This Row],[DATA PEDIDO]]+LANÇAMENTO[[#This Row],[PRAZO]]) -> 45877 | T156: =IF(LANÇAMENTO[[#This Row],[OBRA COM MATERIAL]]="OK","ENTREGUE",IF(LANÇAMENTO[[#This Row],[PRAZO]]="","",LANÇAMENTO[[#This Row],[PREVISÃO ENTREGA OBRA]]-$E$1)) -> ENTREGUE | U156: OK
A157: 45877 | B157: ERICO VERISSIMO | C157: =VLOOKUP(LANÇAMENTO[[#This Row],[OBRA]],OBRAS[],2,FALSE) -> INTERIORANA | D157: LOCAÇÃO | E157: 10 DIAGONAL TRAVAS | F157: 30 | G157: VERBA | H157: 1796 | I157: ASAP | J157: 10 DIAGONAL TRAVAS | K157: 3 | L157: =LANÇAMENTO[[#This Row],[VALOR UNITARIO]]*LANÇAMENTO[[#This Row],[QTDADE]] -> 90 | M157: 45877 | N157: =TEXT(LANÇAMENTO[[#This Row],[DATA PEDIDO]],"MMM")&"-"&TEXT(M157,"AAAA") -> ago-2025 | O157: 28 | P157: BOLETO | Q157: ENTREGA | R157: 0 | S157: =IF(LANÇAMENTO[[#This Row],[DATA PEDIDO]]="","",LANÇAMENTO[[#This Row],[DATA PEDIDO]]+LANÇAMENTO[[#This Row],[PRAZO]]) -> 45877 | T157: =IF(LANÇAMENTO[[#This Row],[OBRA COM MATERIAL]]="OK","ENTREGUE",IF(LANÇAMENTO[[#This Row],[PRAZO]]="","",LANÇAMENTO[[#This Row],[PREVISÃO ENTREGA OBRA]]-$E$1)) -> ENTREGUE | U157: OK
A158: 45877 | B158: ERICO VERISSIMO | C158: =VLOOKUP(LANÇAMENTO[[#This Row],[OBRA]],OBRAS[],2,FALSE) -> INTERIORANA | D158: LOCAÇÃO | E158: 08 RODAS DE POLIURETANO P/ ANDAIMES | F158: 30 | G158: VERBA | H158: 1796 | I158: ASAP | J158: 08 RODAS DE POLIURETANO P/ ANDAIMES | K158: 4 | L158: =LANÇAMENTO[[#This Row],[VALOR UNITARIO]]*LANÇAMENTO[[#This Row],[QTDADE]] -> 120 | M158: 45877 | N158: =TEXT(LANÇAMENTO[[#This Row],[DATA PEDIDO]],"MMM")&"-"&TEXT(M158,"AAAA") -> ago-2025 | O158: 28 | P158: BOLETO | Q158: ENTREGA | R158: 0 | S158: =IF(LANÇAMENTO[[#This Row],[DATA PEDIDO]]="","",LANÇAMENTO[[#This Row],[DATA PEDIDO]]+LANÇAMENTO[[#This Row],[PRAZO]]) -> 45877 | T158: =IF(LANÇAMENTO[[#This Row],[OBRA COM MATERIAL]]="OK","ENTREGUE",IF(LANÇAMENTO[[#This Row],[PRAZO]]="","",LANÇAMENTO[[#This Row],[PREVISÃO ENTREGA OBRA]]-$E$1)) -> ENTREGUE | U158: OK
A159: 45877 | B159: ANTONIO NUNES LOPES | C159: =VLOOKUP(LANÇAMENTO[[#This Row],[OBRA]],OBRAS[],2,FALSE) -> B&B | D159: LOCAÇÃO | E159: GUARDA CORPO S/ PORTA C/ ROD. METALSAFE 1.50m | F159: 8 | G159: UNID. | H159: 1797 | I159: CASA DO CONSTRUTOR P.G | J159: GUARDA CORPO S/ PORTA C/ ROD. METALSAFE 1.50m | K159: 25.3 | L159: =LANÇAMENTO[[#This Row],[VALOR UNITARIO]]*LANÇAMENTO[[#This Row],[QTDADE]] -> 202.4 | M159: 45877 | N159: =TEXT(LANÇAMENTO[[#This Row],[DATA PEDIDO]],"MMM")&"-"&TEXT(M159,"AAAA") -> ago-2025 | O159: 15 | P159: BOLETO | Q159: ENTREGA | R159: 0 | S159: =IF(LANÇAMENTO[[#This Row],[DATA PEDIDO]]="","",LANÇAMENTO[[#This Row],[DATA PEDIDO]]+LANÇAMENTO[[#This Row],[PRAZO]]) -> 45877 | T159: =IF(LANÇAMENTO[[#This Row],[OBRA COM MATERIAL]]="OK","ENTREGUE",IF(LANÇAMENTO[[#This Row],[PRAZO]]="","",LANÇAMENTO[[#This Row],[PREVISÃO ENTREGA OBRA]]-$E$1)) -> ENTREGUE | U159: OK
A160: 45877 | B160: ANTONIO NUNES LOPES | C160: =VLOOKUP(LANÇAMENTO[[#This Row],[OBRA]],OBRAS[],2,FALSE) -> B&B | D160: LOCAÇÃO | E160: BARRA LIGACAO METALSAFE 1.50m A | F160: 4 | G160: UNID. | H160: 1797 | I160: CASA DO CONSTRUTOR P.G | J160: BARRA LIGACAO METALSAFE 1.50m A | K160: 3.45 | L160: =LANÇAMENTO[[#This Row],[VALOR UNITARIO]]*LANÇAMENTO[[#This Row],[QTDADE]] -> 13.8 | M160: 45877 | N160: =TEXT(LANÇAMENTO[[#This Row],[DATA PEDIDO]],"MMM")&"-"&TEXT(M160,"AAAA") -> ago-2025 | O160: 15 | P160: BOLETO | Q160: ENTREGA | R160: 0 | S160: =IF(LANÇAMENTO[[#This Row],[DATA PEDIDO]]="","",LANÇAMENTO[[#This Row],[DATA PEDIDO]]+LANÇAMENTO[[#This Row],[PRAZO]]) -> 45877 | T160: =IF(LANÇAMENTO[[#This Row],[OBRA COM MATERIAL]]="OK","ENTREGUE",IF(LANÇAMENTO[[#This Row],[PRAZO]]="","",LANÇAMENTO[[#This Row],[PREVISÃO ENTREGA OBRA]]-$E$1)) -> ENTREGUE | U160: OK
A161: 45877 | B161: ANTONIO NUNES LOPES | C161: =VLOOKUP(LANÇAMENTO[[#This Row],[OBRA]],OBRAS[],2,FALSE) -> B&B | D161: LOCAÇÃO | E161: ESCADA METALICA DIVERSOS 2.00m | F161: 6 | G161: UNID. | H161: 1797 | I161: CASA DO CONSTRUTOR P.G | J161: ESCADA METALICA DIVERSOS 2.00m | K161: 25.3 | L161: =LANÇAMENTO[[#This Row],[VALOR UNITARIO]]*LANÇAMENTO[[#This Row],[QTDADE]] -> 151.8 | M161: 45877 | N161: =TEXT(LANÇAMENTO[[#This Row],[DATA PEDIDO]],"MMM")&"-"&TEXT(M161,"AAAA") -> ago-2025 | O161: 15 | P161: BOLETO | Q161: ENTREGA | R161: 0 | S161: =IF(LANÇAMENTO[[#This Row],[DATA PEDIDO]]="","",LANÇAMENTO[[#This Row],[DATA PEDIDO]]+LANÇAMENTO[[#This Row],[PRAZO]]) -> 45877 | T161: =IF(LANÇAMENTO[[#This Row],[OBRA COM MATERIAL]]="OK","ENTREGUE",IF(LANÇAMENTO[[#This Row],[PRAZO]]="","",LANÇAMENTO[[#This Row],[PREVISÃO ENTREGA OBRA]]-$E$1)) -> ENTREGUE | U161: OK
A162: 45877 | B162: WADIH JORGE MALUF | C162: =VLOOKUP(LANÇAMENTO[[#This Row],[OBRA]],OBRAS[],2,FALSE) -> INTERIORANA | D162: REVESTMENTO / PISO | E162: PORC. YORK SGR 87,7XS7,7 REI ex 1,54 POR | F162: 90.86 | G162: M2 | H162: 1798 | I162: TELHA NORTE | J162: PORC. YORK SGR 87,7XS7,7 REI ex 1,54 POR | K162: 89.9 | L162: =LANÇAMENTO[[#This Row],[VALOR UNITARIO]]*LANÇAMENTO[[#This Row],[QTDADE]] -> 8168.314 | M162: 45877 | N162: =TEXT(LANÇAMENTO[[#This Row],[DATA PEDIDO]],"MMM")&"-"&TEXT(M162,"AAAA") -> ago-2025 | O162: 28/56/84/112 | P162: BOLETO | Q162: ENTREGA | R162: 5 | S162: =IF(LANÇAMENTO[[#This Row],[DATA PEDIDO]]="","",LANÇAMENTO[[#This Row],[DATA PEDIDO]]+LANÇAMENTO[[#This Row],[PRAZO]]) -> 45882 | T162: =IF(LANÇAMENTO[[#This Row],[OBRA COM MATERIAL]]="OK","ENTREGUE",IF(LANÇAMENTO[[#This Row],[PRAZO]]="","",LANÇAMENTO[[#This Row],[PREVISÃO ENTREGA OBRA]]-$E$1)) -> ENTREGUE | U162: OK
... A204: 45881 | B204: WADIH JORGE MALUF | C204: =VLOOKUP(LANÇAMENTO[[#This Row],[OBRA]],OBRAS[],2,FALSE) -> INTERIORANA | D204: OUTROS | E204: CIMENTO 50KG VOTORAN | F204: 10 | G204: SACO | H204: 1813 | I204: AZEFER MATERIAIS | J204: CIMENTO 50KG VOTORAN | K204: 34.9 | L204: =LANÇAMENTO[[#This Row],[VALOR UNITARIO]]*LANÇAMENTO[[#This Row],[QTDADE]] -> 349 | M204: 45881 | N204: =TEXT(LANÇAMENTO[[#This Row],[DATA PEDIDO]],"MMM")&"-"&TEXT(M204,"AAAA") -> ago-2025 | O204: 7 | P204: BOLETO | Q204: ENTREGA | R204: 1 | S204: =IF(LANÇAMENTO[[#This Row],[DATA PEDIDO]]="","",LANÇAMENTO[[#This Row],[DATA PEDIDO]]+LANÇAMENTO[[#This Row],[PRAZO]]) -> 45882 | T204: =IF(LANÇAMENTO[[#This Row],[OBRA COM MATERIAL]]="OK","ENTREGUE",IF(LANÇAMENTO[[#This Row],[PRAZO]]="","",LANÇAMENTO[[#This Row],[PREVISÃO ENTREGA OBRA]]-$E$1)) -> ENTREGUE | U204: OK
A205: 45881 | B205: JOSE DE ALMEIDA PINHEIRO | C205: =VLOOKUP(LANÇAMENTO[[#This Row],[OBRA]],OBRAS[],2,FALSE) -> B&B | D205: HIDRAULICA | E205: AMANCO JOELHO 90 ESG. 75MM | F205: 3 | G205: UNID. | H205: 1814 | I205: CASA MIMOSA | J205: AMANCO JOELHO 90 ESG. 75MM | K205: 3.56 | L205: =LANÇAMENTO[[#This Row],[VALOR UNITARIO]]*LANÇAMENTO[[#This Row],[QTDADE]] -> 10.68 | M205: 45881 | N205: =TEXT(LANÇAMENTO[[#This Row],[DATA PEDIDO]],"MMM")&"-"&TEXT(M205,"AAAA") -> ago-2025 | O205: 28 | P205: BOLETO | Q205: RETIRA | R205: 1 | S205: =IF(LANÇAMENTO[[#This Row],[DATA PEDIDO]]="","",LANÇAMENTO[[#This Row],[DATA PEDIDO]]+LANÇAMENTO[[#This Row],[PRAZO]]) -> 45882 | T205: =IF(LANÇAMENTO[[#This Row],[OBRA COM MATERIAL]]="OK","ENTREGUE",IF(LANÇAMENTO[[#This Row],[PRAZO]]="","",LANÇAMENTO[[#This Row],[PREVISÃO ENTREGA OBRA]]-$E$1)) -> ENTREGUE | U205: OK | V205: MATERIAL PARA OBRA WADIH JORGE FATURADO B&B
A206: 45881 | B206: JOSE DE ALMEIDA PINHEIRO | C206: =VLOOKUP(LANÇAMENTO[[#This Row],[OBRA]],OBRAS[],2,FALSE) -> B&B | D206: HIDRAULICA | E206: AMANCO TE RD ESG. 75X50 | F206: 3 | G206: UNID. | H206: 1814 | I206: CASA MIMOSA | J206: AMANCO TE RD ESG. 75X50 | K206: 11.48 | L206: =LANÇAMENTO[[#This Row],[VALOR UNITARIO]]*LANÇAMENTO[[#This Row],[QTDADE]] -> 34.44 | M206: 45881 | N206: =TEXT(LANÇAMENTO[[#This Row],[DATA PEDIDO]],"MMM")&"-"&TEXT(M206,"AAAA") -> ago-2025 | O206: 28 | P206: BOLETO | Q206: RETIRA | R206: 1 | S206: =IF(LANÇAMENTO[[#This Row],[DATA PEDIDO]]="","",LANÇAMENTO[[#This Row],[DATA PEDIDO]]+LANÇAMENTO[[#This Row],[PRAZO]]) -> 45882 | T206: =IF(LANÇAMENTO[[#This Row],[OBRA COM MATERIAL]]="OK","ENTREGUE",IF(LANÇAMENTO[[#This Row],[PRAZO]]="","",LANÇAMENTO[[#This Row],[PREVISÃO ENTREGA OBRA]]-$E$1)) -> ENTREGUE | U206: OK | V206: MATERIAL PARA OBRA WADIH JORGE FATURADO B&B
A207: 45881 | B207: JOSE DE ALMEIDA PINHEIRO | C207: =VLOOKUP(LANÇAMENTO[[#This Row],[OBRA]],OBRAS[],2,FALSE) -> B&B | D207: HIDRAULICA | E207: AMANCO JOELHO 90 SOLD. 40MM | F207: 3 | G207: UNID. | H207: 1814 | I207: CASA MIMOSA | J207: AMANCO JOELHO 90 SOLD. 40MM | K207: 3.75 | L207: =LANÇAMENTO[[#This Row],[VALOR UNITARIO]]*LANÇAMENTO[[#This Row],[QTDADE]] -> 11.25 | M207: 45881 | N207: =TEXT(LANÇAMENTO[[#This Row],[DATA PEDIDO]],"MMM")&"-"&TEXT(M207,"AAAA") -> ago-2025 | O207: 28 | P207: BOLETO | Q207: RETIRA | R207: 1 | S207: =IF(LANÇAMENTO[[#This Row],[DATA PEDIDO]]="","",LANÇAMENTO[[#This Row],[DATA PEDIDO]]+LANÇAMENTO[[#This Row],[PRAZO]]) -> 45882 | T207: =IF(LANÇAMENTO[[#This Row],[OBRA COM MATERIAL]]="OK","ENTREGUE",IF(LANÇAMENTO[[#This Row],[PRAZO]]="","",LANÇAMENTO[[#This Row],[PREVISÃO ENTREGA OBRA]]-$E$1)) -> ENTREGUE | U207: OK | V207: MATERIAL PARA OBRA WADIH JORGE FATURADO B&B
A208: 45881 | B208: JOSE DE ALMEIDA PINHEIRO | C208: =VLOOKUP(LANÇAMENTO[[#This Row],[OBRA]],OBRAS[],2,FALSE) -> B&B | D208: HIDRAULICA | E208: DECA BASE GAVETA 4509 402 1.1/4 | F208: 2 | G208: UNID. | H208: 1814 | I208: CASA MIMOSA | J208: DECA BASE GAVETA 4509 402 1.1/4 | K208: 82.8 | L208: =LANÇAMENTO[[#This Row],[VALOR UNITARIO]]*LANÇAMENTO[[#This Row],[QTDADE]] -> 165.6 | M208: 45881 | N208: =TEXT(LANÇAMENTO[[#This Row],[DATA PEDIDO]],"MMM")&"-"&TEXT(M208,"AAAA") -> ago-2025 | O208: 28 | P208: BOLETO | Q208: RETIRA | R208: 1 | S208: =IF(LANÇAMENTO[[#This Row],[DATA PEDIDO]]="","",LANÇAMENTO[[#This Row],[DATA PEDIDO]]+LANÇAMENTO[[#This Row],[PRAZO]]) -> 45882 | T208: =IF(LANÇAMENTO[[#This Row],[OBRA COM MATERIAL]]="OK","ENTREGUE",IF(LANÇAMENTO[[#This Row],[PRAZO]]="","",LANÇAMENTO[[#This Row],[PREVISÃO ENTREGA OBRA]]-$E$1)) -> ENTREGUE | U208: OK | V208: MATERIAL PARA OBRA WADIH JORGE FATURADO B&B
A209: 45881 | B209: JOSE DE ALMEIDA PINHEIRO | C209: =VLOOKUP(LANÇAMENTO[[#This Row],[OBRA]],OBRAS[],2,FALSE) -> B&B | D209: HIDRAULICA | E209: CEMIX ACABAMENTO C50 1.1/2 | F209: 2 | G209: UNID. | H209: 1814 | I209: CASA MIMOSA | J209: CEMIX ACABAMENTO C50 1.1/2 | K209: 15.34 | L209: =LANÇAMENTO[[#This Row],[VALOR UNITARIO]]*LANÇAMENTO[[#This Row],[QTDADE]] -> 30.68 | M209: 45881 | N209: =TEXT(LANÇAMENTO[[#This Row],[DATA PEDIDO]],"MMM")&"-"&TEXT(M209,"AAAA") -> ago-2025 | O209: 28 | P209: BOLETO | Q209: RETIRA | R209: 1 | S209: =IF(LANÇAMENTO[[#This Row],[DATA PEDIDO]]="","",LANÇAMENTO[[#This Row],[DATA PEDIDO]]+LANÇAMENTO[[#This Row],[PRAZO]]) -> 45882 | T209: =IF(LANÇAMENTO[[#This Row],[OBRA COM MATERIAL]]="OK","ENTREGUE",IF(LANÇAMENTO[[#This Row],[PRAZO]]="","",LANÇAMENTO[[#This Row],[PREVISÃO ENTREGA OBRA]]-$E$1)) -> ENTREGUE | U209: OK | V209: MATERIAL PARA OBRA WADIH JORGE FATURADO B&B
A210: 45881 | B210: JOSE DE ALMEIDA PINHEIRO | C210: =VLOOKUP(LANÇAMENTO[[#This Row],[OBRA]],OBRAS[],2,FALSE) -> B&B | D210: HIDRAULICA | E210: AMANCO ADAPT. CURTO SOLD. 40X1.1/4 | F210: 4 | G210: UNID. | H210: 1814 | I210: CASA MIMOSA | J210: AMANCO ADAPT. CURTO SOLD. 40X1.1/4 | K210: 3.04 | L210: =LANÇAMENTO[[#This Row],[VALOR UNITARIO]]*LANÇAMENTO[[#This Row],[QTDADE]] -> 12.16 | M210: 45881 | N210: =TEXT(LANÇAMENTO[[#This Row],[DATA PEDIDO]],"MMM")&"-"&TEXT(M210,"AAAA") -> ago-2025 | O210: 28 | P210: BOLETO | Q210: RETIRA | R210: 1 | S210: =IF(LANÇAMENTO[[#This Row],[DATA PEDIDO]]="","",LANÇAMENTO[[#This Row],[DATA PEDIDO]]+LANÇAMENTO[[#This Row],[PRAZO]]) -> 45882 | T210: =IF(LANÇAMENTO[[#This Row],[OBRA COM MATERIAL]]="OK","ENTREGUE",IF(LANÇAMENTO[[#This Row],[PRAZO]]="","",LANÇAMENTO[[#This Row],[PREVISÃO ENTREGA OBRA]]-$E$1)) -> ENTREGUE | U210: OK | V210: MATERIAL PARA OBRA WADIH JORGE FATURADO B&B
A211: 45881 | B211: JOSE DE ALMEIDA PINHEIRO | C211: =VLOOKUP(LANÇAMENTO[[#This Row],[OBRA]],OBRAS[],2,FALSE) -> B&B | D211: HIDRAULICA | E211: AMANCO JOELHO 90 SOLD. 40MM | F211: 6 | G211: UNID. | H211: 1814 | I211: CASA MIMOSA | J211: AMANCO JOELHO 90 SOLD. 40MM | K211: 3.75 | L211: =LANÇAMENTO[[#This Row],[VALOR UNITARIO]]*LANÇAMENTO[[#This Row],[QTDADE]] -> 22.5 | M211: 45881 | N211: =TEXT(LANÇAMENTO[[#This Row],[DATA PEDIDO]],"MMM")&"-"&TEXT(M211,"AAAA") -> ago-2025 | O211: 28 | P211: BOLETO | Q211: RETIRA | R211: 1 | S211: =IF(LANÇAMENTO[[#This Row],[DATA PEDIDO]]="","",LANÇAMENTO[[#This Row],[DATA PEDIDO]]+LANÇAMENTO[[#This Row],[PRAZO]]) -> 45882 | T211: =IF(LANÇAMENTO[[#This Row],[OBRA COM MATERIAL]]="OK","ENTREGUE",IF(LANÇAMENTO[[#This Row],[PRAZO]]="","",LANÇAMENTO[[#This Row],[PREVISÃO ENTREGA OBRA]]-$E$1)) -> ENTREGUE | U211: OK | V211: MATERIAL PARA OBRA WADIH JORGE FATURADO B&B
A212: 45881 | B212: JOSE DE ALMEIDA PINHEIRO | C212: =VLOOKUP(LANÇAMENTO[[#This Row],[OBRA]],OBRAS[],2,FALSE) -> B&B | D212: HIDRAULICA | E212: AMANCO TE RD SOLD. 40X25 | F212: 2 | G212: UNID. | H212: 1814 | I212: CASA MIMOSA | J212: AMANCO TE RD SOLD. 40X25 | K212: 6.79 | L212: =LANÇAMENTO[[#This Row],[VALOR UNITARIO]]*LANÇAMENTO[[#This Row],[QTDADE]] -> 13.58 | M212: 45881 | N212: =TEXT(LANÇAMENTO[[#This Row],[DATA PEDIDO]],"MMM")&"-"&TEXT(M212,"AAAA") -> ago-2025 | O212: 28 | P212: BOLETO | Q212: RETIRA | R212: 1 | S212: =IF(LANÇAMENTO[[#This Row],[DATA PEDIDO]]="","",LANÇAMENTO[[#This Row],[DATA PEDIDO]]+LANÇAMENTO[[#This Row],[PRAZO]]) -> 45882 | T212: =IF(LANÇAMENTO[[#This Row],[OBRA COM MATERIAL]]="OK","ENTREGUE",IF(LANÇAMENTO[[#This Row],[PRAZO]]="","",LANÇAMENTO[[#This Row],[PREVISÃO ENTREGA OBRA]]-$E$1)) -> ENTREGUE | U212: OK | V212: MATERIAL PARA OBRA WADIH JORGE FATURADO B&B
A213: 45881 | B213: JOSE DE ALMEIDA PINHEIRO | C213: =VLOOKUP(LANÇAMENTO[[#This Row],[OBRA]],OBRAS[],2,FALSE) -> B&B | D213: HIDRAULICA | E213: HF FILT.CARVAO ATIV.9.3/4" 120L/H TR 907-0018 | F213: 1 | G213: UNID. | H213: 1814 | I213: CASA MIMOSA | J213: HF FILT.CARVAO ATIV.9.3/4" 120L/H TR 907-0018 | K213: 107.27 | L213: =LANÇAMENTO[[#This Row],[VALOR UNITARIO]]*LANÇAMENTO[[#This Row],[QTDADE]] -> 107.27 | M213: 45881 | N213: =TEXT(LANÇAMENTO[[#This Row],[DATA PEDIDO]],"MMM")&"-"&TEXT(M213,"AAAA") -> ago-2025 | O213: 28 | P213: BOLETO | Q213: RETIRA | R213: 1 | S213: =IF(LANÇAMENTO[[#This Row],[DATA PEDIDO]]="","",LANÇAMENTO[[#This Row],[DATA PEDIDO]]+LANÇAMENTO[[#This Row],[PRAZO]]) -> 45882 | T213: =IF(LANÇAMENTO[[#This Row],[OBRA COM MATERIAL]]="OK","ENTREGUE",IF(LANÇAMENTO[[#This Row],[PRAZO]]="","",LANÇAMENTO[[#This Row],[PREVISÃO ENTREGA OBRA]]-$E$1)) -> ENTREGUE | U213: OK | V213: MATERIAL PARA OBRA WADIH JORGE FATURADO B&B
A214: 45881 | B214: WADIH JORGE MALUF | C214: =VLOOKUP(LANÇAMENTO[[#This Row],[OBRA]],OBRAS[],2,FALSE) -> INTERIORANA | D214: ELETRICA | E214: BARRAM BIFASICO CEMARPLAST II 4386 DIN 28 100A | F214: 1 | G214: UNID. | H214: 1815 | I214: UEHARA ELETRICA | J214: BARRAM BIFASICO CEMARPLAST II 4386 DIN 28 100A | K214: 183.117 | L214: =LANÇAMENTO[[#This Row],[VALOR UNITARIO]]*LANÇAMENTO[[#This Row],[QTDADE]] -> 183.117 | M214: 45881 | N214: =TEXT(LANÇAMENTO[[#This Row],[DATA PEDIDO]],"MMM")&"-"&TEXT(M214,"AAAA") -> ago-2025 | O214: 28 | P214: BOLETO | Q214: RETIRA | R214: 0 | S214: =IF(LANÇAMENTO[[#This Row],[DATA PEDIDO]]="","",LANÇAMENTO[[#This Row],[DATA PEDIDO]]+LANÇAMENTO[[#This Row],[PRAZO]]) -> 45881 | T214: =IF(LANÇAMENTO[[#This Row],[OBRA COM MATERIAL]]="OK","ENTREGUE",IF(LANÇAMENTO[[#This Row],[PRAZO]]="","",LANÇAMENTO[[#This Row],[PREVISÃO ENTREGA OBRA]]-$E$1)) -> ENTREGUE | U214: OK
A215: 45881 | B215: WADIH JORGE MALUF | C215: =VLOOKUP(LANÇAMENTO[[#This Row],[OBRA]],OBRAS[],2,FALSE) -> INTERIORANA | D215: ELETRICA | E215: CONDUITE CORRUGADO PVC AMARELO ADTEX 25MM | F215: 1 | G215: UNID. | H215: 1815 | I215: UEHARA ELETRICA | J215: CONDUITE CORRUGADO PVC AMARELO ADTEX 25MM | K215: 54.702 | L215: =LANÇAMENTO[[#This Row],[VALOR UNITARIO]]*LANÇAMENTO[[#This Row],[QTDADE]] -> 54.702 | M215: 45881 | N215: =TEXT(LANÇAMENTO[[#This Row],[DATA PEDIDO]],"MMM")&"-"&TEXT(M215,"AAAA") -> ago-2025 | O215: 28 | P215: BOLETO | Q215: RETIRA | R215: 0 | S215: =IF(LANÇAMENTO[[#This Row],[DATA PEDIDO]]="","",LANÇAMENTO[[#This Row],[DATA PEDIDO]]+LANÇAMENTO[[#This Row],[PRAZO]]) -> 45881 | T215: =IF(LANÇAMENTO[[#This Row],[OBRA COM MATERIAL]]="OK","ENTREGUE",IF(LANÇAMENTO[[#This Row],[PRAZO]]="","",LANÇAMENTO[[#This Row],[PREVISÃO ENTREGA OBRA]]-$E$1)) -> ENTREGUE | U215: OK
A216: 45881 | B216: WADIH JORGE MALUF | C216: =VLOOKUP(LANÇAMENTO[[#This Row],[OBRA]],OBRAS[],2,FALSE) -> INTERIORANA | D216: ELETRICA | E216: CX DE LUZ PVC TRAMONTINA 4X2 AM | F216: 25 | G216: UNID. | H216: 1815 | I216: UEHARA ELETRICA | J216: CX DE LUZ PVC TRAMONTINA 4X2 AM | K216: 0.932 | L216: =LANÇAMENTO[[#This Row],[VALOR UNITARIO]]*LANÇAMENTO[[#This Row],[QTDADE]] -> 23.3 | M216: 45881 | N216: =TEXT(LANÇAMENTO[[#This Row],[DATA PEDIDO]],"MMM")&"-"&TEXT(M216,"AAAA") -> ago-2025 | O216: 28 | P216: BOLETO | Q216: RETIRA | R216: 0 | S216: =IF(LANÇAMENTO[[#This Row],[DATA PEDIDO]]="","",LANÇAMENTO[[#This Row],[DATA PEDIDO]]+LANÇAMENTO[[#This Row],[PRAZO]]) -> 45881 | T216: =IF(LANÇAMENTO[[#This Row],[OBRA COM MATERIAL]]="OK","ENTREGUE",IF(LANÇAMENTO[[#This Row],[PRAZO]]="","",LANÇAMENTO[[#This Row],[PREVISÃO ENTREGA OBRA]]-$E$1)) -> ENTREGUE | U216: OK
A217: 45881 | B217: WADIH JORGE MALUF | C217: =VLOOKUP(LANÇAMENTO[[#This Row],[OBRA]],OBRAS[],2,FALSE) -> INTERIORANA | D217: ELETRICA | E217: QUADRO CEMAR II EMB S/B 4362 28/20 100A | F217: 1 | G217: UNID. | H217: 1815 | I217: UEHARA ELETRICA | J217: QUADRO CEMAR II EMB S/B 4362 28/20 100A | K217: 225.41 | L217: =LANÇAMENTO[[#This Row],[VALOR UNITARIO]]*LANÇAMENTO[[#This Row],[QTDADE]] -> 225.41 | M217: 45881 | N217: =TEXT(LANÇAMENTO[[#This Row],[DATA PEDIDO]],"MMM")&"-"&TEXT(M217,"AAAA") -> ago-2025 | O217: 28 | P217: BOLETO | Q217: RETIRA | R217: 0 | S217: =IF(LANÇAMENTO[[#This Row],[DATA PEDIDO]]="","",LANÇAMENTO[[#This Row],[DATA PEDIDO]]+LANÇAMENTO[[#This Row],[PRAZO]]) -> 45881 | T217: =IF(LANÇAMENTO[[#This Row],[OBRA COM MATERIAL]]="OK","ENTREGUE",IF(LANÇAMENTO[[#This Row],[PRAZO]]="","",LANÇAMENTO[[#This Row],[PREVISÃO ENTREGA OBRA]]-$E$1)) -> ENTREGUE | U217: OK
A218: 45881 | B218: WADIH JORGE MALUF | C218: =VLOOKUP(LANÇAMENTO[[#This Row],[OBRA]],OBRAS[],2,FALSE) -> INTERIORANA | D218: LOCAÇÃO | E218: 1 CAÇAMBA | F218: 1 | G218: VERBA | H218: 1816 | I218: HVR LOCAÇÃO | J218: 1 CAÇAMBA | K218: 440 | L218: =LANÇAMENTO[[#This Row],[VALOR UNITARIO]]*LANÇAMENTO[[#This Row],[QTDADE]] -> 440 | M218: 45881 | N218: =TEXT(LANÇAMENTO[[#This Row],[DATA PEDIDO]],"MMM")&"-"&TEXT(M218,"AAAA") -> ago-2025 | O218: 7 | P218: BOLETO | Q218: ENTREGA | R218: 1 | S218: =IF(LANÇAMENTO[[#This Row],[DATA PEDIDO]]="","",LANÇAMENTO[[#This Row],[DATA PEDIDO]]+LANÇAMENTO[[#This Row],[PRAZO]]) -> 45882 | T218: =IF(LANÇAMENTO[[#This Row],[OBRA COM MATERIAL]]="OK","ENTREGUE",IF(LANÇAMENTO[[#This Row],[PRAZO]]="","",LANÇAMENTO[[#This Row],[PREVISÃO ENTREGA OBRA]]-$E$1)) -> ENTREGUE | U218: OK
A219: 45881 | B219: MARIA DE LOURDES | C219: =VLOOKUP(LANÇAMENTO[[#This Row],[OBRA]],OBRAS[],2,FALSE) -> INTERIORANA | D219: OUTROS | E219: TELA POP 3.4 2.00X3.00 MT 20X20 - Q45 | F219: 10 | G219: UNID. | H219: 1817 | I219: AZEFER MATERIAIS | J219: TELA POP 3.4 2.00X3.00 MT 20X20 - Q45 | K219: 44.6 | L219: =LANÇAMENTO[[#This Row],[VALOR UNITARIO]]*LANÇAMENTO[[#This Row],[QTDADE]] -> 446 | M219: 45881 | N219: =TEXT(LANÇAMENTO[[#This Row],[DATA PEDIDO]],"MMM")&"-"&TEXT(M219,"AAAA") -> ago-2025 | O219: 7 | P219: BOLETO | Q219: ENTREGA | R219: 1 | S219: =IF(LANÇAMENTO[[#This Row],[DATA PEDIDO]]="","",LANÇAMENTO[[#This Row],[DATA PEDIDO]]+LANÇAMENTO[[#This Row],[PRAZO]]) -> 45882 | T219: =IF(LANÇAMENTO[[#This Row],[OBRA COM MATERIAL]]="OK","ENTREGUE",IF(LANÇAMENTO[[#This Row],[PRAZO]]="","",LANÇAMENTO[[#This Row],[PREVISÃO ENTREGA OBRA]]-$E$1)) -> ENTREGUE | U219: OK
A220: 45881 | B220: ALDEIA BANANAL | C220: =VLOOKUP(LANÇAMENTO[[#This Row],[OBRA]],OBRAS[],2,FALSE) -> B&B | D220: VIDRO / CAIXILHARIA | E220: VITRO BASCULANTE C/3 FOLHAS, C/2 MODULOS (BANHEIRO) | F220: 3 | G220: UNID. | H220: 1818 | I220: RH ESQUADRIAS E VIDROS | J220: VITRO BASCULANTE C/3 FOLHAS, C/2 MODULOS (BANHEIRO) | K220: 753.53 | L220: =LANÇAMENTO[[#This Row],[VALOR UNITARIO]]*LANÇAMENTO[[#This Row],[QTDADE]] -> 2260.59 | M220: 45881 | N220: =TEXT(LANÇAMENTO[[#This Row],[DATA PEDIDO]],"MMM")&"-"&TEXT(M220,"AAAA") -> ago-2025 | O220: 28/56/84 | P220: BOLETO | Q220: ENTREGA | R220: 15 | S220: =IF(LANÇAMENTO[[#This Row],[DATA PEDIDO]]="","",LANÇAMENTO[[#This Row],[DATA PEDIDO]]+LANÇAMENTO[[#This Row],[PRAZO]]) -> 45896 | T220: =IF(LANÇAMENTO[[#This Row],[OBRA COM MATERIAL]]="OK","ENTREGUE",IF(LANÇAMENTO[[#This Row],[PRAZO]]="","",LANÇAMENTO[[#This Row],[PREVISÃO ENTREGA OBRA]]-$E$1)) -> ENTREGUE | U220: OK
A221: 45881 | B221: ALDEIA BANANAL | C221: =VLOOKUP(LANÇAMENTO[[#This Row],[OBRA]],OBRAS[],2,FALSE) -> B&B | D221: VIDRO / CAIXILHARIA | E221: VITRO BASCULANTE C/6 FOLHAS (COZINHA) | F221: 4 | G221: UNID. | H221: 1818 | I221: RH ESQUADRIAS E VIDROS | J221: VITRO BASCULANTE C/6 FOLHAS (COZINHA) | K221: 994.11 | L221: =LANÇAMENTO[[#This Row],[VALOR UNITARIO]]*LANÇAMENTO[[#This Row],[QTDADE]] -> 3976.44 | M221: 45881 | N221: =TEXT(LANÇAMENTO[[#This Row],[DATA PEDIDO]],"MMM")&"-"&TEXT(M221,"AAAA") -> ago-2025 | O221: 28/56/84 | P221: BOLETO | Q221: ENTREGA | R221: 15 | S221: =IF(LANÇAMENTO[[#This Row],[DATA PEDIDO]]="","",LANÇAMENTO[[#This Row],[DATA PEDIDO]]+LANÇAMENTO[[#This Row],[PRAZO]]) -> 45896 | T221: =IF(LANÇAMENTO[[#This Row],[OBRA COM MATERIAL]]="OK","ENTREGUE",IF(LANÇAMENTO[[#This Row],[PRAZO]]="","",LANÇAMENTO[[#This Row],[PREVISÃO ENTREGA OBRA]]-$E$1)) -> ENTREGUE | U221: OK
...

Sheet Planilha1

Sheet Planilha2

Sheet Planilha3

Sheet PEDIDOS EMITIDOS
A1: DATA PEDIDO | B1: 46128
E2: COMPRADOR: | F2: IURY
A3: PEDIDO | B3: FORNECEDOR | C3: OBRA | D3: CONDIÇÃO PAGAMENTO | E3: FORMA DE PAGAMENTO | F3: Soma de VALOR TOTAL
A4: 2570 | B4: LEROY MERLIN | C4: ANTONIO NUNES LOPES | D4: 0 | E4: PIX | F4: 97.68
A5: 2571 | B5: RENNOVA LOCAÇÕES | C5: MARIA RITA ARAÚJO | D5: 28 | E5: BOLETO | F5: 390
A6: Total Geral | F6: 487.68

Sheet BASE PEDIDO
A1: PEDIDO | B1: 2575
A3: DATA PEDIDO | B3: PRAZO | C3: RETIRA OU ENTREGA | D3: ESCOLA | E3: FORNECEDOR | F3: CONDIÇÃO PAGAMENTO | G3: FORMA DE PAGAMENTO | H3: DESCRIÇÃO MATERIAL | I3: UNID | J3: QTDADE | K3: VALOR UNITARIO | L3: FATURAMENTO | M3: Soma de VALOR TOTAL
A4: 46129 | B4: 5 | C4: ENTREGA | D4: ELIAS MASSUD | E4: TELHA NORTE | F4: 28/56/84/112 | G4: BOLETO | H4: REJ CERAMIC CINZA PLATINA5KG QUARTZOLIT | I4: SACO | J4: 20 | K4: 49.41 | L4: INTERIORANA | M4: 988.2
A5: 46129 | B5: 5 | C5: ENTREGA | D5: ELIAS MASSUD | E5: TELHA NORTE | F5: 28/56/84/112 | G5: BOLETO | H5: ARG PORCEL INT CZ 20KGQUARTZOLIT | I5: SACO | J5: 120 | K5: 21.51 | L5: INTERIORANA | M5: 2581.2
A6: 46129 | B6: 5 | C6: ENTREGA | D6: ELIAS MASSUD | E6: TELHA NORTE | F6: 28/56/84/112 | G6: BOLETO | H6: PORC MUNARI BRANCO AC60X60 RET | I6: M2 | J6: 300.6 | K6: 79.03 | L6: INTERIORANA | M6: 23756.418
A7: 46129 | B7: 5 | C7: ENTREGA | D7: ELIAS MASSUD | E7: TELHA NORTE | F7: 28/56/84/112 | G7: BOLETO | H7: DESCONTO TOTAL | I7: VERBA | J7: 1 | K7: -131.79 | L7: INTERIORANA | M7: -131.79

Sheet JB IMPRIMIR
M1: JB CONSTRUÇÕES E EMPREENDIMENTOS LTDA
M2: Av luis dummount vilares 2078, São Paulo, Brazil 02239-000
M3: Telefone: (11) 3313-8220
M4: e-mail: compras2@brasulconstrutora.com.br
C6: DATA: | D6: ='BASE PEDIDO'!A4 -> 46129 | H6: PEDIDO DE COMPRA | K6: Nº | L6: ='BASE PEDIDO'!B1 -> 2575
L7: ='BASE PEDIDO'!D4 -> ELIAS MASSUD
B9: Razão Social: | E9: =VLOOKUP(E10,FORNECEDOR[#All],2,FALSE) -> SAINT-GOBAIN DISTRIBUIÇÃO BRASUL LTDA
B10: Fornecedor: | E10: ='BASE PEDIDO'!E4 -> TELHA NORTE | J10: Vendedor: | K10: =VLOOKUP(E10,FORNECEDOR[#All],4,FALSE) -> Augusto
B11: E-mail: | E11: =VLOOKUP(E10,FORNECEDOR[#All],3,FALSE) -> augusto.endes@saint-gobain.com | J11: Telefone: | K11: =VLOOKUP(E10,FORNECEDOR[#All],5,FALSE) -> 11 9.8510-6170
B13: Endereço de Cobrança: Rua Coronel Jordão, 440 /450 | I13: Bairro: Vila Paiva | L13: CEP: 02075-030
B14: Cidade: São Paulo | I14: UF: SP | L14: Comprador: IURY
B16: Faturamento: | E16: =MID(B17,1,2) -> 28 | F16: =IF(E16="","","dias") -> dias | G16: ='BASE PEDIDO'!G4 -> BOLETO | H16: =IF(G16="PIX",VLOOKUP(E10,FORNECEDOR[#All],6,FALSE),"") | K16: Estimativa de vencimento: | L16: =$L$22+E16 -> 46162
B17: ='BASE PEDIDO'!F4 -> 28/56/84/112 | E17: =MID(B17,4,2) -> 56 | F17: =IF(E17="","","dias") -> dias | H17: =IF(G16="PIX",VLOOKUP(E10,FORNECEDOR[#All],7,FALSE),"") | L17: =$L$22+E17 -> 46190
B18: {=_xlfn.TEXTSPLIT(C17," ")} -> #VALUE! | C18: OBS: CONTAR FATURAMENTO A PARTIR DO DIA 27/12/24 PARA MANTER OS FATURAMENTOS ANTERIORES DA JB | E18: =MID(B17,7,2) -> 84 | F18: =IF(E18="","","dias") -> dias | L18: =$L$22+E18 -> 46218
E19: =MID(B17,10,3) -> 112 | F19: =IF(E19="","","dias") -> dias | L19: =IF(E19=""," ",$D$6+E19) -> 46241
B20: OBSERVAÇÃO: | E20: NOTA FISCAL DEVE SER FATURADA EM NOME DA EMPRESA | I20: =IF('BASE PEDIDO'!L4="JB","JB CONSTRUÇÕES E EMPREENDIMENTOS LTDA",IF('BASE PEDIDO'!L4="JB CONSTRUÇÕES E EMPREENDIMENTOS LTDA","JB CONSTRUÇÕES E EMPREENDIMENTOS LTDA","JB CONSTRUÇÕES E EMPREENDIMENTOS LTDA")) -> JB CONSTRUÇÕES E EMPREENDIMENTOS LTDA
B22: PRAZO | D22: ='BASE PEDIDO'!C4 -> ENTREGA | F22: ='BASE PEDIDO'!B4 -> 5 | G22: dias | K22: ="DATA PREVISTA DA "&'BASE PEDIDO'!C4 -> DATA PREVISTA DA ENTREGA | L22: =F22+D6 -> 46134
B24: Local de Entrega: | E24: =VLOOKUP(L7,OBRAS[#All],4,FALSE) -> Rua Prof Fauze Calil 30 | H24: Bairro: | I24: =VLOOKUP(L7,OBRAS[#All],5,FALSE) -> Centro
B25: OBRA: | D25: =VLOOKUP(L7,OBRAS[#All],3,FALSE) -> E.E Dr Elias Massud | H25: Contrato Obra: | I25: =VLOOKUP(L7,OBRAS[#All],7,FALSE) -> 0
B26: CEP: | D26: =VLOOKUP(L7,OBRAS[#All],6,FALSE) -> 13190-000 | H26: Cidade: | I26: =VLOOKUP(L7,OBRAS[#All],8,FALSE) -> Monte Mor | K26: UF: | L26: =VLOOKUP(L7,OBRAS[#All],9,FALSE) -> SP
C29: ITEM | D29: DESCRIÇÃO | I29: QTDADE | J29: UNID. | K29: VALOR UNITÁRIO | L29: VALOR TOTAL
C31: 1 | D31: ='BASE PEDIDO'!H4 -> REJ CERAMIC CINZA PLATINA5KG QUARTZOLIT | I31: ='BASE PEDIDO'!J4 -> 20 | J31: ='BASE PEDIDO'!I4 -> SACO | K31: ='BASE PEDIDO'!K4 -> 49.41 | L31: =I31*K31 -> 988.2
C32: 2 | D32: ='BASE PEDIDO'!H5 -> ARG PORCEL INT CZ 20KGQUARTZOLIT | I32: ='BASE PEDIDO'!J5 -> 120 | J32: ='BASE PEDIDO'!I5 -> SACO | K32: ='BASE PEDIDO'!K5 -> 21.51 | L32: =I32*K32 -> 2581.2
C33: 3 | D33: ='BASE PEDIDO'!H6 -> PORC MUNARI BRANCO AC60X60 RET | I33: ='BASE PEDIDO'!J6 -> 300.6 | J33: ='BASE PEDIDO'!I6 -> M2 | K33: ='BASE PEDIDO'!K6 -> 79.03 | L33: =I33*K33 -> 23756.418
C34: 4 | D34: ='BASE PEDIDO'!H7 -> DESCONTO TOTAL | I34: ='BASE PEDIDO'!J7 -> 1 | J34: ='BASE PEDIDO'!I7 -> VERBA | K34: ='BASE PEDIDO'!K7 -> -131.79 | L34: =I34*K34 -> -131.79
C35: 5 | D35: ='BASE PEDIDO'!H8 -> 0 | I35: ='BASE PEDIDO'!J8 -> 0 | J35: ='BASE PEDIDO'!I8 -> 0 | K35: ='BASE PEDIDO'!K8 -> 0 | L35: =I35*K35 -> 0
C36: 6 | D36: ='BASE PEDIDO'!H9 -> 0 | I36: ='BASE PEDIDO'!J9 -> 0 | J36: ='BASE PEDIDO'!I9 -> 0 | K36: ='BASE PEDIDO'!K9 -> 0 | L36: =I36*K36 -> 0
C37: 7 | D37: ='BASE PEDIDO'!H10 -> 0 | I37: ='BASE PEDIDO'!J10 -> 0 | J37: ='BASE PEDIDO'!I10 -> 0 | K37: ='BASE PEDIDO'!K10 -> 0 | L37: =I37*K37 -> 0
C38: 8 | D38: ='BASE PEDIDO'!H11 -> 0 | I38: ='BASE PEDIDO'!J11 -> 0 | J38: ='BASE PEDIDO'!I11 -> 0 | K38: ='BASE PEDIDO'!K11 -> 0 | L38: =I38*K38 -> 0
C39: 9 | D39: ='BASE PEDIDO'!H12 -> 0 | I39: ='BASE PEDIDO'!J12 -> 0 | J39: ='BASE PEDIDO'!I12 -> 0 | K39: ='BASE PEDIDO'!K12 -> 0 | L39: =I39*K39 -> 0
C40: 10 | D40: ='BASE PEDIDO'!H13 -> 0 | I40: ='BASE PEDIDO'!J13 -> 0 | J40: ='BASE PEDIDO'!I13 -> 0 | K40: ='BASE PEDIDO'!K13 -> 0 | L40: =I40*K40 -> 0
C41: 11 | D41: ='BASE PEDIDO'!H14 -> 0 | I41: ='BASE PEDIDO'!J14 -> 0 | J41: ='BASE PEDIDO'!I14 -> 0 | K41: ='BASE PEDIDO'!K14 -> 0 | L41: =I41*K41 -> 0
C42: 12 | D42: ='BASE PEDIDO'!H15 -> 0 | I42: ='BASE PEDIDO'!J15 -> 0 | J42: ='BASE PEDIDO'!I15 -> 0 | K42: ='BASE PEDIDO'!K15 -> 0 | L42: =I42*K42 -> 0
... C60: 30 | D60: ='BASE PEDIDO'!H33 -> 0 | I60: ='BASE PEDIDO'!J33 -> 0 | J60: ='BASE PEDIDO'!I33 -> 0 | K60: ='BASE PEDIDO'!K33 -> 0 | L60: =I60*K60 -> 0
K61: SUB TOTAL | L61: =SUM(L31:L60)-L62 -> 27194.028
K62: DESCONTO | L62: =SUMIF(D31:D58,"DESCONTO",L31:L58) -> 0
K63: TOTAL | L63: =L61+L62 -> 27194.028
L65: Horario de RECEBIMENTO NA OBRA
L66: Segunda a Quinta-feira das 07:30h às 11:30h e das 13:00h as 15:30h
L67: Sexta-feira das 07:30h às 11:30h e das 13:00h as 14:30h

Sheet BRASUL IMPRIMIR
M1: BRASUL CONSTRUTORA LTDA
M2: Rua Coronel Jordão, 440, Vila Paiva - São Paulo, SP - CEP 02075-030
M3: Telefone: (11) 3313-8220
M4: e-mail: compras2@brasulconstrutora.com.br
C6: DATA: | D6: ='BASE PEDIDO'!A4 -> 46129 | H6: PEDIDO DE COMPRA | K6: Nº | L6: ='BASE PEDIDO'!B1 -> 2575
L7: ='BASE PEDIDO'!D4 -> ELIAS MASSUD
B9: Razão Social: | E9: =VLOOKUP(E10,FORNECEDOR[#All],2,FALSE) -> SAINT-GOBAIN DISTRIBUIÇÃO BRASUL LTDA
B10: Fornecedor: | E10: ='BASE PEDIDO'!E4 -> TELHA NORTE | J10: Vendedor: | K10: =VLOOKUP(E10,FORNECEDOR[#All],4,FALSE) -> Augusto
B11: E-mail: | E11: =VLOOKUP(E10,FORNECEDOR[#All],3,FALSE) -> augusto.endes@saint-gobain.com | J11: Telefone: | K11: =VLOOKUP(E10,FORNECEDOR[#All],5,FALSE) -> 11 9.8510-6170
B13: Endereço de Cobrança: Rua Coronel Jordão, 440 /450 | I13: Bairro: Vila Paiva | L13: CEP: 02075-030
B14: Cidade: São Paulo | I14: UF: SP | L14: Comprador: IURY
B16: Faturamento: | E16: =MID(B17,1,2) -> 28 | F16: =IF(E16="","","dias") -> dias | G16: ='BASE PEDIDO'!G4 -> BOLETO | H16: =IF(G16="PIX",VLOOKUP(E10,FORNECEDOR[#All],6,FALSE),"") | K16: Estimativa de vencimento: | L16: =$L$23+E16 -> 46162
B17: ='BASE PEDIDO'!F4 -> 28/56/84/112 | E17: =MID(B17,4,2) -> 56 | F17: =IF(E17="","","dias") -> dias | H17: =IF(G16="PIX",VLOOKUP(E10,FORNECEDOR[#All],7,FALSE),"") | L17: =IF(E17=""," ",$D$6+E17) -> 46185
E18: =MID(B17,7,2) -> 84 | L18: =IF(E18=""," ",$D$6+E18) -> 46213
E19: =MID(B17,10,3) -> 112 | F19: =IF(E19="","","dias") -> dias | L19: =IF(E19=""," ",$D$6+E19) -> 46241
F20: =IF(E20="","","dias") | L20: =IF(E20=""," ",$D$6+E20)
B21: OBSERVAÇÃO: | E21: NOTA FISCAL DEVE SER FATURADA EM NOME DA EMPRESA | I21: =IF('BASE PEDIDO'!L4="JB","JB CONSTRUÇÕES E EMPREENDIMENTOS LTDA",IF('BASE PEDIDO'!L4="BRASUL","BRASUL CONSTRUTORA LTDA","BRASUL CONSTRUTORA LTDA")) -> BRASUL CONSTRUTORA LTDA
B23: PRAZO | D23: ='BASE PEDIDO'!C4 -> ENTREGA | F23: ='BASE PEDIDO'!B4 -> 5 | G23: dias | K23: ="DATA PREVISTA DA "&'BASE PEDIDO'!C4 -> DATA PREVISTA DA ENTREGA | L23: =D6+F23 -> 46134
B25: Local de Entrega: | E25: =VLOOKUP(L7,OBRAS[#All],4,FALSE) -> Rua Prof Fauze Calil 30 | H25: Bairro: | I25: =VLOOKUP(L7,OBRAS[#All],5,FALSE) -> Centro
B26: OBRA: | D26: =VLOOKUP(L7,OBRAS[#All],3,FALSE) -> E.E Dr Elias Massud | H26: Contrato Obra: | I26: =VLOOKUP(L7,OBRAS[#All],7,FALSE) -> 0
B27: CEP: | D27: =VLOOKUP(L7,OBRAS[#All],6,FALSE) -> 13190-000 | H27: Cidade: | I27: =VLOOKUP(L7,OBRAS[#All],8,FALSE) -> Monte Mor | K27: UF: | L27: =VLOOKUP(L7,OBRAS[#All],9,FALSE) -> SP
C30: ITEM | D30: DESCRIÇÃO | I30: QTDADE | J30: UNID. | K30: VALOR UNITÁRIO | L30: VALOR TOTAL
C32: 1 | D32: ='BASE PEDIDO'!H4 -> REJ CERAMIC CINZA PLATINA5KG QUARTZOLIT | I32: ='BASE PEDIDO'!J4 -> 20 | J32: ='BASE PEDIDO'!I4 -> SACO | K32: ='BASE PEDIDO'!K4 -> 49.41 | L32: =I32*K32 -> 988.2
C33: 2 | D33: ='BASE PEDIDO'!H5 -> ARG PORCEL INT CZ 20KGQUARTZOLIT | I33: ='BASE PEDIDO'!J5 -> 120 | J33: ='BASE PEDIDO'!I5 -> SACO | K33: ='BASE PEDIDO'!K5 -> 21.51 | L33: =I33*K33 -> 2581.2
C34: 3 | D34: ='BASE PEDIDO'!H6 -> PORC MUNARI BRANCO AC60X60 RET | I34: ='BASE PEDIDO'!J6 -> 300.6 | J34: ='BASE PEDIDO'!I6 -> M2 | K34: ='BASE PEDIDO'!K6 -> 79.03 | L34: =I34*K34 -> 23756.418
C35: 4 | D35: ='BASE PEDIDO'!H7 -> DESCONTO TOTAL | I35: ='BASE PEDIDO'!J7 -> 1 | J35: ='BASE PEDIDO'!I7 -> VERBA | K35: ='BASE PEDIDO'!K7 -> -131.79 | L35: =I35*K35 -> -131.79
C36: 5 | D36: ='BASE PEDIDO'!H8 -> 0 | I36: ='BASE PEDIDO'!J8 -> 0 | J36: ='BASE PEDIDO'!I8 -> 0 | K36: ='BASE PEDIDO'!K8 -> 0 | L36: =I36*K36 -> 0
C37: 6 | D37: ='BASE PEDIDO'!H9 -> 0 | I37: ='BASE PEDIDO'!J9 -> 0 | J37: ='BASE PEDIDO'!I9 -> 0 | K37: ='BASE PEDIDO'!K9 -> 0 | L37: =I37*K37 -> 0
C38: 7 | D38: ='BASE PEDIDO'!H10 -> 0 | I38: ='BASE PEDIDO'!J10 -> 0 | J38: ='BASE PEDIDO'!I10 -> 0 | K38: ='BASE PEDIDO'!K10 -> 0 | L38: =I38*K38 -> 0
C39: 8 | D39: ='BASE PEDIDO'!H11 -> 0 | I39: ='BASE PEDIDO'!J11 -> 0 | J39: ='BASE PEDIDO'!I11 -> 0 | K39: ='BASE PEDIDO'!K11 -> 0 | L39: =I39*K39 -> 0
C40: 9 | D40: ='BASE PEDIDO'!H12 -> 0 | I40: ='BASE PEDIDO'!J12 -> 0 | J40: ='BASE PEDIDO'!I12 -> 0 | K40: ='BASE PEDIDO'!K12 -> 0 | L40: =I40*K40 -> 0
C41: 10 | D41: ='BASE PEDIDO'!H13 -> 0 | I41: ='BASE PEDIDO'!J13 -> 0 | J41: ='BASE PEDIDO'!I13 -> 0 | K41: ='BASE PEDIDO'!K13 -> 0 | L41: =I41*K41 -> 0
C42: 11 | D42: ='BASE PEDIDO'!H14 -> 0 | I42: ='BASE PEDIDO'!J14 -> 0 | J42: ='BASE PEDIDO'!I14 -> 0 | K42: ='BASE PEDIDO'!K14 -> 0 | L42: =I42*K42 -> 0
C43: 12 | D43: ='BASE PEDIDO'!H15 -> 0 | I43: ='BASE PEDIDO'!J15 -> 0 | J43: ='BASE PEDIDO'!I15 -> 0 | K43: ='BASE PEDIDO'!K15 -> 0 | L43: =I43*K43 -> 0
... C58: 27 | D58: ='BASE PEDIDO'!H30 -> 0 | I58: ='BASE PEDIDO'!J30 -> 0 | J58: ='BASE PEDIDO'!I30 -> 0 | K58: ='BASE PEDIDO'!K30 -> 0 | L58: =I58*K58 -> 0
C59: 30 | D59: ='BASE PEDIDO'!H33 -> 0 | I59: ='BASE PEDIDO'!J33 -> 0 | J59: ='BASE PEDIDO'!I33 -> 0 | K59: ='BASE PEDIDO'!K33 -> 0 | L59: =I59*K59 -> 0
C60: 31 | D60: ='BASE PEDIDO'!H34 -> 0 | I60: ='BASE PEDIDO'!J34 -> 0 | J60: ='BASE PEDIDO'!I34 -> 0 | K60: ='BASE PEDIDO'!K34 -> 0 | L60: =I60*K60 -> 0
K61: SUB TOTAL | L61: =SUM(L32:L60)-L62 -> 27194.028
K62: DESCONTO | L62: =SUMIF(D32:D58,"DESCONTO",L32:L58) -> 0
K63: TOTAL | L63: =L61+L62 -> 27194.028
L65: Horario de RECEBIMENTO NA OBRA
L66: Segunda a Quinta-feira das 07:30h às 11:30h e das 13:00h as 15:30h
L67: Sexta-feira das 07:30h às 11:30h e das 13:00h as 14:30h

Sheet B&B
M1: B & B Engenharia e Construções LTDA
M2: Rua itamonte 33, 440 , Vila Medeiros - São Paulo, SP - CEP 02220-000
M3: Telefone: (11) 3313-8220
M4: e-mail: compras2@brasulconstrutora.com.br
C6: DATA: | D6: ='BASE PEDIDO'!A4 -> 46129 | H6: PEDIDO DE COMPRA | K6: Nº | L6: ='BASE PEDIDO'!B1 -> 2575
L7: ='BASE PEDIDO'!D4 -> ELIAS MASSUD
B9: Razão Social: | E9: =VLOOKUP(E10,FORNECEDOR[#All],2,FALSE) -> SAINT-GOBAIN DISTRIBUIÇÃO BRASUL LTDA
B10: Fornecedor: | E10: ='BASE PEDIDO'!E4 -> TELHA NORTE | J10: Vendedor: | K10: =VLOOKUP(E10,FORNECEDOR[#All],4,FALSE) -> Augusto
B11: E-mail: | E11: =VLOOKUP(E10,FORNECEDOR[#All],3,FALSE) -> augusto.endes@saint-gobain.com | J11: Telefone: | K11: =VLOOKUP(E10,FORNECEDOR[#All],5,FALSE) -> 11 9.8510-6170
B13: Endereço de Cobrança: Rua Coronel Jordão, 440 /450 | I13: Bairro: Vila Paiva | L13: CEP: 02075-030
B14: Cidade: São Paulo | I14: UF: SP | L14: Comprador: IURY
B16: Faturamento: | E16: =MID(B17,1,2) -> 28 | F16: =IF(E16="","","dias") -> dias | G16: ='BASE PEDIDO'!G4 -> BOLETO | H16: =IF(G16="PIX",VLOOKUP(E10,FORNECEDOR[#All],6,FALSE),"") | K16: Estimativa de vencimento: | L16: =$L$23+E16 -> 46162
B17: ='BASE PEDIDO'!F4 -> 28/56/84/112 | E17: =MID(B17,4,2) -> 56 | F17: =IF(E17="","","dias") -> dias | G17: =IF(G16="PIX",VLOOKUP(E10,FORNECEDOR[#All],7,FALSE),"") | L17: =IF(E17=""," ",$D$6+E17) -> 46185
B18: {=_xlfn.TEXTSPLIT(C17," ")} -> #VALUE! | E18: =MID(B17,7,2) -> 84 | F18: =IF(E18="","","dias") -> dias | L18: =IF(E18=""," ",$D$6+E18) -> 46213
E19: =MID(B17,10,3) -> 112 | L19: =IF(E19=""," ",$D$6+E19) -> 46241
B21: OBSERVAÇÃO: | E21: NOTA FISCAL DEVE SER FATURADA EM NOME DA EMPRESA | I21: =IF('BASE PEDIDO'!L4="B&B","B&B Engenharia e Construções LTDA",IF('BASE PEDIDO'!L4="B&B Engenharia e Construções LTDA","B&B Engenharia e Construções LTDA","B&B Engenharia e Construções LTDA")) -> B&B Engenharia e Construções LTDA
B23: PRAZO | D23: ='BASE PEDIDO'!C4 -> ENTREGA | F23: ='BASE PEDIDO'!B4 -> 5 | G23: dias | K23: ="DATA PREVISTA DA "&'BASE PEDIDO'!C4 -> DATA PREVISTA DA ENTREGA | L23: =D6+F23 -> 46134
B25: Local de Entrega: | E25: =VLOOKUP(L7,OBRAS[#All],4,FALSE) -> Rua Prof Fauze Calil 30 | H25: Bairro: | I25: =VLOOKUP(L7,OBRAS[#All],5,FALSE) -> Centro
B26: OBRA: | D26: =VLOOKUP(L7,OBRAS[#All],3,FALSE) -> E.E Dr Elias Massud | H26: Contrato Obra: | I26: =VLOOKUP(L7,OBRAS[#All],7,FALSE) -> 0
B27: CEP: | D27: =VLOOKUP(L7,OBRAS[#All],6,FALSE) -> 13190-000 | H27: Cidade: | I27: =VLOOKUP(L7,OBRAS[#All],8,FALSE) -> Monte Mor | K27: UF: | L27: =VLOOKUP(L7,OBRAS[#All],9,FALSE) -> SP
C30: ITEM | D30: DESCRIÇÃO | I30: QTDADE | J30: UNID. | K30: VALOR UNITÁRIO | L30: VALOR TOTAL
C32: 1 | D32: ='BASE PEDIDO'!H4 -> REJ CERAMIC CINZA PLATINA5KG QUARTZOLIT | I32: ='BASE PEDIDO'!J4 -> 20 | J32: ='BASE PEDIDO'!I4 -> SACO | K32: ='BASE PEDIDO'!K4 -> 49.41 | L32: =I32*K32 -> 988.2
C33: 2 | D33: ='BASE PEDIDO'!H5 -> ARG PORCEL INT CZ 20KGQUARTZOLIT | I33: ='BASE PEDIDO'!J5 -> 120 | J33: ='BASE PEDIDO'!I5 -> SACO | K33: ='BASE PEDIDO'!K5 -> 21.51 | L33: =I33*K33 -> 2581.2
C34: 3 | D34: ='BASE PEDIDO'!H6 -> PORC MUNARI BRANCO AC60X60 RET | I34: ='BASE PEDIDO'!J6 -> 300.6 | J34: ='BASE PEDIDO'!I6 -> M2 | K34: ='BASE PEDIDO'!K6 -> 79.03 | L34: =I34*K34 -> 23756.418
C35: 4 | D35: ='BASE PEDIDO'!H7 -> DESCONTO TOTAL | I35: ='BASE PEDIDO'!J7 -> 1 | J35: ='BASE PEDIDO'!I7 -> VERBA | K35: ='BASE PEDIDO'!K7 -> -131.79 | L35: =I35*K35 -> -131.79
C36: 5 | D36: ='BASE PEDIDO'!H8 -> 0 | I36: ='BASE PEDIDO'!J8 -> 0 | J36: ='BASE PEDIDO'!I8 -> 0 | K36: ='BASE PEDIDO'!K8 -> 0 | L36: =I36*K36 -> 0
C37: 6 | D37: ='BASE PEDIDO'!H9 -> 0 | I37: ='BASE PEDIDO'!J9 -> 0 | J37: ='BASE PEDIDO'!I9 -> 0 | K37: ='BASE PEDIDO'!K9 -> 0 | L37: =I37*K37 -> 0
C38: 7 | D38: ='BASE PEDIDO'!H10 -> 0 | I38: ='BASE PEDIDO'!J10 -> 0 | J38: ='BASE PEDIDO'!I10 -> 0 | K38: ='BASE PEDIDO'!K10 -> 0 | L38: =I38*K38 -> 0
C39: 8 | D39: ='BASE PEDIDO'!H11 -> 0 | I39: ='BASE PEDIDO'!J11 -> 0 | J39: ='BASE PEDIDO'!I11 -> 0 | K39: ='BASE PEDIDO'!K11 -> 0 | L39: =I39*K39 -> 0
C40: 9 | D40: ='BASE PEDIDO'!H12 -> 0 | I40: ='BASE PEDIDO'!J12 -> 0 | J40: ='BASE PEDIDO'!I12 -> 0 | K40: ='BASE PEDIDO'!K12 -> 0 | L40: =I40*K40 -> 0
C41: 10 | D41: ='BASE PEDIDO'!H13 -> 0 | I41: ='BASE PEDIDO'!J13 -> 0 | J41: ='BASE PEDIDO'!I13 -> 0 | K41: ='BASE PEDIDO'!K13 -> 0 | L41: =I41*K41 -> 0
C42: 11 | D42: ='BASE PEDIDO'!H14 -> 0 | I42: ='BASE PEDIDO'!J14 -> 0 | J42: ='BASE PEDIDO'!I14 -> 0 | K42: ='BASE PEDIDO'!K14 -> 0 | L42: =I42*K42 -> 0
C43: 12 | D43: ='BASE PEDIDO'!H15 -> 0 | I43: ='BASE PEDIDO'!J15 -> 0 | J43: ='BASE PEDIDO'!I15 -> 0 | K43: ='BASE PEDIDO'!K15 -> 0 | L43: =I43*K43 -> 0
... C61: 30 | D61: ='BASE PEDIDO'!H33 -> 0 | I61: ='BASE PEDIDO'!J33 -> 0 | J61: ='BASE PEDIDO'!I33 -> 0 | K61: ='BASE PEDIDO'!K33 -> 0 | L61: =I61*K61 -> 0
K62: SUB TOTAL | L62: =SUM(L32:L61)-L63 -> 27194.028
K63: DESCONTO | L63: =SUMIF(D32:D59,"DESCONTO",L32:L59) -> 0
K64: TOTAL | L64: =L62+L63 -> 27194.028
L66: Horario de RECEBIMENTO NA OBRA
L67: Segunda a Quinta-feira das 07:30h às 11:30h e das 13:00h as 15:30h
L68: Sexta-feira das 07:30h às 11:30h e das 13:00h as 14:30h

Sheet INTERIORANA IMPRIMIR
M1: INTERIORANA CONSTRUTORA LTDA
M2: Avª Mofarrej, 348 – Sala 703 – Vila Leopoldina – São Paulo/SP
M3: Telefone: (11) 2892.8916
M4: e-mail: compras2@brasulconstrutora.com.br
C6: DATA: | D6: ='BASE PEDIDO'!A4 -> 46129 | H6: PEDIDO DE COMPRA | K6: Nº | L6: ='BASE PEDIDO'!B1 -> 2575
L7: ='BASE PEDIDO'!D4 -> ELIAS MASSUD
B9: Razão Social: | E9: =VLOOKUP(E10,FORNECEDOR[#All],2,FALSE) -> SAINT-GOBAIN DISTRIBUIÇÃO BRASUL LTDA
B10: Fornecedor: | E10: ='BASE PEDIDO'!E4 -> TELHA NORTE | J10: Vendedor: | K10: =VLOOKUP(E10,FORNECEDOR[#All],4,FALSE) -> Augusto
B11: E-mail: | E11: =VLOOKUP(E10,FORNECEDOR[#All],3,FALSE) -> augusto.endes@saint-gobain.com | J11: Telefone: | K11: =VLOOKUP(E10,FORNECEDOR[#All],5,FALSE) -> 11 9.8510-6170
B13: Endereço de Cobrança: Rua Coronel Jordão, 440 /450 | I13: Bairro: Vila Paiva | L13: CEP: 02075-030
B14: Cidade: São Paulo | I14: UF: SP | L14: Comprador: IURY
B16: Faturamento: | E16: =MID(B17,1,2) -> 28 | F16: =IF(E16="","","dias") -> dias | G16: ='BASE PEDIDO'!G4 -> BOLETO | H16: =IF(G16="PIX",VLOOKUP(E10,FORNECEDOR[#All],6,FALSE),"") | K16: Estimativa de vencimento: | L16: =$L$24+E16 -> 46162
B17: ='BASE PEDIDO'!F4 -> 28/56/84/112 | E17: =MID(B17,4,2) -> 56 | F17: =IF(E17="","","dias") -> dias | H17: =IF(G16="PIX",VLOOKUP(E10,FORNECEDOR[#All],7,FALSE),"") | L17: =IF(E17=""," ",$D$6+E17) -> 46185
B18: {=_xlfn.TEXTSPLIT(C17," ")} -> #VALUE! | E18: =MID(B17,7,2) -> 84 | F18: =IF(E18="","","dias") -> dias | L18: =IF(E18=""," ",$D$6+E18) -> 46213
E19: =MID(B17,10,3) -> 112 | F19: dias | L19: =IF(E19=""," ",$D$6+E19) -> 46241
L20: =IF(E20=""," ",$D$6+E20)
B22: OBSERVAÇÃO: | E22: NOTA FISCAL DEVE SER FATURADA EM NOME DA EMPRESA | I22: =IF('BASE PEDIDO'!L4="JB","JB CONSTRUÇÕES E EMPREENDIMENTOS LTDA",IF('BASE PEDIDO'!L4="BRASUL","BRASUL CONSTRUTORA LTDA","INTERIORANA CONSTRUTORA LTDA")) -> INTERIORANA CONSTRUTORA LTDA
B24: PRAZO | D24: ='BASE PEDIDO'!C4 -> ENTREGA | F24: ='BASE PEDIDO'!B4 -> 5 | G24: dias | K24: ="DATA PREVISTA DA "&'BASE PEDIDO'!C4 -> DATA PREVISTA DA ENTREGA | L24: =D6+F24 -> 46134
B26: Local de Entrega: | E26: =VLOOKUP(L7,OBRAS[#All],4,FALSE) -> Rua Prof Fauze Calil 30 | H26: Bairro: | I26: =VLOOKUP(L7,OBRAS[#All],5,FALSE) -> Centro
B27: OBRA: | D27: =VLOOKUP(L7,OBRAS[#All],3,FALSE) -> E.E Dr Elias Massud | H27: Contrato Obra: | I27: =VLOOKUP(L7,OBRAS[#All],7,FALSE) -> 0
B28: CEP: | D28: =VLOOKUP(L7,OBRAS[#All],6,FALSE) -> 13190-000 | H28: Cidade: | I28: =VLOOKUP(L7,OBRAS[#All],8,FALSE) -> Monte Mor | K28: UF: | L28: =VLOOKUP(L7,OBRAS[#All],9,FALSE) -> SP
C31: ITEM | D31: DESCRIÇÃO | I31: QTDADE | J31: UNID. | K31: VALOR UNITÁRIO | L31: VALOR TOTAL
C33: 1 | D33: ='BASE PEDIDO'!H4 -> REJ CERAMIC CINZA PLATINA5KG QUARTZOLIT | I33: ='BASE PEDIDO'!J4 -> 20 | J33: ='BASE PEDIDO'!I4 -> SACO | K33: ='BASE PEDIDO'!K4 -> 49.41 | L33: =I33*K33 -> 988.2
C34: 2 | D34: ='BASE PEDIDO'!H5 -> ARG PORCEL INT CZ 20KGQUARTZOLIT | I34: ='BASE PEDIDO'!J5 -> 120 | J34: ='BASE PEDIDO'!I5 -> SACO | K34: ='BASE PEDIDO'!K5 -> 21.51 | L34: =I34*K34 -> 2581.2
C35: 3 | D35: ='BASE PEDIDO'!H6 -> PORC MUNARI BRANCO AC60X60 RET | I35: ='BASE PEDIDO'!J6 -> 300.6 | J35: ='BASE PEDIDO'!I6 -> M2 | K35: ='BASE PEDIDO'!K6 -> 79.03 | L35: =I35*K35 -> 23756.418
C36: 4 | D36: ='BASE PEDIDO'!H7 -> DESCONTO TOTAL | I36: ='BASE PEDIDO'!J7 -> 1 | J36: ='BASE PEDIDO'!I7 -> VERBA | K36: ='BASE PEDIDO'!K7 -> -131.79 | L36: =I36*K36 -> -131.79
C37: 5 | D37: ='BASE PEDIDO'!H8 -> 0 | I37: ='BASE PEDIDO'!J8 -> 0 | J37: ='BASE PEDIDO'!I8 -> 0 | K37: ='BASE PEDIDO'!K8 -> 0 | L37: =I37*K37 -> 0
C38: 6 | D38: ='BASE PEDIDO'!H9 -> 0 | I38: ='BASE PEDIDO'!J9 -> 0 | J38: ='BASE PEDIDO'!I9 -> 0 | K38: ='BASE PEDIDO'!K9 -> 0 | L38: =I38*K38 -> 0
C39: 7 | D39: ='BASE PEDIDO'!H10 -> 0 | I39: ='BASE PEDIDO'!J10 -> 0 | J39: ='BASE PEDIDO'!I10 -> 0 | K39: ='BASE PEDIDO'!K10 -> 0 | L39: =I39*K39 -> 0
C40: 8 | D40: ='BASE PEDIDO'!H11 -> 0 | I40: ='BASE PEDIDO'!J11 -> 0 | J40: ='BASE PEDIDO'!I11 -> 0 | K40: ='BASE PEDIDO'!K11 -> 0 | L40: =I40*K40 -> 0
C41: 9 | D41: ='BASE PEDIDO'!H12 -> 0 | I41: ='BASE PEDIDO'!J12 -> 0 | J41: ='BASE PEDIDO'!I12 -> 0 | K41: ='BASE PEDIDO'!K12 -> 0 | L41: =I41*K41 -> 0
C42: 10 | D42: ='BASE PEDIDO'!H13 -> 0 | I42: ='BASE PEDIDO'!J13 -> 0 | J42: ='BASE PEDIDO'!I13 -> 0 | K42: ='BASE PEDIDO'!K13 -> 0 | L42: =I42*K42 -> 0
C43: 11 | D43: ='BASE PEDIDO'!H14 -> 0 | I43: ='BASE PEDIDO'!J14 -> 0 | J43: ='BASE PEDIDO'!I14 -> 0 | K43: ='BASE PEDIDO'!K14 -> 0 | L43: =I43*K43 -> 0
C44: 12 | D44: ='BASE PEDIDO'!H15 -> 0 | I44: ='BASE PEDIDO'!J15 -> 0 | J44: ='BASE PEDIDO'!I15 -> 0 | K44: ='BASE PEDIDO'!K15 -> 0 | L44: =I44*K44 -> 0
... C67: 35 | D67: ='BASE PEDIDO'!H38 -> 0 | I67: ='BASE PEDIDO'!J38 -> 0 | J67: ='BASE PEDIDO'!I38 -> 0 | K67: ='BASE PEDIDO'!K38 -> 0 | L67: =I67*K67 -> 0
K68: SUB TOTAL | L68: =SUM(L33:L66)-L69 -> 27194.028
K69: DESCONTO | L69: =SUMIF(D33:D60,"DESCONTO",L33:L60) -> 0
K70: TOTAL | L70: =L68+L69 -> 27194.028
L72: Horario de RECEBIMENTO NA OBRA
L73: Segunda a Quinta-feira das 07:30h às 11:30h e das 13:00h as 15:30h
L74: Sexta-feira das 07:30h às 11:30h e das 13:00h as 14:30h

Sheet DADOS DAS OBRAS
A1: OBRA | B1: FATURAMENTO | C1: ESCOLA | D1: Local de Entrega: | E1: Bairro: | F1: CEP: | G1: Contrato Obra: | H1: Cidade: | I1: UF: | J1: Empreiteiro | K1: Contato
A2: FCO MIGNONE | B2: BRASUL | C2: EE FRANCISCO MIGNONE | D2: Rua Rio Birigui nº 01 | E2: Gleba do Pessego - Parque do Carmo | F2: 08265-290 | G2: 70/00146/23/01 | H2: São Paulo | I2: SP | J2: BERNARDO | K2: (11) 9.8506-0719
A3: KEIZO - JB | B3: JB | C3: EE KEIZO ISHIHARA | D3: Rua Mário Gessulho, 60 | E3: Conj. Res. Butanta | F3: 05540-130 | G3: 10/00005/23-01-051 | H3: São Paulo | I3: SP | J3: GEORGE | K3: (11) 9.8033-4770
A4: SOLON BORGES - JB | B4: JB | C4: EE/CEL SOLON BORGES DOS REIS | D4: Av. José Joaquim Seabra, 1187 | E4: Rio Pequeno | F4: 05364-000 | G4: 10/00005/23-01-051 | H4: São Paulo | I4: SP | J4: GEORGE | K4: (11) 9.8033-4770
A5: PEDRO COSTA - JB | B5: JB | C5: EE DEP PEDRO COSTA | D5: Rua Nilo Luís Mazzei, 378 | E5: Vila Isolina Mazzei | F5: 02081-070 | G5: 10/00005/23-01-051 | H5: São Paulo | I5: SP | J5: BERNARDO | K5: (11) 9.8506-0719
A6: BENEDITO TOLOSA - JB | B6: JB | C6: EE PROF BENEDITO TOLOSA | D6: Rua Jaguarete, 617 | E6: Casa Verde | F6: 02515-010 | G6: 10/00005/23-01-051 | H6: São Paulo | I6: SP | J6: KERLISON | K6: (11) 9.8570-2178
A7: THEREZA | B7: BRASUL | C7: EE THEREZA SILVEIRA | D7: Rua: Santo Antonio, 41 | E7: Jd. São Miguel | F7: 11440-080 | H7: Guaruja | I7: SP
A8: PE NILDO | B8: BRASUL | C8: EE Padre Nildo do Amaral Junior | D8: R. da Tropicália, s/n | E8: Jardim Pedro José Nunes | F8: 08061-010 | H8: São Paulo | I8: SP
A9: ALDEIA CAPOEIRÃO | B9: BRASUL | C9: EEI ALDEIA CAPOEIRAO | D9: ALDEIA CAPOEIRAO | E9: KM 93 | F9: 11760 - 000 | H9: Itariri | I9: SP | J9: SANDOVAL | K9: (11) 9.7792-3909
A10: ARY BARROSO | B10: BRASUL
A11: ANTONIO FERNANDES | B11: BRASUL | C11: EE PROF ANTONIO FERNANDES | D11: Rua Prof Antonio Fernandes 74 | E11: Vila Tupy | F11: 11900-000 | G11: 69/00811/23/01 | H11: Registro | I11: SP
A12: WALDEMAR RIGOTO - B&B | B12: B&B | C12: E. E. Prof. Waldemar da Silva Rigotto | D12: R. Primeiro de Maio, S/N | E12: Sítio Paecara (Vicente de Carvalho) | F12: 11460-000 | H12: Guaruja | I12: SP
A13: PEDRO BARROS | B13: BRASUL | C13: EE/EMEF PEDRO BARROS | D13: Rod. Régis Bittencourt, 384 | E13: Pedro Barros | F13: 11850-00 | G13: 69/00077/24-001-001 | H13: Miracatu | I13: SP
A14: EE ITARIRI | B14: BRASUL | C14: EE PEI ITARIRI | D14: Rua Benedito Calixto, 306 | E14: Centro Itariri | F14: 11760-000 | G14: 70/00158/23/01 | H14: Itariri | I14: SP
A15: EE WALDOMIRO MARIANI | B15: B&B | C15: EE Prof. Waldomiro Marian | D15: R. Orlando Terras, s/n | E15: Jardim Rea | F15: 11534-870 | H15: Cubatão | I15: SP | K15: (13) 3323-6265
A16: THEREZINHA ARANHA | B16: BRASUL | C16: EE Therezinha A Mantelli | D16: Rua Profº Antonio de Castro Lopes, 930 | E16: PQ Boturussu/Ermelindo Matarazzo | F16: 03805-080 | G16: 70/00146/23/01 | H16: São Paulo | I16: SP
A17: MARIO CORADIN | B17: BRASUL | C17: MARIO CORADIN | D17: Rod. Regis Bittencourt, Km 555 | E17: Rio Vermelho | F17: 11955-000 | G17: 69/01135/23/01 | H17: Barra do Turco | I17: SP
A18: EE GODOFREDO FURTADO - JB | B18: JB | C18: GODOFREDO FURTADO - JB | D18: R. João Moura, 727 - Jardim Paulista, São Paulo | E18: São Paulo | F18: 05412-001 | H18: São Paulo | I18: SP
A19: ALAY CORREA | B19: BRASUL | C19: ALAY JOSE CORREA VEREADOR | D19: R. Serra da Juréia, 130 - Jardim Valeri | E19: Registro | F19: 11900-000 | H19: São Paulo | I19: SP
A20: FDE | B20: BRASUL | C20: Fundação para o Desenvolvimento da Educação | D20: Av. São Luís, 99 - Centro Historico de São Paulo | E20: São Paulo | F20: 01046-001 | H20: São Paulo | I20: SP
A21: JOSE VICENTE BERTOLI | B21: BRASUL | C21: EE Prof. José Vicente Bertoli | D21: Estrada Municipal do Bairro Angatuba, S/N | E21: Angatuba | F21: 11930-000 | H21: Pariquera-Açu | I21: SP
A22: DARWIN FELIX | B22: BRASUL | C22: Escola Estadual Professor Darwin Felix | D22: Rua Quintino Bocaiúva, 406 - V Esperanca | E22: Piquete | F22: 12620-000 | H22: São Paulo | I22: SP
A23: WILSON SIMONINI | B23: BRASUL | C23: EE Wilson Roberto Simonini | D23: Rua João correa magalhães 200 | E23: Pq D João Neri | F23: 08151-260 | G23: 70/00553/22-01 | H23: São Paulo | I23: SP
A24: POETA DOMINGUES | B24: BRASUL | C24: EE POETA DOMINGUES | D24: EE Poeta Domingos Bauer Leite | E24: Miracatu | F24: 11850-000 | H24: Miracatu | I24: SP
A25: CLAY PRESGRAVE | B25: BRASUL | C25: EE Engenheiro Clay Presgrave do Amaral | D25: Av. Engº Clay P. do Amaral, 386 | E25: Ana Dias | F25: 11760-000 | H25: Itariri | I25: SP
A26: ANA ROSA DE ARAUJO | B26: JB | C26: E.E. Dona Ana Rosa De Araújo | D26: R. Eden, 100 | E26: Vila Inah | F26: 05619-000 | H26: São Paulo | I26: SP
A27: FERNANDO ABBUD | B27: BRASUL | C27: E.E Prof. José Fernando Abbud | D27: Av. Afonso Monteiro da Cruz, 261 | E27: Serraria | F27: 09980-550 | H27: Diadema | I27: SP
A28: DE CENTRO | B28: JB | C28: DE CENTRO | D28: Avenida Olavo Fontoura, 2.222 | E28: Casa Verde | F28: 02510-110 | H28: São Paulo | I28: SP
A29: ANTONIO PRADO | B29: JB | C29: EE CONS ANTÔNIO PRADO - JB | D29: R. Vitorino Carmilo, 621 | E29: Barra Funda | F29: 01153-000 | H29: São Paulo | I29: SP
A30: MARIA AP VIANA MUNIZ | B30: BRASUL | C30: MARIA APARECIDA VIANA MUNIZ PROFESSORA | D30: RUA 9 DE JULHO , 112 | E30: CENTRO | H30: Eldorado Registro | I30: SP
A31: ARLINDO BETIO | B31: BRASUL | C31: EE ARLINDO BETIO | D31: R. Vítor Brecheret, 31 | E31: Jardim Casa Grande | H31: Diadema | I31: SP
A32: OROSIMBO MAIA | B32: JB | C32: EE OROSIMBO MAIA | D32: Av. Andrade Neves, 214 | E32: Centro | F32: 13013-160 | H32: Campinas | I32: SP
A33: JOAQUIM FERREIRA | B33: JB | C33: EE JOAQUIM FERREIRA LIMA PROFESSOR | D33: RUA JOAO NOGUEIRA FERRAZ FILHO | E33: Vila Trinta e um de março | F33: 13091-558 | H33: Campinas | I33: SP
A34: MSN LUIS GONZAGA | B34: JB | C34: EE MNS LUIS GONZAGA DE MOURA | D34: R. Carlos Francheu 100 - Centro | E34: Centro | F34: 13023-610 | H34: Campinas | I34: SP
A35: DE MIRACATU | B35: BRASUL | C35: DIRETORIA DE ENSINO MIRACATU | D35: Av. Doná Evarista de Castro Ferreira | E35: Centro | F35: 11850-000 | H35: Miracatu | I35: SP
A36: JOAQUIM LEME PRADO | B36: JB | C36: Escola Estadual Joaquim Leme do Prado | D36: Av. Imirim, 2113 | E36: Imirim | F36: 02465-200 | H36: São Paulo | I36: SP
A37: MARIA MONTESSORI | B37: BRASUL | C37: EE MARIA MONTESSORI | D37: Av. Conceição, 2288 | E37: Vila Maria Alta | F37: 02072-002 | H37: São Paulo | I37: SP
A38: MARIA JOSE MORAIS | B38: BRASUL | C38: EE. Professora Maria José Morais de Carvalho | D38: Estrada dos Moraes, BR-116 | E38: Miracatu | F38: 11850-000 | H38: Miracatu | I38: SP
A39: ANA RITA GODINHO | B39: JB | C39: Escola Estadual Professora Ana Rita Godinho Pousa | D39: R. Benedita Franco Gomes, 165 | E39: Vila Esmeralda | F39: 13077-066 | H39: Campinas | I39: SP
A40: EE Fabio Farias | B40: JB | C40: Escola Estadual Fabio Farias | D40: AV. BRIGADEIRO RAFAEL TOBIAS DE AGUIAR 501 | E40: Jardim Aurelia | F40: 13033-010 | H40: Campinas | I40: SP
A41: PEI RAPOSO TAVARES | B41: BRASUL | C41: E. E. PEI Raposo Tavares | D41: Rua Anízio Pedro Oliveira, 22 | E41: Raposo Tavares | F41: 11760-000 | H41: Itariri | I41: SP
A42: DE REGISTRO | B42: BRASUL | C42: DIRETORIA DE ENSINO REGISTRO | D42: R. Vitória, 465 | E42: Jardim America | F42: 11900-000 | H42: Registro | I42: SP
A43: JOSE BARTOCCI | B43: BRASUL | C43: EE PROFESSOR JOSE BARTOCCI | D43: R. São Serapião, 396 | E43: Vila Ré | F43: 03664-000 | H43: São Paulo | I43: SP
... A56: DJALMA OCTAVIANO | B56: JB | C56: EE Djalma Octaviano | D56: Rua Willian Booth | E56: Jardim Pauliceia | F56: 13034-685 | H56: Campinas | I56: SP
A57: CASTINAUTA DE BARROS | B57: JB | C57: EE Prof Castinauta de Barros Mello e Albuquerque | D57: Rua Orlando de Oliveira 700 | E57: Jardim Campineiro | H57: Campinas | I57: SP
A58: FRANCISCO ALVARES | B58: JB | C58: EE Prof Francisco Álvares | D58: Estrada da Rhodia KM 15 N | E58: Vila Holandia | H58: Campinas | I58: SP
A59: MARIA MATOSINHO | B59: JB | C59: E.E José Maria Matosinho | D59: Praça Professsor Paulo José Otaviano, s/n | E59: São Bernardo | F59: 13030-571 | H59: Campinas | I59: SP
A60: SERRA NEGRA | B60: BRASUL | C60: SERRA NEGRA
A61: OMAR DONATO | B61: BRASUL | C61: ​Escola Estadual Omar Donato Bassani | D61: Estr. Ernesto Zabeu, 253 | E61: Tatetos | F61: 09837-150 | H61: São Bernardo | I61: SP
A62: MIGUEL ABU-YAGHI | B62: BRASUL | C62: Escola Miguel Abu-Yaghi | D62: R. Sete de Setembro, 2-58 | F62: 11940-000 | H62: Jacupiranga | I62: SP
A63: ADALBERTO NASCIMENTO | B63: BRASUL | C63: E. E. Adalberto Nascimento | D63: R. Adalberto Maia, 235 | E63: Taquaral | F63: 13076-007 | H63: Campinas | I63: SP
A64: ALBINO LUIZ CALDAS | B64: B&B | C64: Escola Estadual Albino Luiz Caldas | D64: Rua Irma Maria Rita de Souza Brito Lopes (Irma Dulce) | E64: Conjunto Residencial Humaitá | F64: 11349-330 | H64: São Vicente | I64: SP
A65: MARIA DE LOURDES | B65: INTERIORANA | C65: MARIA DE LOURDES MARTINS PROFESSORA | D65: RUA OSVALDO VACARI , 777 | E65: JARDIM MARIA ANTONIA | F65: 13178-374 | H65: Sumaré | I65: SP
A66: CARMELA CHIARA | B66: INTERIORANA | C66: E.E CARMELA CHIARA GINEFRA | D66: CENTRO | E66: CENTRO | F66: 13190-000 | H66: MONTE MOR | I66: SP
A67: CRISTIANE CHAVES | B67: INTERIORANA | C67: PEI CRISTIANE CHAVES MOREIRA | D67: R. Fabiano Pinheiro da Silva, 40 | E67: Jardim Santana | F67: 13184-547 | H67: Hortolandia | I67: SP
A68: JOSE DE ALMEIDA PINHEIRO | B68: B&B | C68: JOSE DE ALMEIDA PINHEIRO JUNIOR PROFESSOR | D68: RUA DOUTOR JOSE BENEDITO ALMEIDA RIBEIRO , SN | E68: PARQUE DAS BANDEIRAS | F68: 11346-030 | H68: São Vicente | I68: SP
A69: DONA ARACY | B69: INTERIORANA | C69: E.E DONA ARACY | D69: TRAVESSA FRANCISCO PARROTA SN | E69: VILA MONTE CARLO | F69: 13572-410 | H69: SÃO CARLOS | I69: SP
A70: ATTILIA PRADO | B70: INTERIORANA | C70: EE ATTILIA PRADO | D70: RUA JOAQUIM AUGUSTO RIBEIRO DE SOUZA SN | E70: PLANALTO PARAISO | F70: 13563-330 | H70: SÃO CARLOS | I70: SP
A71: PEDRO CELESTINO | B71: INTERIORANA | C71: EE PEDRO CELESTINO | D71: RUA DAS ARAPONGAS, SN | E71: JARDIM SÃO JOAQUIM | F71: 13615-600 | H71: LEME | I71: SP
A72: ELOI CHAVES | B72: INTERIORANA | C72: EE ELOI CHAVES | D72: AVENIDA ROSA SENHORINI ZERO 100 | E72: CACHOEIRA DE EMAS | F72: 13641-002 | H72: PIRASSUNUNGA | I72: SP
A73: ESTERINA PLACO | B73: INTERIORANA | C73: EE ESTERINA PLACO | D73: AVENIDA ARARAQUARA 451 | E73: VILA BRASILIA | F73: 13566-770 | H73: SÃO CARLOS | I73: SP
A74: JESUINO DE ARRUDA | B74: INTERIORANA | C74: EE JESUINO DE ARRUDA | D74: PRAÇA DONA MARIA GERTRUDES DE ARRUDA, SN | E74: VILA SONIA | F74: 13572-215 | H74: SÃO CARLOS | I74: SP
... A109: MARISTELA CAROLINA | B109: INTERIORANA | C109: EE Maristela Carolina Mellin | D109: R. Valdevino Isidoro Márciano, 174 | E109: Jardim Minda | F109: 13184-680 | H109: Hortolandia | I109: SP
A110: ESCRITORIO | B110: BRASUL | D110: Rua Coronel Jordão 440 | E110: Vila Paiva | F110: 02075-030 | H110: São Paulo | I110: SP
A111: JOSÉ MIRANDA | B111: INTERIORANA | C111: E.E JOSÉ MIRANDA PREFEITO | D111: Rua Alair Moreira 578 | E111: Parque Bandeirantes II (Nova Veneza) | F111: 13181-775 | H111: Sumaré | I111: SP
A112: GENNY PIMAZZONI | B112: INTERIORANA | C112: E.E GENNY PIMAZZONI PROFESSORA | D112: Rua São Jose, 305 | E112: Cardeal | F112: 13355-000 | H112: Elias Fausto | I112: SP
A113: PAULINA ROSA | B113: INTERIORANA | C113: E.E PAULINA ROSA PROF | D113: R. Renê Descartes, 75 | E113: Jd Santa Rita de Cassia | F113: 13186-290 | H113: Hortolândia | I113: SP
A114: MARIA RITA | B114: INTERIORANA | C114: E.E. Prof° Maria Rita Araújo Costa | D114: R. Ernesto Bergamasco, 665 | E114: Vila São Pedro | F114: 13183-080 | H114: Hortolândia | I114: SP
A115: ALDEIA SOL NASCENTE | B115: B&B | C115: E.E ALDEIA SOL NASCENTE | D115: AVENIDA ALDEIA ITAOCA | E115: Aldeia Itaoca | F115: 11730-000 | H115: Mongaguá | I115: SP
A116: MAGALI ALONSO | B116: B&B | C116: E E Prof Magali Alonso | D116: R. Manoel Alves, 122 | E116: Vila Tupi | F116: 11719-150 | H116: Praia Grande | I116: SP
A117: ELIAS MASSUD | B117: INTERIORANA | C117: E.E Dr Elias Massud | D117: Rua Prof Fauze Calil 30 | E117: Centro | F117: 13190-000 | H117: Monte Mor | I117: SP
A118: MARIA RITA ARAÚJO | B118: INTERIORANA | C118: E.E Maria Rita Araújo | D118: R. Ernesto Bergamasco, 665 | E118: Vila São Pedro | F118: 13183-080 | H118: Hortolândia | I118: SP

Sheet FORNECEDORES
A1: FORNECEDOR | B1: Razão Social | C1: E-mail | D1: Vendedor | E1: Telefone | F1: PIX | G1: FAVORECIDO
A2: F PINHEIRO | B2: F Pinheiro Comercio de Mat. p/ Construção LTDA | C2: beatriz@fpinheiro.com.br | D2: Beatriz | E2: (11) 96591-4597 | F2: 54.773.338/0001-05 | G2: F. PINHEIRO COMERCIO DE MATERIAL PARA CONSTRUCAO SLU LTDA
A3: BIG TELHAS | B3: BIG TELHAS CNPJ: 05.167.149/0001-83 | C3: marcos.paulo@telhasmp.com.br | D3: Marcos Paulo | E3: 19 99806-7474
A4: C&C | B4: C&C CASA E CONSTRUÇÃO LTDA | D4: Luciane | E4: (11) 94778-9353
A5: OLD RIVER | B5: PRO LIMA - COMERCIAL E DISTRIBUIDORA LTDA | C5: cotacao@oldriver.com.br | D5: Rudy | E5: 94015-2734
A6: CORANTE | B6: OZ MATERIAIS PARA CONSTRUCAO LTDA - MATRIZ | C6: aretusa@corantetintas.com.br | D6: Aretusa | E6: 11 98269-0417
A7: OBRAMESTRE | B7: OBRAMESTRE DEP MAT CONST LTDA | C7: adm01@obramestre.com | D7: Mayra | E7: 11 93950-6104
A8: CIMENTOFORT | B8: CimentoFort Distribuidora | C8: silvia@cimentofort.com.br | D8: Silvia | E8: (11)97514-9578
A9: ECO AMBIENTAL | B9: ECO AMBIENTAL CACAMBAS ESTACIONARIAS LTDA | C9: rodrigo@ecoambientalcacambas.com.br | D9: Rodrigo | E9: 11 97697-2621
A10: INOVABAN | B10: INOVABAN COMERCIO, LOCAÇÃO E MANUTENÇÃO DE EQUIPAMENTOS LTDA | C10: priscila@inovaban.com.br | D10: Priscila | E10: 11 98908-1735
A11: UEHARA ELETRICA | B11: UEHARA COM.DE MATS ELETRLTDA | C11: fernando@ueharaeletrica.com.br | D11: Fernando | E11: 11 3856-7501 | F11: 53.934.626/0001-31 | G11: UEHARA ELETRICA
A12: THIAGO ELETRICA | B12: 31.191.128 THIAGO DOS SANTOS SOUZA | C12: tseletricargt@hotmail.com | D12: Thiago | E12: 13 99746-9888 | F12: 31.391.128/0001-57 | G12: 31.391.128 Thiago dos Santos Souza Banco: BTG Pactual
A13: CATEL | B13: CATEL HIDRAULICOS LOUCAS E METAIS | C13: alan@catelhlm.com.br | D13: Alan | E13: 11 3313-8220
A14: CASA MIMOSA | B14: CASA MIMOSA HIDRAULICA E ACABAMENTOS LTDA | C14: vendas@casamimosa.com.br | D14: Rodrigo | E14: (11) 27825500 | F14: 62.978.978/0001-80 | G14: Casa Mimosa Hidráulica e Acabamentos Ltd
A15: PORTUGUÊS CAÇAMBAS | B15: JOYCE MARION ZORGDRAGER GUARUJÁ | C15: jmzcacamba@gmail.com | D15: Andrade | E15: 13 97812-3658
A16: PARADA DA LIMPEZA | B16: PARADA DA LIMPEZA 16.657.550/0001-18
A17: BECO GÁS | B17: TERMOGAS AQUECIMENTO E CONTROLE LTDA 02.793.273/0001-66 | D17: JOSÉ | E17: 11 2692-6150 | F17: CNPJ 57.288.482/0001-44 | G17: BECO DOS FOGÕES PEÇAS E ACESSÓRIOS LTDA
A18: ANDAIMES ZONA LESTE | B18: ZONA LESTE ANDAIMES | D18: Amanda | E18: (11) 2765-8733
A19: CONSTRUSILVA | B19: Construsilva CNPJ: 03.533.447/0001-14 | D19: Ana Clara | E19: 11) 9 8599-5296 | F19: CNPJ: 03.533.447/0001-14 | G19: ADRIANA PINA DA SILVEIRA E SILVA
A20: LESTE SÃO PAULO | B20: LESTE SÃO PAULO MATERIAIS DE CONSTRUÇÃO LTDA | C20: leticia@futuramadeiras.com.br | D20: Leticia | E20: 11 2254-8764
A21: DEPOSITO PADRÃO | B21: DEPOSITO E COMERCIO PADRAO LOJA 2 LTDA | C21: viviane@brasulconstrutora.com.br | D21: Melissa | E21: 11963310257 | F21: CNPJ 53.198.573/0001-38 | G21: Deposito e COmercio Padrao - loja 02
A22: AREA ELETRICOS | B22: AEA DISTRIBUIDORA DE MAT. ELETRICOS LTDA | D22: Wellison | E22: 1133931842
A23: ITA AÇOS | B23: AÇOS ITAPETININGA LTDA | C23: sebachvocal@gmail.com | D23: Erik Maluf | E23: (15) 3259-8333 | F23: 37.121.213/0001-02 | G23: BRADESCO INDÚSTRIA Ag: 0261 CC: 0050998-1
A24: ART VIDROS | B24: ART VIDROS VIDRAÇARIA | C24: artvidros@vidracariaartvidros.com.br | D24: Beth | E24: (11) 2905-5804 | F24: CNPJ 43.479.500/0001-60 | G24: ART VIDROS LTDA BANCO ITAU
A25: GFENDS ESQUADRIAS | B25: GFENDS ESQUADRIAS DE ALUMINIO LTDA | D25: Geraldo | E25: (11) 94784-5189
A26: GUARUJÁ EXTINTORES | B26: GUARUJA EXTINTORES CNPJ: 17338751000115 | E26: (13) 3323-6265
A27: DIRECT BORRACHAS | B27: DIRECT BORRACHAS CNPJ: 23.447.624/0001-57 | D27: GISELE | E27: (11)2011-9058 | F27: 234476240001-57 | G27: DIRECT B I C PLASTICOS
A28: DEPOSITO ZONA NORTE | B28: DEPÓSITO ZONA NORTE | C28: vendas@depositozonanorte.com.br | D28: JOÃO | E28: 11) 2638-2438
A29: CS EXTINTORES | B29: CS EXTINTORES REPRESENTAÇÕES | D29: BRUNO | E29: 11 96359-7115
A30: CM MARMORE E GRANITO | B30: CM MARMORES E GRANITOS | C30: cm.marmore@hotmail.com | D30: ANGELO | E30: (11) 99677-8779 | F30: CNPJ: 42.794.567/0001-27 | G30: C E M ALVENARIA E COMERCIO LTDA
A31: BARRACAO ANDAIMES | B31: BARRACAO DO CONSTRUTOR PERUÍBE CNPJ: 46.387.169/0001-47 | D31: PEDRO | E31: (13) 99645-1016 | F31: CNPJ: 46387169000147 | G31: Barracao do Construtor Peruíbe
A32: MAD VERDE | B32: Concretex Com. Madeiras LTDA / Madpinus Com. Madeiras LTDA | C32: roseli.madverde@hotmail.com | D32: Roseli | E32: 11 95967-8300
A33: ITATERRA | B33: Itaterra Transportes LTDA 43.223.981/0001-49 | C33: contato@itaterraentulho.com.br | D33: Aline | E33: 11 94012-5563
A34: HAMAN BLOCOS | B34: HAMAN BLOCOS INDUSTRIA E COMERCIO LTDA | C34: financeiro_hamanblocos@hotmail.com | D34: Nilton | E34: (11) 4656-1096
A35: CASA DA LOCAÇÃO | B35: CASA DA LOCAÇÃO EIRELI-ME | C35: casadalocacao2018@hotmail.com | E35: 13 3821-2007
A36: WRC | B36: WRC HIDRAULICA LOUÇAS E METAIS LTDA | C36: gabriel@wrchidrulica.com | D36: Gabriel | E36: 11 2254-8764
A37: NSA | B37: N.S.A COMERCIO DE PARAFUSOS LTDA | C37: vendas@gruponsa.com.br | D37: Cosme | E37: 11 3976-2869
A38: RV PLASTIC | B38: RV PLASTIC FORROS E DIVISORIAS LTDA | C38: rvplastic@rvplastic.com.br | D38: Junior | E38: 11 3326-2994
A39: TELHA NORTE | B39: SAINT-GOBAIN DISTRIBUIÇÃO BRASUL LTDA | C39: augusto.endes@saint-gobain.com | D39: Augusto | E39: 11 9.8510-6170
A40: INFINITY MADEIRAS
A41: RICARDO FRETE VIDROS | B41: RICARDO FRETE DE VIDROS | D41: Ricardo | E41: 11 99965-2665 | F41: CPF :116.776.968-69 | G41: Ricardo Julio
A42: SIRO MATERIAIS ELETRICO | B42: Siro Materiais Elétricos Ltda | C42: luciana.soares@siro.com.br | D42: Luciana | E42: 11 3879-6102 | F42: 44.019.149/0001-98 | G42: Siro Materiais Eletricos
A43: SANTA ROSA | B43: H A C MATERIAIS PARA CONTRUÇÃO LTDA - SANTA ROSA
A44: NAKA | B44: NAKA GRANILITE | C44: nakagranilite@gmail.com | D44: Silvia | E44: 11 98378-6009
A45: TELHADÃO | B45: Telhadão Comercial Ltda. 02.470.293/0002-87 | C45: leonardo@telhadao.com.br | D45: Leonardo | E45: 11 97668-4346
A46: JMD | B46: JMD COMERCIO DE MATERIAIS ELETRICOS LTDA - EPP | D46: Junior | E46: 11 97562-8201
A47: N TINTAS | B47: N TINTAS COMERCIO DE TINTAS LTDA | D47: Gabriela | E47: 11 2950-5070
A48: LITOS LOCAÇÃO | B48: LITO ENTULHOS - BRUNO CEZAR CREPALDI - ME | C48: crepaldi.bruno@hotmail.com | D48: Nadja | E48: 11 94735-3954
A49: JD ONIX | B49: JD ONIX FECHADURAS E SERVIÇOS PARA ESCOLA | D49: Julio Rodrigues | E49: 11 98598-3967
A50: POLIBRA | B50: POLIBRA REPRESENTAÇÕES LTDA | D50: Percival
A51: ALTISSIMO | B51: ALTISSIMO EQUIPAMENTOS PARA CONSTRUÇÃO LTDA | D51: Fernanda | E51: 11 3526-5777
A52: ANDAIMENORTE | B52: ANDAIMENORTE LOCAÇÃO DE EQUIPAMENTO PARA CONSTRUÇÃO CIVIL LTDA | D52: Ygor
A53: BRN | B53: BRN INDUSTRIA DE QUIMICOS PARA CONSTRUÇÃO LTDA | C53: maria.santos@grupobarone.com.br | D53: Maria | E53: 11 97816-3074
A54: RISATEC | B54: RISATEC DISTRIBUIDORA DE FERRO E AÇO LTDA | C54: francisca.cavalcante@risatec.com.br | D54: Francisca | E54: 11 91315-0876
A55: LONGAMETRAGEM | B55: LONGAMETRAGEM FERRAGENS LTDA | D55: REINALDO | E55: 11 97336-0474
A56: JOSE CARLOS | B56: JOSE CARLOS DE LMEIDA M.E | C56: jc1232106@gmail.com | D56: Zeca | E56: 13 99701-2267
A57: ALFA MAQUINAS | B57: Alfa maquinas locação e serviços | C57: pablodantas@alfamaquinas.com | D57: Pablo | E57: 11 94703-7896
A58: LAJE GODEK | B58: GODEK MATERIAIS PARA CONSTRUÇÃO | C58: materiais.godek2930@gmail.com | D58: Amanda | E58: 13 99641-0608 | F58: 17.955.910.0004-73 | G58: Domingos Ramos da Silva Filho
A59: GAMELINHA | B59: GAMELINHA MATERIAIS P/ CONSTRUÇÃO LTDA ME | C59: gamelinha@terra.com.br | D59: Maria Paula | E59: 11 3313-8220
A60: DUTRA MAQUINAS | B60: DUTRA MAQUINAS | D60: Alisson
A61: TRANSLINO | B61: Translino Comercio de Areia e Pedra | C61: translinotransporte@hotmail.com | D61: Athos | E61: 11 94128-1161
A62: MAD MAIS | B62: MAD MAIS MADEIRAS LTDA | C62: NFE@MADMAIS.COM.BR | D62: Thais | E62: 11 2902-0505 | F62: CNPJ: 10785708000159 | G62: MAD MAIS MADEIRAS EM
A63: BRASIL NOVO | B63: Concreto e Lajes Brasil Novo 08408532000174 | C63: rafarocha25@hotmail.com | D63: Leandro | E63: 11 95477-5297
A64: CASA DO LOJISTA | B64: Casa do lojista atacadista de materiais para construção | C64: eduardo.silva@casadolojista.com.br | D64: Daniela | E64: 11 95839-1541
A65: GOLDONI | B65: IND. DE TELAS E ARAMES N GOLDONI LTDA | C65: comercial@telasgoldoni.com.br | D65: Priscila | E65: 11 3313-8220
A66: MITSUNARI | B66: TELAS METALICAS TELMETAL LTDA 61.217.188/0001-19 | C66: anamitsunarivendas@hotmail.com | D66: Ana Mitsunari | E66: 11 98771-7367
A67: IMPERIO AÇO | B67: IMPÉRIO COMÉRCIO DE PERFIS E TUBOS | C67: anamitsunarivendas@hotmail.com | D67: Ana Mitsunari | E67: 11 98771-7367
A68: SOUZA GÁS | B68: LF Souza Comercio de Gás - 43316169000168 | C68: van.gas2013@gmail.com | D68: LF Souza | E68: 11 91318-9870 | F68: 11984971323 | G68: LUIS FELIPE SOUZA SILVA GAS
A69: DEPOSITO ZONA SUL | B69: DEPOSITO ZONA SUL | C69: we.vendas@dzs.com.br | D69: Wellington | E69: 11 3501-1014
A70: THAMES DEEP CLEAN | B70: JLARA IND DE MAQUINAS E PRODS LIMPEZA LTDA. | C70: VENDAS@THAMESJLARA.COM.BR | D70: Thames | E70: 11 2207-7820
A71: LUMICENTER LIGHTING | B71: LUMICENTER LIGHTING | C71: lucineia.nascimento@lumicenter.com | D71: Lucineia | E71: 41 2103-2750 Ramal 2820 | F71: CNPJ: 78.331.899/0001-12
A72: CONSIGAZ MIRACATU | B72: CONSIGAZ MIRACATU CNPJ: 22.921.038/0005-63 | C72: consigazmiracatu@hotmail.com | D72: Ivan | E72: 13 99799-5103 | F72: CNPJ : 22.921.038/0005-63 | G72: Itaú Empresas MH Distribuidora
A73: ANDAIME NORTE | B73: 09.525.694/0001-55 - ANDAIMENORTE LOCACAO DE EQUIPAMENTOS | C73: Juan@andaimenorte.com.br | D73: Juan | E73: 11 93074-6369
A74: CSA AUTOMATAÇÃO | B74: CPF/CNPJ: 20.297.280/0001-59 | C74: vendas@csaautomacao.com.br | D74: Juliana | E74: 11 4200-1320 | F74: CNPJ: 20297280000159 | G74: CSA Centro de Serviços e Automação Ltda
A75: DRYKO IMPERMEABILIZANTES | B75: Indústria Dryko Ltda. CNPJ: 03.081.895/0005-58 | C75: RONALDO.AMIN1705@GMAIL.COM | D75: Ronaldo | E75: 11 99106-5488
A76: CEARÁ | B76: CEARÁ MATERIAIS P/ CONSTRUÇÃO | D76: Reginaldo | E76: 13 99195-2746
A77: CASA DA BETONEIRA | B77: 49.842.041 KARINE LARA DA SILVA | C77: adm@acasadabetoneira.com.br | D77: Karina | E77: 13 98135-1437 | F77: 49.842.041/0001-14 | G77: KARINE LARA DA SILVA
A78: ZECA | B78: José Carlos de Almeida ME CNPJ 179366170001-16 | C78: CNPJ 179366170001-16 | D78: Zeca | E78: 13 99701-2267 | F78: CNPJ 179366170001-16 | G78: José Carlos de Almeida ME
A79: ARTESANA | B79: ARTESANA DIVISÓRIAS E FORROS LTDA | D79: Amanda | E79: 11 2797-7444 | F79: 55.010.060/0001-87 | G79: Artesana Divisórias e forros LTDA
A80: OBRAMAX | B80: BMB Material de Construcao S.A. - CNPJ: 23.476.033/0001-08 | C80: lastolpho@obramax.com.br | D80: Lucia | E80: 11 94210-4263
A81: GRAMA VERDE | B81: JOSE ALEXANDRE PONTES COSTA E OUTROS CNPJ : 27.255.936/0003-81 | C81: grama4357@gmail.com | D81: Alexandre | E81: 15 99742-4670
A82: CRISTAL ATACADO | B82: Cristal Atacado de Ferramentas CNPJ: 02.054.258/0001-04 | C82: cristal.atafer@gmail.com | D82: Edmilson | E82: 11 93450-3167
A83: ELETRICA FUSÃO | B83: ELETRICA FUSÃO LTDA CNPJ: 29.719.702/0001-01 | C83: contato@eletricafusao.com.br | D83: Bruno | E83: 11 98690-3513
A84: SODIMAC | B84: Construdecor S.A - Cumbica CD | D84: Otilio | E84: 11 94006-9257
A85: BRASCON | B85: DF INDUSTRIA E COMERCIO DE CONDUTORES ELETRICOS LTDA | D85: Luciani | E85: 11 94778-9353
A86: GARCEZ | B86: Garcez Locação de Caçambas CNPJ : 16.863.500/0001-97 | C86: garcezlocacao@outlook.com | D86: Elaine | E86: 11 94032-3919
A87: CIMEMPRIMO | B87: CIMEMPRIMO DISTRIBUIDORA DE MATERIAIS DE CONSTRUÇÃO LTDA | D87: Isabel | E87: 11 2782-2004
A88: RARIDADE PISOS & AZULEJOS | B88: ROBERTO CESAR CORREA PISOS | D88: Cleide | E88: 11 97155-7219 | F88: 11 96060-7199 | G88: Cleide Tavares Ramalho
A89: PASQUETTI HIDRAULICA | B89: PASQUETTI COM MAT HIDR LTDA | C89: Marcelo@pasquetti.com.br | D89: Marcelo | E89: 11 98562-0246
A90: PRESIDENTE PARAFUSO | B90: PRESIDENTE COMERCIO DE PARAFUSOS FERRAGENS E FERRAMENTAS SOC | D90: Renato | E90: 11 99952-9490
A91: MULTI SOLUÇOES | B91: MULTI SOLUÇÕES MATERIAIS PARA CONSTRUÇÃO E SERVIÇOS | C91: adm.multisolucoes@gmail.com | D91: Bismarck | E91: (11) 940352683 | F91: CNPJ 05867073000107 | G91: LUCI MARIA CAETANO CONSTRUÇÃO
A92: DIMIBU | B92: DIMIBU INDUSTRIA DE ARTEFATOS DE PAPEL E PAPELÃO TLDA | C92: dimibu@dimibu.com.br | D92: Tainá | E92: 11 94028-2822 | F92: CNPJ: 60.810.611/0001-27 | G92: Dimibu industria de artefatos de papel e Papelão ltda
A93: ENNOVE | B93: E.N.V COMPONETES PLASTICOS E FERRAMENTARIA LTDA | C93: financeiro@ennove.ind.br | D93: Priscila | E93: (16) 3413-7235
A94: SANTA ODILA | B94: PLACHE E PLACHE LTDA | C94: staodila@uol.com.br | D94: Bianca | E94: 19 98742-6560
A95: METROPOLIS | B95: UBERTI - COMERCIO DE MATERIAIS PARA CONSTRUÇÃO LTDA | C95: compras@webmetropolis.com.br | D95: Leticia | E95: 19 2138-3519
A96: LEDMOURA | B96: LED MOURA COMERCIAL ELETRICA E HIDRAULICA LTDA EPP | C96: luccas@ledmoura.com.br | D96: Luccas | E96: 19 99191-0025
A97: ARTEX | B97: GESSO ARTEX DECOR 53.875.813/0001-91 | D97: Artex | E97: 13 3458-3922 | F97: contato@gessoartexdecor.com | G97: GESSO ARTEX DECOR COMÉRCIO E PRESTAÇÃO DE SERVIÇOS LTDA
A98: RW SOLUÇÃO AMBIENTAL | B98: RW SOLUÇÃO AMBIENTAL LTDA | C98: rwcacambas@hotmail.com | D98: Valquiria | E98: 19 98116-8363
A99: CALHAS ENGENHEIRO | B99: C. FERREIRA DOS SANTOS COMÉRCIO E SERVIÇO | D99: Cirlene | E99: 11 95803-1004
A100: FERRONOR | B100: FERRONOR COMERCIO DE FERRO E ACO LTDA | C100: ferronor@ferronor.com.br | D100: Vivian | E100: 11 2223-3913
...

Sheet UNIDADES + ITENS
A1: ITEM | C1: UNID. | E1: FORMA DE PAGAMENTO
A2: FUNDAÇÃO / ESTRUTURA | C2: UNID. | E2: PIX
A3: COBERTURA / FORRO | C3: PEÇA | E3: BOLETO
A4: HIDRAULICA | C4: LATA | E4: CARTÃO
A5: ELETRICA | C5: GALÃO
A6: REVESTMENTO / PISO | C6: M
A7: VIDRO / CAIXILHARIA | C7: M2
A8: PINTURA | C8: JOGO
A9: INCENDIO | C9: CONJ.
A10: LOCAÇÃO | C10: VERBA
A11: OUTROS | C11: KG
C12: SACO
C13: ROLO
C14: PACOTE
C15: BARRICA
C16: BALDE
C17: M3
C18: BARRA

Sheet TOTAL GERAL
A1: OBRA | B1: ITEM | C1: TOTAL | D1: 45444 | E1: 45474 | F1: 45505 | G1: 45536 | H1: 45566 | I1: 45597 | J1: 45627 | K1: 45658
A2: =A3&"-"&"TOTAL" -> WALDEMAR RIGOTO - B&B-TOTAL | C2: =SUM(D2:L2) -> 0 | D2: =SUM(D3:D12) -> 0 | E2: =SUM(E3:E12) -> 0 | F2: =SUM(F3:F12) -> 0 | G2: =SUM(G3:G12) -> 0 | H2: =SUM(H3:H12) -> 0 | I2: =SUM(I3:I12) -> 0 | J2: =SUM(J3:J12) -> 0 | K2: =SUM(K3:K12) -> 0 | L2: =SUM(L3:L12) -> 0 | M2: OBRA FINALIZADA
A3: WALDEMAR RIGOTO - B&B | B3: FUNDAÇÃO / ESTRUTURA | D3: =SUMIFS(LANÇAMENTO!$L:$L,LANÇAMENTO!$B:$B,'TOTAL GERAL'!$A$3,LANÇAMENTO!$N:$N,'TOTAL GERAL'!$D$1,LANÇAMENTO!$D:$D,'TOTAL GERAL'!$B3) -> 0 | E3: =SUMIFS(LANÇAMENTO!$L:$L,LANÇAMENTO!$B:$B,'TOTAL GERAL'!$A$3,LANÇAMENTO!$N:$N,'TOTAL GERAL'!$E$1,LANÇAMENTO!$D:$D,'TOTAL GERAL'!$B3) -> 0 | F3: =SUMIFS(LANÇAMENTO!$L:$L,LANÇAMENTO!$B:$B,'TOTAL GERAL'!$A$3,LANÇAMENTO!$N:$N,'TOTAL GERAL'!$F$1,LANÇAMENTO!$D:$D,'TOTAL GERAL'!$B3) -> 0
B4: COBERTURA / FORRO | D4: =SUMIFS(LANÇAMENTO!$L:$L,LANÇAMENTO!$B:$B,'TOTAL GERAL'!$A$3,LANÇAMENTO!$N:$N,'TOTAL GERAL'!$D$1,LANÇAMENTO!$D:$D,'TOTAL GERAL'!$B4) -> 0 | E4: =SUMIFS(LANÇAMENTO!$L:$L,LANÇAMENTO!$B:$B,'TOTAL GERAL'!$A$3,LANÇAMENTO!$N:$N,'TOTAL GERAL'!$E$1,LANÇAMENTO!$D:$D,'TOTAL GERAL'!$B4) -> 0 | F4: =SUMIFS(LANÇAMENTO!$L:$L,LANÇAMENTO!$B:$B,'TOTAL GERAL'!$A$3,LANÇAMENTO!$N:$N,'TOTAL GERAL'!$F$1,LANÇAMENTO!$D:$D,'TOTAL GERAL'!$B4) -> 0
B5: HIDRAULICA | D5: =SUMIFS(LANÇAMENTO!$L:$L,LANÇAMENTO!$B:$B,'TOTAL GERAL'!$A$3,LANÇAMENTO!$N:$N,'TOTAL GERAL'!$D$1,LANÇAMENTO!$D:$D,'TOTAL GERAL'!$B5) -> 0 | E5: =SUMIFS(LANÇAMENTO!$L:$L,LANÇAMENTO!$B:$B,'TOTAL GERAL'!$A$3,LANÇAMENTO!$N:$N,'TOTAL GERAL'!$E$1,LANÇAMENTO!$D:$D,'TOTAL GERAL'!$B5) -> 0 | F5: =SUMIFS(LANÇAMENTO!$L:$L,LANÇAMENTO!$B:$B,'TOTAL GERAL'!$A$3,LANÇAMENTO!$N:$N,'TOTAL GERAL'!$F$1,LANÇAMENTO!$D:$D,'TOTAL GERAL'!$B5) -> 0
B6: ELETRICA | D6: =SUMIFS(LANÇAMENTO!$L:$L,LANÇAMENTO!$B:$B,'TOTAL GERAL'!$A$3,LANÇAMENTO!$N:$N,'TOTAL GERAL'!$D$1,LANÇAMENTO!$D:$D,'TOTAL GERAL'!$B6) -> 0 | E6: =SUMIFS(LANÇAMENTO!$L:$L,LANÇAMENTO!$B:$B,'TOTAL GERAL'!$A$3,LANÇAMENTO!$N:$N,'TOTAL GERAL'!$E$1,LANÇAMENTO!$D:$D,'TOTAL GERAL'!$B6) -> 0 | F6: =SUMIFS(LANÇAMENTO!$L:$L,LANÇAMENTO!$B:$B,'TOTAL GERAL'!$A$3,LANÇAMENTO!$N:$N,'TOTAL GERAL'!$F$1,LANÇAMENTO!$D:$D,'TOTAL GERAL'!$B6) -> 0
B7: REVESTMENTO / PISO | D7: =SUMIFS(LANÇAMENTO!$L:$L,LANÇAMENTO!$B:$B,'TOTAL GERAL'!$A$3,LANÇAMENTO!$N:$N,'TOTAL GERAL'!$D$1,LANÇAMENTO!$D:$D,'TOTAL GERAL'!$B7) -> 0 | E7: =SUMIFS(LANÇAMENTO!$L:$L,LANÇAMENTO!$B:$B,'TOTAL GERAL'!$A$3,LANÇAMENTO!$N:$N,'TOTAL GERAL'!$E$1,LANÇAMENTO!$D:$D,'TOTAL GERAL'!$B7) -> 0 | F7: =SUMIFS(LANÇAMENTO!$L:$L,LANÇAMENTO!$B:$B,'TOTAL GERAL'!$A$3,LANÇAMENTO!$N:$N,'TOTAL GERAL'!$F$1,LANÇAMENTO!$D:$D,'TOTAL GERAL'!$B7) -> 0
B8: VIDRO / CAIXILHARIA | D8: =SUMIFS(LANÇAMENTO!$L:$L,LANÇAMENTO!$B:$B,'TOTAL GERAL'!$A$3,LANÇAMENTO!$N:$N,'TOTAL GERAL'!$D$1,LANÇAMENTO!$D:$D,'TOTAL GERAL'!$B8) -> 0 | E8: =SUMIFS(LANÇAMENTO!$L:$L,LANÇAMENTO!$B:$B,'TOTAL GERAL'!$A$3,LANÇAMENTO!$N:$N,'TOTAL GERAL'!$E$1,LANÇAMENTO!$D:$D,'TOTAL GERAL'!$B8) -> 0 | F8: =SUMIFS(LANÇAMENTO!$L:$L,LANÇAMENTO!$B:$B,'TOTAL GERAL'!$A$3,LANÇAMENTO!$N:$N,'TOTAL GERAL'!$F$1,LANÇAMENTO!$D:$D,'TOTAL GERAL'!$B8) -> 0
B9: PINTURA | D9: =SUMIFS(LANÇAMENTO!$L:$L,LANÇAMENTO!$B:$B,'TOTAL GERAL'!$A$3,LANÇAMENTO!$N:$N,'TOTAL GERAL'!$D$1,LANÇAMENTO!$D:$D,'TOTAL GERAL'!$B9) -> 0 | E9: =SUMIFS(LANÇAMENTO!$L:$L,LANÇAMENTO!$B:$B,'TOTAL GERAL'!$A$3,LANÇAMENTO!$N:$N,'TOTAL GERAL'!$E$1,LANÇAMENTO!$D:$D,'TOTAL GERAL'!$B9) -> 0 | F9: =SUMIFS(LANÇAMENTO!$L:$L,LANÇAMENTO!$B:$B,'TOTAL GERAL'!$A$3,LANÇAMENTO!$N:$N,'TOTAL GERAL'!$F$1,LANÇAMENTO!$D:$D,'TOTAL GERAL'!$B9) -> 0
B10: INCENDIO | D10: =SUMIFS(LANÇAMENTO!$L:$L,LANÇAMENTO!$B:$B,'TOTAL GERAL'!$A$3,LANÇAMENTO!$N:$N,'TOTAL GERAL'!$D$1,LANÇAMENTO!$D:$D,'TOTAL GERAL'!$B10) -> 0 | E10: =SUMIFS(LANÇAMENTO!$L:$L,LANÇAMENTO!$B:$B,'TOTAL GERAL'!$A$3,LANÇAMENTO!$N:$N,'TOTAL GERAL'!$E$1,LANÇAMENTO!$D:$D,'TOTAL GERAL'!$B10) -> 0 | F10: =SUMIFS(LANÇAMENTO!$L:$L,LANÇAMENTO!$B:$B,'TOTAL GERAL'!$A$3,LANÇAMENTO!$N:$N,'TOTAL GERAL'!$F$1,LANÇAMENTO!$D:$D,'TOTAL GERAL'!$B10) -> 0
B11: LOCAÇÃO | D11: =SUMIFS(LANÇAMENTO!$L:$L,LANÇAMENTO!$B:$B,'TOTAL GERAL'!$A$3,LANÇAMENTO!$N:$N,'TOTAL GERAL'!$D$1,LANÇAMENTO!$D:$D,'TOTAL GERAL'!$B11) -> 0 | E11: =SUMIFS(LANÇAMENTO!$L:$L,LANÇAMENTO!$B:$B,'TOTAL GERAL'!$A$3,LANÇAMENTO!$N:$N,'TOTAL GERAL'!$E$1,LANÇAMENTO!$D:$D,'TOTAL GERAL'!$B11) -> 0 | F11: =SUMIFS(LANÇAMENTO!$L:$L,LANÇAMENTO!$B:$B,'TOTAL GERAL'!$A$3,LANÇAMENTO!$N:$N,'TOTAL GERAL'!$F$1,LANÇAMENTO!$D:$D,'TOTAL GERAL'!$B11) -> 0
B12: OUTROS | D12: =SUMIFS(LANÇAMENTO!$L:$L,LANÇAMENTO!$B:$B,'TOTAL GERAL'!$A$3,LANÇAMENTO!$N:$N,'TOTAL GERAL'!$D$1,LANÇAMENTO!$D:$D,'TOTAL GERAL'!$B12) -> 0 | E12: =SUMIFS(LANÇAMENTO!$L:$L,LANÇAMENTO!$B:$B,'TOTAL GERAL'!$A$3,LANÇAMENTO!$N:$N,'TOTAL GERAL'!$E$1,LANÇAMENTO!$D:$D,'TOTAL GERAL'!$B12) -> 0 | F12: =SUMIFS(LANÇAMENTO!$L:$L,LANÇAMENTO!$B:$B,'TOTAL GERAL'!$A$3,LANÇAMENTO!$N:$N,'TOTAL GERAL'!$F$1,LANÇAMENTO!$D:$D,'TOTAL GERAL'!$B12) -> 0
A13: =A14&"-"&"TOTAL" -> PEDRO COSTA - JB-TOTAL | C13: =SUM(F13:L13) -> 0 | F13: =SUM(F14:F23) -> 0 | G13: =SUM(G14:G23) -> 0 | H13: =SUM(H14:H23) -> 0 | I13: =SUM(I14:I23) -> 0 | J13: =SUM(J14:J23) -> 0 | K13: =SUM(K14:K23) -> 0 | L13: =SUM(L14:L23) -> 0 | N13: OK
A14: PEDRO COSTA - JB | B14: FUNDAÇÃO / ESTRUTURA | F14: =SUMIFS(LANÇAMENTO!$L:$L,LANÇAMENTO!$B:$B,'TOTAL GERAL'!$A$14,LANÇAMENTO!$N:$N,'TOTAL GERAL'!$F$1,LANÇAMENTO!$D:$D,'TOTAL GERAL'!$B14) -> 0 | G14: =SUMIFS(LANÇAMENTO!$L:$L,LANÇAMENTO!$B:$B,'TOTAL GERAL'!$A$14,LANÇAMENTO!$N:$N,'TOTAL GERAL'!$G$1,LANÇAMENTO!$D:$D,'TOTAL GERAL'!$B14) -> 0 | H14: =SUMIFS(LANÇAMENTO!$L:$L,LANÇAMENTO!$B:$B,'TOTAL GERAL'!$A$14,LANÇAMENTO!$N:$N,'TOTAL GERAL'!$H$1,LANÇAMENTO!$D:$D,'TOTAL GERAL'!$B14) -> 0
B15: COBERTURA / FORRO | F15: =SUMIFS(LANÇAMENTO!$L:$L,LANÇAMENTO!$B:$B,'TOTAL GERAL'!$A$14,LANÇAMENTO!$N:$N,'TOTAL GERAL'!$F$1,LANÇAMENTO!$D:$D,'TOTAL GERAL'!$B15) -> 0 | G15: =SUMIFS(LANÇAMENTO!$L:$L,LANÇAMENTO!$B:$B,'TOTAL GERAL'!$A$14,LANÇAMENTO!$N:$N,'TOTAL GERAL'!$G$1,LANÇAMENTO!$D:$D,'TOTAL GERAL'!$B15) -> 0 | H15: =SUMIFS(LANÇAMENTO!$L:$L,LANÇAMENTO!$B:$B,'TOTAL GERAL'!$A$14,LANÇAMENTO!$N:$N,'TOTAL GERAL'!$H$1,LANÇAMENTO!$D:$D,'TOTAL GERAL'!$B15) -> 0
B16: HIDRAULICA | F16: =SUMIFS(LANÇAMENTO!$L:$L,LANÇAMENTO!$B:$B,'TOTAL GERAL'!$A$14,LANÇAMENTO!$N:$N,'TOTAL GERAL'!$F$1,LANÇAMENTO!$D:$D,'TOTAL GERAL'!$B16) -> 0 | G16: =SUMIFS(LANÇAMENTO!$L:$L,LANÇAMENTO!$B:$B,'TOTAL GERAL'!$A$14,LANÇAMENTO!$N:$N,'TOTAL GERAL'!$G$1,LANÇAMENTO!$D:$D,'TOTAL GERAL'!$B16) -> 0 | H16: =SUMIFS(LANÇAMENTO!$L:$L,LANÇAMENTO!$B:$B,'TOTAL GERAL'!$A$14,LANÇAMENTO!$N:$N,'TOTAL GERAL'!$H$1,LANÇAMENTO!$D:$D,'TOTAL GERAL'!$B16) -> 0
B17: ELETRICA | F17: =SUMIFS(LANÇAMENTO!$L:$L,LANÇAMENTO!$B:$B,'TOTAL GERAL'!$A$14,LANÇAMENTO!$N:$N,'TOTAL GERAL'!$F$1,LANÇAMENTO!$D:$D,'TOTAL GERAL'!$B17) -> 0 | G17: =SUMIFS(LANÇAMENTO!$L:$L,LANÇAMENTO!$B:$B,'TOTAL GERAL'!$A$14,LANÇAMENTO!$N:$N,'TOTAL GERAL'!$G$1,LANÇAMENTO!$D:$D,'TOTAL GERAL'!$B17) -> 0 | H17: =SUMIFS(LANÇAMENTO!$L:$L,LANÇAMENTO!$B:$B,'TOTAL GERAL'!$A$14,LANÇAMENTO!$N:$N,'TOTAL GERAL'!$H$1,LANÇAMENTO!$D:$D,'TOTAL GERAL'!$B17) -> 0
B18: REVESTMENTO / PISO | F18: =SUMIFS(LANÇAMENTO!$L:$L,LANÇAMENTO!$B:$B,'TOTAL GERAL'!$A$14,LANÇAMENTO!$N:$N,'TOTAL GERAL'!$F$1,LANÇAMENTO!$D:$D,'TOTAL GERAL'!$B18) -> 0 | G18: =SUMIFS(LANÇAMENTO!$L:$L,LANÇAMENTO!$B:$B,'TOTAL GERAL'!$A$14,LANÇAMENTO!$N:$N,'TOTAL GERAL'!$G$1,LANÇAMENTO!$D:$D,'TOTAL GERAL'!$B18) -> 0 | H18: =SUMIFS(LANÇAMENTO!$L:$L,LANÇAMENTO!$B:$B,'TOTAL GERAL'!$A$14,LANÇAMENTO!$N:$N,'TOTAL GERAL'!$H$1,LANÇAMENTO!$D:$D,'TOTAL GERAL'!$B18) -> 0
B19: VIDRO / CAIXILHARIA | F19: =SUMIFS(LANÇAMENTO!$L:$L,LANÇAMENTO!$B:$B,'TOTAL GERAL'!$A$14,LANÇAMENTO!$N:$N,'TOTAL GERAL'!$F$1,LANÇAMENTO!$D:$D,'TOTAL GERAL'!$B19) -> 0 | G19: =SUMIFS(LANÇAMENTO!$L:$L,LANÇAMENTO!$B:$B,'TOTAL GERAL'!$A$14,LANÇAMENTO!$N:$N,'TOTAL GERAL'!$G$1,LANÇAMENTO!$D:$D,'TOTAL GERAL'!$B19) -> 0 | H19: =SUMIFS(LANÇAMENTO!$L:$L,LANÇAMENTO!$B:$B,'TOTAL GERAL'!$A$14,LANÇAMENTO!$N:$N,'TOTAL GERAL'!$H$1,LANÇAMENTO!$D:$D,'TOTAL GERAL'!$B19) -> 0
B20: PINTURA | F20: =SUMIFS(LANÇAMENTO!$L:$L,LANÇAMENTO!$B:$B,'TOTAL GERAL'!$A$14,LANÇAMENTO!$N:$N,'TOTAL GERAL'!$F$1,LANÇAMENTO!$D:$D,'TOTAL GERAL'!$B20) -> 0 | G20: =SUMIFS(LANÇAMENTO!$L:$L,LANÇAMENTO!$B:$B,'TOTAL GERAL'!$A$14,LANÇAMENTO!$N:$N,'TOTAL GERAL'!$G$1,LANÇAMENTO!$D:$D,'TOTAL GERAL'!$B20) -> 0 | H20: =SUMIFS(LANÇAMENTO!$L:$L,LANÇAMENTO!$B:$B,'TOTAL GERAL'!$A$14,LANÇAMENTO!$N:$N,'TOTAL GERAL'!$H$1,LANÇAMENTO!$D:$D,'TOTAL GERAL'!$B20) -> 0
B21: INCENDIO | F21: =SUMIFS(LANÇAMENTO!$L:$L,LANÇAMENTO!$B:$B,'TOTAL GERAL'!$A$14,LANÇAMENTO!$N:$N,'TOTAL GERAL'!$F$1,LANÇAMENTO!$D:$D,'TOTAL GERAL'!$B21) -> 0 | G21: =SUMIFS(LANÇAMENTO!$L:$L,LANÇAMENTO!$B:$B,'TOTAL GERAL'!$A$14,LANÇAMENTO!$N:$N,'TOTAL GERAL'!$G$1,LANÇAMENTO!$D:$D,'TOTAL GERAL'!$B21) -> 0 | H21: =SUMIFS(LANÇAMENTO!$L:$L,LANÇAMENTO!$B:$B,'TOTAL GERAL'!$A$14,LANÇAMENTO!$N:$N,'TOTAL GERAL'!$H$1,LANÇAMENTO!$D:$D,'TOTAL GERAL'!$B21) -> 0
B22: LOCAÇÃO | F22: =SUMIFS(LANÇAMENTO!$L:$L,LANÇAMENTO!$B:$B,'TOTAL GERAL'!$A$14,LANÇAMENTO!$N:$N,'TOTAL GERAL'!$F$1,LANÇAMENTO!$D:$D,'TOTAL GERAL'!$B22) -> 0 | G22: =SUMIFS(LANÇAMENTO!$L:$L,LANÇAMENTO!$B:$B,'TOTAL GERAL'!$A$14,LANÇAMENTO!$N:$N,'TOTAL GERAL'!$G$1,LANÇAMENTO!$D:$D,'TOTAL GERAL'!$B22) -> 0 | H22: =SUMIFS(LANÇAMENTO!$L:$L,LANÇAMENTO!$B:$B,'TOTAL GERAL'!$A$14,LANÇAMENTO!$N:$N,'TOTAL GERAL'!$H$1,LANÇAMENTO!$D:$D,'TOTAL GERAL'!$B22) -> 0
B23: OUTROS | F23: =SUMIFS(LANÇAMENTO!$L:$L,LANÇAMENTO!$B:$B,'TOTAL GERAL'!$A$14,LANÇAMENTO!$N:$N,'TOTAL GERAL'!$F$1,LANÇAMENTO!$D:$D,'TOTAL GERAL'!$B23) -> 0 | G23: =SUMIFS(LANÇAMENTO!$L:$L,LANÇAMENTO!$B:$B,'TOTAL GERAL'!$A$14,LANÇAMENTO!$N:$N,'TOTAL GERAL'!$G$1,LANÇAMENTO!$D:$D,'TOTAL GERAL'!$B23) -> 0 | H23: =SUMIFS(LANÇAMENTO!$L:$L,LANÇAMENTO!$B:$B,'TOTAL GERAL'!$A$14,LANÇAMENTO!$N:$N,'TOTAL GERAL'!$H$1,LANÇAMENTO!$D:$D,'TOTAL GERAL'!$B23) -> 0
A24: =A25&"-"&"TOTAL" -> BENEDITO TOLOSA - JB-TOTAL | C24: =SUM(F24:L24) -> 0 | F24: =SUM(F25:F34) -> 0 | G24: =SUM(G25:G34) -> 0 | H24: =SUM(H25:H34) -> 0 | I24: =SUM(I25:I34) -> 0 | J24: =SUM(J25:J34) -> 0 | K24: =SUM(K25:K34) -> 0 | L24: =SUM(L25:L34) -> 0 | N24: OK
A25: BENEDITO TOLOSA - JB | B25: FUNDAÇÃO / ESTRUTURA | F25: =SUMIFS(LANÇAMENTO!$L:$L,LANÇAMENTO!$B:$B,'TOTAL GERAL'!$A$25,LANÇAMENTO!$N:$N,'TOTAL GERAL'!$F$1,LANÇAMENTO!$D:$D,'TOTAL GERAL'!$B25) -> 0 | G25: =SUMIFS(LANÇAMENTO!$L:$L,LANÇAMENTO!$B:$B,'TOTAL GERAL'!$A$25,LANÇAMENTO!$N:$N,'TOTAL GERAL'!$G$1,LANÇAMENTO!$D:$D,'TOTAL GERAL'!$B25) -> 0 | H25: =SUMIFS(LANÇAMENTO!$L:$L,LANÇAMENTO!$B:$B,'TOTAL GERAL'!$A$25,LANÇAMENTO!$N:$N,'TOTAL GERAL'!$H$1,LANÇAMENTO!$D:$D,'TOTAL GERAL'!$B25) -> 0
B26: COBERTURA / FORRO | F26: =SUMIFS(LANÇAMENTO!$L:$L,LANÇAMENTO!$B:$B,'TOTAL GERAL'!$A$25,LANÇAMENTO!$N:$N,'TOTAL GERAL'!$F$1,LANÇAMENTO!$D:$D,'TOTAL GERAL'!$B26) -> 0 | G26: =SUMIFS(LANÇAMENTO!$L:$L,LANÇAMENTO!$B:$B,'TOTAL GERAL'!$A$25,LANÇAMENTO!$N:$N,'TOTAL GERAL'!$G$1,LANÇAMENTO!$D:$D,'TOTAL GERAL'!$B26) -> 0 | H26: =SUMIFS(LANÇAMENTO!$L:$L,LANÇAMENTO!$B:$B,'TOTAL GERAL'!$A$25,LANÇAMENTO!$N:$N,'TOTAL GERAL'!$H$1,LANÇAMENTO!$D:$D,'TOTAL GERAL'!$B26) -> 0
B27: HIDRAULICA | F27: =SUMIFS(LANÇAMENTO!$L:$L,LANÇAMENTO!$B:$B,'TOTAL GERAL'!$A$25,LANÇAMENTO!$N:$N,'TOTAL GERAL'!$F$1,LANÇAMENTO!$D:$D,'TOTAL GERAL'!$B27) -> 0 | G27: =SUMIFS(LANÇAMENTO!$L:$L,LANÇAMENTO!$B:$B,'TOTAL GERAL'!$A$25,LANÇAMENTO!$N:$N,'TOTAL GERAL'!G$1,LANÇAMENTO!$D:$D,'TOTAL GERAL'!$B27) -> 0 | H27: =SUMIFS(LANÇAMENTO!$L:$L,LANÇAMENTO!$B:$B,'TOTAL GERAL'!$A$25,LANÇAMENTO!$N:$N,'TOTAL GERAL'!H$1,LANÇAMENTO!$D:$D,'TOTAL GERAL'!$B27) -> 0
B28: ELETRICA | F28: =SUMIFS(LANÇAMENTO!$L:$L,LANÇAMENTO!$B:$B,'TOTAL GERAL'!$A$25,LANÇAMENTO!$N:$N,'TOTAL GERAL'!$F$1,LANÇAMENTO!$D:$D,'TOTAL GERAL'!$B28) -> 0 | G28: =SUMIFS(LANÇAMENTO!$L:$L,LANÇAMENTO!$B:$B,'TOTAL GERAL'!$A$25,LANÇAMENTO!$N:$N,'TOTAL GERAL'!$G$1,LANÇAMENTO!$D:$D,'TOTAL GERAL'!$B28) -> 0 | H28: =SUMIFS(LANÇAMENTO!$L:$L,LANÇAMENTO!$B:$B,'TOTAL GERAL'!$A$25,LANÇAMENTO!$N:$N,'TOTAL GERAL'!$H$1,LANÇAMENTO!$D:$D,'TOTAL GERAL'!$B28) -> 0
B29: REVESTMENTO / PISO | F29: =SUMIFS(LANÇAMENTO!$L:$L,LANÇAMENTO!$B:$B,'TOTAL GERAL'!$A$25,LANÇAMENTO!$N:$N,'TOTAL GERAL'!$F$1,LANÇAMENTO!$D:$D,'TOTAL GERAL'!$B29) -> 0 | G29: =SUMIFS(LANÇAMENTO!$L:$L,LANÇAMENTO!$B:$B,'TOTAL GERAL'!$A$25,LANÇAMENTO!$N:$N,'TOTAL GERAL'!$G$1,LANÇAMENTO!$D:$D,'TOTAL GERAL'!$B29) -> 0 | H29: =SUMIFS(LANÇAMENTO!$L:$L,LANÇAMENTO!$B:$B,'TOTAL GERAL'!$A$25,LANÇAMENTO!$N:$N,'TOTAL GERAL'!$H$1,LANÇAMENTO!$D:$D,'TOTAL GERAL'!$B29) -> 0
B30: VIDRO / CAIXILHARIA | F30: =SUMIFS(LANÇAMENTO!$L:$L,LANÇAMENTO!$B:$B,'TOTAL GERAL'!$A$25,LANÇAMENTO!$N:$N,'TOTAL GERAL'!$F$1,LANÇAMENTO!$D:$D,'TOTAL GERAL'!$B30) -> 0 | G30: =SUMIFS(LANÇAMENTO!$L:$L,LANÇAMENTO!$B:$B,'TOTAL GERAL'!$A$25,LANÇAMENTO!$N:$N,'TOTAL GERAL'!$G$1,LANÇAMENTO!$D:$D,'TOTAL GERAL'!$B30) -> 0 | H30: =SUMIFS(LANÇAMENTO!$L:$L,LANÇAMENTO!$B:$B,'TOTAL GERAL'!$A$25,LANÇAMENTO!$N:$N,'TOTAL GERAL'!$H$1,LANÇAMENTO!$D:$D,'TOTAL GERAL'!$B30) -> 0
B31: PINTURA | F31: =SUMIFS(LANÇAMENTO!$L:$L,LANÇAMENTO!$B:$B,'TOTAL GERAL'!$A$25,LANÇAMENTO!$N:$N,'TOTAL GERAL'!$F$1,LANÇAMENTO!$D:$D,'TOTAL GERAL'!$B31) -> 0 | G31: =SUMIFS(LANÇAMENTO!$L:$L,LANÇAMENTO!$B:$B,'TOTAL GERAL'!$A$25,LANÇAMENTO!$N:$N,'TOTAL GERAL'!$G$1,LANÇAMENTO!$D:$D,'TOTAL GERAL'!$B31) -> 0 | H31: =SUMIFS(LANÇAMENTO!$L:$L,LANÇAMENTO!$B:$B,'TOTAL GERAL'!$A$25,LANÇAMENTO!$N:$N,'TOTAL GERAL'!$H$1,LANÇAMENTO!$D:$D,'TOTAL GERAL'!$B31) -> 0
B32: INCENDIO | F32: =SUMIFS(LANÇAMENTO!$L:$L,LANÇAMENTO!$B:$B,'TOTAL GERAL'!$A$25,LANÇAMENTO!$N:$N,'TOTAL GERAL'!$F$1,LANÇAMENTO!$D:$D,'TOTAL GERAL'!$B32) -> 0 | G32: =SUMIFS(LANÇAMENTO!$L:$L,LANÇAMENTO!$B:$B,'TOTAL GERAL'!$A$25,LANÇAMENTO!$N:$N,'TOTAL GERAL'!$G$1,LANÇAMENTO!$D:$D,'TOTAL GERAL'!$B32) -> 0 | H32: =SUMIFS(LANÇAMENTO!$L:$L,LANÇAMENTO!$B:$B,'TOTAL GERAL'!$A$25,LANÇAMENTO!$N:$N,'TOTAL GERAL'!$H$1,LANÇAMENTO!$D:$D,'TOTAL GERAL'!$B32) -> 0
B33: LOCAÇÃO | F33: =SUMIFS(LANÇAMENTO!$L:$L,LANÇAMENTO!$B:$B,'TOTAL GERAL'!$A$25,LANÇAMENTO!$N:$N,'TOTAL GERAL'!$F$1,LANÇAMENTO!$D:$D,'TOTAL GERAL'!$B33) -> 0 | G33: =SUMIFS(LANÇAMENTO!$L:$L,LANÇAMENTO!$B:$B,'TOTAL GERAL'!$A$25,LANÇAMENTO!$N:$N,'TOTAL GERAL'!$G$1,LANÇAMENTO!$D:$D,'TOTAL GERAL'!$B33) -> 0 | H33: =SUMIFS(LANÇAMENTO!$L:$L,LANÇAMENTO!$B:$B,'TOTAL GERAL'!$A$25,LANÇAMENTO!$N:$N,'TOTAL GERAL'!$H$1,LANÇAMENTO!$D:$D,'TOTAL GERAL'!$B33) -> 0
B34: OUTROS | F34: =SUMIFS(LANÇAMENTO!$L:$L,LANÇAMENTO!$B:$B,'TOTAL GERAL'!$A$25,LANÇAMENTO!$N:$N,'TOTAL GERAL'!$F$1,LANÇAMENTO!$D:$D,'TOTAL GERAL'!$B34) -> 0 | G34: =SUMIFS(LANÇAMENTO!$L:$L,LANÇAMENTO!$B:$B,'TOTAL GERAL'!$A$25,LANÇAMENTO!$N:$N,'TOTAL GERAL'!$G$1,LANÇAMENTO!$D:$D,'TOTAL GERAL'!$B34) -> 0 | H34: =SUMIFS(LANÇAMENTO!$L:$L,LANÇAMENTO!$B:$B,'TOTAL GERAL'!$A$25,LANÇAMENTO!$N:$N,'TOTAL GERAL'!$H$1,LANÇAMENTO!$D:$D,'TOTAL GERAL'!$B34) -> 0
A35: =A36&"-"&"TOTAL" -> PEDRO BARROS-TOTAL | C35: =SUM(F35:L35) -> 0 | F35: =SUM(F36:F45) -> 0 | G35: =SUM(G36:G45) -> 0 | H35: =SUM(H36:H45) -> 0 | I35: =SUM(I36:I45) -> 0 | J35: =SUM(J36:J45) -> 0 | K35: =SUM(K36:K45) -> 0 | L35: =SUM(L36:L45) -> 0 | N35: OK
A36: PEDRO BARROS | B36: FUNDAÇÃO / ESTRUTURA | F36: =SUMIFS(LANÇAMENTO!$L:$L,LANÇAMENTO!$B:$B,'TOTAL GERAL'!$A$36,LANÇAMENTO!$N:$N,'TOTAL GERAL'!$F$1,LANÇAMENTO!$D:$D,'TOTAL GERAL'!$B36) -> 0 | G36: =SUMIFS(LANÇAMENTO!$L:$L,LANÇAMENTO!$B:$B,'TOTAL GERAL'!$A$36,LANÇAMENTO!$N:$N,'TOTAL GERAL'!$G$1,LANÇAMENTO!$D:$D,'TOTAL GERAL'!$B36) -> 0 | H36: =SUMIFS(LANÇAMENTO!$L:$L,LANÇAMENTO!$B:$B,'TOTAL GERAL'!$A$36,LANÇAMENTO!$N:$N,'TOTAL GERAL'!$H$1,LANÇAMENTO!$D:$D,'TOTAL GERAL'!$B36) -> 0
B37: COBERTURA / FORRO | F37: =SUMIFS(LANÇAMENTO!$L:$L,LANÇAMENTO!$B:$B,'TOTAL GERAL'!$A$36,LANÇAMENTO!$N:$N,'TOTAL GERAL'!$F$1,LANÇAMENTO!$D:$D,'TOTAL GERAL'!$B37) -> 0 | G37: =SUMIFS(LANÇAMENTO!$L:$L,LANÇAMENTO!$B:$B,'TOTAL GERAL'!$A$36,LANÇAMENTO!$N:$N,'TOTAL GERAL'!$G$1,LANÇAMENTO!$D:$D,'TOTAL GERAL'!$B37) -> 0 | H37: =SUMIFS(LANÇAMENTO!$L:$L,LANÇAMENTO!$B:$B,'TOTAL GERAL'!$A$36,LANÇAMENTO!$N:$N,'TOTAL GERAL'!$H$1,LANÇAMENTO!$D:$D,'TOTAL GERAL'!$B37) -> 0
B38: HIDRAULICA | F38: =SUMIFS(LANÇAMENTO!$L:$L,LANÇAMENTO!$B:$B,'TOTAL GERAL'!$A$36,LANÇAMENTO!$N:$N,'TOTAL GERAL'!$F$1,LANÇAMENTO!$D:$D,'TOTAL GERAL'!$B38) -> 0 | G38: =SUMIFS(LANÇAMENTO!$L:$L,LANÇAMENTO!$B:$B,'TOTAL GERAL'!$A$36,LANÇAMENTO!$N:$N,'TOTAL GERAL'!$G$1,LANÇAMENTO!$D:$D,'TOTAL GERAL'!$B38) -> 0 | H38: =SUMIFS(LANÇAMENTO!$L:$L,LANÇAMENTO!$B:$B,'TOTAL GERAL'!$A$36,LANÇAMENTO!$N:$N,'TOTAL GERAL'!$H$1,LANÇAMENTO!$D:$D,'TOTAL GERAL'!$B38) -> 0
B39: ELETRICA | F39: =SUMIFS(LANÇAMENTO!$L:$L,LANÇAMENTO!$B:$B,'TOTAL GERAL'!$A$36,LANÇAMENTO!$N:$N,'TOTAL GERAL'!$F$1,LANÇAMENTO!$D:$D,'TOTAL GERAL'!$B39) -> 0 | G39: =SUMIFS(LANÇAMENTO!$L:$L,LANÇAMENTO!$B:$B,'TOTAL GERAL'!$A$36,LANÇAMENTO!$N:$N,'TOTAL GERAL'!$G$1,LANÇAMENTO!$D:$D,'TOTAL GERAL'!$B39) -> 0 | H39: =SUMIFS(LANÇAMENTO!$L:$L,LANÇAMENTO!$B:$B,'TOTAL GERAL'!$A$36,LANÇAMENTO!$N:$N,'TOTAL GERAL'!$H$1,LANÇAMENTO!$D:$D,'TOTAL GERAL'!$B39) -> 0
B40: REVESTMENTO / PISO | F40: =SUMIFS(LANÇAMENTO!$L:$L,LANÇAMENTO!$B:$B,'TOTAL GERAL'!$A$36,LANÇAMENTO!$N:$N,'TOTAL GERAL'!$F$1,LANÇAMENTO!$D:$D,'TOTAL GERAL'!$B40) -> 0 | G40: =SUMIFS(LANÇAMENTO!$L:$L,LANÇAMENTO!$B:$B,'TOTAL GERAL'!$A$36,LANÇAMENTO!$N:$N,'TOTAL GERAL'!$G$1,LANÇAMENTO!$D:$D,'TOTAL GERAL'!$B40) -> 0 | H40: =SUMIFS(LANÇAMENTO!$L:$L,LANÇAMENTO!$B:$B,'TOTAL GERAL'!$A$36,LANÇAMENTO!$N:$N,'TOTAL GERAL'!$H$1,LANÇAMENTO!$D:$D,'TOTAL GERAL'!$B40) -> 0
B41: VIDRO / CAIXILHARIA | F41: =SUMIFS(LANÇAMENTO!$L:$L,LANÇAMENTO!$B:$B,'TOTAL GERAL'!$A$36,LANÇAMENTO!$N:$N,'TOTAL GERAL'!$F$1,LANÇAMENTO!$D:$D,'TOTAL GERAL'!$B41) -> 0 | G41: =SUMIFS(LANÇAMENTO!$L:$L,LANÇAMENTO!$B:$B,'TOTAL GERAL'!$A$36,LANÇAMENTO!$N:$N,'TOTAL GERAL'!$G$1,LANÇAMENTO!$D:$D,'TOTAL GERAL'!$B41) -> 0 | H41: =SUMIFS(LANÇAMENTO!$L:$L,LANÇAMENTO!$B:$B,'TOTAL GERAL'!$A$36,LANÇAMENTO!$N:$N,'TOTAL GERAL'!$H$1,LANÇAMENTO!$D:$D,'TOTAL GERAL'!$B41) -> 0
B42: PINTURA | F42: =SUMIFS(LANÇAMENTO!$L:$L,LANÇAMENTO!$B:$B,'TOTAL GERAL'!$A$36,LANÇAMENTO!$N:$N,'TOTAL GERAL'!$F$1,LANÇAMENTO!$D:$D,'TOTAL GERAL'!$B42) -> 0 | G42: =SUMIFS(LANÇAMENTO!$L:$L,LANÇAMENTO!$B:$B,'TOTAL GERAL'!$A$36,LANÇAMENTO!$N:$N,'TOTAL GERAL'!$G$1,LANÇAMENTO!$D:$D,'TOTAL GERAL'!$B42) -> 0 | H42: =SUMIFS(LANÇAMENTO!$L:$L,LANÇAMENTO!$B:$B,'TOTAL GERAL'!$A$36,LANÇAMENTO!$N:$N,'TOTAL GERAL'!$H$1,LANÇAMENTO!$D:$D,'TOTAL GERAL'!$B42) -> 0
B43: INCENDIO | F43: =SUMIFS(LANÇAMENTO!$L:$L,LANÇAMENTO!$B:$B,'TOTAL GERAL'!$A$36,LANÇAMENTO!$N:$N,'TOTAL GERAL'!$F$1,LANÇAMENTO!$D:$D,'TOTAL GERAL'!$B43) -> 0 | G43: =SUMIFS(LANÇAMENTO!$L:$L,LANÇAMENTO!$B:$B,'TOTAL GERAL'!$A$36,LANÇAMENTO!$N:$N,'TOTAL GERAL'!$G$1,LANÇAMENTO!$D:$D,'TOTAL GERAL'!$B43) -> 0 | H43: =SUMIFS(LANÇAMENTO!$L:$L,LANÇAMENTO!$B:$B,'TOTAL GERAL'!$A$36,LANÇAMENTO!$N:$N,'TOTAL GERAL'!$H$1,LANÇAMENTO!$D:$D,'TOTAL GERAL'!$B43) -> 0
B44: LOCAÇÃO | F44: =SUMIFS(LANÇAMENTO!$L:$L,LANÇAMENTO!$B:$B,'TOTAL GERAL'!$A$36,LANÇAMENTO!$N:$N,'TOTAL GERAL'!$F$1,LANÇAMENTO!$D:$D,'TOTAL GERAL'!$B44) -> 0 | G44: =SUMIFS(LANÇAMENTO!$L:$L,LANÇAMENTO!$B:$B,'TOTAL GERAL'!$A$36,LANÇAMENTO!$N:$N,'TOTAL GERAL'!$G$1,LANÇAMENTO!$D:$D,'TOTAL GERAL'!$B44) -> 0 | H44: =SUMIFS(LANÇAMENTO!$L:$L,LANÇAMENTO!$B:$B,'TOTAL GERAL'!$A$36,LANÇAMENTO!$N:$N,'TOTAL GERAL'!$H$1,LANÇAMENTO!$D:$D,'TOTAL GERAL'!$B44) -> 0
B45: OUTROS | F45: =SUMIFS(LANÇAMENTO!$L:$L,LANÇAMENTO!$B:$B,'TOTAL GERAL'!$A$36,LANÇAMENTO!$N:$N,'TOTAL GERAL'!$F$1,LANÇAMENTO!$D:$D,'TOTAL GERAL'!$B45) -> 0 | G45: =SUMIFS(LANÇAMENTO!$L:$L,LANÇAMENTO!$B:$B,'TOTAL GERAL'!$A$36,LANÇAMENTO!$N:$N,'TOTAL GERAL'!$G$1,LANÇAMENTO!$D:$D,'TOTAL GERAL'!$B45) -> 0 | H45: =SUMIFS(LANÇAMENTO!$L:$L,LANÇAMENTO!$B:$B,'TOTAL GERAL'!$A$36,LANÇAMENTO!$N:$N,'TOTAL GERAL'!$H$1,LANÇAMENTO!$D:$D,'TOTAL GERAL'!$B45) -> 0
A46: =A47&"-"&"TOTAL" -> ALDEIA CAPOEIRÃO-TOTAL | C46: =SUM(F46:L46) -> 0 | F46: =SUM(F47:F56) -> 0 | G46: =SUM(G47:G56) -> 0 | H46: =SUM(H47:H56) -> 0 | I46: =SUM(I47:I56) -> 0 | J46: =SUM(J47:J56) -> 0 | K46: =SUM(K47:K56) -> 0 | L46: =SUM(L47:L56) -> 0 | N46: OK
A47: ALDEIA CAPOEIRÃO | B47: FUNDAÇÃO / ESTRUTURA | F47: =SUMIFS(LANÇAMENTO!$L:$L,LANÇAMENTO!$B:$B,'TOTAL GERAL'!$A$47,LANÇAMENTO!$N:$N,'TOTAL GERAL'!$F$1,LANÇAMENTO!$D:$D,'TOTAL GERAL'!$B47) -> 0 | G47: =SUMIFS(LANÇAMENTO!$L:$L,LANÇAMENTO!$B:$B,'TOTAL GERAL'!$A$47,LANÇAMENTO!$N:$N,'TOTAL GERAL'!$G$1,LANÇAMENTO!$D:$D,'TOTAL GERAL'!$B47) -> 0 | H47: =SUMIFS(LANÇAMENTO!$L:$L,LANÇAMENTO!$B:$B,'TOTAL GERAL'!$A$47,LANÇAMENTO!$N:$N,'TOTAL GERAL'!$H$1,LANÇAMENTO!$D:$D,'TOTAL GERAL'!$B47) -> 0
B48: COBERTURA / FORRO | F48: =SUMIFS(LANÇAMENTO!$L:$L,LANÇAMENTO!$B:$B,'TOTAL GERAL'!$A$47,LANÇAMENTO!$N:$N,'TOTAL GERAL'!$F$1,LANÇAMENTO!$D:$D,'TOTAL GERAL'!$B48) -> 0 | G48: =SUMIFS(LANÇAMENTO!$L:$L,LANÇAMENTO!$B:$B,'TOTAL GERAL'!$A$47,LANÇAMENTO!$N:$N,'TOTAL GERAL'!$G$1,LANÇAMENTO!$D:$D,'TOTAL GERAL'!$B48) -> 0 | H48: =SUMIFS(LANÇAMENTO!$L:$L,LANÇAMENTO!$B:$B,'TOTAL GERAL'!$A$47,LANÇAMENTO!$N:$N,'TOTAL GERAL'!$H$1,LANÇAMENTO!$D:$D,'TOTAL GERAL'!$B48) -> 0
B49: HIDRAULICA | F49: =SUMIFS(LANÇAMENTO!$L:$L,LANÇAMENTO!$B:$B,'TOTAL GERAL'!$A$47,LANÇAMENTO!$N:$N,'TOTAL GERAL'!$F$1,LANÇAMENTO!$D:$D,'TOTAL GERAL'!$B49) -> 0 | G49: =SUMIFS(LANÇAMENTO!$L:$L,LANÇAMENTO!$B:$B,'TOTAL GERAL'!$A$47,LANÇAMENTO!$N:$N,'TOTAL GERAL'!$G$1,LANÇAMENTO!$D:$D,'TOTAL GERAL'!$B49) -> 0 | H49: =SUMIFS(LANÇAMENTO!$L:$L,LANÇAMENTO!$B:$B,'TOTAL GERAL'!$A$47,LANÇAMENTO!$N:$N,'TOTAL GERAL'!$H$1,LANÇAMENTO!$D:$D,'TOTAL GERAL'!$B49) -> 0
B50: ELETRICA | F50: =SUMIFS(LANÇAMENTO!$L:$L,LANÇAMENTO!$B:$B,'TOTAL GERAL'!$A$47,LANÇAMENTO!$N:$N,'TOTAL GERAL'!$F$1,LANÇAMENTO!$D:$D,'TOTAL GERAL'!$B50) -> 0 | G50: =SUMIFS(LANÇAMENTO!$L:$L,LANÇAMENTO!$B:$B,'TOTAL GERAL'!$A$47,LANÇAMENTO!$N:$N,'TOTAL GERAL'!$G$1,LANÇAMENTO!$D:$D,'TOTAL GERAL'!$B50) -> 0 | H50: =SUMIFS(LANÇAMENTO!$L:$L,LANÇAMENTO!$B:$B,'TOTAL GERAL'!$A$47,LANÇAMENTO!$N:$N,'TOTAL GERAL'!$H$1,LANÇAMENTO!$D:$D,'TOTAL GERAL'!$B50) -> 0
B51: REVESTMENTO / PISO | F51: =SUMIFS(LANÇAMENTO!$L:$L,LANÇAMENTO!$B:$B,'TOTAL GERAL'!$A$47,LANÇAMENTO!$N:$N,'TOTAL GERAL'!$F$1,LANÇAMENTO!$D:$D,'TOTAL GERAL'!$B51) -> 0 | G51: =SUMIFS(LANÇAMENTO!$L:$L,LANÇAMENTO!$B:$B,'TOTAL GERAL'!$A$47,LANÇAMENTO!$N:$N,'TOTAL GERAL'!$G$1,LANÇAMENTO!$D:$D,'TOTAL GERAL'!$B51) -> 0 | H51: =SUMIFS(LANÇAMENTO!$L:$L,LANÇAMENTO!$B:$B,'TOTAL GERAL'!$A$47,LANÇAMENTO!$N:$N,'TOTAL GERAL'!$H$1,LANÇAMENTO!$D:$D,'TOTAL GERAL'!$B51) -> 0
B52: VIDRO / CAIXILHARIA | F52: =SUMIFS(LANÇAMENTO!$L:$L,LANÇAMENTO!$B:$B,'TOTAL GERAL'!$A$47,LANÇAMENTO!$N:$N,'TOTAL GERAL'!$F$1,LANÇAMENTO!$D:$D,'TOTAL GERAL'!$B52) -> 0 | G52: =SUMIFS(LANÇAMENTO!$L:$L,LANÇAMENTO!$B:$B,'TOTAL GERAL'!$A$47,LANÇAMENTO!$N:$N,'TOTAL GERAL'!$G$1,LANÇAMENTO!$D:$D,'TOTAL GERAL'!$B52) -> 0 | H52: =SUMIFS(LANÇAMENTO!$L:$L,LANÇAMENTO!$B:$B,'TOTAL GERAL'!$A$47,LANÇAMENTO!$N:$N,'TOTAL GERAL'!$H$1,LANÇAMENTO!$D:$D,'TOTAL GERAL'!$B52) -> 0
B53: PINTURA | F53: =SUMIFS(LANÇAMENTO!$L:$L,LANÇAMENTO!$B:$B,'TOTAL GERAL'!$A$47,LANÇAMENTO!$N:$N,'TOTAL GERAL'!$F$1,LANÇAMENTO!$D:$D,'TOTAL GERAL'!$B53) -> 0 | G53: =SUMIFS(LANÇAMENTO!$L:$L,LANÇAMENTO!$B:$B,'TOTAL GERAL'!$A$47,LANÇAMENTO!$N:$N,'TOTAL GERAL'!$G$1,LANÇAMENTO!$D:$D,'TOTAL GERAL'!$B53) -> 0 | H53: =SUMIFS(LANÇAMENTO!$L:$L,LANÇAMENTO!$B:$B,'TOTAL GERAL'!$A$47,LANÇAMENTO!$N:$N,'TOTAL GERAL'!$H$1,LANÇAMENTO!$D:$D,'TOTAL GERAL'!$B53) -> 0
B54: INCENDIO | F54: =SUMIFS(LANÇAMENTO!$L:$L,LANÇAMENTO!$B:$B,'TOTAL GERAL'!$A$47,LANÇAMENTO!$N:$N,'TOTAL GERAL'!$F$1,LANÇAMENTO!$D:$D,'TOTAL GERAL'!$B54) -> 0 | G54: =SUMIFS(LANÇAMENTO!$L:$L,LANÇAMENTO!$B:$B,'TOTAL GERAL'!$A$47,LANÇAMENTO!$N:$N,'TOTAL GERAL'!$G$1,LANÇAMENTO!$D:$D,'TOTAL GERAL'!$B54) -> 0 | H54: =SUMIFS(LANÇAMENTO!$L:$L,LANÇAMENTO!$B:$B,'TOTAL GERAL'!$A$47,LANÇAMENTO!$N:$N,'TOTAL GERAL'!$H$1,LANÇAMENTO!$D:$D,'TOTAL GERAL'!$B54) -> 0
B55: LOCAÇÃO | F55: =SUMIFS(LANÇAMENTO!$L:$L,LANÇAMENTO!$B:$B,'TOTAL GERAL'!$A$47,LANÇAMENTO!$N:$N,'TOTAL GERAL'!$F$1,LANÇAMENTO!$D:$D,'TOTAL GERAL'!$B55) -> 0 | G55: =SUMIFS(LANÇAMENTO!$L:$L,LANÇAMENTO!$B:$B,'TOTAL GERAL'!$A$47,LANÇAMENTO!$N:$N,'TOTAL GERAL'!$G$1,LANÇAMENTO!$D:$D,'TOTAL GERAL'!$B55) -> 0 | H55: =SUMIFS(LANÇAMENTO!$L:$L,LANÇAMENTO!$B:$B,'TOTAL GERAL'!$A$47,LANÇAMENTO!$N:$N,'TOTAL GERAL'!$H$1,LANÇAMENTO!$D:$D,'TOTAL GERAL'!$B55) -> 0
B56: OUTROS | F56: =SUMIFS(LANÇAMENTO!$L:$L,LANÇAMENTO!$B:$B,'TOTAL GERAL'!$A$47,LANÇAMENTO!$N:$N,'TOTAL GERAL'!$F$1,LANÇAMENTO!$D:$D,'TOTAL GERAL'!$B56) -> 0 | G56: =SUMIFS(LANÇAMENTO!$L:$L,LANÇAMENTO!$B:$B,'TOTAL GERAL'!$A$47,LANÇAMENTO!$N:$N,'TOTAL GERAL'!$G$1,LANÇAMENTO!$D:$D,'TOTAL GERAL'!$B56) -> 0 | H56: =SUMIFS(LANÇAMENTO!$L:$L,LANÇAMENTO!$B:$B,'TOTAL GERAL'!$A$47,LANÇAMENTO!$N:$N,'TOTAL GERAL'!$H$1,LANÇAMENTO!$D:$D,'TOTAL GERAL'!$B56) -> 0
A57: =A58&"-"&"TOTAL" -> EE ITARIRI-TOTAL | C57: =SUM(D57:L57) -> 0 | D57: =SUM(D58:D67) -> 0 | E57: =SUM(E58:E67) -> 0 | F57: =SUM(F58:F67) -> 0 | G57: =SUM(G58:G67) -> 0 | H57: =SUM(H58:H67) -> 0 | I57: =SUM(I58:I67) -> 0 | J57: =SUM(J58:J67) -> 0 | K57: =SUM(K58:K67) -> 0 | L57: =SUM(L58:L67) -> 0
A58: EE ITARIRI | B58: FUNDAÇÃO / ESTRUTURA | D58: =SUMIFS(LANÇAMENTO!$L:$L,LANÇAMENTO!$B:$B,'TOTAL GERAL'!$A$58,LANÇAMENTO!$N:$N,'TOTAL GERAL'!$D$1,LANÇAMENTO!$D:$D,'TOTAL GERAL'!$B58) -> 0 | E58: =SUMIFS(LANÇAMENTO!$L:$L,LANÇAMENTO!$B:$B,'TOTAL GERAL'!$A$58,LANÇAMENTO!$N:$N,'TOTAL GERAL'!$E$1,LANÇAMENTO!$D:$D,'TOTAL GERAL'!$B58) -> 0 | F58: =SUMIFS(LANÇAMENTO!$L:$L,LANÇAMENTO!$B:$B,'TOTAL GERAL'!$A$58,LANÇAMENTO!$N:$N,'TOTAL GERAL'!$F$1,LANÇAMENTO!$D:$D,'TOTAL GERAL'!$B58) -> 0 | G58: =SUMIFS(LANÇAMENTO!$L:$L,LANÇAMENTO!$B:$B,'TOTAL GERAL'!$A$58,LANÇAMENTO!$N:$N,'TOTAL GERAL'!$G$1,LANÇAMENTO!$D:$D,'TOTAL GERAL'!$B58) -> 0 | H58: =SUMIFS(LANÇAMENTO!$L:$L,LANÇAMENTO!$B:$B,'TOTAL GERAL'!$A$58,LANÇAMENTO!$N:$N,'TOTAL GERAL'!$H$1,LANÇAMENTO!$D:$D,'TOTAL GERAL'!$B58) -> 0
B59: COBERTURA / FORRO | D59: =SUMIFS(LANÇAMENTO!$L:$L,LANÇAMENTO!$B:$B,'TOTAL GERAL'!$A$58,LANÇAMENTO!$N:$N,'TOTAL GERAL'!$D$1,LANÇAMENTO!$D:$D,'TOTAL GERAL'!$B59) -> 0 | E59: =SUMIFS(LANÇAMENTO!$L:$L,LANÇAMENTO!$B:$B,'TOTAL GERAL'!$A$58,LANÇAMENTO!$N:$N,'TOTAL GERAL'!$E$1,LANÇAMENTO!$D:$D,'TOTAL GERAL'!$B59) -> 0 | F59: =SUMIFS(LANÇAMENTO!$L:$L,LANÇAMENTO!$B:$B,'TOTAL GERAL'!$A$58,LANÇAMENTO!$N:$N,'TOTAL GERAL'!$F$1,LANÇAMENTO!$D:$D,'TOTAL GERAL'!$B59) -> 0 | G59: =SUMIFS(LANÇAMENTO!$L:$L,LANÇAMENTO!$B:$B,'TOTAL GERAL'!$A$58,LANÇAMENTO!$N:$N,'TOTAL GERAL'!$G$1,LANÇAMENTO!$D:$D,'TOTAL GERAL'!$B59) -> 0 | H59: =SUMIFS(LANÇAMENTO!$L:$L,LANÇAMENTO!$B:$B,'TOTAL GERAL'!$A$58,LANÇAMENTO!$N:$N,'TOTAL GERAL'!$H$1,LANÇAMENTO!$D:$D,'TOTAL GERAL'!$B59) -> 0
B60: HIDRAULICA | D60: =SUMIFS(LANÇAMENTO!$L:$L,LANÇAMENTO!$B:$B,'TOTAL GERAL'!$A$58,LANÇAMENTO!$N:$N,'TOTAL GERAL'!$D$1,LANÇAMENTO!$D:$D,'TOTAL GERAL'!$B60) -> 0 | E60: =SUMIFS(LANÇAMENTO!$L:$L,LANÇAMENTO!$B:$B,'TOTAL GERAL'!$A$58,LANÇAMENTO!$N:$N,'TOTAL GERAL'!$E$1,LANÇAMENTO!$D:$D,'TOTAL GERAL'!$B60) -> 0 | F60: =SUMIFS(LANÇAMENTO!$L:$L,LANÇAMENTO!$B:$B,'TOTAL GERAL'!$A$58,LANÇAMENTO!$N:$N,'TOTAL GERAL'!$F$1,LANÇAMENTO!$D:$D,'TOTAL GERAL'!$B60) -> 0 | G60: =SUMIFS(LANÇAMENTO!$L:$L,LANÇAMENTO!$B:$B,'TOTAL GERAL'!$A$58,LANÇAMENTO!$N:$N,'TOTAL GERAL'!$G$1,LANÇAMENTO!$D:$D,'TOTAL GERAL'!$B60) -> 0 | H60: =SUMIFS(LANÇAMENTO!$L:$L,LANÇAMENTO!$B:$B,'TOTAL GERAL'!$A$58,LANÇAMENTO!$N:$N,'TOTAL GERAL'!$H$1,LANÇAMENTO!$D:$D,'TOTAL GERAL'!$B60) -> 0
B61: ELETRICA | D61: =SUMIFS(LANÇAMENTO!$L:$L,LANÇAMENTO!$B:$B,'TOTAL GERAL'!$A$58,LANÇAMENTO!$N:$N,'TOTAL GERAL'!$D$1,LANÇAMENTO!$D:$D,'TOTAL GERAL'!$B61) -> 0 | E61: =SUMIFS(LANÇAMENTO!$L:$L,LANÇAMENTO!$B:$B,'TOTAL GERAL'!$A$58,LANÇAMENTO!$N:$N,'TOTAL GERAL'!$E$1,LANÇAMENTO!$D:$D,'TOTAL GERAL'!$B61) -> 0 | F61: =SUMIFS(LANÇAMENTO!$L:$L,LANÇAMENTO!$B:$B,'TOTAL GERAL'!$A$58,LANÇAMENTO!$N:$N,'TOTAL GERAL'!$F$1,LANÇAMENTO!$D:$D,'TOTAL GERAL'!$B61) -> 0 | G61: =SUMIFS(LANÇAMENTO!$L:$L,LANÇAMENTO!$B:$B,'TOTAL GERAL'!$A$58,LANÇAMENTO!$N:$N,'TOTAL GERAL'!$G$1,LANÇAMENTO!$D:$D,'TOTAL GERAL'!$B61) -> 0 | H61: =SUMIFS(LANÇAMENTO!$L:$L,LANÇAMENTO!$B:$B,'TOTAL GERAL'!$A$58,LANÇAMENTO!$N:$N,'TOTAL GERAL'!$H$1,LANÇAMENTO!$D:$D,'TOTAL GERAL'!$B61) -> 0
B62: REVESTMENTO / PISO | D62: =SUMIFS(LANÇAMENTO!$L:$L,LANÇAMENTO!$B:$B,'TOTAL GERAL'!$A$58,LANÇAMENTO!$N:$N,'TOTAL GERAL'!$D$1,LANÇAMENTO!$D:$D,'TOTAL GERAL'!$B62) -> 0 | E62: =SUMIFS(LANÇAMENTO!$L:$L,LANÇAMENTO!$B:$B,'TOTAL GERAL'!$A$58,LANÇAMENTO!$N:$N,'TOTAL GERAL'!$E$1,LANÇAMENTO!$D:$D,'TOTAL GERAL'!$B62) -> 0 | F62: =SUMIFS(LANÇAMENTO!$L:$L,LANÇAMENTO!$B:$B,'TOTAL GERAL'!$A$58,LANÇAMENTO!$N:$N,'TOTAL GERAL'!$F$1,LANÇAMENTO!$D:$D,'TOTAL GERAL'!$B62) -> 0 | G62: =SUMIFS(LANÇAMENTO!$L:$L,LANÇAMENTO!$B:$B,'TOTAL GERAL'!$A$58,LANÇAMENTO!$N:$N,'TOTAL GERAL'!$G$1,LANÇAMENTO!$D:$D,'TOTAL GERAL'!$B62) -> 0 | H62: =SUMIFS(LANÇAMENTO!$L:$L,LANÇAMENTO!$B:$B,'TOTAL GERAL'!$A$58,LANÇAMENTO!$N:$N,'TOTAL GERAL'!$H$1,LANÇAMENTO!$D:$D,'TOTAL GERAL'!$B62) -> 0
B63: VIDRO / CAIXILHARIA | D63: =SUMIFS(LANÇAMENTO!$L:$L,LANÇAMENTO!$B:$B,'TOTAL GERAL'!$A$58,LANÇAMENTO!$N:$N,'TOTAL GERAL'!$D$1,LANÇAMENTO!$D:$D,'TOTAL GERAL'!$B63) -> 0 | E63: =SUMIFS(LANÇAMENTO!$L:$L,LANÇAMENTO!$B:$B,'TOTAL GERAL'!$A$58,LANÇAMENTO!$N:$N,'TOTAL GERAL'!$E$1,LANÇAMENTO!$D:$D,'TOTAL GERAL'!$B63) -> 0 | F63: =SUMIFS(LANÇAMENTO!$L:$L,LANÇAMENTO!$B:$B,'TOTAL GERAL'!$A$58,LANÇAMENTO!$N:$N,'TOTAL GERAL'!$F$1,LANÇAMENTO!$D:$D,'TOTAL GERAL'!$B63) -> 0 | G63: =SUMIFS(LANÇAMENTO!$L:$L,LANÇAMENTO!$B:$B,'TOTAL GERAL'!$A$58,LANÇAMENTO!$N:$N,'TOTAL GERAL'!$G$1,LANÇAMENTO!$D:$D,'TOTAL GERAL'!$B63) -> 0 | H63: =SUMIFS(LANÇAMENTO!$L:$L,LANÇAMENTO!$B:$B,'TOTAL GERAL'!$A$58,LANÇAMENTO!$N:$N,'TOTAL GERAL'!$H$1,LANÇAMENTO!$D:$D,'TOTAL GERAL'!$B63) -> 0
B64: PINTURA | D64: =SUMIFS(LANÇAMENTO!$L:$L,LANÇAMENTO!$B:$B,'TOTAL GERAL'!$A$58,LANÇAMENTO!$N:$N,'TOTAL GERAL'!$D$1,LANÇAMENTO!$D:$D,'TOTAL GERAL'!$B64) -> 0 | E64: =SUMIFS(LANÇAMENTO!$L:$L,LANÇAMENTO!$B:$B,'TOTAL GERAL'!$A$58,LANÇAMENTO!$N:$N,'TOTAL GERAL'!$E$1,LANÇAMENTO!$D:$D,'TOTAL GERAL'!$B64) -> 0 | F64: =SUMIFS(LANÇAMENTO!$L:$L,LANÇAMENTO!$B:$B,'TOTAL GERAL'!$A$58,LANÇAMENTO!$N:$N,'TOTAL GERAL'!$F$1,LANÇAMENTO!$D:$D,'TOTAL GERAL'!$B64) -> 0 | G64: =SUMIFS(LANÇAMENTO!$L:$L,LANÇAMENTO!$B:$B,'TOTAL GERAL'!$A$58,LANÇAMENTO!$N:$N,'TOTAL GERAL'!$G$1,LANÇAMENTO!$D:$D,'TOTAL GERAL'!$B64) -> 0 | H64: =SUMIFS(LANÇAMENTO!$L:$L,LANÇAMENTO!$B:$B,'TOTAL GERAL'!$A$58,LANÇAMENTO!$N:$N,'TOTAL GERAL'!$H$1,LANÇAMENTO!$D:$D,'TOTAL GERAL'!$B64) -> 0
B65: INCENDIO | D65: =SUMIFS(LANÇAMENTO!$L:$L,LANÇAMENTO!$B:$B,'TOTAL GERAL'!$A$58,LANÇAMENTO!$N:$N,'TOTAL GERAL'!$D$1,LANÇAMENTO!$D:$D,'TOTAL GERAL'!$B65) -> 0 | E65: =SUMIFS(LANÇAMENTO!$L:$L,LANÇAMENTO!$B:$B,'TOTAL GERAL'!$A$58,LANÇAMENTO!$N:$N,'TOTAL GERAL'!$E$1,LANÇAMENTO!$D:$D,'TOTAL GERAL'!$B65) -> 0 | F65: =SUMIFS(LANÇAMENTO!$L:$L,LANÇAMENTO!$B:$B,'TOTAL GERAL'!$A$58,LANÇAMENTO!$N:$N,'TOTAL GERAL'!$F$1,LANÇAMENTO!$D:$D,'TOTAL GERAL'!$B65) -> 0 | G65: =SUMIFS(LANÇAMENTO!$L:$L,LANÇAMENTO!$B:$B,'TOTAL GERAL'!$A$58,LANÇAMENTO!$N:$N,'TOTAL GERAL'!$G$1,LANÇAMENTO!$D:$D,'TOTAL GERAL'!$B65) -> 0 | H65: =SUMIFS(LANÇAMENTO!$L:$L,LANÇAMENTO!$B:$B,'TOTAL GERAL'!$A$58,LANÇAMENTO!$N:$N,'TOTAL GERAL'!$H$1,LANÇAMENTO!$D:$D,'TOTAL GERAL'!$B65) -> 0
B66: LOCAÇÃO | D66: =SUMIFS(LANÇAMENTO!$L:$L,LANÇAMENTO!$B:$B,'TOTAL GERAL'!$A$58,LANÇAMENTO!$N:$N,'TOTAL GERAL'!$D$1,LANÇAMENTO!$D:$D,'TOTAL GERAL'!$B66) -> 0 | E66: =SUMIFS(LANÇAMENTO!$L:$L,LANÇAMENTO!$B:$B,'TOTAL GERAL'!$A$58,LANÇAMENTO!$N:$N,'TOTAL GERAL'!$E$1,LANÇAMENTO!$D:$D,'TOTAL GERAL'!$B66) -> 0 | F66: =SUMIFS(LANÇAMENTO!$L:$L,LANÇAMENTO!$B:$B,'TOTAL GERAL'!$A$58,LANÇAMENTO!$N:$N,'TOTAL GERAL'!$F$1,LANÇAMENTO!$D:$D,'TOTAL GERAL'!$B66) -> 0 | G66: =SUMIFS(LANÇAMENTO!$L:$L,LANÇAMENTO!$B:$B,'TOTAL GERAL'!$A$58,LANÇAMENTO!$N:$N,'TOTAL GERAL'!$G$1,LANÇAMENTO!$D:$D,'TOTAL GERAL'!$B66) -> 0 | H66: =SUMIFS(LANÇAMENTO!$L:$L,LANÇAMENTO!$B:$B,'TOTAL GERAL'!$A$58,LANÇAMENTO!$N:$N,'TOTAL GERAL'!$H$1,LANÇAMENTO!$D:$D,'TOTAL GERAL'!$B66) -> 0
B67: OUTROS | D67: =SUMIFS(LANÇAMENTO!$L:$L,LANÇAMENTO!$B:$B,'TOTAL GERAL'!$A$58,LANÇAMENTO!$N:$N,'TOTAL GERAL'!$D$1,LANÇAMENTO!$D:$D,'TOTAL GERAL'!$B67) -> 0 | E67: =SUMIFS(LANÇAMENTO!$L:$L,LANÇAMENTO!$B:$B,'TOTAL GERAL'!$A$58,LANÇAMENTO!$N:$N,'TOTAL GERAL'!$E$1,LANÇAMENTO!$D:$D,'TOTAL GERAL'!$B67) -> 0 | F67: =SUMIFS(LANÇAMENTO!$L:$L,LANÇAMENTO!$B:$B,'TOTAL GERAL'!$A$58,LANÇAMENTO!$N:$N,'TOTAL GERAL'!$F$1,LANÇAMENTO!$D:$D,'TOTAL GERAL'!$B67) -> 0 | G67: =SUMIFS(LANÇAMENTO!$L:$L,LANÇAMENTO!$B:$B,'TOTAL GERAL'!$A$58,LANÇAMENTO!$N:$N,'TOTAL GERAL'!$G$1,LANÇAMENTO!$D:$D,'TOTAL GERAL'!$B67) -> 0 | H67: =SUMIFS(LANÇAMENTO!$L:$L,LANÇAMENTO!$B:$B,'TOTAL GERAL'!$A$58,LANÇAMENTO!$N:$N,'TOTAL GERAL'!$H$1,LANÇAMENTO!$D:$D,'TOTAL GERAL'!$B67) -> 0
A68: =A69&"-"&"TOTAL" -> EE GODOFREDO FURTADO - JB-TOTAL | C68: =SUM(D68:L68) -> 0 | D68: =SUM(D69:D78) -> 0 | E68: =SUM(E69:E78) -> 0 | F68: =SUM(F69:F78) -> 0 | G68: =SUM(G69:G78) -> 0 | H68: =SUM(H69:H78) -> 0 | I68: =SUM(I69:I78) -> 0 | J68: =SUM(J69:J78) -> 0 | K68: =SUM(K69:K78) -> 0 | L68: =SUM(L69:L78) -> 0
A69: EE GODOFREDO FURTADO - JB | B69: FUNDAÇÃO / ESTRUTURA | D69: =SUMIFS(LANÇAMENTO!$L:$L,LANÇAMENTO!$B:$B,'TOTAL GERAL'!$A$69,LANÇAMENTO!$N:$N,'TOTAL GERAL'!$D$1,LANÇAMENTO!$D:$D,'TOTAL GERAL'!$B69) -> 0 | E69: =SUMIFS(LANÇAMENTO!$L:$L,LANÇAMENTO!$B:$B,'TOTAL GERAL'!$A$69,LANÇAMENTO!$N:$N,'TOTAL GERAL'!$E$1,LANÇAMENTO!$D:$D,'TOTAL GERAL'!$B69) -> 0 | F69: =SUMIFS(LANÇAMENTO!$L:$L,LANÇAMENTO!$B:$B,'TOTAL GERAL'!$A$69,LANÇAMENTO!$N:$N,'TOTAL GERAL'!$F$1,LANÇAMENTO!$D:$D,'TOTAL GERAL'!$B69) -> 0 | G69: =SUMIFS(LANÇAMENTO!$L:$L,LANÇAMENTO!$B:$B,'TOTAL GERAL'!$A$69,LANÇAMENTO!$N:$N,'TOTAL GERAL'!$G$1,LANÇAMENTO!$D:$D,'TOTAL GERAL'!$B69) -> 0 | H69: =SUMIFS(LANÇAMENTO!$L:$L,LANÇAMENTO!$B:$B,'TOTAL GERAL'!$A$69,LANÇAMENTO!$N:$N,'TOTAL GERAL'!$H$1,LANÇAMENTO!$D:$D,'TOTAL GERAL'!$B69) -> 0
B70: COBERTURA / FORRO | D70: =SUMIFS(LANÇAMENTO!$L:$L,LANÇAMENTO!$B:$B,'TOTAL GERAL'!$A$69,LANÇAMENTO!$N:$N,'TOTAL GERAL'!$D$1,LANÇAMENTO!$D:$D,'TOTAL GERAL'!$B70) -> 0 | E70: =SUMIFS(LANÇAMENTO!$L:$L,LANÇAMENTO!$B:$B,'TOTAL GERAL'!$A$69,LANÇAMENTO!$N:$N,'TOTAL GERAL'!$E$1,LANÇAMENTO!$D:$D,'TOTAL GERAL'!$B70) -> 0 | F70: =SUMIFS(LANÇAMENTO!$L:$L,LANÇAMENTO!$B:$B,'TOTAL GERAL'!$A$69,LANÇAMENTO!$N:$N,'TOTAL GERAL'!$F$1,LANÇAMENTO!$D:$D,'TOTAL GERAL'!$B70) -> 0 | G70: =SUMIFS(LANÇAMENTO!$L:$L,LANÇAMENTO!$B:$B,'TOTAL GERAL'!$A$69,LANÇAMENTO!$N:$N,'TOTAL GERAL'!$G$1,LANÇAMENTO!$D:$D,'TOTAL GERAL'!$B70) -> 0 | H70: =SUMIFS(LANÇAMENTO!$L:$L,LANÇAMENTO!$B:$B,'TOTAL GERAL'!$A$69,LANÇAMENTO!$N:$N,'TOTAL GERAL'!$H$1,LANÇAMENTO!$D:$D,'TOTAL GERAL'!$B70) -> 0
B71: HIDRAULICA | D71: =SUMIFS(LANÇAMENTO!$L:$L,LANÇAMENTO!$B:$B,'TOTAL GERAL'!$A$69,LANÇAMENTO!$N:$N,'TOTAL GERAL'!$D$1,LANÇAMENTO!$D:$D,'TOTAL GERAL'!$B71) -> 0 | E71: =SUMIFS(LANÇAMENTO!$L:$L,LANÇAMENTO!$B:$B,'TOTAL GERAL'!$A$69,LANÇAMENTO!$N:$N,'TOTAL GERAL'!$E$1,LANÇAMENTO!$D:$D,'TOTAL GERAL'!$B71) -> 0 | F71: =SUMIFS(LANÇAMENTO!$L:$L,LANÇAMENTO!$B:$B,'TOTAL GERAL'!$A$69,LANÇAMENTO!$N:$N,'TOTAL GERAL'!$F$1,LANÇAMENTO!$D:$D,'TOTAL GERAL'!$B71) -> 0 | G71: =SUMIFS(LANÇAMENTO!$L:$L,LANÇAMENTO!$B:$B,'TOTAL GERAL'!$A$69,LANÇAMENTO!$N:$N,'TOTAL GERAL'!$G$1,LANÇAMENTO!$D:$D,'TOTAL GERAL'!$B71) -> 0 | H71: =SUMIFS(LANÇAMENTO!$L:$L,LANÇAMENTO!$B:$B,'TOTAL GERAL'!$A$69,LANÇAMENTO!$N:$N,'TOTAL GERAL'!$H$1,LANÇAMENTO!$D:$D,'TOTAL GERAL'!$B71) -> 0
B72: ELETRICA | D72: =SUMIFS(LANÇAMENTO!$L:$L,LANÇAMENTO!$B:$B,'TOTAL GERAL'!$A$69,LANÇAMENTO!$N:$N,'TOTAL GERAL'!$D$1,LANÇAMENTO!$D:$D,'TOTAL GERAL'!$B72) -> 0 | E72: =SUMIFS(LANÇAMENTO!$L:$L,LANÇAMENTO!$B:$B,'TOTAL GERAL'!$A$69,LANÇAMENTO!$N:$N,'TOTAL GERAL'!$E$1,LANÇAMENTO!$D:$D,'TOTAL GERAL'!$B72) -> 0 | F72: =SUMIFS(LANÇAMENTO!$L:$L,LANÇAMENTO!$B:$B,'TOTAL GERAL'!$A$69,LANÇAMENTO!$N:$N,'TOTAL GERAL'!$F$1,LANÇAMENTO!$D:$D,'TOTAL GERAL'!$B72) -> 0 | G72: =SUMIFS(LANÇAMENTO!$L:$L,LANÇAMENTO!$B:$B,'TOTAL GERAL'!$A$69,LANÇAMENTO!$N:$N,'TOTAL GERAL'!$G$1,LANÇAMENTO!$D:$D,'TOTAL GERAL'!$B72) -> 0 | H72: =SUMIFS(LANÇAMENTO!$L:$L,LANÇAMENTO!$B:$B,'TOTAL GERAL'!$A$69,LANÇAMENTO!$N:$N,'TOTAL GERAL'!$H$1,LANÇAMENTO!$D:$D,'TOTAL GERAL'!$B72) -> 0
B73: REVESTMENTO / PISO | D73: =SUMIFS(LANÇAMENTO!$L:$L,LANÇAMENTO!$B:$B,'TOTAL GERAL'!$A$69,LANÇAMENTO!$N:$N,'TOTAL GERAL'!$D$1,LANÇAMENTO!$D:$D,'TOTAL GERAL'!$B73) -> 0 | E73: =SUMIFS(LANÇAMENTO!$L:$L,LANÇAMENTO!$B:$B,'TOTAL GERAL'!$A$69,LANÇAMENTO!$N:$N,'TOTAL GERAL'!$E$1,LANÇAMENTO!$D:$D,'TOTAL GERAL'!$B73) -> 0 | F73: =SUMIFS(LANÇAMENTO!$L:$L,LANÇAMENTO!$B:$B,'TOTAL GERAL'!$A$69,LANÇAMENTO!$N:$N,'TOTAL GERAL'!$F$1,LANÇAMENTO!$D:$D,'TOTAL GERAL'!$B73) -> 0 | G73: =SUMIFS(LANÇAMENTO!$L:$L,LANÇAMENTO!$B:$B,'TOTAL GERAL'!$A$69,LANÇAMENTO!$N:$N,'TOTAL GERAL'!$G$1,LANÇAMENTO!$D:$D,'TOTAL GERAL'!$B73) -> 0 | H73: =SUMIFS(LANÇAMENTO!$L:$L,LANÇAMENTO!$B:$B,'TOTAL GERAL'!$A$69,LANÇAMENTO!$N:$N,'TOTAL GERAL'!$H$1,LANÇAMENTO!$D:$D,'TOTAL GERAL'!$B73) -> 0
B74: VIDRO / CAIXILHARIA | D74: =SUMIFS(LANÇAMENTO!$L:$L,LANÇAMENTO!$B:$B,'TOTAL GERAL'!$A$69,LANÇAMENTO!$N:$N,'TOTAL GERAL'!$D$1,LANÇAMENTO!$D:$D,'TOTAL GERAL'!$B74) -> 0 | E74: =SUMIFS(LANÇAMENTO!$L:$L,LANÇAMENTO!$B:$B,'TOTAL GERAL'!$A$69,LANÇAMENTO!$N:$N,'TOTAL GERAL'!$E$1,LANÇAMENTO!$D:$D,'TOTAL GERAL'!$B74) -> 0 | F74: =SUMIFS(LANÇAMENTO!$L:$L,LANÇAMENTO!$B:$B,'TOTAL GERAL'!$A$69,LANÇAMENTO!$N:$N,'TOTAL GERAL'!$F$1,LANÇAMENTO!$D:$D,'TOTAL GERAL'!$B74) -> 0 | G74: =SUMIFS(LANÇAMENTO!$L:$L,LANÇAMENTO!$B:$B,'TOTAL GERAL'!$A$69,LANÇAMENTO!$N:$N,'TOTAL GERAL'!$G$1,LANÇAMENTO!$D:$D,'TOTAL GERAL'!$B74) -> 0 | H74: =SUMIFS(LANÇAMENTO!$L:$L,LANÇAMENTO!$B:$B,'TOTAL GERAL'!$A$69,LANÇAMENTO!$N:$N,'TOTAL GERAL'!$H$1,LANÇAMENTO!$D:$D,'TOTAL GERAL'!$B74) -> 0
B75: PINTURA | D75: =SUMIFS(LANÇAMENTO!$L:$L,LANÇAMENTO!$B:$B,'TOTAL GERAL'!$A$69,LANÇAMENTO!$N:$N,'TOTAL GERAL'!$D$1,LANÇAMENTO!$D:$D,'TOTAL GERAL'!$B75) -> 0 | E75: =SUMIFS(LANÇAMENTO!$L:$L,LANÇAMENTO!$B:$B,'TOTAL GERAL'!$A$69,LANÇAMENTO!$N:$N,'TOTAL GERAL'!$E$1,LANÇAMENTO!$D:$D,'TOTAL GERAL'!$B75) -> 0 | F75: =SUMIFS(LANÇAMENTO!$L:$L,LANÇAMENTO!$B:$B,'TOTAL GERAL'!$A$69,LANÇAMENTO!$N:$N,'TOTAL GERAL'!$F$1,LANÇAMENTO!$D:$D,'TOTAL GERAL'!$B75) -> 0 | G75: =SUMIFS(LANÇAMENTO!$L:$L,LANÇAMENTO!$B:$B,'TOTAL GERAL'!$A$69,LANÇAMENTO!$N:$N,'TOTAL GERAL'!$G$1,LANÇAMENTO!$D:$D,'TOTAL GERAL'!$B75) -> 0 | H75: =SUMIFS(LANÇAMENTO!$L:$L,LANÇAMENTO!$B:$B,'TOTAL GERAL'!$A$69,LANÇAMENTO!$N:$N,'TOTAL GERAL'!$H$1,LANÇAMENTO!$D:$D,'TOTAL GERAL'!$B75) -> 0
B76: INCENDIO | D76: =SUMIFS(LANÇAMENTO!$L:$L,LANÇAMENTO!$B:$B,'TOTAL GERAL'!$A$69,LANÇAMENTO!$N:$N,'TOTAL GERAL'!$D$1,LANÇAMENTO!$D:$D,'TOTAL GERAL'!$B76) -> 0 | E76: =SUMIFS(LANÇAMENTO!$L:$L,LANÇAMENTO!$B:$B,'TOTAL GERAL'!$A$69,LANÇAMENTO!$N:$N,'TOTAL GERAL'!$E$1,LANÇAMENTO!$D:$D,'TOTAL GERAL'!$B76) -> 0 | F76: =SUMIFS(LANÇAMENTO!$L:$L,LANÇAMENTO!$B:$B,'TOTAL GERAL'!$A$69,LANÇAMENTO!$N:$N,'TOTAL GERAL'!$F$1,LANÇAMENTO!$D:$D,'TOTAL GERAL'!$B76) -> 0 | G76: =SUMIFS(LANÇAMENTO!$L:$L,LANÇAMENTO!$B:$B,'TOTAL GERAL'!$A$69,LANÇAMENTO!$N:$N,'TOTAL GERAL'!$G$1,LANÇAMENTO!$D:$D,'TOTAL GERAL'!$B76) -> 0 | H76: =SUMIFS(LANÇAMENTO!$L:$L,LANÇAMENTO!$B:$B,'TOTAL GERAL'!$A$69,LANÇAMENTO!$N:$N,'TOTAL GERAL'!$H$1,LANÇAMENTO!$D:$D,'TOTAL GERAL'!$B76) -> 0
B77: LOCAÇÃO | D77: =SUMIFS(LANÇAMENTO!$L:$L,LANÇAMENTO!$B:$B,'TOTAL GERAL'!$A$69,LANÇAMENTO!$N:$N,'TOTAL GERAL'!$D$1,LANÇAMENTO!$D:$D,'TOTAL GERAL'!$B77) -> 0 | E77: =SUMIFS(LANÇAMENTO!$L:$L,LANÇAMENTO!$B:$B,'TOTAL GERAL'!$A$69,LANÇAMENTO!$N:$N,'TOTAL GERAL'!$E$1,LANÇAMENTO!$D:$D,'TOTAL GERAL'!$B77) -> 0 | F77: =SUMIFS(LANÇAMENTO!$L:$L,LANÇAMENTO!$B:$B,'TOTAL GERAL'!$A$69,LANÇAMENTO!$N:$N,'TOTAL GERAL'!$F$1,LANÇAMENTO!$D:$D,'TOTAL GERAL'!$B77) -> 0 | G77: =SUMIFS(LANÇAMENTO!$L:$L,LANÇAMENTO!$B:$B,'TOTAL GERAL'!$A$69,LANÇAMENTO!$N:$N,'TOTAL GERAL'!$G$1,LANÇAMENTO!$D:$D,'TOTAL GERAL'!$B77) -> 0 | H77: =SUMIFS(LANÇAMENTO!$L:$L,LANÇAMENTO!$B:$B,'TOTAL GERAL'!$A$69,LANÇAMENTO!$N:$N,'TOTAL GERAL'!$H$1,LANÇAMENTO!$D:$D,'TOTAL GERAL'!$B77) -> 0
B78: OUTROS | D78: =SUMIFS(LANÇAMENTO!$L:$L,LANÇAMENTO!$B:$B,'TOTAL GERAL'!$A$69,LANÇAMENTO!$N:$N,'TOTAL GERAL'!$D$1,LANÇAMENTO!$D:$D,'TOTAL GERAL'!$B78) -> 0 | E78: =SUMIFS(LANÇAMENTO!$L:$L,LANÇAMENTO!$B:$B,'TOTAL GERAL'!$A$69,LANÇAMENTO!$N:$N,'TOTAL GERAL'!$E$1,LANÇAMENTO!$D:$D,'TOTAL GERAL'!$B78) -> 0 | F78: =SUMIFS(LANÇAMENTO!$L:$L,LANÇAMENTO!$B:$B,'TOTAL GERAL'!$A$69,LANÇAMENTO!$N:$N,'TOTAL GERAL'!$F$1,LANÇAMENTO!$D:$D,'TOTAL GERAL'!$B78) -> 0 | G78: =SUMIFS(LANÇAMENTO!$L:$L,LANÇAMENTO!$B:$B,'TOTAL GERAL'!$A$69,LANÇAMENTO!$N:$N,'TOTAL GERAL'!$G$1,LANÇAMENTO!$D:$D,'TOTAL GERAL'!$B78) -> 0 | H78: =SUMIFS(LANÇAMENTO!$L:$L,LANÇAMENTO!$B:$B,'TOTAL GERAL'!$A$69,LANÇAMENTO!$N:$N,'TOTAL GERAL'!$H$1,LANÇAMENTO!$D:$D,'TOTAL GERAL'!$B78) -> 0

Sheet Detalhes1
A1: Detalhes do Soma de VALOR TOTAL - OBRA: PADRE NILDO (+)
A3: DATA SOLICITAÇÃO | B3: OBRA | C3: FATURAMENTO | D3: ITEM | E3: MATERIAL SOLICITADO | F3: QTDADE | G3: UNID | H3: PEDIDO | I3: FORNECEDOR | J3: DESCRIÇÃO MATERIAL | K3: VALOR UNITARIO | L3: VALOR TOTAL | M3: DATA PEDIDO | N3: MÊS/ANO PEDIDO | O3: CONDIÇÃO PAGAMENTO | P3: FORMA DE PAGAMENTO | Q3: RETIRA OU ENTREGA | R3: PRAZO | S3: PREVISÃO ENTREGA OBRA | T3: RESTA | U3: OBRA COM MATERIAL | V3: OBSERVAÇÃO
A4: 46093 | B4: ANTONIO NUNES LOPES | C4: B&B | D4: OUTROS | E4: MASSA PRONTA P/ DRYWALL MAXCRYL 30 KG | F4: 1 | G4: BALDE | H4: 2503 | I4: ARTESANA BELENZINHO | J4: MASSA PRONTA P/ DRYWALL MAXCRYL 30 KG | K4: 56.99 | L4: 56.99 | M4: 46093 | N4: mar-2026 | O4: 28/35/42 | P4: BOLETO | Q4: RETIRA | R4: 1 | S4: 46094 | T4: 0
A5: 46080 | B5: ANTONIO NUNES LOPES | C5: B&B | D5: OUTROS | E5: TB RD 31,75 X 1,55 MM (1.1/4") GALV | F5: 35 | G5: BARRA | H5: 2485 | I5: IMPERIO AÇO | J5: TB RD 31,75 X 1,55 MM (1.1/4") GALV | K5: 63 | L5: 2205 | M5: 46080 | N5: fev-2026 | O5: 30/45/60 | P5: BOLETO | Q5: RETIRA | R5: 5 | S5: 46085 | T5: ENTREGUE | U5: OK
A6: 46080 | B6: ANTONIO NUNES LOPES | C6: B&B | D6: OUTROS | E6: TB RD 50,80 X 1,55 MM (2") GALV | F6: 13 | G6: BARRA | H6: 2485 | I6: IMPERIO AÇO | J6: TB RD 50,80 X 1,55 MM (2") GALV | K6: 104 | L6: 1352 | M6: 46080 | N6: fev-2026 | O6: 30/45/60 | P6: BOLETO | Q6: RETIRA | R6: 5 | S6: 46085 | T6: ENTREGUE | U6: OK
A7: 46087 | B7: ANTONIO NUNES LOPES | C7: B&B | D7: PINTURA | E7: ITAQUA THINNER 116 5L | F7: 1 | G7: GALÃO | H7: 2497 | I7: OLD RIVER | J7: ITAQUA THINNER 116 5L | K7: 69.9 | L7: 69.9 | M7: 46087 | N7: mar-2026 | O7: 28/42 | P7: BOLETO | Q7: RETIRA | R7: 0 | S7: 46087 | T7: ENTREGUE | U7: OK
A8: 46087 | B8: ANTONIO NUNES LOPES | C8: B&B | D8: PINTURA | E8: FUTURA FUTURIT ESM SINT.BRILHO BRANCO 3,6L | F8: 2 | G8: GALÃO | H8: 2497 | I8: OLD RIVER | J8: FUTURA FUTURIT ESM SINT.BRILHO BRANCO 3,6L | K8: 89.9 | L8: 179.8 | M8: 46087 | N8: mar-2026 | O8: 28/42 | P8: BOLETO | Q8: RETIRA | R8: 0 | S8: 46087 | T8: ENTREGUE | U8: OK
A9: 46083 | B9: ANTONIO NUNES LOPES | C9: B&B | D9: PINTURA | E9: GALÃO TINTA CORAL ALUMINIO | F9: 1 | G9: GALÃO | H9: 2489 | I9: N TINTAS | J9: GALÃO TINTA CORAL ALUMINIO | K9: 234 | L9: 234 | M9: 46083 | N9: mar-2026 | O9: 7 | P9: BOLETO | Q9: RETIRA | R9: 0 | S9: 46083 | T9: ENTREGUE | U9: OK
A10: 46080 | B10: ANTONIO NUNES LOPES | C10: B&B | D10: OUTROS | E10: ELETRODO GERDAU E 601- 2.5MM AZ KG | F10: 5 | G10: KG | H10: 2487 | I10: DEPOSITO PADRÃO | J10: ELETRODO GERDAU E 601- 2.5MM AZ KG | K10: 39 | L10: 195 | M10: 46080 | N10: fev-2026 | O10: 21 | P10: BOLETO | Q10: ENTREGA | R10: 0 | S10: 46080 | T10: ENTREGUE | U10: OK
A11: 46087 | B11: ANTONIO NUNES LOPES | C11: B&B | D11: PINTURA | E11: FUTURA STANDARD SUPER RENDIMENTO TANGERINA 18L | F11: 3 | G11: LATA | H11: 2497 | I11: OLD RIVER | J11: FUTURA STANDARD SUPER RENDIMENTO TANGERINA 18L | K11: 249.9 | L11: 749.7 | M11: 46087 | N11: mar-2026 | O11: 28/42 | P11: BOLETO | Q11: RETIRA | R11: 0 | S11: 46087 | T11: ENTREGUE | U11: OK
A12: 46080 | B12: ANTONIO NUNES LOPES | C12: B&B | D12: OUTROS | E12: TELA ALAMBRADO MALHA 2" FIO 12 GALV. | F12: 84 | G12: M2 | H12: 2486 | I12: MITSUNARI | J12: TELA ALAMBRADO MALHA 2" FIO 12 GALV. | K12: 25.3 | L12: 2125.2 | M12: 46080 | N12: fev-2026 | O12: 28/35/42 | P12: BOLETO | Q12: ENTREGA | R12: 7 | S12: 46087 | T12: ENTREGUE | U12: OK
A13: 46080 | B13: ANTONIO NUNES LOPES | C13: B&B | D13: OUTROS | E13: TELA ALAMBRADO MALHA 2" FIO 10 GALV | F13: 78 | G13: M2 | H13: 2486 | I13: MITSUNARI | J13: TELA ALAMBRADO MALHA 2" FIO 10 GALV | K13: 43.1 | L13: 3361.8 | M13: 46080 | N13: fev-2026 | O13: 28/35/42 | P13: BOLETO | Q13: ENTREGA | R13: 7 | S13: 46087 | T13: ENTREGUE | U13: OK
A14: 46080 | B14: ANTONIO NUNES LOPES | C14: B&B | D14: OUTROS | E14: ARAME FIO 18 GALV. | F14: 10 | G14: M2 | H14: 2486 | I14: MITSUNARI | J14: ARAME FIO 18 GALV. | K14: 25 | L14: 250 | M14: 46080 | N14: fev-2026 | O14: 28/35/42 | P14: BOLETO | Q14: ENTREGA | R14: 7 | S14: 46087 | T14: ENTREGUE | U14: OK
A15: 46087 | B15: ANTONIO NUNES LOPES | C15: B&B | D15: PINTURA | E15: FENIX 1500/23 ROLO LA ZERO RESPINGO CANARINHO 23CM | F15: 4 | G15: PACOTE | H15: 2497 | I15: OLD RIVER | J15: FENIX 1500/23 ROLO LA ZERO RESPINGO CANARINHO 23CM | K15: 14.9 | L15: 59.6 | M15: 46087 | N15: mar-2026 | O15: 28/42 | P15: BOLETO | Q15: RETIRA | R15: 0 | S15: 46087 | T15: ENTREGUE | U15: OK
A16: 46087 | B16: ANTONIO NUNES LOPES | C16: B&B | D16: PINTURA | E16: ROMA 301/005 TRINCHA CABO PRETO/CERDA GRIS 301 2" | F16: 3 | G16: PACOTE | H16: 2497 | I16: OLD RIVER | J16: ROMA 301/005 TRINCHA CABO PRETO/CERDA GRIS 301 2" | K16: 4.99 | L16: 14.97 | M16: 46087 | N16: mar-2026 | O16: 28/42 | P16: BOLETO | Q16: RETIRA | R16: 0 | S16: 46087 | T16: ENTREGUE | U16: OK
A17: 46093 | B17: ANTONIO NUNES LOPES | C17: B&B | D17: OUTROS | E17: PARAFUSO GN25 ANCORA CAIXA COM 1000 PECAS | F17: 1 | G17: PACOTE | H17: 2503 | I17: ARTESANA BELENZINHO | J17: PARAFUSO GN25 ANCORA CAIXA COM 1000 PECAS | K17: 41.65 | L17: 41.65 | M17: 46093 | N17: mar-2026 | O17: 28/35/42 | P17: BOLETO | Q17: RETIRA | R17: 1 | S17: 46094 | T17: 0
A18: 46087 | B18: ANTONIO NUNES LOPES | C18: B&B | D18: PINTURA | E18: FENIX 3501/23 SUPORTE DE PRESSAO REFORCADO P/ROLO 23CM | F18: 4 | G18: PACOTE | H18: 2497 | I18: OLD RIVER | J18: FENIX 3501/23 SUPORTE DE PRESSAO REFORCADO P/ROLO 23CM | K18: 4.99 | L18: 19.96 | M18: 46087 | N18: mar-2026 | O18: 28/42 | P18: BOLETO | Q18: RETIRA | R18: 0 | S18: 46087 | T18: ENTREGUE | U18: OK
A19: 46007 | B19: ANTONIO NUNES LOPES | C19: B&B | D19: OUTROS | E19: CUMEEIRA T.O. 1,10X300MM CRFS BRASILIT 15GR | F19: 4 | G19: PEÇA | H19: 2371 | I19: TELHADÃO | J19: CUMEEIRA T.O. 1,10X300MM CRFS BRASILIT 15GR | K19: 63.61 | L19: 254.44 | M19: 46007 | N19: dez-2025 | O19: 28/35/42 | P19: BOLETO | Q19: ENTREGA | R19: 7 | S19: 46014 | T19: ENTREGUE | U19: OK
A20: 46007 | B20: ANTONIO NUNES LOPES | C20: B&B | D20: OUTROS | E20: PINUS/TABUA 30 BR 3,0M | F20: 5 | G20: PEÇA | H20: 2371 | I20: TELHADÃO | J20: PINUS/TABUA 30 BR 3,0M | K20: 46.1 | L20: 230.5 | M20: 46007 | N20: dez-2025 | O20: 28/35/42 | P20: BOLETO | Q20: ENTREGA | R20: 7 | S20: 46014 | T20: ENTREGUE | U20: OK
A21: 46007 | B21: ANTONIO NUNES LOPES | C21: B&B | D21: OUTROS | E21: CONJUNTO DE VEDACAO 1/4 FRAZAO | F21: 100 | G21: PEÇA | H21: 2371 | I21: TELHADÃO | J21: CONJUNTO DE VEDACAO 1/4 FRAZAO | K21: 0.2 | L21: 20 | M21: 46007 | N21: dez-2025 | O21: 28/35/42 | P21: BOLETO | Q21: ENTREGA | R21: 7 | S21: 46014 | T21: ENTREGUE | U21: OK
A22: 46007 | B22: ANTONIO NUNES LOPES | C22: B&B | D22: OUTROS | E22: HASTE C/ ROSCA PORCA 6X300MM FRAZAO | F22: 100 | G22: PEÇA | H22: 2371 | I22: TELHADÃO | J22: HASTE C/ ROSCA PORCA 6X300MM FRAZAO | K22: 3.39 | L22: 339 | M22: 46007 | N22: dez-2025 | O22: 28/35/42 | P22: BOLETO | Q22: ENTREGA | R22: 7 | S22: 46014 | T22: ENTREGUE | U22: OK
A23: 46007 | B23: ANTONIO NUNES LOPES | C23: B&B | D23: OUTROS | E23: TELHA OND. CRFS BRASILIT 1,83X1,10X8MM | F23: 20 | G23: PEÇA | H23: 2371 | I23: TELHADÃO | J23: TELHA OND. CRFS BRASILIT 1,83X1,10X8MM | K23: 81.02 | L23: 1620.4 | M23: 46007 | N23: dez-2025 | O23: 28/35/42 | P23: BOLETO | Q23: ENTREGA | R23: 7 | S23: 46014 | T23: ENTREGUE | U23: OK
A24: 46083 | B24: ANTONIO NUNES LOPES | C24: B&B | D24: OUTROS | E24: CIMENTO CPII 50KG LIZ/CAMPEAO/ CSN | F24: 3 | G24: SACO | H24: 2490 | I24: DEPOSITO PADRÃO | J24: CIMENTO CPII 50KG LIZ/CAMPEAO/ CSN | K24: 42.9 | L24: 128.7 | M24: 46083 | N24: mar-2026 | O24: 7 | P24: BOLETO | Q24: RETIRA | R24: 0 | S24: 46083 | T24: ENTREGUE | U24: OK
A25: 46092 | B25: ANTONIO NUNES LOPES | C25: B&B | D25: OUTROS | E25: CAÇAMBA | F25: 1 | G25: UNID. | H25: 2500 | I25: AVA ENTULHO | J25: CAÇAMBA | K25: 350 | L25: 350 | M25: 46092 | N25: mar-2026 | O25: 15 | P25: BOLETO | Q25: ENTREGA | R25: 1 | S25: 46093 | T25: -1
A26: 45884 | B26: ANTONIO NUNES LOPES | C26: B&B | D26: HIDRAULICA | E26: BOCAL RED. 4" CHAPA GALV. | F26: 4 | G26: UNID. | H26: 1832 | I26: CASA MIMOSA | J26: BOCAL RED. 4" CHAPA GALV. | K26: 10.64 | L26: 42.56 | M26: 45884 | N26: ago-2025 | O26: 28 | P26: BOLETO | Q26: RETIRA | R26: 0 | S26: 45884 | T26: ENTREGUE | U26: OK
A27: 46093 | B27: ANTONIO NUNES LOPES | C27: B&B | D27: OUTROS | E27: PAINEL STANDARD 12,5X1200X1800MM | F27: 40 | G27: UNID. | H27: 2503 | I27: ARTESANA BELENZINHO | J27: PAINEL STANDARD 12,5X1200X1800MM | K27: 37.44 | L27: 1497.6 | M27: 46093 | N27: mar-2026 | O27: 28/35/42 | P27: BOLETO | Q27: RETIRA | R27: 1 | S27: 46094 | T27: 0
A28: 46093 | B28: ANTONIO NUNES LOPES | C28: B&B | D28: OUTROS | E28: FITA TELADA FIBATAPE ROLO 90M | F28: 1 | G28: UNID. | H28: 2503 | I28: ARTESANA BELENZINHO | J28: FITA TELADA FIBATAPE ROLO 90M | K28: 31.34 | L28: 31.34 | M28: 46093 | N28: mar-2026 | O28: 28/35/42 | P28: BOLETO | Q28: RETIRA | R28: 1 | S28: 46094 | T28: 0
A29: 45884 | B29: ANTONIO NUNES LOPES | C29: B&B | D29: HIDRAULICA | E29: EMMETI DUCHA HIG.ECO.1/2 GAT.ABS BR RG.MET. B665014 | F29: 1 | G29: UNID. | H29: 1832 | I29: CASA MIMOSA | J29: EMMETI DUCHA HIG.ECO.1/2 GAT.ABS BR RG.MET. B665014 | K29: 68.73 | L29: 68.73 | M29: 45884 | N29: ago-2025 | O29: 28 | P29: BOLETO | Q29: RETIRA | R29: 0 | S29: 45884 | T29: ENTREGUE | U29: OK | V29: MATERIAL PARA OBRA PEI CRISTIANE CHAVES, FATURAR PARA A B&B
A30: 46093 | B30: ANTONIO NUNES LOPES | C30: B&B | D30: OUTROS | E30: CANALETA F-530 3000MM DRYWALL | F30: 39 | G30: UNID. | H30: 2503 | I30: ARTESANA BELENZINHO | J30: CANALETA F-530 3000MM DRYWALL | K30: 13.04 | L30: 508.56 | M30: 46093 | N30: mar-2026 | O30: 28/35/42 | P30: BOLETO | Q30: RETIRA | R30: 1 | S30: 46094 | T30: 0
A31: 45884 | B31: ANTONIO NUNES LOPES | C31: B&B | D31: HIDRAULICA | E31: DECA CANOPLA VALV.HYDRA MAX C | F31: 1 | G31: UNID. | H31: 1832 | I31: CASA MIMOSA | J31: DECA CANOPLA VALV.HYDRA MAX C | K31: 122.26 | L31: 122.26 | M31: 45884 | N31: ago-2025 | O31: 28 | P31: BOLETO | Q31: RETIRA | R31: 0 | S31: 45884 | T31: ENTREGUE | U31: OK | V31: MATERIAL PARA OBRA PEI CRISTIANE CHAVES, FATURAR PARA A B&B
A32: 45923 | B32: ANTONIO NUNES LOPES | C32: B&B | D32: OUTROS | E32: TELHA OND. CRFS BRASILIT 1,83X1,10X6MM | F32: 12 | G32: UNID. | H32: 2053 | I32: TELHADÃO | J32: TELHA OND. CRFS BRASILIT 1,83X1,10X6MM | K32: 49.061 | L32: 588.732 | M32: 45923 | N32: set-2025 | O32: 28 | P32: BOLETO | Q32: RETIRA | R32: 1 | S32: 45924 | T32: ENTREGUE | U32: OK
A33: 45923 | B33: ANTONIO NUNES LOPES | C33: B&B | D33: OUTROS | E33: CUMEEIRA T.O. 1,10X300MM CRFS BRASILIT 15GR | F33: 3 | G33: UNID. | H33: 2053 | I33: TELHADÃO | J33: CUMEEIRA T.O. 1,10X300MM CRFS BRASILIT 15GR | K33: 54.77 | L33: 164.31 | M33: 45923 | N33: set-2025 | O33: 28 | P33: BOLETO | Q33: RETIRA | R33: 1 | S33: 45924 | T33: ENTREGUE | U33: OK
A34: 46093 | B34: ANTONIO NUNES LOPES | C34: B&B | D34: OUTROS | E34: CUMEEIRA T.O. 1,10X300MM CRFS BRASILIT 15GR | F34: 13 | G34: UNID. | H34: 2502 | I34: TELHADÃO | J34: CUMEEIRA T.O. 1,10X300MM CRFS BRASILIT 15GR | K34: 59.2 | L34: 769.6 | M34: 46093 | N34: mar-2026 | O34: 28/35/42 | P34: BOLETO | Q34: ENTREGA | R34: 5 | S34: 46098 | T34: 4
A35: 46093 | B35: ANTONIO NUNES LOPES | C35: B&B | D35: OUTROS | E35: PARAFUSO GALVANIZADO R.S. 110MM FRAZAO | F35: 240 | G35: UNID. | H35: 2502 | I35: TELHADÃO | J35: PARAFUSO GALVANIZADO R.S. 110MM FRAZAO | K35: 0.98 | L35: 235.2 | M35: 46093 | N35: mar-2026 | O35: 28/35/42 | P35: BOLETO | Q35: ENTREGA | R35: 5 | S35: 46098 | T35: 4
A36: 46093 | B36: ANTONIO NUNES LOPES | C36: B&B | D36: OUTROS | E36: CONJUNTO DE VEDACAO 5/16 FRAZAO | F36: 240 | G36: UNID. | H36: 2502 | I36: TELHADÃO | J36: CONJUNTO DE VEDACAO 5/16 FRAZAO | K36: 0.2 | L36: 48 | M36: 46093 | N36: mar-2026 | O36: 28/35/42 | P36: BOLETO | Q36: ENTREGA | R36: 5 | S36: 46098 | T36: 4
A37: 46086 | B37: ANTONIO NUNES LOPES | C37: B&B | D37: OUTROS | E37: OTTO B.NEUTROL 45 A LATA 900ML | F37: 1 | G37: UNID. | H37: 2496 | I37: DEPOSITO PADRÃO | J37: OTTO B.NEUTROL 45 A LATA 900ML | K37: 69.25 | L37: 69.25 | M37: 46086 | N37: mar-2026 | O37: 14 | P37: BOLETO | Q37: RETIRA | R37: 1 | S37: 46087 | T37: ENTREGUE | U37: OK
A38: 46028 | B38: ANTONIO NUNES LOPES | C38: B&B | D38: LOCAÇÃO | E38: RODA METALICA C/ ROLAMENTO DIVERSOS POLIURETANO FREIO | F38: 4 | G38: UNID. | H38: 2400 | I38: CASA DO CONSTRUTOR P.G | J38: RODA METALICA C/ ROLAMENTO DIVERSOS POLIURETANO FREIO | K38: 25.3 | L38: 101.2 | M38: 46028 | N38: jan-2026 | O38: 28 | P38: BOLETO | Q38: ENTREGA | R38: 2 | S38: 46030 | T38: ENTREGUE | U38: OK
A39: 46086 | B39: ANTONIO NUNES LOPES | C39: B&B | D39: LOCAÇÃO | E39: RODA METALICA C/ ROLAMENTO DIVERSOS POLIURETANO FREIO | F39: 4 | G39: UNID. | H39: 2494 | I39: CASA DO CONSTRUTOR P.G | J39: RODA METALICA C/ ROLAMENTO DIVERSOS POLIURETANO FREIO | K39: 25.3 | L39: 101.2 | M39: 46086 | N39: mar-2026 | O39: 28 | P39: BOLETO | Q39: ENTREGA | R39: 0 | S39: 46086 | T39: ENTREGUE | U39: OK
A40: 46083 | B40: ANTONIO NUNES LOPES | C40: B&B | D40: OUTROS | E40: DISCO SPED/INOX WAVES PLUS 4.1/2X7/8X1,0 | F40: 20 | G40: UNID. | H40: 2490 | I40: DEPOSITO PADRÃO | J40: DISCO SPED/INOX WAVES PLUS 4.1/2X7/8X1,0 | K40: 2.3 | L40: 46 | M40: 46083 | N40: mar-2026 | O40: 7 | P40: BOLETO | Q40: RETIRA | R40: 0 | S40: 46083 | T40: ENTREGUE | U40: OK
A41: 46086 | B41: ANTONIO NUNES LOPES | C41: B&B | D41: OUTROS | E41: DISCO SPED/INOX WAVES PLUS 4.1/2X7/8X1,0 | F41: 20 | G41: UNID. | H41: 2496 | I41: DEPOSITO PADRÃO | J41: DISCO SPED/INOX WAVES PLUS 4.1/2X7/8X1,0 | K41: 2.5 | L41: 50 | M41: 46086 | N41: mar-2026 | O41: 14 | P41: BOLETO | Q41: RETIRA | R41: 1 | S41: 46087 | T41: ENTREGUE | U41: OK
A42: 46028 | B42: ANTONIO NUNES LOPES | C42: B&B | D42: LOCAÇÃO | E42: PAINEL METALICO DIVERSOS 1.00x1.50m | F42: 44 | G42: UNID. | H42: 2400 | I42: CASA DO CONSTRUTOR P.G | J42: PAINEL METALICO DIVERSOS 1.00x1.50m | K42: 13.8 | L42: 607.2 | M42: 46028 | N42: jan-2026 | O42: 28 | P42: BOLETO | Q42: ENTREGA | R42: 2 | S42: 46030 | T42: ENTREGUE | U42: OK
A43: 46086 | B43: ANTONIO NUNES LOPES | C43: B&B | D43: LOCAÇÃO | E43: PAINEL METALICO DIVERSOS 1.00x1.50m | F43: 20 | G43: UNID. | H43: 2494 | I43: CASA DO CONSTRUTOR P.G | J43: PAINEL METALICO DIVERSOS 1.00x1.50m | K43: 13.8 | L43: 276 | M43: 46086 | N43: mar-2026 | O43: 28 | P43: BOLETO | Q43: ENTREGA | R43: 0 | S43: 46086 | T43: ENTREGUE | U43: OK
A44: 46028 | B44: ANTONIO NUNES LOPES | C44: B&B | D44: LOCAÇÃO | E44: PISO METALICO METALSAFE 0.30x1.50m | F44: 10 | G44: UNID. | H44: 2400 | I44: CASA DO CONSTRUTOR P.G | J44: PISO METALICO METALSAFE 0.30x1.50m | K44: 20.7 | L44: 207 | M44: 46028 | N44: jan-2026 | O44: 28 | P44: BOLETO | Q44: ENTREGA | R44: 2 | S44: 46030 | T44: ENTREGUE | U44: OK
A45: 46086 | B45: ANTONIO NUNES LOPES | C45: B&B | D45: LOCAÇÃO | E45: PISO METALICO METALSAFE 0.30x1.50m | F45: 5 | G45: UNID. | H45: 2494 | I45: CASA DO CONSTRUTOR P.G | J45: PISO METALICO METALSAFE 0.30x1.50m | K45: 20.7 | L45: 103.5 | M45: 46086 | N45: mar-2026 | O45: 28 | P45: BOLETO | Q45: ENTREGA | R45: 0 | S45: 46086 | T45: ENTREGUE | U45: OK
A46: 46028 | B46: ANTONIO NUNES LOPES | C46: B&B | D46: LOCAÇÃO | E46: DIAGONAL METALICA DIVERSOS 2.12m | F46: 8 | G46: UNID. | H46: 2400 | I46: CASA DO CONSTRUTOR P.G | J46: DIAGONAL METALICA DIVERSOS 2.12m | K46: 3.45 | L46: 27.6 | M46: 46028 | N46: jan-2026 | O46: 28 | P46: BOLETO | Q46: ENTREGA | R46: 2 | S46: 46030 | T46: ENTREGUE | U46: OK
A47: 46086 | B47: ANTONIO NUNES LOPES | C47: B&B | D47: LOCAÇÃO | E47: DIAGONAL METALICA DIVERSOS 2.12m | F47: 3 | G47: UNID. | H47: 2494 | I47: CASA DO CONSTRUTOR P.G | J47: DIAGONAL METALICA DIVERSOS 2.12m | K47: 3.45 | L47: 10.35 | M47: 46086 | N47: mar-2026 | O47: 28 | P47: BOLETO | Q47: ENTREGA | R47: 0 | S47: 46086 | T47: ENTREGUE | U47: OK
A48: 46028 | B48: ANTONIO NUNES LOPES | C48: B&B | D48: LOCAÇÃO | E48: SAPATA DIVERSOS AJUSTAVEL | F48: 4 | G48: UNID. | H48: 2400 | I48: CASA DO CONSTRUTOR P.G | J48: SAPATA DIVERSOS AJUSTAVEL | K48: 18.4 | L48: 73.6 | M48: 46028 | N48: jan-2026 | O48: 28 | P48: BOLETO | Q48: ENTREGA | R48: 2 | S48: 46030 | T48: ENTREGUE | U48: OK
... A64: 46080 | B64: ANTONIO NUNES LOPES | C64: B&B | D64: OUTROS | E64: FUNDO SHERWIN W.GALVITE P/GALV GL 3,6 | F64: 1 | G64: UNID. | H64: 2487 | I64: DEPOSITO PADRÃO | J64: FUNDO SHERWIN W.GALVITE P/GALV GL 3,6 | K64: 249.9 | L64: 249.9 | M64: 46080 | N64: fev-2026 | O64: 21 | P64: BOLETO | Q64: ENTREGA | R64: 0 | S64: 46080 | T64: ENTREGUE | U64: OK
A65: 46093 | B65: ANTONIO NUNES LOPES | C65: B&B | D65: OUTROS | E65: TELHA OND. CRFS BRASILIT 2,13X1,10X8MM | F65: 13 | G65: UNID. | H65: 2502 | I65: TELHADÃO | J65: TELHA OND. CRFS BRASILIT 2,13X1,10X8MM | K65: 99.88 | L65: 1298.44 | M65: 46093 | N65: mar-2026 | O65: 28/35/42 | P65: BOLETO | Q65: ENTREGA | R65: 5 | S65: 46098 | T65: 4
A66: 46093 | B66: ANTONIO NUNES LOPES | C66: B&B | D66: OUTROS | E66: TELHA OND. CRFS BRASILIT 2,13X1,10X6MM | F66: 65 | G66: UNID. | H66: 2502 | I66: TELHADÃO | J66: TELHA OND. CRFS BRASILIT 2,13X1,10X6MM | K66: 61.43 | L66: 3992.95 | M66: 46093 | N66: mar-2026 | O66: 28/35/42 | P66: BOLETO | Q66: ENTREGA | R66: 5 | S66: 46098 | T66: 4
A67: 46086 | B67: ANTONIO NUNES LOPES | C67: B&B | D67: OUTROS | E67: FITA ALUMINIO 10CMX10MT DRYCO/SIKA | F67: 20 | G67: UNID. | H67: 2496 | I67: DEPOSITO PADRÃO | J67: FITA ALUMINIO 10CMX10MT DRYCO/SIKA | K67: 3.57 | L67: 71.4 | M67: 46086 | N67: mar-2026 | O67: 14 | P67: BOLETO | Q67: RETIRA | R67: 1 | S67: 46087 | T67: ENTREGUE | U67: OK
A68: 46080 | B68: ANTONIO NUNES LOPES | C68: B&B | D68: OUTROS | E68: ROLO LA FEPOX 05 CM C/ CABO FENIX 1203/05 | F68: 5 | G68: UNID. | H68: 2487 | I68: DEPOSITO PADRÃO | J68: ROLO LA FEPOX 05 CM C/ CABO FENIX 1203/05 | K68: 6.6 | L68: 33 | M68: 46080 | N68: fev-2026 | O68: 21 | P68: BOLETO | Q68: ENTREGA | R68: 0 | S68: 46080 | T68: ENTREGUE | U68: OK
A69: 46086 | B69: ANTONIO NUNES LOPES | C69: B&B | D69: OUTROS | E69: TUBO ESGOTO 4' (100MM) KRONA/FORTLEV/PLASTILIT | F69: 6 | G69: UNID. | H69: 2496 | I69: DEPOSITO PADRÃO | J69: TUBO ESGOTO 4' (100MM) KRONA/FORTLEV/PLASTILIT | K69: 20.42 | L69: 122.52 | M69: 46086 | N69: mar-2026 | O69: 14 | P69: BOLETO | Q69: RETIRA | R69: 1 | S69: 46087 | T69: ENTREGUE | U69: OK
A70: 46086 | B70: ANTONIO NUNES LOPES | C70: B&B | D70: OUTROS | E70: JOELHO ESGOTO 4 KRONA/FORTLEV/PLASTILIT 100X90MM | F70: 4 | G70: UNID. | H70: 2496 | I70: DEPOSITO PADRÃO | J70: JOELHO ESGOTO 4 KRONA/FORTLEV/PLASTILIT 100X90MM | K70: 9.5 | L70: 38 | M70: 46086 | N70: mar-2026 | O70: 14 | P70: BOLETO | Q70: RETIRA | R70: 1 | S70: 46087 | T70: ENTREGUE | U70: OK
A71: 46080 | B71: ANTONIO NUNES LOPES | C71: B&B | D71: OUTROS | E71: Impostos(IPI e ICMSST): | F71: 1 | G71: VERBA | H71: 2485 | I71: IMPERIO AÇO | J71: Impostos(IPI e ICMSST): | K71: 126.97 | L71: 126.97 | M71: 46080 | N71: fev-2026 | O71: 30/45/60 | P71: BOLETO | Q71: RETIRA | R71: 5 | S71: 46085 | T71: ENTREGUE | U71: OK
A72: 46034 | B72: ANTONIO NUNES LOPES | C72: B&B | D72: LOCAÇÃO | E72: 1 CAÇAMBA | F72: 1 | G72: VERBA | H72: 2418 | I72: FOX CAÇAMBAS | J72: 1 CAÇAMBA | K72: 350 | L72: 350 | M72: 46034 | N72: jan-2026 | O72: 15 | P72: BOLETO | Q72: ENTREGA | R72: 1 | S72: 46035 | T72: ENTREGUE | U72: OK
A73: 46028 | B73: ANTONIO NUNES LOPES | C73: B&B | D73: LOCAÇÃO | E73: DESLOCAMENTO ENTREGA E RETIRADA | F73: 2 | G73: VERBA | H73: 2400 | I73: CASA DO CONSTRUTOR P.G | J73: DESLOCAMENTO ENTREGA E RETIRADA | K73: 40 | L73: 80 | M73: 46028 | N73: jan-2026 | O73: 28 | P73: BOLETO | Q73: ENTREGA | R73: 2 | S73: 46030 | T73: ENTREGUE | U73: OK
A74: 46093 | B74: ANTONIO NUNES LOPES | C74: B&B | D74: OUTROS | E74: FRETE ENTREGA | F74: 1 | G74: VERBA | H74: 2502 | I74: TELHADÃO | J74: FRETE ENTREGA | K74: 200 | L74: 200 | M74: 46093 | N74: mar-2026 | O74: 28/35/42 | P74: BOLETO | Q74: ENTREGA | R74: 5 | S74: 46098 | T74: 4
A75: 45912 | B75: ANTONIO NUNES LOPES | C75: B&B | D75: LOCAÇÃO | E75: PISO ANDAIME | F75: 1 | G75: VERBA | H75: 2001 | I75: CASA DO CONSTRUTOR P.G | J75: PISO ANDAIME | K75: 18.4 | L75: 18.4 | M75: 45912 | N75: set-2025 | O75: 11 | P75: BOLETO | Q75: ENTREGA | R75: 0 | S75: 45912 | T75: ENTREGUE | U75: OK
A76: 45912 | B76: ANTONIO NUNES LOPES | C76: B&B | D76: LOCAÇÃO | E76: INDENIZAÇÃO DE PARTES DE EQUIPAMENTOS | F76: 1 | G76: VERBA | H76: 2009 | I76: CASA DO CONSTRUTOR P.G | J76: INDENIZAÇÃO DE PARTES DE EQUIPAMENTOS | K76: 257.15 | L76: 257.15 | M76: 45912 | N76: set-2025 | O76: 15 | P76: BOLETO | Q76: ENTREGA | R76: 0 | S76: 45912 | T76: ENTREGUE | U76: OK
A77: 46086 | B77: ANTONIO NUNES LOPES | C77: B&B | D77: OUTROS | E77: TABELA BASQUETE OFICIAL (COMPENSADO NAVAL) - ARO FIXO E REDE 2MM - PERFIS E AROS GALV | F77: 1 | G77: CONJ. | H77: 2495 | I77: POWER SPORTS | J77: TABELA BASQUETE OFICIAL (COMPENSADO NAVAL) - ARO FIXO E REDE 2MM - PERFIS E AROS GALV | K77: 1930 | L77: 1930 | M77: 46086 | N77: mar-2026 | O77: 28/42 | P77: BOLETO | Q77: ENTREGA | R77: 1 | S77: 46087 | T77: ENTREGUE | U77: OK

Sheet PEDIDOS EMITIDOS + DESCRIÇÃO
A2: OBRA | B2: SYLVIA DE MELLO
A4: ITEM | B4: PEDIDO | C4: FORNECEDOR | D4: DESCRIÇÃO MATERIAL | E4: UNID | F4: Soma de QTDADE | G4: Soma de VALOR TOTAL
A5: ELETRICA | B5: 1846 | C5: AREA ELETRICOS | D5: CABO FLEX750V 2,5MM2 AZ CL | E5: ROLO | F5: 4 | G5: 768
D6: CABO FLEX750V 2,5MM2 VD | E6: ROLO | F6: 4 | G6: 768
D7: PLACA 4X2 1MOD HORIZONTA BR SIENA | E7: UNID. | F7: 1 | G7: 2.8
D8: UNIDUT MULTIPLO ALUM 3/4 | E8: UNID. | F8: 100 | G8: 210
D9: CABO FLEX750V 2,5MM2 PT | E9: ROLO | F9: 14 | G9: 2688
D10: TAMPA ALUM CEGA 3/4 OU 1/2 | E10: UNID. | F10: 70 | G10: 147
D11: PARAFUSO SEXTAVADO 3/16X60MM P/BUCHA S08 | E11: UNID. | F11: 500 | G11: 50
D12: UNIDUT RETO ALUM 1 | E12: UNID. | F12: 20 | G12: 62
D13: TAMPAO PLASTICO PVC 1 | E13: UNID. | F13: 40 | G13: 9.6
D14: BUCHA FUS-8 P/ PARAFUSO PVC BLOCO | E14: UNID. | F14: 500 | G14: 100
D15: PLACA 4X4 2MOD BR SIENA | E15: UNID. | F15: 1 | G15: 5.5
D16: PLACA 4X2 SAIDA DE FIO BR SIENA | E16: UNID. | F16: 1 | G16: 2.8
D17: ELETRODUTO GALV LEVE 1 (0,50) C/LV | E17: UNID. | F17: 40 | G17: 700
... D27: TOMADA IND SOB 2P+T 32A 200/250V 6H AZ | E27: UNID. | F27: 1 | G27: 65.1
B28: 1963 | C28: IDEA&LUZ | D28: FRETE | E28: VERBA | F28: 1 | G28: 90
D29: Luminaria comercial de sobrepor, corpo em chapa de aço com pintura eletrostatica a pó na cor branca, com difusor em acrilico transparente . Para 2x18W - Largura: 90mm Altura:60mm Comprimento: 1235mm | E29: UNID. | F29: 18 | G29: 1197
B30: 1965 | C30: UEHARA ELETRICA | D30: CONDUITE PRE-ZINCADO B LEVE 3/4 | E30: BARRA | F30: 70 | G30: 978.6
D31: DAISA UNIDUT 08 CONICO 3/4 UCN034C-PB | E31: UNID. | F31: 100 | G31: 215
D32: DAISA PLACA P/DAILET A 3/4 CEGA | E32: UNID. | F32: 80 | G32: 172
D33: DAISA UNIDUT 35 RETO B 3/4 URN034C | E33: UNID. | F33: 50 | G33: 137.5
D34: TRAMONTINA TAMPAO A 3/4 56114/252 | E34: UNID. | F34: 60 | G34: 13.2
D35: ABRACADEIRA D C/CUNHA PERFILACO B 3/4 C/100 | E35: PACOTE | F35: 1 | G35: 42.3
D36: COND.FLEXIVEL METALICO DELCAFLEX PR C C/30M 3/4RL | E36: ROLO | F36: 1 | G36: 236
D37: DAISA UNIDUT 09 CONICO 1 UCN100C-PB | E37: UNID. | F37: 30 | G37: 76.5
D38: DAISA UNIDUT 36 RETO C 1 URN100C | E38: UNID. | F38: 30 | G38: 94.2
D39: FITA ISOLANTE 3M IMPERIAL 20M | E39: UNID. | F39: 10 | G39: 72
B40: 1977 | C40: JMD | D40: LAMP. TUBO LED 20,5W 6500K T8 BIV TASCHIBRA | E40: UNID. | F40: 48 | G40: 384
B41: 2043 | C41: UEHARA ELETRICA | D41: CABO FLEX COBRECOM 6,00 MM C/100M VERDE | E41: ROLO | F41: 1 | G41: 467.9
D42: CABO FLEX COBRECOM 10,00 MM C/100M AZUL CLARO | E42: ROLO | F42: 1 | G42: 812.5
D43: CABO FLEX COBRECOM 10,00 MM C/100M PRETO | E43: ROLO | F43: 3 | G43: 2437.5
B44: 2070 | C44: SIRO MATERIAIS ELETRICO | D44: REFLETOR LED IP66 200W 6500K - 140130020 | E44: UNID. | F44: 12 | G44: 933.66
D45: TAMPA PVC - UNICANAL 3/4" - - | E45: UNID. | F45: 100 | G45: 23
D46: BUCHA NYLON 08 C/PARAF. A.A. PAN/PH 4,8 | E46: PACOTE | F46: 2 | G46: 51.044
D47: FITA ISOLANTE IMPERIAL SLIM 18MM X 20M PT HB004216360 - - | E47: ROLO | F47: 12 | G47: 96
D48: CONDUITE SEALTUBO NORMAL ESTANHADO S/CAP 3/4" - - | E48: M | F48: 30 | G48: 264
D49: ABRACADEIRA COMPLETA 3/4" BC034 (X) - - | E49: UNID. | F49: 250 | G49: 590
