Workbook
Name bb: LANÇAMENTO[[#Headers],[OBRA]]
Name bb: LANÇAMENTO[[#Headers],[OBRA]]
Name FORNECEDORES: FORNECEDOR[]
Name FORNECEDORES: FORNECEDOR[]
Name FORNECEDORES: FORNECEDOR[]
Name FORNECEDORES: FORNECEDOR[]
Name FORNECEDORES: FORNECEDOR[]
Name FORNECEDORES: FORNECEDOR[]
Name OBRA: LANÇAMENTO[[#Headers],[OBRA]]
Name OBRA: LANÇAMENTO[[#Headers],[OBRA]]
Name OBRA: LANÇAMENTO[[#Headers],[OBRA]]
Name OBRA: LANÇAMENTO[[#Headers],[OBRA]]
Name OBRA: LANÇAMENTO[[#Headers],[OBRA]]
Name OBRA: LANÇAMENTO[[#Headers],[OBRA]]
Name OBRA: LANÇAMENTO[[#Headers],[OBRA]]

Sheet LANÇAMENTO
E1: =TODAY() -> 46129
A2: a | B2: OBRA | C2: FATURAMENTO | D2: ITEM | E2: MATERIAL SOLICITADO | F2: QTDADE | G2: UNID | H2: PEDIDO | I2: FORNECEDOR | J2: DESCRIÇÃO MATERIAL | K2: VALOR UNITARIO | L2: VALOR TOTAL | M2: DATA PEDIDO | N2: MÊS/ANO PEDIDO | O2: CONDIÇÃO PAGAMENTO | P2: FORMA DE PAGAMENTO | Q2: RETIRA OU ENTREGA | R2: PRAZO | S2: PREVISÃO ENTREGA OBRA | T2: RESTA | U2: OBRA COM MATERIAL | V2: OBSERVAÇÃO
A3: 45327 | B3: FCO MIGNONE | C3: =VLOOKUP(LANÇAMENTO[[#This Row],[OBRA]],OBRAS[],2,FALSE) -> BRASUL | D3: OUTROS | E3: ARG USO INTERNO AC1 20KG FORT | F3: 20 | G3: SACO | H3: 878 | I3: C&C | J3: ARG USO INTERNO AC1 20KG FORT | K3: 12.9 | L3: =LANÇAMENTO[[#This Row],[VALOR UNITARIO]]*LANÇAMENTO[[#This Row],[QTDADE]] -> 258 | M3: 45327 | N3: =TEXT(LANÇAMENTO[[#This Row],[DATA PEDIDO]],"MMM")&"-"&TEXT(M3,"AAAA") -> fev-2024 | O3: 30/60/90/120/150 | P3: BOLETO | Q3: ENTREGA | R3: 4 | S3: =IF(LANÇAMENTO[[#This Row],[DATA PEDIDO]]="","",LANÇAMENTO[[#This Row],[DATA PEDIDO]]+LANÇAMENTO[[#This Row],[PRAZO]]) -> 45331 | T3: =IF(LANÇAMENTO[[#This Row],[OBRA COM MATERIAL]]="OK","ENTREGUE",IF(LANÇAMENTO[[#This Row],[PRAZO]]="","",LANÇAMENTO[[#This Row],[PREVISÃO ENTREGA OBRA]]-$E$1)) -> -798
A4: 45873 | B4: GUIDO ROSOLÉN | C4: INTERIORANA | D4: LOCAÇÃO | E4: CAÇAMBA | F4: 1 | G4: UNID. | H4: 7304 | I4: HORTOCAÇAMBAS | J4: CAÇAMBA | K4: 400 | L4: =LANÇAMENTO[[#This Row],[VALOR UNITARIO]]*LANÇAMENTO[[#This Row],[QTDADE]] -> 400 | M4: 45873 | N4: =TEXT(LANÇAMENTO[[#This Row],[DATA PEDIDO]],"MMM")&"-"&TEXT(M4,"AAAA") -> ago-2025 | O4: 7 | P4: BOLETO | Q4: ENTREGA | R4: 0 | S4: =IF(LANÇAMENTO[[#This Row],[DATA PEDIDO]]="","",LANÇAMENTO[[#This Row],[DATA PEDIDO]]+LANÇAMENTO[[#This Row],[PRAZO]]) -> 45873 | T4: =IF(LANÇAMENTO[[#This Row],[OBRA COM MATERIAL]]="OK","ENTREGUE",IF(LANÇAMENTO[[#This Row],[PRAZO]]="","",LANÇAMENTO[[#This Row],[PREVISÃO ENTREGA OBRA]]-$E$1)) -> ENTREGUE | U4: OK
A5: 45873 | B5: DEPUTADO ANTONIO | C5: B&B | D5: COBERTURA / FORRO | E5: TELHA OND. CRFS BRASILIT 2,44X1,10X8MM | F5: 4 | G5: UNID. | H5: 7305 | I5: TELHADÃO | J5: TELHA OND. CRFS BRASILIT 2,44X1,10X8MM | K5: 101.75 | L5: =LANÇAMENTO[[#This Row],[VALOR UNITARIO]]*LANÇAMENTO[[#This Row],[QTDADE]] -> 407 | M5: 45873 | N5: =TEXT(LANÇAMENTO[[#This Row],[DATA PEDIDO]],"MMM")&"-"&TEXT(M5,"AAAA") -> ago-2025 | O5: 28/35/42 | P5: BOLETO | Q5: RETIRA | R5: 1 | S5: =IF(LANÇAMENTO[[#This Row],[DATA PEDIDO]]="","",LANÇAMENTO[[#This Row],[DATA PEDIDO]]+LANÇAMENTO[[#This Row],[PRAZO]]) -> 45874 | T5: =IF(LANÇAMENTO[[#This Row],[OBRA COM MATERIAL]]="OK","ENTREGUE",IF(LANÇAMENTO[[#This Row],[PRAZO]]="","",LANÇAMENTO[[#This Row],[PREVISÃO ENTREGA OBRA]]-$E$1)) -> ENTREGUE | U5: OK
A6: 45873 | B6: DEPUTADO ANTONIO | C6: B&B | D6: COBERTURA / FORRO | E6: TELHA OND. CRFS BRASILIT 2,13X1,10X8MM | F6: 20 | G6: UNID. | H6: 7305 | I6: TELHADÃO | J6: TELHA OND. CRFS BRASILIT 2,13X1,10X8MM | K6: 97.38 | L6: =LANÇAMENTO[[#This Row],[VALOR UNITARIO]]*LANÇAMENTO[[#This Row],[QTDADE]] -> 1947.6 | M6: 45873 | N6: =TEXT(LANÇAMENTO[[#This Row],[DATA PEDIDO]],"MMM")&"-"&TEXT(M6,"AAAA") -> ago-2025 | O6: 28/35/42 | P6: BOLETO | Q6: RETIRA | R6: 1 | S6: =IF(LANÇAMENTO[[#This Row],[DATA PEDIDO]]="","",LANÇAMENTO[[#This Row],[DATA PEDIDO]]+LANÇAMENTO[[#This Row],[PRAZO]]) -> 45874 | T6: =IF(LANÇAMENTO[[#This Row],[OBRA COM MATERIAL]]="OK","ENTREGUE",IF(LANÇAMENTO[[#This Row],[PRAZO]]="","",LANÇAMENTO[[#This Row],[PREVISÃO ENTREGA OBRA]]-$E$1)) -> ENTREGUE | U6: OK
A7: 45873 | B7: DEPUTADO ANTONIO | C7: B&B | D7: COBERTURA / FORRO | E7: TELHA OND. CRFS BRASILIT 1,83X1,10X8MM | F7: 10 | G7: UNID. | H7: 7305 | I7: TELHADÃO | J7: TELHA OND. CRFS BRASILIT 1,83X1,10X8MM | K7: 81.02 | L7: =LANÇAMENTO[[#This Row],[VALOR UNITARIO]]*LANÇAMENTO[[#This Row],[QTDADE]] -> 810.2 | M7: 45873 | N7: =TEXT(LANÇAMENTO[[#This Row],[DATA PEDIDO]],"MMM")&"-"&TEXT(M7,"AAAA") -> ago-2025 | O7: 28/35/42 | P7: BOLETO | Q7: RETIRA | R7: 1 | S7: =IF(LANÇAMENTO[[#This Row],[DATA PEDIDO]]="","",LANÇAMENTO[[#This Row],[DATA PEDIDO]]+LANÇAMENTO[[#This Row],[PRAZO]]) -> 45874 | T7: =IF(LANÇAMENTO[[#This Row],[OBRA COM MATERIAL]]="OK","ENTREGUE",IF(LANÇAMENTO[[#This Row],[PRAZO]]="","",LANÇAMENTO[[#This Row],[PREVISÃO ENTREGA OBRA]]-$E$1)) -> ENTREGUE | U7: OK
A8: 45873 | B8: DEPUTADO ANTONIO | C8: B&B | D8: COBERTURA / FORRO | E8: CUMEEIRA T.O. 1,10X300MM CRFS BRASILIT 15GR | F8: 3 | G8: UNID. | H8: 7305 | I8: TELHADÃO | J8: CUMEEIRA T.O. 1,10X300MM CRFS BRASILIT 15GR | K8: 54.77 | L8: =LANÇAMENTO[[#This Row],[VALOR UNITARIO]]*LANÇAMENTO[[#This Row],[QTDADE]] -> 164.31 | M8: 45873 | N8: =TEXT(LANÇAMENTO[[#This Row],[DATA PEDIDO]],"MMM")&"-"&TEXT(M8,"AAAA") -> ago-2025 | O8: 28/35/42 | P8: BOLETO | Q8: RETIRA | R8: 1 | S8: =IF(LANÇAMENTO[[#This Row],[DATA PEDIDO]]="","",LANÇAMENTO[[#This Row],[DATA PEDIDO]]+LANÇAMENTO[[#This Row],[PRAZO]]) -> 45874 | T8: =IF(LANÇAMENTO[[#This Row],[OBRA COM MATERIAL]]="OK","ENTREGUE",IF(LANÇAMENTO[[#This Row],[PRAZO]]="","",LANÇAMENTO[[#This Row],[PREVISÃO ENTREGA OBRA]]-$E$1)) -> ENTREGUE | U8: OK
A9: 45873 | B9: ALEXANDRINA SANTIAGO | C9: B&B | D9: COBERTURA / FORRO | E9: TELHA CERAMICA ROMANA IMP. REALEZA GOLD BARROBELLO | F9: 50 | G9: UNID. | H9: 7306 | I9: TELHADÃO | J9: TELHA CERAMICA ROMANA IMP. REALEZA GOLD BARROBELLO | K9: 2.28 | L9: =LANÇAMENTO[[#This Row],[VALOR UNITARIO]]*LANÇAMENTO[[#This Row],[QTDADE]] -> 114 | M9: 45873 | N9: =TEXT(LANÇAMENTO[[#This Row],[DATA PEDIDO]],"MMM")&"-"&TEXT(M9,"AAAA") -> ago-2025 | O9: 28 | P9: BOLETO | Q9: RETIRA | R9: 1 | S9: =IF(LANÇAMENTO[[#This Row],[DATA PEDIDO]]="","",LANÇAMENTO[[#This Row],[DATA PEDIDO]]+LANÇAMENTO[[#This Row],[PRAZO]]) -> 45874 | T9: =IF(LANÇAMENTO[[#This Row],[OBRA COM MATERIAL]]="OK","ENTREGUE",IF(LANÇAMENTO[[#This Row],[PRAZO]]="","",LANÇAMENTO[[#This Row],[PREVISÃO ENTREGA OBRA]]-$E$1)) -> ENTREGUE | U9: OK
A10: 45873 | B10: ALEXANDRINA SANTIAGO | C10: B&B | D10: COBERTURA / FORRO | E10: TELHA CERAMICA PAULISTINHA CAPA IMPER BARROBELLO | F10: 13 | G10: UNID. | H10: 7306 | I10: TELHADÃO | J10: TELHA CERAMICA PAULISTINHA CAPA IMPER BARROBELLO | K10: 3.76 | L10: =LANÇAMENTO[[#This Row],[VALOR UNITARIO]]*LANÇAMENTO[[#This Row],[QTDADE]] -> 48.88 | M10: 45873 | N10: =TEXT(LANÇAMENTO[[#This Row],[DATA PEDIDO]],"MMM")&"-"&TEXT(M10,"AAAA") -> ago-2025 | O10: 28 | P10: BOLETO | Q10: RETIRA | R10: 1 | S10: =IF(LANÇAMENTO[[#This Row],[DATA PEDIDO]]="","",LANÇAMENTO[[#This Row],[DATA PEDIDO]]+LANÇAMENTO[[#This Row],[PRAZO]]) -> 45874 | T10: =IF(LANÇAMENTO[[#This Row],[OBRA COM MATERIAL]]="OK","ENTREGUE",IF(LANÇAMENTO[[#This Row],[PRAZO]]="","",LANÇAMENTO[[#This Row],[PREVISÃO ENTREGA OBRA]]-$E$1)) -> ENTREGUE | U10: OK
A11: 45873 | B11: PRÉDIO VAGO | C11: B&B | D11: HIDRAULICA | E11: AMANCO TE SOLD. 50MM | F11: 2 | G11: UNID. | H11: 7307 | I11: CASA MIMOSA | J11: AMANCO TE SOLD. 50MM | K11: 12.02 | L11: =LANÇAMENTO[[#This Row],[VALOR UNITARIO]]*LANÇAMENTO[[#This Row],[QTDADE]] -> 24.04 | M11: 45873 | N11: =TEXT(LANÇAMENTO[[#This Row],[DATA PEDIDO]],"MMM")&"-"&TEXT(M11,"AAAA") -> ago-2025 | O11: 28 | P11: BOLETO | Q11: RETIRA | R11: 1 | S11: =IF(LANÇAMENTO[[#This Row],[DATA PEDIDO]]="","",LANÇAMENTO[[#This Row],[DATA PEDIDO]]+LANÇAMENTO[[#This Row],[PRAZO]]) -> 45874 | T11: =IF(LANÇAMENTO[[#This Row],[OBRA COM MATERIAL]]="OK","ENTREGUE",IF(LANÇAMENTO[[#This Row],[PRAZO]]="","",LANÇAMENTO[[#This Row],[PREVISÃO ENTREGA OBRA]]-$E$1)) -> ENTREGUE | U11: OK
A12: 45873 | B12: PRÉDIO VAGO | C12: B&B | D12: HIDRAULICA | E12: AMANCO CAP SOLD. 50MM | F12: 3 | G12: UNID. | H12: 7307 | I12: CASA MIMOSA | J12: AMANCO CAP SOLD. 50MM | K12: 5.4 | L12: =LANÇAMENTO[[#This Row],[VALOR UNITARIO]]*LANÇAMENTO[[#This Row],[QTDADE]] -> 16.2 | M12: 45873 | N12: =TEXT(LANÇAMENTO[[#This Row],[DATA PEDIDO]],"MMM")&"-"&TEXT(M12,"AAAA") -> ago-2025 | O12: 28 | P12: BOLETO | Q12: RETIRA | R12: 1 | S12: =IF(LANÇAMENTO[[#This Row],[DATA PEDIDO]]="","",LANÇAMENTO[[#This Row],[DATA PEDIDO]]+LANÇAMENTO[[#This Row],[PRAZO]]) -> 45874 | T12: =IF(LANÇAMENTO[[#This Row],[OBRA COM MATERIAL]]="OK","ENTREGUE",IF(LANÇAMENTO[[#This Row],[PRAZO]]="","",LANÇAMENTO[[#This Row],[PREVISÃO ENTREGA OBRA]]-$E$1)) -> ENTREGUE | U12: OK
A13: 45873 | B13: PRÉDIO VAGO | C13: B&B | D13: HIDRAULICA | E13: AMANCO LUVA SOLD. 50MM | F13: 4 | G13: UNID. | H13: 7307 | I13: CASA MIMOSA | J13: AMANCO LUVA SOLD. 50MM | K13: 2.49 | L13: =LANÇAMENTO[[#This Row],[VALOR UNITARIO]]*LANÇAMENTO[[#This Row],[QTDADE]] -> 9.96 | M13: 45873 | N13: =TEXT(LANÇAMENTO[[#This Row],[DATA PEDIDO]],"MMM")&"-"&TEXT(M13,"AAAA") -> ago-2025 | O13: 28 | P13: BOLETO | Q13: RETIRA | R13: 1 | S13: =IF(LANÇAMENTO[[#This Row],[DATA PEDIDO]]="","",LANÇAMENTO[[#This Row],[DATA PEDIDO]]+LANÇAMENTO[[#This Row],[PRAZO]]) -> 45874 | T13: =IF(LANÇAMENTO[[#This Row],[OBRA COM MATERIAL]]="OK","ENTREGUE",IF(LANÇAMENTO[[#This Row],[PRAZO]]="","",LANÇAMENTO[[#This Row],[PREVISÃO ENTREGA OBRA]]-$E$1)) -> ENTREGUE | U13: OK
A14: 45873 | B14: PRÉDIO VAGO | C14: B&B | D14: HIDRAULICA | E14: AMANCO TE ESG. 50MM | F14: 2 | G14: UNID. | H14: 7307 | I14: CASA MIMOSA | J14: AMANCO TE ESG. 50MM | K14: 4.6 | L14: =LANÇAMENTO[[#This Row],[VALOR UNITARIO]]*LANÇAMENTO[[#This Row],[QTDADE]] -> 9.2 | M14: 45873 | N14: =TEXT(LANÇAMENTO[[#This Row],[DATA PEDIDO]],"MMM")&"-"&TEXT(M14,"AAAA") -> ago-2025 | O14: 28 | P14: BOLETO | Q14: RETIRA | R14: 1 | S14: =IF(LANÇAMENTO[[#This Row],[DATA PEDIDO]]="","",LANÇAMENTO[[#This Row],[DATA PEDIDO]]+LANÇAMENTO[[#This Row],[PRAZO]]) -> 45874 | T14: =IF(LANÇAMENTO[[#This Row],[OBRA COM MATERIAL]]="OK","ENTREGUE",IF(LANÇAMENTO[[#This Row],[PRAZO]]="","",LANÇAMENTO[[#This Row],[PREVISÃO ENTREGA OBRA]]-$E$1)) -> ENTREGUE | U14: OK
A15: 45873 | B15: PRÉDIO VAGO | C15: B&B | D15: HIDRAULICA | E15: AMANCO JOELHO 90 ESG. 50MM | F15: 8 | G15: UNID. | H15: 7307 | I15: CASA MIMOSA | J15: AMANCO JOELHO 90 ESG. 50MM | K15: 1.76 | L15: =LANÇAMENTO[[#This Row],[VALOR UNITARIO]]*LANÇAMENTO[[#This Row],[QTDADE]] -> 14.08 | M15: 45873 | N15: =TEXT(LANÇAMENTO[[#This Row],[DATA PEDIDO]],"MMM")&"-"&TEXT(M15,"AAAA") -> ago-2025 | O15: 28 | P15: BOLETO | Q15: RETIRA | R15: 1 | S15: =IF(LANÇAMENTO[[#This Row],[DATA PEDIDO]]="","",LANÇAMENTO[[#This Row],[DATA PEDIDO]]+LANÇAMENTO[[#This Row],[PRAZO]]) -> 45874 | T15: =IF(LANÇAMENTO[[#This Row],[OBRA COM MATERIAL]]="OK","ENTREGUE",IF(LANÇAMENTO[[#This Row],[PRAZO]]="","",LANÇAMENTO[[#This Row],[PREVISÃO ENTREGA OBRA]]-$E$1)) -> ENTREGUE | U15: OK
... A22: 45873 | B22: PRÉDIO VAGO | C22: B&B | D22: HIDRAULICA | E22: AMANCO TUBO 6M MARROM SOLD. 25MM | F22: 1 | G22: UNID. | H22: 7307 | I22: CASA MIMOSA | J22: AMANCO TUBO 6M MARROM SOLD. 25MM | K22: 16.15 | L22: =LANÇAMENTO[[#This Row],[VALOR UNITARIO]]*LANÇAMENTO[[#This Row],[QTDADE]] -> 16.15 | M22: 45873 | N22: =TEXT(LANÇAMENTO[[#This Row],[DATA PEDIDO]],"MMM")&"-"&TEXT(M22,"AAAA") -> ago-2025 | O22: 28 | P22: BOLETO | Q22: RETIRA | R22: 1 | S22: =IF(LANÇAMENTO[[#This Row],[DATA PEDIDO]]="","",LANÇAMENTO[[#This Row],[DATA PEDIDO]]+LANÇAMENTO[[#This Row],[PRAZO]]) -> 45874 | T22: =IF(LANÇAMENTO[[#This Row],[OBRA COM MATERIAL]]="OK","ENTREGUE",IF(LANÇAMENTO[[#This Row],[PRAZO]]="","",LANÇAMENTO[[#This Row],[PREVISÃO ENTREGA OBRA]]-$E$1)) -> ENTREGUE | U22: OK
A23: 45870 | B23: ZILDA DOMINGOS | C23: INTERIORANA | D23: OUTROS | E23: 16 m3 concreto 25 mpa , pedrisco , slump 12 , com bomba | L23: =LANÇAMENTO[[#This Row],[VALOR UNITARIO]]*LANÇAMENTO[[#This Row],[QTDADE]] -> 0 | N23: =TEXT(LANÇAMENTO[[#This Row],[DATA PEDIDO]],"MMM")&"-"&TEXT(M23,"AAAA") -> jan-1900 | S23: =IF(LANÇAMENTO[[#This Row],[DATA PEDIDO]]="","",LANÇAMENTO[[#This Row],[DATA PEDIDO]]+LANÇAMENTO[[#This Row],[PRAZO]]) | T23: =IF(LANÇAMENTO[[#This Row],[OBRA COM MATERIAL]]="OK","ENTREGUE",IF(LANÇAMENTO[[#This Row],[PRAZO]]="","",LANÇAMENTO[[#This Row],[PREVISÃO ENTREGA OBRA]]-$E$1)) -> ENTREGUE | U23: OK
A24: 45873 | B24: ELVIRA SILVA | C24: BRASUL | D24: ELETRICA | E24: ARMACAO PRESBOW P/1 ISOL MEDIA | F24: 6 | G24: UNID. | H24: 7308 | I24: AREA ELETRICOS | J24: ARMACAO PRESBOW P/1 ISOL MEDIA | K24: 18.4 | L24: =LANÇAMENTO[[#This Row],[VALOR UNITARIO]]*LANÇAMENTO[[#This Row],[QTDADE]] -> 110.4 | M24: 45873 | N24: =TEXT(LANÇAMENTO[[#This Row],[DATA PEDIDO]],"MMM")&"-"&TEXT(M24,"AAAA") -> ago-2025 | O24: 28 | P24: BOLETO | Q24: ENTREGA | R24: 0 | S24: =IF(LANÇAMENTO[[#This Row],[DATA PEDIDO]]="","",LANÇAMENTO[[#This Row],[DATA PEDIDO]]+LANÇAMENTO[[#This Row],[PRAZO]]) -> 45873 | T24: =IF(LANÇAMENTO[[#This Row],[OBRA COM MATERIAL]]="OK","ENTREGUE",IF(LANÇAMENTO[[#This Row],[PRAZO]]="","",LANÇAMENTO[[#This Row],[PREVISÃO ENTREGA OBRA]]-$E$1)) -> ENTREGUE | U24: OK
A25: 45873 | B25: ELVIRA SILVA | C25: BRASUL | D25: ELETRICA | E25: ISOLADOR ROLDANA 67X72 PRESSBOW | F25: 6 | G25: UNID. | H25: 7308 | I25: AREA ELETRICOS | J25: ISOLADOR ROLDANA 67X72 PRESSBOW | K25: 14.6 | L25: =LANÇAMENTO[[#This Row],[VALOR UNITARIO]]*LANÇAMENTO[[#This Row],[QTDADE]] -> 87.6 | M25: 45873 | N25: =TEXT(LANÇAMENTO[[#This Row],[DATA PEDIDO]],"MMM")&"-"&TEXT(M25,"AAAA") -> ago-2025 | O25: 28 | P25: BOLETO | Q25: ENTREGA | R25: 0 | S25: =IF(LANÇAMENTO[[#This Row],[DATA PEDIDO]]="","",LANÇAMENTO[[#This Row],[DATA PEDIDO]]+LANÇAMENTO[[#This Row],[PRAZO]]) -> 45873 | T25: =IF(LANÇAMENTO[[#This Row],[OBRA COM MATERIAL]]="OK","ENTREGUE",IF(LANÇAMENTO[[#This Row],[PRAZO]]="","",LANÇAMENTO[[#This Row],[PREVISÃO ENTREGA OBRA]]-$E$1)) -> ENTREGUE | U25: OK
A26: 45873 | B26: ELVIRA SILVA | C26: BRASUL | D26: ELETRICA | E26: ELETRODUTO GALV MED 2 (0,75)C/LV | F26: 6 | G26: UNID. | H26: 7308 | I26: AREA ELETRICOS | J26: ELETRODUTO GALV MED 2 (0,75)C/LV | K26: 84 | L26: =LANÇAMENTO[[#This Row],[VALOR UNITARIO]]*LANÇAMENTO[[#This Row],[QTDADE]] -> 504 | M26: 45873 | N26: =TEXT(LANÇAMENTO[[#This Row],[DATA PEDIDO]],"MMM")&"-"&TEXT(M26,"AAAA") -> ago-2025 | O26: 28 | P26: BOLETO | Q26: ENTREGA | R26: 0 | S26: =IF(LANÇAMENTO[[#This Row],[DATA PEDIDO]]="","",LANÇAMENTO[[#This Row],[DATA PEDIDO]]+LANÇAMENTO[[#This Row],[PRAZO]]) -> 45873 | T26: =IF(LANÇAMENTO[[#This Row],[OBRA COM MATERIAL]]="OK","ENTREGUE",IF(LANÇAMENTO[[#This Row],[PRAZO]]="","",LANÇAMENTO[[#This Row],[PREVISÃO ENTREGA OBRA]]-$E$1)) -> ENTREGUE | U26: OK
A27: 45873 | B27: PRÉDIO VAGO | C27: B&B | D27: LOCAÇÃO | E27: Caçamba | F27: 2 | G27: UNID. | H27: 7309 | I27: SOS CAÇAMBAS | J27: CAÇAMBA | K27: 200 | L27: =LANÇAMENTO[[#This Row],[VALOR UNITARIO]]*LANÇAMENTO[[#This Row],[QTDADE]] -> 400 | M27: 45873 | N27: =TEXT(LANÇAMENTO[[#This Row],[DATA PEDIDO]],"MMM")&"-"&TEXT(M27,"AAAA") -> ago-2025 | O27: 7 | P27: BOLETO | Q27: ENTREGA | R27: 0 | S27: =IF(LANÇAMENTO[[#This Row],[DATA PEDIDO]]="","",LANÇAMENTO[[#This Row],[DATA PEDIDO]]+LANÇAMENTO[[#This Row],[PRAZO]]) -> 45873 | T27: =IF(LANÇAMENTO[[#This Row],[OBRA COM MATERIAL]]="OK","ENTREGUE",IF(LANÇAMENTO[[#This Row],[PRAZO]]="","",LANÇAMENTO[[#This Row],[PREVISÃO ENTREGA OBRA]]-$E$1)) -> ENTREGUE | U27: OK
A28: 45873 | B28: VIRGILIO SILVEIRA | C28: INTERIORANA | D28: LOCAÇÃO | E28: BETONEIRA CID RENTAL 400L 220V | F28: 1 | G28: UNID. | H28: 7310 | I28: Casa do construtor Itapetininga | J28: BETONEIRA CID RENTAL 400L 220V | K28: 280 | L28: =LANÇAMENTO[[#This Row],[VALOR UNITARIO]]*LANÇAMENTO[[#This Row],[QTDADE]] -> 280 | M28: 45873 | N28: =TEXT(LANÇAMENTO[[#This Row],[DATA PEDIDO]],"MMM")&"-"&TEXT(M28,"AAAA") -> ago-2025 | O28: 15 | P28: BOLETO | Q28: ENTREGA | R28: 1 | S28: =IF(LANÇAMENTO[[#This Row],[DATA PEDIDO]]="","",LANÇAMENTO[[#This Row],[DATA PEDIDO]]+LANÇAMENTO[[#This Row],[PRAZO]]) -> 45874 | T28: =IF(LANÇAMENTO[[#This Row],[OBRA COM MATERIAL]]="OK","ENTREGUE",IF(LANÇAMENTO[[#This Row],[PRAZO]]="","",LANÇAMENTO[[#This Row],[PREVISÃO ENTREGA OBRA]]-$E$1)) -> ENTREGUE | U28: OK
A29: 45873 | B29: JOSÉ DE CAMPOS | C29: INTERIORANA | D29: OUTROS | E29: TESTE E LAUDO DE ESTANQUEIDADE DE GÁS | F29: 1 | G29: UNID. | H29: 7311 | I29: CS INSTALAÇÕES | J29: TESTE E LAUDO DE ESTANQUEIDADE DE GÁS | K29: 850 | L29: =LANÇAMENTO[[#This Row],[VALOR UNITARIO]]*LANÇAMENTO[[#This Row],[QTDADE]] -> 850 | M29: 45873 | N29: =TEXT(LANÇAMENTO[[#This Row],[DATA PEDIDO]],"MMM")&"-"&TEXT(M29,"AAAA") -> ago-2025 | O29: 2 | P29: PIX | Q29: ENTREGA | R29: 2 | S29: =IF(LANÇAMENTO[[#This Row],[DATA PEDIDO]]="","",LANÇAMENTO[[#This Row],[DATA PEDIDO]]+LANÇAMENTO[[#This Row],[PRAZO]]) -> 45875 | T29: =IF(LANÇAMENTO[[#This Row],[OBRA COM MATERIAL]]="OK","ENTREGUE",IF(LANÇAMENTO[[#This Row],[PRAZO]]="","",LANÇAMENTO[[#This Row],[PREVISÃO ENTREGA OBRA]]-$E$1)) -> ENTREGUE | U29: OK
A30: 45874 | B30: LUIZ CAMPO | C30: INTERIORANA | D30: REVESTMENTO / PISO | E30: ARGAMASSA PARA PORCELANATO INTERNO 20KG CINZA | F30: 100 | G30: SACO | H30: 7312 | I30: SODIMAC | J30: ARGAMASSA PARA PORCELANATO INTERNO 20KG CINZA | K30: 21.51 | L30: =LANÇAMENTO[[#This Row],[VALOR UNITARIO]]*LANÇAMENTO[[#This Row],[QTDADE]] -> 2151 | M30: 45874 | N30: =TEXT(LANÇAMENTO[[#This Row],[DATA PEDIDO]],"MMM")&"-"&TEXT(M30,"AAAA") -> ago-2025 | O30: 28/56/84/112 | P30: BOLETO | Q30: ENTREGA | R30: 3 | S30: =IF(LANÇAMENTO[[#This Row],[DATA PEDIDO]]="","",LANÇAMENTO[[#This Row],[DATA PEDIDO]]+LANÇAMENTO[[#This Row],[PRAZO]]) -> 45877 | T30: =IF(LANÇAMENTO[[#This Row],[OBRA COM MATERIAL]]="OK","ENTREGUE",IF(LANÇAMENTO[[#This Row],[PRAZO]]="","",LANÇAMENTO[[#This Row],[PREVISÃO ENTREGA OBRA]]-$E$1)) -> ENTREGUE | U30: OK
A31: 45874 | B31: LUIZ CAMPO | C31: INTERIORANA | D31: REVESTMENTO / PISO | E31: REVESTIMENTO RETIFICADO FORMA BRANCO BRILHANTE 32X60CM CAIXA 2,30 M² | F31: 200.1 | G31: M2 | H31: 7312 | I31: SODIMAC | J31: REVESTIMENTO RETIFICADO FORMA BRANCO BRILHANTE 32X60CM CAIXA 2,30 M² | K31: 53.91 | L31: =LANÇAMENTO[[#This Row],[VALOR UNITARIO]]*LANÇAMENTO[[#This Row],[QTDADE]] -> 10787.391 | M31: 45874 | N31: =TEXT(LANÇAMENTO[[#This Row],[DATA PEDIDO]],"MMM")&"-"&TEXT(M31,"AAAA") -> ago-2025 | O31: 28/56/84/112 | P31: BOLETO | Q31: ENTREGA | R31: 3 | S31: =IF(LANÇAMENTO[[#This Row],[DATA PEDIDO]]="","",LANÇAMENTO[[#This Row],[DATA PEDIDO]]+LANÇAMENTO[[#This Row],[PRAZO]]) -> 45877 | T31: =IF(LANÇAMENTO[[#This Row],[OBRA COM MATERIAL]]="OK","ENTREGUE",IF(LANÇAMENTO[[#This Row],[PRAZO]]="","",LANÇAMENTO[[#This Row],[PREVISÃO ENTREGA OBRA]]-$E$1)) -> ENTREGUE | U31: OK
A32: 45874 | B32: LUIZ CAMPO | C32: INTERIORANA | D32: REVESTMENTO / PISO | E32: ARGAMASSA USO INTERNO ACI 20KG 45X25X10CM CINZA | F32: 50 | G32: SACO | H32: 7312 | I32: SODIMAC | J32: ARGAMASSA USO INTERNO ACI 20KG 45X25X10CM CINZA | K32: 15.26 | L32: =LANÇAMENTO[[#This Row],[VALOR UNITARIO]]*LANÇAMENTO[[#This Row],[QTDADE]] -> 763 | M32: 45874 | N32: =TEXT(LANÇAMENTO[[#This Row],[DATA PEDIDO]],"MMM")&"-"&TEXT(M32,"AAAA") -> ago-2025 | O32: 28/56/84/112 | P32: BOLETO | Q32: ENTREGA | R32: 3 | S32: =IF(LANÇAMENTO[[#This Row],[DATA PEDIDO]]="","",LANÇAMENTO[[#This Row],[DATA PEDIDO]]+LANÇAMENTO[[#This Row],[PRAZO]]) -> 45877 | T32: =IF(LANÇAMENTO[[#This Row],[OBRA COM MATERIAL]]="OK","ENTREGUE",IF(LANÇAMENTO[[#This Row],[PRAZO]]="","",LANÇAMENTO[[#This Row],[PREVISÃO ENTREGA OBRA]]-$E$1)) -> ENTREGUE | U32: OK
A33: 45874 | B33: LUIZ CAMPO | C33: INTERIORANA | D33: REVESTMENTO / PISO | E33: REJUNTE FLEXÍVEL 5KG BRANCO WEBER QUARTZOLIT | F33: 8 | G33: SACO | H33: 7312 | I33: SODIMAC | J33: REJUNTE FLEXÍVEL 5KG BRANCO WEBER QUARTZOLIT | K33: 49.41 | L33: =LANÇAMENTO[[#This Row],[VALOR UNITARIO]]*LANÇAMENTO[[#This Row],[QTDADE]] -> 395.28 | M33: 45874 | N33: =TEXT(LANÇAMENTO[[#This Row],[DATA PEDIDO]],"MMM")&"-"&TEXT(M33,"AAAA") -> ago-2025 | O33: 28/56/84/112 | P33: BOLETO | Q33: ENTREGA | R33: 3 | S33: =IF(LANÇAMENTO[[#This Row],[DATA PEDIDO]]="","",LANÇAMENTO[[#This Row],[DATA PEDIDO]]+LANÇAMENTO[[#This Row],[PRAZO]]) -> 45877 | T33: =IF(LANÇAMENTO[[#This Row],[OBRA COM MATERIAL]]="OK","ENTREGUE",IF(LANÇAMENTO[[#This Row],[PRAZO]]="","",LANÇAMENTO[[#This Row],[PREVISÃO ENTREGA OBRA]]-$E$1)) -> ENTREGUE | U33: OK
A34: 45874 | B34: LUIZ CAMPO | C34: INTERIORANA | D34: REVESTMENTO / PISO | E34: REJUNTE FLEXÍVEL, CINZA PLATINA, 5KG | F34: 10 | G34: SACO | H34: 7312 | I34: SODIMAC | J34: REJUNTE FLEXÍVEL, CINZA PLATINA, 5KG | K34: 49.41 | L34: =LANÇAMENTO[[#This Row],[VALOR UNITARIO]]*LANÇAMENTO[[#This Row],[QTDADE]] -> 494.1 | M34: 45874 | N34: =TEXT(LANÇAMENTO[[#This Row],[DATA PEDIDO]],"MMM")&"-"&TEXT(M34,"AAAA") -> ago-2025 | O34: 28/56/84/112 | P34: BOLETO | Q34: ENTREGA | R34: 3 | S34: =IF(LANÇAMENTO[[#This Row],[DATA PEDIDO]]="","",LANÇAMENTO[[#This Row],[DATA PEDIDO]]+LANÇAMENTO[[#This Row],[PRAZO]]) -> 45877 | T34: =IF(LANÇAMENTO[[#This Row],[OBRA COM MATERIAL]]="OK","ENTREGUE",IF(LANÇAMENTO[[#This Row],[PRAZO]]="","",LANÇAMENTO[[#This Row],[PREVISÃO ENTREGA OBRA]]-$E$1)) -> ENTREGUE | U34: OK
A35: 45874 | B35: LUIZ CAMPO | C35: INTERIORANA | D35: REVESTMENTO / PISO | E35: PORCELANATO YORK SGR CINZA 87,7X87,7 CAIXA 1,54M²PORTINARI | F35: 360.36 | G35: M2 | H35: 7312 | I35: SODIMAC | J35: PORCELANATO YORK SGR CINZA 87,7X87,7 CAIXA 1,54M²PORTINARI | K35: 82.71 | L35: =LANÇAMENTO[[#This Row],[VALOR UNITARIO]]*LANÇAMENTO[[#This Row],[QTDADE]] -> 29805.376 | M35: 45874 | N35: =TEXT(LANÇAMENTO[[#This Row],[DATA PEDIDO]],"MMM")&"-"&TEXT(M35,"AAAA") -> ago-2025 | O35: 28/56/84/112 | P35: BOLETO | Q35: ENTREGA | R35: 3 | S35: =IF(LANÇAMENTO[[#This Row],[DATA PEDIDO]]="","",LANÇAMENTO[[#This Row],[DATA PEDIDO]]+LANÇAMENTO[[#This Row],[PRAZO]]) -> 45877 | T35: =IF(LANÇAMENTO[[#This Row],[OBRA COM MATERIAL]]="OK","ENTREGUE",IF(LANÇAMENTO[[#This Row],[PRAZO]]="","",LANÇAMENTO[[#This Row],[PREVISÃO ENTREGA OBRA]]-$E$1)) -> ENTREGUE | U35: OK
... A61: 45874 | B61: WANDA FÉLIX | C61: INTERIORANA | D61: REVESTMENTO / PISO | E61: FRETE | F61: 1 | G61: UNID. | H61: 7321 | I61: SODIMAC | J61: FRETE | K61: 218.13 | L61: =LANÇAMENTO[[#This Row],[VALOR UNITARIO]]*LANÇAMENTO[[#This Row],[QTDADE]] -> 218.13 | M61: 45874 | N61: =TEXT(LANÇAMENTO[[#This Row],[DATA PEDIDO]],"MMM")&"-"&TEXT(M61,"AAAA") -> ago-2025 | O61: 28/56/84 | P61: BOLETO | Q61: ENTREGA | R61: 3 | S61: =IF(LANÇAMENTO[[#This Row],[DATA PEDIDO]]="","",LANÇAMENTO[[#This Row],[DATA PEDIDO]]+LANÇAMENTO[[#This Row],[PRAZO]]) -> 45877 | T61: =IF(LANÇAMENTO[[#This Row],[OBRA COM MATERIAL]]="OK","ENTREGUE",IF(LANÇAMENTO[[#This Row],[PRAZO]]="","",LANÇAMENTO[[#This Row],[PREVISÃO ENTREGA OBRA]]-$E$1)) -> ENTREGUE | U61: OK
A62: 45874 | B62: LUIZ CAMPO | C62: INTERIORANA | D62: LOCAÇÃO | E62: CAÇAMBA | F62: 1 | G62: UNID. | H62: 7322 | I62: HVR LOCAÇÃO | J62: CAÇAMBA | K62: 440 | L62: =LANÇAMENTO[[#This Row],[VALOR UNITARIO]]*LANÇAMENTO[[#This Row],[QTDADE]] -> 440 | M62: 45874 | N62: =TEXT(LANÇAMENTO[[#This Row],[DATA PEDIDO]],"MMM")&"-"&TEXT(M62,"AAAA") -> ago-2025 | O62: 10 | P62: BOLETO | Q62: ENTREGA | R62: 1 | S62: =IF(LANÇAMENTO[[#This Row],[DATA PEDIDO]]="","",LANÇAMENTO[[#This Row],[DATA PEDIDO]]+LANÇAMENTO[[#This Row],[PRAZO]]) -> 45875 | T62: =IF(LANÇAMENTO[[#This Row],[OBRA COM MATERIAL]]="OK","ENTREGUE",IF(LANÇAMENTO[[#This Row],[PRAZO]]="","",LANÇAMENTO[[#This Row],[PREVISÃO ENTREGA OBRA]]-$E$1)) -> ENTREGUE | U62: OK
A63: 45874 | B63: APARECIDA DE FATIMA | C63: INTERIORANA | D63: ELETRICA | E63: TOMADA RED 2P+T 10A 250V C/HASTE PT GRIS | F63: 7 | G63: UNID. | H63: 7323 | I63: AREA ELETRICOS | J63: TOMADA RED 2P+T 10A 250V C/HASTE PT GRIS | K63: 6.9 | L63: =LANÇAMENTO[[#This Row],[VALOR UNITARIO]]*LANÇAMENTO[[#This Row],[QTDADE]] -> 48.3 | M63: 45874 | N63: =TEXT(LANÇAMENTO[[#This Row],[DATA PEDIDO]],"MMM")&"-"&TEXT(M63,"AAAA") -> ago-2025 | O63: 28 | P63: BOLETO | Q63: ENTREGA | R63: 1 | S63: =IF(LANÇAMENTO[[#This Row],[DATA PEDIDO]]="","",LANÇAMENTO[[#This Row],[DATA PEDIDO]]+LANÇAMENTO[[#This Row],[PRAZO]]) -> 45875 | T63: =IF(LANÇAMENTO[[#This Row],[OBRA COM MATERIAL]]="OK","ENTREGUE",IF(LANÇAMENTO[[#This Row],[PRAZO]]="","",LANÇAMENTO[[#This Row],[PREVISÃO ENTREGA OBRA]]-$E$1)) -> ENTREGUE | U63: OK
A64: 45874 | B64: APARECIDA DE FATIMA | C64: INTERIORANA | D64: ELETRICA | E64: TOMADA RED HOR 2P+T 20A 250V S/PLACA PT | F64: 1 | G64: UNID. | H64: 7323 | I64: AREA ELETRICOS | J64: TOMADA RED HOR 2P+T 20A 250V S/PLACA PT | K64: 8.9 | L64: =LANÇAMENTO[[#This Row],[VALOR UNITARIO]]*LANÇAMENTO[[#This Row],[QTDADE]] -> 8.9 | M64: 45874 | N64: =TEXT(LANÇAMENTO[[#This Row],[DATA PEDIDO]],"MMM")&"-"&TEXT(M64,"AAAA") -> ago-2025 | O64: 28 | P64: BOLETO | Q64: ENTREGA | R64: 1 | S64: =IF(LANÇAMENTO[[#This Row],[DATA PEDIDO]]="","",LANÇAMENTO[[#This Row],[DATA PEDIDO]]+LANÇAMENTO[[#This Row],[PRAZO]]) -> 45875 | T64: =IF(LANÇAMENTO[[#This Row],[OBRA COM MATERIAL]]="OK","ENTREGUE",IF(LANÇAMENTO[[#This Row],[PRAZO]]="","",LANÇAMENTO[[#This Row],[PREVISÃO ENTREGA OBRA]]-$E$1)) -> ENTREGUE | U64: OK
A65: 45874 | B65: APARECIDA DE FATIMA | C65: INTERIORANA | D65: ELETRICA | E65: LUMINARIA EMERG 30LED BIV 100LM SLIM SEG | F65: 6 | G65: UNID. | H65: 7323 | I65: AREA ELETRICOS | J65: LUMINARIA EMERG 30LED BIV 100LM SLIM SEG | K65: 20.2 | L65: =LANÇAMENTO[[#This Row],[VALOR UNITARIO]]*LANÇAMENTO[[#This Row],[QTDADE]] -> 121.2 | M65: 45874 | N65: =TEXT(LANÇAMENTO[[#This Row],[DATA PEDIDO]],"MMM")&"-"&TEXT(M65,"AAAA") -> ago-2025 | O65: 28 | P65: BOLETO | Q65: ENTREGA | R65: 1 | S65: =IF(LANÇAMENTO[[#This Row],[DATA PEDIDO]]="","",LANÇAMENTO[[#This Row],[DATA PEDIDO]]+LANÇAMENTO[[#This Row],[PRAZO]]) -> 45875 | T65: =IF(LANÇAMENTO[[#This Row],[OBRA COM MATERIAL]]="OK","ENTREGUE",IF(LANÇAMENTO[[#This Row],[PRAZO]]="","",LANÇAMENTO[[#This Row],[PREVISÃO ENTREGA OBRA]]-$E$1)) -> ENTREGUE | U65: OK
A66: 45874 | B66: APARECIDA DE FATIMA | C66: INTERIORANA | D66: ELETRICA | E66: TAMPA ALUM CEGA 1 | F66: 20 | G66: UNID. | H66: 7323 | I66: AREA ELETRICOS | J66: TAMPA ALUM CEGA 1 | K66: 2.8 | L66: =LANÇAMENTO[[#This Row],[VALOR UNITARIO]]*LANÇAMENTO[[#This Row],[QTDADE]] -> 56 | M66: 45874 | N66: =TEXT(LANÇAMENTO[[#This Row],[DATA PEDIDO]],"MMM")&"-"&TEXT(M66,"AAAA") -> ago-2025 | O66: 28 | P66: BOLETO | Q66: ENTREGA | R66: 1 | S66: =IF(LANÇAMENTO[[#This Row],[DATA PEDIDO]]="","",LANÇAMENTO[[#This Row],[DATA PEDIDO]]+LANÇAMENTO[[#This Row],[PRAZO]]) -> 45875 | T66: =IF(LANÇAMENTO[[#This Row],[OBRA COM MATERIAL]]="OK","ENTREGUE",IF(LANÇAMENTO[[#This Row],[PRAZO]]="","",LANÇAMENTO[[#This Row],[PREVISÃO ENTREGA OBRA]]-$E$1)) -> ENTREGUE | U66: OK
A67: 45874 | B67: APARECIDA DE FATIMA | C67: INTERIORANA | D67: ELETRICA | E67: TAMPA ALUM CEGA 3/4 OU 1/2 | F67: 20 | G67: UNID. | H67: 7323 | I67: AREA ELETRICOS | J67: TAMPA ALUM CEGA 3/4 OU 1/2 | K67: 2.2 | L67: =LANÇAMENTO[[#This Row],[VALOR UNITARIO]]*LANÇAMENTO[[#This Row],[QTDADE]] -> 44 | M67: 45874 | N67: =TEXT(LANÇAMENTO[[#This Row],[DATA PEDIDO]],"MMM")&"-"&TEXT(M67,"AAAA") -> ago-2025 | O67: 28 | P67: BOLETO | Q67: ENTREGA | R67: 1 | S67: =IF(LANÇAMENTO[[#This Row],[DATA PEDIDO]]="","",LANÇAMENTO[[#This Row],[DATA PEDIDO]]+LANÇAMENTO[[#This Row],[PRAZO]]) -> 45875 | T67: =IF(LANÇAMENTO[[#This Row],[OBRA COM MATERIAL]]="OK","ENTREGUE",IF(LANÇAMENTO[[#This Row],[PRAZO]]="","",LANÇAMENTO[[#This Row],[PREVISÃO ENTREGA OBRA]]-$E$1)) -> ENTREGUE | U67: OK
A68: 45874 | B68: APARECIDA DE FATIMA | C68: INTERIORANA | D68: ELETRICA | E68: TAMPA P/1 TOM RED 3/4 OU 1/2 | F68: 8 | G68: UNID. | H68: 7323 | I68: AREA ELETRICOS | J68: TAMPA P/1 TOM RED 3/4 OU 1/2 | K68: 2.2 | L68: =LANÇAMENTO[[#This Row],[VALOR UNITARIO]]*LANÇAMENTO[[#This Row],[QTDADE]] -> 17.6 | M68: 45874 | N68: =TEXT(LANÇAMENTO[[#This Row],[DATA PEDIDO]],"MMM")&"-"&TEXT(M68,"AAAA") -> ago-2025 | O68: 28 | P68: BOLETO | Q68: ENTREGA | R68: 1 | S68: =IF(LANÇAMENTO[[#This Row],[DATA PEDIDO]]="","",LANÇAMENTO[[#This Row],[DATA PEDIDO]]+LANÇAMENTO[[#This Row],[PRAZO]]) -> 45875 | T68: =IF(LANÇAMENTO[[#This Row],[OBRA COM MATERIAL]]="OK","ENTREGUE",IF(LANÇAMENTO[[#This Row],[PRAZO]]="","",LANÇAMENTO[[#This Row],[PREVISÃO ENTREGA OBRA]]-$E$1)) -> ENTREGUE | U68: OK
A69: 45874 | B69: APARECIDA DE FATIMA | C69: INTERIORANA | D69: ELETRICA | E69: TAMPAO PLASTICO PVC 1 | F69: 40 | G69: UNID. | H69: 7323 | I69: AREA ELETRICOS | J69: TAMPAO PLASTICO PVC 1 | K69: 0.8 | L69: =LANÇAMENTO[[#This Row],[VALOR UNITARIO]]*LANÇAMENTO[[#This Row],[QTDADE]] -> 32 | M69: 45874 | N69: =TEXT(LANÇAMENTO[[#This Row],[DATA PEDIDO]],"MMM")&"-"&TEXT(M69,"AAAA") -> ago-2025 | O69: 28 | P69: BOLETO | Q69: ENTREGA | R69: 1 | S69: =IF(LANÇAMENTO[[#This Row],[DATA PEDIDO]]="","",LANÇAMENTO[[#This Row],[DATA PEDIDO]]+LANÇAMENTO[[#This Row],[PRAZO]]) -> 45875 | T69: =IF(LANÇAMENTO[[#This Row],[OBRA COM MATERIAL]]="OK","ENTREGUE",IF(LANÇAMENTO[[#This Row],[PRAZO]]="","",LANÇAMENTO[[#This Row],[PREVISÃO ENTREGA OBRA]]-$E$1)) -> ENTREGUE | U69: OK
A70: 45874 | B70: APARECIDA DE FATIMA | C70: INTERIORANA | D70: ELETRICA | E70: TAMPAO PLASTICO PVC 3/4 | F70: 40 | G70: UNID. | H70: 7323 | I70: AREA ELETRICOS | J70: TAMPAO PLASTICO PVC 3/4 | K70: 0.7 | L70: =LANÇAMENTO[[#This Row],[VALOR UNITARIO]]*LANÇAMENTO[[#This Row],[QTDADE]] -> 28 | M70: 45874 | N70: =TEXT(LANÇAMENTO[[#This Row],[DATA PEDIDO]],"MMM")&"-"&TEXT(M70,"AAAA") -> ago-2025 | O70: 28 | P70: BOLETO | Q70: ENTREGA | R70: 1 | S70: =IF(LANÇAMENTO[[#This Row],[DATA PEDIDO]]="","",LANÇAMENTO[[#This Row],[DATA PEDIDO]]+LANÇAMENTO[[#This Row],[PRAZO]]) -> 45875 | T70: =IF(LANÇAMENTO[[#This Row],[OBRA COM MATERIAL]]="OK","ENTREGUE",IF(LANÇAMENTO[[#This Row],[PRAZO]]="","",LANÇAMENTO[[#This Row],[PREVISÃO ENTREGA OBRA]]-$E$1)) -> ENTREGUE | U70: OK
A71: 45874 | B71: NEUSA DE FATIMA | C71: INTERIORANA | D71: COBERTURA / FORRO | E71: Pu construcao tubo - 420 gramas - Branco | F71: 25 | G71: UNID. | H71: 7325 | I71: VEDAPREMIX | J71: Pu construcao tubo - 420 gramas - Branco | K71: 13.8 | L71: =LANÇAMENTO[[#This Row],[VALOR UNITARIO]]*LANÇAMENTO[[#This Row],[QTDADE]] -> 345 | M71: 45875 | N71: =TEXT(LANÇAMENTO[[#This Row],[DATA PEDIDO]],"MMM")&"-"&TEXT(M71,"AAAA") -> ago-2025 | O71: 7 | P71: PIX | Q71: ENTREGA | R71: 0 | S71: =IF(LANÇAMENTO[[#This Row],[DATA PEDIDO]]="","",LANÇAMENTO[[#This Row],[DATA PEDIDO]]+LANÇAMENTO[[#This Row],[PRAZO]]) -> 45875 | T71: =IF(LANÇAMENTO[[#This Row],[OBRA COM MATERIAL]]="OK","ENTREGUE",IF(LANÇAMENTO[[#This Row],[PRAZO]]="","",LANÇAMENTO[[#This Row],[PREVISÃO ENTREGA OBRA]]-$E$1)) -> ENTREGUE | U71: OK
A72: 45874 | B72: NEUSA DE FATIMA | C72: INTERIORANA | D72: COBERTURA / FORRO | E72: Parafuso brocante - milheiro | F72: 1 | G72: PACOTE | H72: 7325 | I72: VEDAPREMIX | J72: Parafuso brocante - milheiro | K72: 79 | L72: =LANÇAMENTO[[#This Row],[VALOR UNITARIO]]*LANÇAMENTO[[#This Row],[QTDADE]] -> 79 | M72: 45875 | N72: =TEXT(LANÇAMENTO[[#This Row],[DATA PEDIDO]],"MMM")&"-"&TEXT(M72,"AAAA") -> ago-2025 | O72: 7 | P72: PIX | Q72: ENTREGA | R72: 0 | S72: =IF(LANÇAMENTO[[#This Row],[DATA PEDIDO]]="","",LANÇAMENTO[[#This Row],[DATA PEDIDO]]+LANÇAMENTO[[#This Row],[PRAZO]]) -> 45875 | T72: =IF(LANÇAMENTO[[#This Row],[OBRA COM MATERIAL]]="OK","ENTREGUE",IF(LANÇAMENTO[[#This Row],[PRAZO]]="","",LANÇAMENTO[[#This Row],[PREVISÃO ENTREGA OBRA]]-$E$1)) -> ENTREGUE | U72: OK
A73: 45874 | B73: MARIA CÉLIA | C73: INTERIORANA | D73: COBERTURA / FORRO | E73: Telhas PVR40/980 Simples 0,50 2975 Branco Branco | F73: 6 | G73: M | H73: 7324 | I73: PROVERAÇO | J73: Telhas PVR40/980 Simples 0,50 2975 Branco Branco | K73: 54.5 | L73: =LANÇAMENTO[[#This Row],[VALOR UNITARIO]]*LANÇAMENTO[[#This Row],[QTDADE]] -> 327 | M73: 45874 | N73: =TEXT(LANÇAMENTO[[#This Row],[DATA PEDIDO]],"MMM")&"-"&TEXT(M73,"AAAA") -> ago-2025 | O73: 28 | P73: BOLETO | Q73: RETIRA | R73: 3 | S73: =IF(LANÇAMENTO[[#This Row],[DATA PEDIDO]]="","",LANÇAMENTO[[#This Row],[DATA PEDIDO]]+LANÇAMENTO[[#This Row],[PRAZO]]) -> 45877 | T73: =IF(LANÇAMENTO[[#This Row],[OBRA COM MATERIAL]]="OK","ENTREGUE",IF(LANÇAMENTO[[#This Row],[PRAZO]]="","",LANÇAMENTO[[#This Row],[PREVISÃO ENTREGA OBRA]]-$E$1)) -> ENTREGUE | U73: OK
A74: 45875 | B74: ZILDA DOMINGOS | C74: INTERIORANA | D74: OUTROS | E74: Concreto FCK 25,0 MPA B0 Slump 12,00+/-2,00 PISO | F74: 16 | G74: M3 | H74: 7326 | I74: CORTESIA CONCRETO | J74: Concreto FCK 25,0 MPA B0 Slump 12,00+/-2,00 PISO | K74: 514 | L74: =LANÇAMENTO[[#This Row],[VALOR UNITARIO]]*LANÇAMENTO[[#This Row],[QTDADE]] -> 8224 | M74: 45875 | N74: =TEXT(LANÇAMENTO[[#This Row],[DATA PEDIDO]],"MMM")&"-"&TEXT(M74,"AAAA") -> ago-2025 | O74: 28 | P74: BOLETO | Q74: ENTREGA | R74: 3 | S74: =IF(LANÇAMENTO[[#This Row],[DATA PEDIDO]]="","",LANÇAMENTO[[#This Row],[DATA PEDIDO]]+LANÇAMENTO[[#This Row],[PRAZO]]) -> 45878 | T74: =IF(LANÇAMENTO[[#This Row],[OBRA COM MATERIAL]]="OK","ENTREGUE",IF(LANÇAMENTO[[#This Row],[PRAZO]]="","",LANÇAMENTO[[#This Row],[PREVISÃO ENTREGA OBRA]]-$E$1)) -> ENTREGUE | U74: OK
... A332: 45882 | B332: PRÉDIO VAGO | C332: B&B | D332: HIDRAULICA | E332: AMANCO TUBO 6M ESG. 50MM | F332: 1 | G332: UNID. | H332: 7396 | I332: CASA MIMOSA | J332: AMANCO TUBO 6M ESG. 50MM | K332: 50.92 | L332: =LANÇAMENTO[[#This Row],[VALOR UNITARIO]]*LANÇAMENTO[[#This Row],[QTDADE]] -> 50.92 | M332: 45882 | N332: =TEXT(LANÇAMENTO[[#This Row],[DATA PEDIDO]],"MMM")&"-"&TEXT(M332,"AAAA") -> ago-2025 | O332: 28/56/84 | P332: BOLETO | Q332: ENTREGA | R332: 0 | S332: =IF(LANÇAMENTO[[#This Row],[DATA PEDIDO]]="","",LANÇAMENTO[[#This Row],[DATA PEDIDO]]+LANÇAMENTO[[#This Row],[PRAZO]]) -> 45882 | T332: =IF(LANÇAMENTO[[#This Row],[OBRA COM MATERIAL]]="OK","ENTREGUE",IF(LANÇAMENTO[[#This Row],[PRAZO]]="","",LANÇAMENTO[[#This Row],[PREVISÃO ENTREGA OBRA]]-$E$1)) -> ENTREGUE | U332: ok
A333: 45882 | B333: MARIA CÉLIA | C333: INTERIORANA | D333: OUTROS | E333: TELA ALAMBRADO MALHA 2" FIO 10 GALV. 2,30 11 | F333: 25 | G333: M2 | H333: 7397 | I333: MITSUNARI | J333: TELA ALAMBRADO MALHA 2" FIO 10 GALV. 2,30 | K333: 43.1 | L333: =LANÇAMENTO[[#This Row],[VALOR UNITARIO]]*LANÇAMENTO[[#This Row],[QTDADE]] -> 1077.5 | M333: 45882 | N333: =TEXT(LANÇAMENTO[[#This Row],[DATA PEDIDO]],"MMM")&"-"&TEXT(M333,"AAAA") -> ago-2025 | O333: 28 | P333: BOLETO | Q333: ENTREGA | R333: 7 | S333: =IF(LANÇAMENTO[[#This Row],[DATA PEDIDO]]="","",LANÇAMENTO[[#This Row],[DATA PEDIDO]]+LANÇAMENTO[[#This Row],[PRAZO]]) -> 45889 | T333: =IF(LANÇAMENTO[[#This Row],[OBRA COM MATERIAL]]="OK","ENTREGUE",IF(LANÇAMENTO[[#This Row],[PRAZO]]="","",LANÇAMENTO[[#This Row],[PREVISÃO ENTREGA OBRA]]-$E$1)) -> ENTREGUE | U333: ok
A334: 45882 | B334: APARECIDA DE FATIMA | C334: INTERIORANA | D334: PINTURA | E334: TINTA PISO AZUL 18L FUTURA | F334: 5 | G334: LATA | H334: 7399 | I334: CORANTE | J334: TINTA PISO AZUL 18L FUTURA | K334: 240 | L334: =LANÇAMENTO[[#This Row],[VALOR UNITARIO]]*LANÇAMENTO[[#This Row],[QTDADE]] -> 1200 | M334: 45882 | N334: =TEXT(LANÇAMENTO[[#This Row],[DATA PEDIDO]],"MMM")&"-"&TEXT(M334,"AAAA") -> ago-2025 | O334: 30/60 | P334: BOLETO | Q334: ENTREGA | R334: 1 | S334: =IF(LANÇAMENTO[[#This Row],[DATA PEDIDO]]="","",LANÇAMENTO[[#This Row],[DATA PEDIDO]]+LANÇAMENTO[[#This Row],[PRAZO]]) -> 45883 | T334: =IF(LANÇAMENTO[[#This Row],[OBRA COM MATERIAL]]="OK","ENTREGUE",IF(LANÇAMENTO[[#This Row],[PRAZO]]="","",LANÇAMENTO[[#This Row],[PREVISÃO ENTREGA OBRA]]-$E$1)) -> ENTREGUE | U334: ok
A335: 45882 | B335: APARECIDA DE FATIMA | C335: INTERIORANA | D335: PINTURA | E335: TINTA PISO CONCRETO 18L FUTURA | F335: 1 | G335: LATA | H335: 7399 | I335: CORANTE | J335: TINTA PISO CONCRETO 18L FUTURA | K335: 240 | L335: =LANÇAMENTO[[#This Row],[VALOR UNITARIO]]*LANÇAMENTO[[#This Row],[QTDADE]] -> 240 | M335: 45882 | N335: =TEXT(LANÇAMENTO[[#This Row],[DATA PEDIDO]],"MMM")&"-"&TEXT(M335,"AAAA") -> ago-2025 | O335: 30/60 | P335: BOLETO | Q335: ENTREGA | R335: 1 | S335: =IF(LANÇAMENTO[[#This Row],[DATA PEDIDO]]="","",LANÇAMENTO[[#This Row],[DATA PEDIDO]]+LANÇAMENTO[[#This Row],[PRAZO]]) -> 45883 | T335: =IF(LANÇAMENTO[[#This Row],[OBRA COM MATERIAL]]="OK","ENTREGUE",IF(LANÇAMENTO[[#This Row],[PRAZO]]="","",LANÇAMENTO[[#This Row],[PREVISÃO ENTREGA OBRA]]-$E$1)) -> ENTREGUE | U335: ok
A336: 45882 | B336: APARECIDA DE FATIMA | C336: INTERIORANA | D336: PINTURA | E336: SUPER RENDIMENTO BRANCO 18L FUTURA | F336: 1 | G336: LATA | H336: 7399 | I336: CORANTE | J336: SUPER RENDIMENTO BRANCO 18L FUTURA | K336: 260 | L336: =LANÇAMENTO[[#This Row],[VALOR UNITARIO]]*LANÇAMENTO[[#This Row],[QTDADE]] -> 260 | M336: 45882 | N336: =TEXT(LANÇAMENTO[[#This Row],[DATA PEDIDO]],"MMM")&"-"&TEXT(M336,"AAAA") -> ago-2025 | O336: 30/60 | P336: BOLETO | Q336: ENTREGA | R336: 1 | S336: =IF(LANÇAMENTO[[#This Row],[DATA PEDIDO]]="","",LANÇAMENTO[[#This Row],[DATA PEDIDO]]+LANÇAMENTO[[#This Row],[PRAZO]]) -> 45883 | T336: =IF(LANÇAMENTO[[#This Row],[OBRA COM MATERIAL]]="OK","ENTREGUE",IF(LANÇAMENTO[[#This Row],[PRAZO]]="","",LANÇAMENTO[[#This Row],[PREVISÃO ENTREGA OBRA]]-$E$1)) -> ENTREGUE | U336: ok
A337: 45882 | B337: APARECIDA DE FATIMA | C337: INTERIORANA | D337: PINTURA | E337: TINTA PISO AMARELO 3,6L FUTURA | F337: 1 | G337: GALÃO | H337: 7399 | I337: CORANTE | J337: TINTA PISO AMARELO 3,6L FUTURA | K337: 84 | L337: =LANÇAMENTO[[#This Row],[VALOR UNITARIO]]*LANÇAMENTO[[#This Row],[QTDADE]] -> 84 | M337: 45882 | N337: =TEXT(LANÇAMENTO[[#This Row],[DATA PEDIDO]],"MMM")&"-"&TEXT(M337,"AAAA") -> ago-2025 | O337: 30/60 | P337: BOLETO | Q337: ENTREGA | R337: 1 | S337: =IF(LANÇAMENTO[[#This Row],[DATA PEDIDO]]="","",LANÇAMENTO[[#This Row],[DATA PEDIDO]]+LANÇAMENTO[[#This Row],[PRAZO]]) -> 45883 | T337: =IF(LANÇAMENTO[[#This Row],[OBRA COM MATERIAL]]="OK","ENTREGUE",IF(LANÇAMENTO[[#This Row],[PRAZO]]="","",LANÇAMENTO[[#This Row],[PREVISÃO ENTREGA OBRA]]-$E$1)) -> ENTREGUE | U337: ok
A338: 45882 | B338: APARECIDA DE FATIMA | C338: INTERIORANA | D338: PINTURA | E338: FITA CREPE 24MM X 50M ADERE | F338: 10 | G338: UNID. | H338: 7399 | I338: CORANTE | J338: FITA CREPE 24MM X 50M ADERE | K338: 6 | L338: =LANÇAMENTO[[#This Row],[VALOR UNITARIO]]*LANÇAMENTO[[#This Row],[QTDADE]] -> 60 | M338: 45882 | N338: =TEXT(LANÇAMENTO[[#This Row],[DATA PEDIDO]],"MMM")&"-"&TEXT(M338,"AAAA") -> ago-2025 | O338: 30/60 | P338: BOLETO | Q338: ENTREGA | R338: 1 | S338: =IF(LANÇAMENTO[[#This Row],[DATA PEDIDO]]="","",LANÇAMENTO[[#This Row],[DATA PEDIDO]]+LANÇAMENTO[[#This Row],[PRAZO]]) -> 45883 | T338: =IF(LANÇAMENTO[[#This Row],[OBRA COM MATERIAL]]="OK","ENTREGUE",IF(LANÇAMENTO[[#This Row],[PRAZO]]="","",LANÇAMENTO[[#This Row],[PREVISÃO ENTREGA OBRA]]-$E$1)) -> ENTREGUE | U338: ok
A339: 45882 | B339: APARECIDA DE FATIMA | C339: INTERIORANA | D339: PINTURA | E339: TRINCHA 500 - 2 LATEX & ACRILICA TIGRE | F339: 2 | G339: UNID. | H339: 7399 | I339: CORANTE | J339: TRINCHA 500 - 2 LATEX & ACRILICA TIGRE | K339: 4.9 | L339: =LANÇAMENTO[[#This Row],[VALOR UNITARIO]]*LANÇAMENTO[[#This Row],[QTDADE]] -> 9.8 | M339: 45882 | N339: =TEXT(LANÇAMENTO[[#This Row],[DATA PEDIDO]],"MMM")&"-"&TEXT(M339,"AAAA") -> ago-2025 | O339: 30/60 | P339: BOLETO | Q339: ENTREGA | R339: 1 | S339: =IF(LANÇAMENTO[[#This Row],[DATA PEDIDO]]="","",LANÇAMENTO[[#This Row],[DATA PEDIDO]]+LANÇAMENTO[[#This Row],[PRAZO]]) -> 45883 | T339: =IF(LANÇAMENTO[[#This Row],[OBRA COM MATERIAL]]="OK","ENTREGUE",IF(LANÇAMENTO[[#This Row],[PRAZO]]="","",LANÇAMENTO[[#This Row],[PREVISÃO ENTREGA OBRA]]-$E$1)) -> ENTREGUE | U339: ok
A340: 45882 | B340: APARECIDA DE FATIMA | C340: INTERIORANA | D340: PINTURA | E340: ROLO 23CM LA SINTETICA 1312 TIGRE | F340: 3 | G340: UNID. | H340: 7399 | I340: CORANTE | J340: ROLO 23CM LA SINTETICA 1312 TIGRE | K340: 10 | L340: =LANÇAMENTO[[#This Row],[VALOR UNITARIO]]*LANÇAMENTO[[#This Row],[QTDADE]] -> 30 | M340: 45882 | N340: =TEXT(LANÇAMENTO[[#This Row],[DATA PEDIDO]],"MMM")&"-"&TEXT(M340,"AAAA") -> ago-2025 | O340: 30/60 | P340: BOLETO | Q340: ENTREGA | R340: 1 | S340: =IF(LANÇAMENTO[[#This Row],[DATA PEDIDO]]="","",LANÇAMENTO[[#This Row],[DATA PEDIDO]]+LANÇAMENTO[[#This Row],[PRAZO]]) -> 45883 | T340: =IF(LANÇAMENTO[[#This Row],[OBRA COM MATERIAL]]="OK","ENTREGUE",IF(LANÇAMENTO[[#This Row],[PRAZO]]="","",LANÇAMENTO[[#This Row],[PREVISÃO ENTREGA OBRA]]-$E$1)) -> ENTREGUE | U340: ok
A341: 45882 | B341: APARECIDA DE FATIMA | C341: INTERIORANA | D341: PINTURA | E341: SUPORTE PARA ROLO 1301 23CM TIGRE | F341: 3 | G341: UNID. | H341: 7399 | I341: CORANTE | J341: SUPORTE PARA ROLO 1301 23CM TIGRE | K341: 6.5 | L341: =LANÇAMENTO[[#This Row],[VALOR UNITARIO]]*LANÇAMENTO[[#This Row],[QTDADE]] -> 19.5 | M341: 45882 | N341: =TEXT(LANÇAMENTO[[#This Row],[DATA PEDIDO]],"MMM")&"-"&TEXT(M341,"AAAA") -> ago-2025 | O341: 30/60 | P341: BOLETO | Q341: ENTREGA | R341: 1 | S341: =IF(LANÇAMENTO[[#This Row],[DATA PEDIDO]]="","",LANÇAMENTO[[#This Row],[DATA PEDIDO]]+LANÇAMENTO[[#This Row],[PRAZO]]) -> 45883 | T341: =IF(LANÇAMENTO[[#This Row],[OBRA COM MATERIAL]]="OK","ENTREGUE",IF(LANÇAMENTO[[#This Row],[PRAZO]]="","",LANÇAMENTO[[#This Row],[PREVISÃO ENTREGA OBRA]]-$E$1)) -> ENTREGUE | U341: ok
A342: 45882 | B342: LUIZ CAMPO | C342: INTERIORANA | D342: LOCAÇÃO | E342: CAÇAMBA | F342: 1 | G342: UNID. | H342: 7398 | I342: HVR LOCAÇÃO | J342: CAÇAMBA | K342: 440 | L342: =LANÇAMENTO[[#This Row],[VALOR UNITARIO]]*LANÇAMENTO[[#This Row],[QTDADE]] -> 440 | M342: 45882 | N342: =TEXT(LANÇAMENTO[[#This Row],[DATA PEDIDO]],"MMM")&"-"&TEXT(M342,"AAAA") -> ago-2025 | O342: 10 | P342: BOLETO | Q342: ENTREGA | R342: 1 | S342: =IF(LANÇAMENTO[[#This Row],[DATA PEDIDO]]="","",LANÇAMENTO[[#This Row],[DATA PEDIDO]]+LANÇAMENTO[[#This Row],[PRAZO]]) -> 45883 | T342: =IF(LANÇAMENTO[[#This Row],[OBRA COM MATERIAL]]="OK","ENTREGUE",IF(LANÇAMENTO[[#This Row],[PRAZO]]="","",LANÇAMENTO[[#This Row],[PREVISÃO ENTREGA OBRA]]-$E$1)) -> ENTREGUE | U342: ok
A343: 45882 | B343: WANDA FÉLIX | C343: INTERIORANA | D343: LOCAÇÃO | E343: CAÇAMBA | F343: 1 | G343: UNID. | H343: 7400 | I343: HVR LOCAÇÃO | J343: CAÇAMBA | K343: 440 | L343: =LANÇAMENTO[[#This Row],[VALOR UNITARIO]]*LANÇAMENTO[[#This Row],[QTDADE]] -> 440 | M343: 45882 | N343: =TEXT(LANÇAMENTO[[#This Row],[DATA PEDIDO]],"MMM")&"-"&TEXT(M343,"AAAA") -> ago-2025 | O343: 10 | P343: BOLETO | Q343: ENTREGA | R343: 1 | S343: =IF(LANÇAMENTO[[#This Row],[DATA PEDIDO]]="","",LANÇAMENTO[[#This Row],[DATA PEDIDO]]+LANÇAMENTO[[#This Row],[PRAZO]]) -> 45883 | T343: =IF(LANÇAMENTO[[#This Row],[OBRA COM MATERIAL]]="OK","ENTREGUE",IF(LANÇAMENTO[[#This Row],[PRAZO]]="","",LANÇAMENTO[[#This Row],[PREVISÃO ENTREGA OBRA]]-$E$1)) -> ENTREGUE | U343: ok
A344: 45882 | B344: WANDA FÉLIX | C344: INTERIORANA | D344: LOCAÇÃO | E344: BETONEIRA 220V | F344: 1 | G344: UNID. | H344: 7390 | I344: GALIETA LOCAÇÕES | J344: BETONEIRA 220V | K344: 350 | L344: =LANÇAMENTO[[#This Row],[VALOR UNITARIO]]*LANÇAMENTO[[#This Row],[QTDADE]] -> 350 | M344: 45882 | N344: =TEXT(LANÇAMENTO[[#This Row],[DATA PEDIDO]],"MMM")&"-"&TEXT(M344,"AAAA") -> ago-2025 | O344: 10 | P344: BOLETO | Q344: ENTREGA | R344: 0 | S344: =IF(LANÇAMENTO[[#This Row],[DATA PEDIDO]]="","",LANÇAMENTO[[#This Row],[DATA PEDIDO]]+LANÇAMENTO[[#This Row],[PRAZO]]) -> 45882 | T344: =IF(LANÇAMENTO[[#This Row],[OBRA COM MATERIAL]]="OK","ENTREGUE",IF(LANÇAMENTO[[#This Row],[PRAZO]]="","",LANÇAMENTO[[#This Row],[PREVISÃO ENTREGA OBRA]]-$E$1)) -> ENTREGUE | U344: ok
A345: 45882 | B345: WANDA FÉLIX | C345: INTERIORANA | D345: LOCAÇÃO | E345: ANDAIME 1,5 X 1,5 | F345: 8 | G345: UNID. | H345: 7391 | I345: GALIETA LOCAÇÕES | J345: ANDAIME 1,5 X 1,5 | K345: 10.5 | L345: =LANÇAMENTO[[#This Row],[VALOR UNITARIO]]*LANÇAMENTO[[#This Row],[QTDADE]] -> 84 | M345: 45882 | N345: =TEXT(LANÇAMENTO[[#This Row],[DATA PEDIDO]],"MMM")&"-"&TEXT(M345,"AAAA") -> ago-2025 | O345: 10 | P345: BOLETO | Q345: ENTREGA | R345: 0 | S345: =IF(LANÇAMENTO[[#This Row],[DATA PEDIDO]]="","",LANÇAMENTO[[#This Row],[DATA PEDIDO]]+LANÇAMENTO[[#This Row],[PRAZO]]) -> 45882 | T345: =IF(LANÇAMENTO[[#This Row],[OBRA COM MATERIAL]]="OK","ENTREGUE",IF(LANÇAMENTO[[#This Row],[PRAZO]]="","",LANÇAMENTO[[#This Row],[PREVISÃO ENTREGA OBRA]]-$E$1)) -> ENTREGUE | U345: ok
A346: 45882 | B346: WANDA FÉLIX | C346: INTERIORANA | D346: LOCAÇÃO | E346: PLATAFORMA 1,5 | F346: 8 | G346: UNID. | H346: 7391 | I346: GALIETA LOCAÇÕES | J346: PLATAFORMA 1,5 | K346: 21 | L346: =LANÇAMENTO[[#This Row],[VALOR UNITARIO]]*LANÇAMENTO[[#This Row],[QTDADE]] -> 168 | M346: 45882 | N346: =TEXT(LANÇAMENTO[[#This Row],[DATA PEDIDO]],"MMM")&"-"&TEXT(M346,"AAAA") -> ago-2025 | O346: 10 | P346: BOLETO | Q346: ENTREGA | R346: 0 | S346: =IF(LANÇAMENTO[[#This Row],[DATA PEDIDO]]="","",LANÇAMENTO[[#This Row],[DATA PEDIDO]]+LANÇAMENTO[[#This Row],[PRAZO]]) -> 45882 | T346: =IF(LANÇAMENTO[[#This Row],[OBRA COM MATERIAL]]="OK","ENTREGUE",IF(LANÇAMENTO[[#This Row],[PRAZO]]="","",LANÇAMENTO[[#This Row],[PREVISÃO ENTREGA OBRA]]-$E$1)) -> ENTREGUE | U346: ok
A347: 45882 | B347: WANDA FÉLIX | C347: INTERIORANA | D347: LOCAÇÃO | E347: DIAGONAIS | F347: 1 | G347: UNID. | H347: 7391 | I347: GALIETA LOCAÇÕES | J347: DIAGONAIS | K347: 0 | L347: =LANÇAMENTO[[#This Row],[VALOR UNITARIO]]*LANÇAMENTO[[#This Row],[QTDADE]] -> 0 | M347: 45882 | N347: =TEXT(LANÇAMENTO[[#This Row],[DATA PEDIDO]],"MMM")&"-"&TEXT(M347,"AAAA") -> ago-2025 | O347: 10 | P347: BOLETO | Q347: ENTREGA | R347: 0 | S347: =IF(LANÇAMENTO[[#This Row],[DATA PEDIDO]]="","",LANÇAMENTO[[#This Row],[DATA PEDIDO]]+LANÇAMENTO[[#This Row],[PRAZO]]) -> 45882 | T347: =IF(LANÇAMENTO[[#This Row],[OBRA COM MATERIAL]]="OK","ENTREGUE",IF(LANÇAMENTO[[#This Row],[PRAZO]]="","",LANÇAMENTO[[#This Row],[PREVISÃO ENTREGA OBRA]]-$E$1)) -> ENTREGUE | U347: ok
A348: 45882 | B348: WANDA FÉLIX | C348: INTERIORANA | D348: LOCAÇÃO | E348: ANDAIME 1,5 X 1,5 | F348: 8 | G348: UNID. | H348: 7392 | I348: GALIETA LOCAÇÕES | J348: ANDAIME 1,5 X 1,5 | K348: 10.5 | L348: =LANÇAMENTO[[#This Row],[VALOR UNITARIO]]*LANÇAMENTO[[#This Row],[QTDADE]] -> 84 | M348: 45882 | N348: =TEXT(LANÇAMENTO[[#This Row],[DATA PEDIDO]],"MMM")&"-"&TEXT(M348,"AAAA") -> ago-2025 | O348: 10 | P348: BOLETO | Q348: ENTREGA | R348: 0 | S348: =IF(LANÇAMENTO[[#This Row],[DATA PEDIDO]]="","",LANÇAMENTO[[#This Row],[DATA PEDIDO]]+LANÇAMENTO[[#This Row],[PRAZO]]) -> 45882 | T348: =IF(LANÇAMENTO[[#This Row],[OBRA COM MATERIAL]]="OK","ENTREGUE",IF(LANÇAMENTO[[#This Row],[PRAZO]]="","",LANÇAMENTO[[#This Row],[PREVISÃO ENTREGA OBRA]]-$E$1)) -> ENTREGUE | U348: ok
A349: 45882 | B349: WANDA FÉLIX | C349: INTERIORANA | D349: LOCAÇÃO | E349: DIAGONAIS | F349: 1 | G349: UNID. | H349: 7392 | I349: GALIETA LOCAÇÕES | J349: DIAGONAIS | K349: 0 | L349: =LANÇAMENTO[[#This Row],[VALOR UNITARIO]]*LANÇAMENTO[[#This Row],[QTDADE]] -> 0 | M349: 45882 | N349: =TEXT(LANÇAMENTO[[#This Row],[DATA PEDIDO]],"MMM")&"-"&TEXT(M349,"AAAA") -> ago-2025 | O349: 10 | P349: BOLETO | Q349: ENTREGA | R349: 0 | S349: =IF(LANÇAMENTO[[#This Row],[DATA PEDIDO]]="","",LANÇAMENTO[[#This Row],[DATA PEDIDO]]+LANÇAMENTO[[#This Row],[PRAZO]]) -> 45882 | T349: =IF(LANÇAMENTO[[#This Row],[OBRA COM MATERIAL]]="OK","ENTREGUE",IF(LANÇAMENTO[[#This Row],[PRAZO]]="","",LANÇAMENTO[[#This Row],[PREVISÃO ENTREGA OBRA]]-$E$1)) -> ENTREGUE | U349: ok
A350: 45883 | B350: MARIA CÉLIA | C350: INTERIORANA | D350: LOCAÇÃO | E350: Painel andaime 1,5X1,5 | F350: 76 | G350: UNID. | H350: 7404 | I350: ANDAIME NORTE | J350: Painel andaime 1,5X1,5 | K350: 9.86 | L350: =LANÇAMENTO[[#This Row],[VALOR UNITARIO]]*LANÇAMENTO[[#This Row],[QTDADE]] -> 749.36 | M350: 45883 | N350: =TEXT(LANÇAMENTO[[#This Row],[DATA PEDIDO]],"MMM")&"-"&TEXT(M350,"AAAA") -> ago-2025 | O350: 28 | P350: BOLETO | Q350: ENTREGA | R350: 0 | S350: =IF(LANÇAMENTO[[#This Row],[DATA PEDIDO]]="","",LANÇAMENTO[[#This Row],[DATA PEDIDO]]+LANÇAMENTO[[#This Row],[PRAZO]]) -> 45883 | T350: =IF(LANÇAMENTO[[#This Row],[OBRA COM MATERIAL]]="OK","ENTREGUE",IF(LANÇAMENTO[[#This Row],[PRAZO]]="","",LANÇAMENTO[[#This Row],[PREVISÃO ENTREGA OBRA]]-$E$1)) -> ENTREGUE | U350: ok
A351: 45883 | B351: MARIA CÉLIA | C351: INTERIORANA | D351: LOCAÇÃO | E351: Diagonais para travamento de andaimes de 1,50 mts. | F351: 16 | G351: UNID. | H351: 7404 | I351: ANDAIME NORTE | J351: Diagonais para travamento de andaimes de 1,50 mts. | K351: 0 | L351: =LANÇAMENTO[[#This Row],[VALOR UNITARIO]]*LANÇAMENTO[[#This Row],[QTDADE]] -> 0 | M351: 45883 | N351: =TEXT(LANÇAMENTO[[#This Row],[DATA PEDIDO]],"MMM")&"-"&TEXT(M351,"AAAA") -> ago-2025 | O351: 28 | P351: BOLETO | Q351: ENTREGA | R351: 0 | S351: =IF(LANÇAMENTO[[#This Row],[DATA PEDIDO]]="","",LANÇAMENTO[[#This Row],[DATA PEDIDO]]+LANÇAMENTO[[#This Row],[PRAZO]]) -> 45883 | T351: =IF(LANÇAMENTO[[#This Row],[OBRA COM MATERIAL]]="OK","ENTREGUE",IF(LANÇAMENTO[[#This Row],[PRAZO]]="","",LANÇAMENTO[[#This Row],[PREVISÃO ENTREGA OBRA]]-$E$1)) -> ENTREGUE | U351: ok
A352: 45883 | B352: MARIA CÉLIA | C352: INTERIORANA | D352: LOCAÇÃO | E352: Barra de ligação para andaimes de 1,50 mts | F352: 16 | G352: UNID. | H352: 7404 | I352: ANDAIME NORTE | J352: Barra de ligação para andaimes de 1,50 mts | K352: 0 | L352: =LANÇAMENTO[[#This Row],[VALOR UNITARIO]]*LANÇAMENTO[[#This Row],[QTDADE]] -> 0 | M352: 45883 | N352: =TEXT(LANÇAMENTO[[#This Row],[DATA PEDIDO]],"MMM")&"-"&TEXT(M352,"AAAA") -> ago-2025 | O352: 28 | P352: BOLETO | Q352: ENTREGA | R352: 0 | S352: =IF(LANÇAMENTO[[#This Row],[DATA PEDIDO]]="","",LANÇAMENTO[[#This Row],[DATA PEDIDO]]+LANÇAMENTO[[#This Row],[PRAZO]]) -> 45883 | T352: =IF(LANÇAMENTO[[#This Row],[OBRA COM MATERIAL]]="OK","ENTREGUE",IF(LANÇAMENTO[[#This Row],[PRAZO]]="","",LANÇAMENTO[[#This Row],[PREVISÃO ENTREGA OBRA]]-$E$1)) -> ENTREGUE | U352: ok
A353: 45883 | B353: MARIA CÉLIA | C353: INTERIORANA | D353: LOCAÇÃO | E353: Plataformas metálicas p/ andaimes de 1,50 mt | F353: 16 | G353: UNID. | H353: 7404 | I353: ANDAIMENORTE | J353: Plataformas metálicas p/ andaimes de 1,50 mt | K353: 30 | L353: =LANÇAMENTO[[#This Row],[VALOR UNITARIO]]*LANÇAMENTO[[#This Row],[QTDADE]] -> 480 | M353: 45883 | N353: =TEXT(LANÇAMENTO[[#This Row],[DATA PEDIDO]],"MMM")&"-"&TEXT(M353,"AAAA") -> ago-2025 | O353: 28 | P353: BOLETO | Q353: ENTREGA | R353: 0 | S353: =IF(LANÇAMENTO[[#This Row],[DATA PEDIDO]]="","",LANÇAMENTO[[#This Row],[DATA PEDIDO]]+LANÇAMENTO[[#This Row],[PRAZO]]) -> 45883 | T353: =IF(LANÇAMENTO[[#This Row],[OBRA COM MATERIAL]]="OK","ENTREGUE",IF(LANÇAMENTO[[#This Row],[PRAZO]]="","",LANÇAMENTO[[#This Row],[PREVISÃO ENTREGA OBRA]]-$E$1)) -> ENTREGUE | U353: ok
A354: 45883 | B354: MARIA CÉLIA | C354: INTERIORANA | D354: LOCAÇÃO | E354: Sapata com roscas ajustáveis | F354: 16 | G354: UNID. | H354: 7404 | I354: ANDAIME NORTE | J354: Sapata com roscas ajustáveis | K354: 20 | L354: =LANÇAMENTO[[#This Row],[VALOR UNITARIO]]*LANÇAMENTO[[#This Row],[QTDADE]] -> 320 | M354: 45883 | N354: =TEXT(LANÇAMENTO[[#This Row],[DATA PEDIDO]],"MMM")&"-"&TEXT(M354,"AAAA") -> ago-2025 | O354: 28 | P354: BOLETO | Q354: ENTREGA | R354: 0 | S354: =IF(LANÇAMENTO[[#This Row],[DATA PEDIDO]]="","",LANÇAMENTO[[#This Row],[DATA PEDIDO]]+LANÇAMENTO[[#This Row],[PRAZO]]) -> 45883 | T354: =IF(LANÇAMENTO[[#This Row],[OBRA COM MATERIAL]]="OK","ENTREGUE",IF(LANÇAMENTO[[#This Row],[PRAZO]]="","",LANÇAMENTO[[#This Row],[PREVISÃO ENTREGA OBRA]]-$E$1)) -> ENTREGUE | U354: ok
A355: 45883 | B355: DEPUTADO ANTONIO | C355: B&B | D355: LOCAÇÃO | E355: CAÇAMBA | F355: 1 | G355: UNID. | H355: 7405 | I355: TIRA ENTULHO | J355: CAÇAMBA | K355: 450 | L355: =LANÇAMENTO[[#This Row],[VALOR UNITARIO]]*LANÇAMENTO[[#This Row],[QTDADE]] -> 450 | M355: 45883 | N355: =TEXT(LANÇAMENTO[[#This Row],[DATA PEDIDO]],"MMM")&"-"&TEXT(M355,"AAAA") -> ago-2025 | O355: 7 | P355: BOLETO | Q355: ENTREGA | R355: 1 | S355: =IF(LANÇAMENTO[[#This Row],[DATA PEDIDO]]="","",LANÇAMENTO[[#This Row],[DATA PEDIDO]]+LANÇAMENTO[[#This Row],[PRAZO]]) -> 45884 | T355: =IF(LANÇAMENTO[[#This Row],[OBRA COM MATERIAL]]="OK","ENTREGUE",IF(LANÇAMENTO[[#This Row],[PRAZO]]="","",LANÇAMENTO[[#This Row],[PREVISÃO ENTREGA OBRA]]-$E$1)) -> ENTREGUE | U355: ok
A356: 45883 | B356: EURINY DE SOUZA | C356: INTERIORANA | D356: LOCAÇÃO | E356: PAINEL ANDAIME 1,5 X 1,5 | F356: 48 | G356: UNID. | H356: 7406 | I356: MORIAH LOCACAO | J356: PAINEL ANDAIME 1,5 X 1,5 | K356: 11.25 | L356: =LANÇAMENTO[[#This Row],[VALOR UNITARIO]]*LANÇAMENTO[[#This Row],[QTDADE]] -> 540 | M356: 45883 | N356: =TEXT(LANÇAMENTO[[#This Row],[DATA PEDIDO]],"MMM")&"-"&TEXT(M356,"AAAA") -> ago-2025 | O356: 26 | P356: BOLETO | Q356: ENTREGA | R356: 0 | S356: =IF(LANÇAMENTO[[#This Row],[DATA PEDIDO]]="","",LANÇAMENTO[[#This Row],[DATA PEDIDO]]+LANÇAMENTO[[#This Row],[PRAZO]]) -> 45883 | T356: =IF(LANÇAMENTO[[#This Row],[OBRA COM MATERIAL]]="OK","ENTREGUE",IF(LANÇAMENTO[[#This Row],[PRAZO]]="","",LANÇAMENTO[[#This Row],[PREVISÃO ENTREGA OBRA]]-$E$1)) -> ENTREGUE | U356: ok
A357: 45883 | B357: EURINY DE SOUZA | C357: INTERIORANA | D357: LOCAÇÃO | E357: PLATAFORMAS | F357: 10 | G357: UNID. | H357: 7406 | I357: MORIAH LOCACAO | J357: PLATAFORMAS | K357: 22.5 | L357: =LANÇAMENTO[[#This Row],[VALOR UNITARIO]]*LANÇAMENTO[[#This Row],[QTDADE]] -> 225 | M357: 45883 | N357: =TEXT(LANÇAMENTO[[#This Row],[DATA PEDIDO]],"MMM")&"-"&TEXT(M357,"AAAA") -> ago-2025 | O357: 26 | P357: BOLETO | Q357: ENTREGA | R357: 0 | S357: =IF(LANÇAMENTO[[#This Row],[DATA PEDIDO]]="","",LANÇAMENTO[[#This Row],[DATA PEDIDO]]+LANÇAMENTO[[#This Row],[PRAZO]]) -> 45883 | T357: =IF(LANÇAMENTO[[#This Row],[OBRA COM MATERIAL]]="OK","ENTREGUE",IF(LANÇAMENTO[[#This Row],[PRAZO]]="","",LANÇAMENTO[[#This Row],[PREVISÃO ENTREGA OBRA]]-$E$1)) -> ENTREGUE | U357: ok
A358: 45883 | B358: EURINY DE SOUZA | C358: INTERIORANA | D358: LOCAÇÃO | E358: SAPATAS | F358: 8 | G358: UNID. | H358: 7406 | I358: MORIAH LOCACAO | J358: SAPATAS | K358: 22.5 | L358: =LANÇAMENTO[[#This Row],[VALOR UNITARIO]]*LANÇAMENTO[[#This Row],[QTDADE]] -> 180 | M358: 45883 | N358: =TEXT(LANÇAMENTO[[#This Row],[DATA PEDIDO]],"MMM")&"-"&TEXT(M358,"AAAA") -> ago-2025 | O358: 26 | P358: BOLETO | Q358: ENTREGA | R358: 0 | S358: =IF(LANÇAMENTO[[#This Row],[DATA PEDIDO]]="","",LANÇAMENTO[[#This Row],[DATA PEDIDO]]+LANÇAMENTO[[#This Row],[PRAZO]]) -> 45883 | T358: =IF(LANÇAMENTO[[#This Row],[OBRA COM MATERIAL]]="OK","ENTREGUE",IF(LANÇAMENTO[[#This Row],[PRAZO]]="","",LANÇAMENTO[[#This Row],[PREVISÃO ENTREGA OBRA]]-$E$1)) -> ENTREGUE | U358: ok
A359: 45883 | B359: PRÉDIO VAGO | C359: B&B | D359: LOCAÇÃO | E359: CAÇAMBA | F359: 1 | G359: UNID. | H359: 7407 | I359: SOS CAÇAMBAS | J359: CAÇAMBA | K359: 200 | L359: =LANÇAMENTO[[#This Row],[VALOR UNITARIO]]*LANÇAMENTO[[#This Row],[QTDADE]] -> 200 | M359: 45883 | N359: =TEXT(LANÇAMENTO[[#This Row],[DATA PEDIDO]],"MMM")&"-"&TEXT(M359,"AAAA") -> ago-2025 | O359: 7 | P359: BOLETO | Q359: ENTREGA | R359: 0 | S359: =IF(LANÇAMENTO[[#This Row],[DATA PEDIDO]]="","",LANÇAMENTO[[#This Row],[DATA PEDIDO]]+LANÇAMENTO[[#This Row],[PRAZO]]) -> 45883 | T359: =IF(LANÇAMENTO[[#This Row],[OBRA COM MATERIAL]]="OK","ENTREGUE",IF(LANÇAMENTO[[#This Row],[PRAZO]]="","",LANÇAMENTO[[#This Row],[PREVISÃO ENTREGA OBRA]]-$E$1)) -> ENTREGUE | U359: ok
A360: 45883 | B360: LUIZ CAMPO | C360: INTERIORANA | D360: OUTROS | E360: PEDRA I MT³ | F360: 3 | G360: M3 | H360: 7408 | I360: AZEFER MATERIAIS | J360: PEDRA I MT³ | K360: 118.59 | L360: =LANÇAMENTO[[#This Row],[VALOR UNITARIO]]*LANÇAMENTO[[#This Row],[QTDADE]] -> 355.77 | M360: 45883 | N360: =TEXT(LANÇAMENTO[[#This Row],[DATA PEDIDO]],"MMM")&"-"&TEXT(M360,"AAAA") -> ago-2025 | O360: 7 | P360: BOLETO | Q360: ENTREGA | R360: 1 | S360: =IF(LANÇAMENTO[[#This Row],[DATA PEDIDO]]="","",LANÇAMENTO[[#This Row],[DATA PEDIDO]]+LANÇAMENTO[[#This Row],[PRAZO]]) -> 45884 | T360: =IF(LANÇAMENTO[[#This Row],[OBRA COM MATERIAL]]="OK","ENTREGUE",IF(LANÇAMENTO[[#This Row],[PRAZO]]="","",LANÇAMENTO[[#This Row],[PREVISÃO ENTREGA OBRA]]-$E$1)) -> ENTREGUE | U360: ok
A361: 45883 | B361: LUIZ CAMPO | C361: INTERIORANA | D361: OUTROS | E361: CANTONEIRA AZULEJO EM L 3/4 BRANCA | F361: 20 | G361: UNID. | H361: 7408 | I361: AZEFER MATERIAIS | J361: CANTONEIRA AZULEJO EM L 3/4 BRANCA | K361: 22.89 | L361: =LANÇAMENTO[[#This Row],[VALOR UNITARIO]]*LANÇAMENTO[[#This Row],[QTDADE]] -> 457.8 | M361: 45883 | N361: =TEXT(LANÇAMENTO[[#This Row],[DATA PEDIDO]],"MMM")&"-"&TEXT(M361,"AAAA") -> ago-2025 | O361: 7 | P361: BOLETO | Q361: ENTREGA | R361: 1 | S361: =IF(LANÇAMENTO[[#This Row],[DATA PEDIDO]]="","",LANÇAMENTO[[#This Row],[DATA PEDIDO]]+LANÇAMENTO[[#This Row],[PRAZO]]) -> 45884 | T361: =IF(LANÇAMENTO[[#This Row],[OBRA COM MATERIAL]]="OK","ENTREGUE",IF(LANÇAMENTO[[#This Row],[PRAZO]]="","",LANÇAMENTO[[#This Row],[PREVISÃO ENTREGA OBRA]]-$E$1)) -> ENTREGUE | U361: ok
... A444: 45888 | B444: MARIA DE LOURDES | C444: INTERIORANA | D444: OUTROS | E444: CAÇAMBA | F444: 1 | G444: UNID. | H444: 7437 | I444: POSTE PADRÃO RANGEL | J444: CAÇAMBA | K444: 320 | L444: =LANÇAMENTO[[#This Row],[VALOR UNITARIO]]*LANÇAMENTO[[#This Row],[QTDADE]] -> 320 | M444: 45888 | N444: =TEXT(LANÇAMENTO[[#This Row],[DATA PEDIDO]],"MMM")&"-"&TEXT(M444,"AAAA") -> ago-2025 | O444: 7 | P444: PIX | Q444: ENTREGA | R444: 2 | S444: =IF(LANÇAMENTO[[#This Row],[DATA PEDIDO]]="","",LANÇAMENTO[[#This Row],[DATA PEDIDO]]+LANÇAMENTO[[#This Row],[PRAZO]]) -> 45890 | T444: =IF(LANÇAMENTO[[#This Row],[OBRA COM MATERIAL]]="OK","ENTREGUE",IF(LANÇAMENTO[[#This Row],[PRAZO]]="","",LANÇAMENTO[[#This Row],[PREVISÃO ENTREGA OBRA]]-$E$1)) -> ENTREGUE | U444: ok
A445: 45889 | B445: EURINY DE SOUZA | C445: INTERIORANA | D445: OUTROS | E445: TEL AUTO-BROCANTE SX AUTO BR CH.5/16 N12X3 | F445: 5 | G445: PACOTE | H445: 7438 | I445: NSA | J445: TEL AUTO-BROCANTE SX AUTO BR CH.5/16 N12X3 | K445: 38,05 | L445: =LANÇAMENTO[[#This Row],[VALOR UNITARIO]]*LANÇAMENTO[[#This Row],[QTDADE]] -> 190.25 | M445: 45889 | N445: =TEXT(LANÇAMENTO[[#This Row],[DATA PEDIDO]],"MMM")&"-"&TEXT(M445,"AAAA") -> ago-2025 | O445: 28 | P445: BOLETO | Q445: RETIRA | R445: 0 | S445: =IF(LANÇAMENTO[[#This Row],[DATA PEDIDO]]="","",LANÇAMENTO[[#This Row],[DATA PEDIDO]]+LANÇAMENTO[[#This Row],[PRAZO]]) -> 45889 | T445: =IF(LANÇAMENTO[[#This Row],[OBRA COM MATERIAL]]="OK","ENTREGUE",IF(LANÇAMENTO[[#This Row],[PRAZO]]="","",LANÇAMENTO[[#This Row],[PREVISÃO ENTREGA OBRA]]-$E$1)) -> ENTREGUE | U445: ok
A446: 45889 | B446: EURINY DE SOUZA | C446: INTERIORANA | D446: OUTROS | E446: TEL AUTO-BROCANTE SX AUTO BR CH.5/16 N12X1 | F446: 6 | G446: PACOTE | H446: 7438 | I446: NSA | J446: TEL AUTO-BROCANTE SX AUTO BR CH.5/16 N12X1 | K446: 16,38 | L446: =LANÇAMENTO[[#This Row],[VALOR UNITARIO]]*LANÇAMENTO[[#This Row],[QTDADE]] -> 98.28 | M446: 45889 | N446: =TEXT(LANÇAMENTO[[#This Row],[DATA PEDIDO]],"MMM")&"-"&TEXT(M446,"AAAA") -> ago-2025 | O446: 28 | P446: BOLETO | Q446: RETIRA | R446: 0 | S446: =IF(LANÇAMENTO[[#This Row],[DATA PEDIDO]]="","",LANÇAMENTO[[#This Row],[DATA PEDIDO]]+LANÇAMENTO[[#This Row],[PRAZO]]) -> 45889 | T446: =IF(LANÇAMENTO[[#This Row],[OBRA COM MATERIAL]]="OK","ENTREGUE",IF(LANÇAMENTO[[#This Row],[PRAZO]]="","",LANÇAMENTO[[#This Row],[PREVISÃO ENTREGA OBRA]]-$E$1)) -> ENTREGUE | U446: ok
A447: 45889 | B447: EURINY DE SOUZA | C447: INTERIORANA | D447: OUTROS | E447: TEL AUTO-BROCANTE P/EMENDA SX AUTO BR CH.5/16 N12X7/8 COSTURA | F447: 3 | G447: PACOTE | H447: 7438 | I447: NSA | J447: TEL AUTO-BROCANTE P/EMENDA SX AUTO BR CH.5/16 N12X7/8 COSTURA | K447: 19,74 | L447: =LANÇAMENTO[[#This Row],[VALOR UNITARIO]]*LANÇAMENTO[[#This Row],[QTDADE]] -> 59.22 | M447: 45889 | N447: =TEXT(LANÇAMENTO[[#This Row],[DATA PEDIDO]],"MMM")&"-"&TEXT(M447,"AAAA") -> ago-2025 | O447: 28 | P447: BOLETO | Q447: RETIRA | R447: 0 | S447: =IF(LANÇAMENTO[[#This Row],[DATA PEDIDO]]="","",LANÇAMENTO[[#This Row],[DATA PEDIDO]]+LANÇAMENTO[[#This Row],[PRAZO]]) -> 45889 | T447: =IF(LANÇAMENTO[[#This Row],[OBRA COM MATERIAL]]="OK","ENTREGUE",IF(LANÇAMENTO[[#This Row],[PRAZO]]="","",LANÇAMENTO[[#This Row],[PREVISÃO ENTREGA OBRA]]-$E$1)) -> ENTREGUE | U447: ok
A448: 45889 | B448: WANDA FÉLIX | C448: INTERIORANA | D448: OUTROS | E448: CIMENTO CPII 50KG | F448: 50 | G448: SACO | H448: 7439 | I448: CASA CAMPOS | J448: CIMENTO CPII 50KG | K448: 35.99 | L448: =LANÇAMENTO[[#This Row],[VALOR UNITARIO]]*LANÇAMENTO[[#This Row],[QTDADE]] -> 1799.5 | M448: 45889 | N448: =TEXT(LANÇAMENTO[[#This Row],[DATA PEDIDO]],"MMM")&"-"&TEXT(M448,"AAAA") -> ago-2025 | O448: 10 | P448: PIX | Q448: ENTREGA | R448: 1 | S448: =IF(LANÇAMENTO[[#This Row],[DATA PEDIDO]]="","",LANÇAMENTO[[#This Row],[DATA PEDIDO]]+LANÇAMENTO[[#This Row],[PRAZO]]) -> 45890 | T448: =IF(LANÇAMENTO[[#This Row],[OBRA COM MATERIAL]]="OK","ENTREGUE",IF(LANÇAMENTO[[#This Row],[PRAZO]]="","",LANÇAMENTO[[#This Row],[PREVISÃO ENTREGA OBRA]]-$E$1)) -> ENTREGUE | U448: ok
A449: 45889 | B449: LUIZ CAMPO | C449: INTERIORANA | D449: OUTROS | E449: CIMENTO CPII 50KG | F449: 30 | G449: SACO | H449: 7440 | I449: CASA CAMPOS | J449: CIMENTO CPII 50KG | K449: 35.99 | L449: =LANÇAMENTO[[#This Row],[VALOR UNITARIO]]*LANÇAMENTO[[#This Row],[QTDADE]] -> 1079.7 | M449: 45889 | N449: =TEXT(LANÇAMENTO[[#This Row],[DATA PEDIDO]],"MMM")&"-"&TEXT(M449,"AAAA") -> ago-2025 | O449: 10 | P449: PIX | Q449: ENTREGA | R449: 1 | S449: =IF(LANÇAMENTO[[#This Row],[DATA PEDIDO]]="","",LANÇAMENTO[[#This Row],[DATA PEDIDO]]+LANÇAMENTO[[#This Row],[PRAZO]]) -> 45890 | T449: =IF(LANÇAMENTO[[#This Row],[OBRA COM MATERIAL]]="OK","ENTREGUE",IF(LANÇAMENTO[[#This Row],[PRAZO]]="","",LANÇAMENTO[[#This Row],[PREVISÃO ENTREGA OBRA]]-$E$1)) -> ENTREGUE | U449: ok
A450: 45889 | B450: LUIZ CAMPO | C450: INTERIORANA | D450: OUTROS | E450: AREIA GROSSA | F450: 3 | G450: M3 | H450: 7440 | I450: CASA CAMPOS | J450: AREIA GROSSA | K450: 185.9 | L450: =LANÇAMENTO[[#This Row],[VALOR UNITARIO]]*LANÇAMENTO[[#This Row],[QTDADE]] -> 557.7 | M450: 45889 | N450: =TEXT(LANÇAMENTO[[#This Row],[DATA PEDIDO]],"MMM")&"-"&TEXT(M450,"AAAA") -> ago-2025 | O450: 10 | P450: PIX | Q450: ENTREGA | R450: 1 | S450: =IF(LANÇAMENTO[[#This Row],[DATA PEDIDO]]="","",LANÇAMENTO[[#This Row],[DATA PEDIDO]]+LANÇAMENTO[[#This Row],[PRAZO]]) -> 45890 | T450: =IF(LANÇAMENTO[[#This Row],[OBRA COM MATERIAL]]="OK","ENTREGUE",IF(LANÇAMENTO[[#This Row],[PRAZO]]="","",LANÇAMENTO[[#This Row],[PREVISÃO ENTREGA OBRA]]-$E$1)) -> ENTREGUE | U450: ok
A451: 45889 | B451: MARIA DE LOURDES | C451: INTERIORANA | D451: OUTROS | E451: Argamassa para Porcelanato Interno 20kg Cinza Quartzolit, CINZA, 20KG | F451: 55 | G451: SACO | H451: 7441 | I451: SODIMAC | J451: Argamassa para Porcelanato Interno 20kg Cinza Quartzolit, CINZA, 20KG | K451: 21.51 | L451: =LANÇAMENTO[[#This Row],[VALOR UNITARIO]]*LANÇAMENTO[[#This Row],[QTDADE]] -> 1183.05 | M451: 45889 | N451: =TEXT(LANÇAMENTO[[#This Row],[DATA PEDIDO]],"MMM")&"-"&TEXT(M451,"AAAA") -> ago-2025 | O451: 28/56/84/112 | P451: BOLETO | Q451: ENTREGA | R451: 5 | S451: =IF(LANÇAMENTO[[#This Row],[DATA PEDIDO]]="","",LANÇAMENTO[[#This Row],[DATA PEDIDO]]+LANÇAMENTO[[#This Row],[PRAZO]]) -> 45894 | T451: =IF(LANÇAMENTO[[#This Row],[OBRA COM MATERIAL]]="OK","ENTREGUE",IF(LANÇAMENTO[[#This Row],[PRAZO]]="","",LANÇAMENTO[[#This Row],[PREVISÃO ENTREGA OBRA]]-$E$1)) -> ENTREGUE | U451: ok
A452: 45889 | B452: MARIA DE LOURDES | C452: INTERIORANA | D452: OUTROS | E452: PORCELANATO RETIFICADO MUNARI BRANCO ACETINADO 60X60CM CAIXA 1,80 M² - | F452: 167.4 | G452: M2 | H452: 7441 | I452: SODIMAC | J452: Porcelanato York WH 87,7x87,7cm Caixa 1,54m² Retificado Branco, BRANCO, ., 87,7X87,7 | K452: 73.51 | L452: =LANÇAMENTO[[#This Row],[VALOR UNITARIO]]*LANÇAMENTO[[#This Row],[QTDADE]] -> 12305.574 | M452: 45889 | N452: =TEXT(LANÇAMENTO[[#This Row],[DATA PEDIDO]],"MMM")&"-"&TEXT(M452,"AAAA") -> ago-2025 | O452: 28/56/84/112 | P452: BOLETO | Q452: ENTREGA | R452: 5 | S452: =IF(LANÇAMENTO[[#This Row],[DATA PEDIDO]]="","",LANÇAMENTO[[#This Row],[DATA PEDIDO]]+LANÇAMENTO[[#This Row],[PRAZO]]) -> 45894 | T452: =IF(LANÇAMENTO[[#This Row],[OBRA COM MATERIAL]]="OK","ENTREGUE",IF(LANÇAMENTO[[#This Row],[PRAZO]]="","",LANÇAMENTO[[#This Row],[PREVISÃO ENTREGA OBRA]]-$E$1)) -> ENTREGUE | U452: ok
A453: 45889 | B453: MARIA DE LOURDES | C453: INTERIORANA | D453: OUTROS | E453: Rejunte Flexível, Cinza Platina, 5kg, CINZA PLATINA, 5KG, | F453: 6 | G453: SACO | H453: 7441 | I453: SODIMAC | J453: Rejunte Flexível, Cinza Platina, 5kg, CINZA PLATINA, 5KG, | K453: 49.41 | L453: =LANÇAMENTO[[#This Row],[VALOR UNITARIO]]*LANÇAMENTO[[#This Row],[QTDADE]] -> 296.46 | M453: 45889 | N453: =TEXT(LANÇAMENTO[[#This Row],[DATA PEDIDO]],"MMM")&"-"&TEXT(M453,"AAAA") -> ago-2025 | O453: 28/56/84/112 | P453: BOLETO | Q453: ENTREGA | R453: 5 | S453: =IF(LANÇAMENTO[[#This Row],[DATA PEDIDO]]="","",LANÇAMENTO[[#This Row],[DATA PEDIDO]]+LANÇAMENTO[[#This Row],[PRAZO]]) -> 45894 | T453: =IF(LANÇAMENTO[[#This Row],[OBRA COM MATERIAL]]="OK","ENTREGUE",IF(LANÇAMENTO[[#This Row],[PRAZO]]="","",LANÇAMENTO[[#This Row],[PREVISÃO ENTREGA OBRA]]-$E$1)) -> ENTREGUE | U453: ok
A454: 45889 | B454: MARIA DE LOURDES | C454: INTERIORANA | D454: OUTROS | E454: FRETE | F454: 1 | G454: UNID. | H454: 7441 | I454: SODIMAC | J454: FRETE | K454: 1144.16 | L454: =LANÇAMENTO[[#This Row],[VALOR UNITARIO]]*LANÇAMENTO[[#This Row],[QTDADE]] -> 1144.16 | M454: 45889 | N454: =TEXT(LANÇAMENTO[[#This Row],[DATA PEDIDO]],"MMM")&"-"&TEXT(M454,"AAAA") -> ago-2025 | O454: 28/56/84/112 | P454: BOLETO | Q454: ENTREGA | R454: 5 | S454: =IF(LANÇAMENTO[[#This Row],[DATA PEDIDO]]="","",LANÇAMENTO[[#This Row],[DATA PEDIDO]]+LANÇAMENTO[[#This Row],[PRAZO]]) -> 45894 | T454: =IF(LANÇAMENTO[[#This Row],[OBRA COM MATERIAL]]="OK","ENTREGUE",IF(LANÇAMENTO[[#This Row],[PRAZO]]="","",LANÇAMENTO[[#This Row],[PREVISÃO ENTREGA OBRA]]-$E$1)) -> ENTREGUE | U454: ok
L455: =LANÇAMENTO[[#This Row],[VALOR UNITARIO]]*LANÇAMENTO[[#This Row],[QTDADE]] -> 0 | N455: =TEXT(LANÇAMENTO[[#This Row],[DATA PEDIDO]],"MMM")&"-"&TEXT(M455,"AAAA") -> jan-1900 | S455: =IF(LANÇAMENTO[[#This Row],[DATA PEDIDO]]="","",LANÇAMENTO[[#This Row],[DATA PEDIDO]]+LANÇAMENTO[[#This Row],[PRAZO]]) | T455: =IF(LANÇAMENTO[[#This Row],[OBRA COM MATERIAL]]="OK","ENTREGUE",IF(LANÇAMENTO[[#This Row],[PRAZO]]="","",LANÇAMENTO[[#This Row],[PREVISÃO ENTREGA OBRA]]-$E$1)) -> ENTREGUE | U455: ok
A456: 45889 | B456: JD ALINE | C456: INTERIORANA | D456: OUTROS | E456: PAINEL STANDARD 12,5X1200X1800MM | F456: 20 | G456: UNID. | H456: 7442 | I456: ARTESANA | J456: PAINEL STANDARD 12,5X1200X1800MM | K456: 37.44 | L456: =LANÇAMENTO[[#This Row],[VALOR UNITARIO]]*LANÇAMENTO[[#This Row],[QTDADE]] -> 748.8 | M456: 45889 | N456: =TEXT(LANÇAMENTO[[#This Row],[DATA PEDIDO]],"MMM")&"-"&TEXT(M456,"AAAA") -> ago-2025 | O456: 28/35/42 | P456: BOLETO | Q456: RETIRA | R456: 2 | S456: =IF(LANÇAMENTO[[#This Row],[DATA PEDIDO]]="","",LANÇAMENTO[[#This Row],[DATA PEDIDO]]+LANÇAMENTO[[#This Row],[PRAZO]]) -> 45891 | T456: =IF(LANÇAMENTO[[#This Row],[OBRA COM MATERIAL]]="OK","ENTREGUE",IF(LANÇAMENTO[[#This Row],[PRAZO]]="","",LANÇAMENTO[[#This Row],[PREVISÃO ENTREGA OBRA]]-$E$1)) -> ENTREGUE | U456: ok
A457: 45889 | B457: JD ALINE | C457: INTERIORANA | D457: OUTROS | E457: GUIA 70X30X3000MM | F457: 6 | G457: UNID. | H457: 7442 | I457: ARTESANA | J457: GUIA 70X30X3000MM | K457: 17.76 | L457: =LANÇAMENTO[[#This Row],[VALOR UNITARIO]]*LANÇAMENTO[[#This Row],[QTDADE]] -> 106.56 | M457: 45889 | N457: =TEXT(LANÇAMENTO[[#This Row],[DATA PEDIDO]],"MMM")&"-"&TEXT(M457,"AAAA") -> ago-2025 | O457: 28/35/42 | P457: BOLETO | Q457: RETIRA | R457: 2 | S457: =IF(LANÇAMENTO[[#This Row],[DATA PEDIDO]]="","",LANÇAMENTO[[#This Row],[DATA PEDIDO]]+LANÇAMENTO[[#This Row],[PRAZO]]) -> 45891 | T457: =IF(LANÇAMENTO[[#This Row],[OBRA COM MATERIAL]]="OK","ENTREGUE",IF(LANÇAMENTO[[#This Row],[PRAZO]]="","",LANÇAMENTO[[#This Row],[PREVISÃO ENTREGA OBRA]]-$E$1)) -> ENTREGUE | U457: ok
A458: 45889 | B458: JD ALINE | C458: INTERIORANA | D458: OUTROS | E458: MON TANTE 70X30X3000MM DRYWALL | F458: 15 | G458: UNID. | H458: 7442 | I458: ARTESANA | J458: MON TANTE 70X30X3000MM DRYWALL | K458: 18.89 | L458: =LANÇAMENTO[[#This Row],[VALOR UNITARIO]]*LANÇAMENTO[[#This Row],[QTDADE]] -> 283.35 | M458: 45889 | N458: =TEXT(LANÇAMENTO[[#This Row],[DATA PEDIDO]],"MMM")&"-"&TEXT(M458,"AAAA") -> ago-2025 | O458: 28/35/42 | P458: BOLETO | Q458: RETIRA | R458: 2 | S458: =IF(LANÇAMENTO[[#This Row],[DATA PEDIDO]]="","",LANÇAMENTO[[#This Row],[DATA PEDIDO]]+LANÇAMENTO[[#This Row],[PRAZO]]) -> 45891 | T458: =IF(LANÇAMENTO[[#This Row],[OBRA COM MATERIAL]]="OK","ENTREGUE",IF(LANÇAMENTO[[#This Row],[PRAZO]]="","",LANÇAMENTO[[#This Row],[PREVISÃO ENTREGA OBRA]]-$E$1)) -> ENTREGUE | U458: ok
A459: 45889 | B459: JD ALINE | C459: INTERIORANA | D459: OUTROS | E459: MAS SA PRONTA P/ DRYWALL MAXCRYL 15 KG | F459: 1 | G459: UNID. | H459: 7442 | I459: ARTESANA | J459: MAS SA PRONTA P/ DRYWALL MAXCRYL 15 KG | K459: 39.2 | L459: =LANÇAMENTO[[#This Row],[VALOR UNITARIO]]*LANÇAMENTO[[#This Row],[QTDADE]] -> 39.2 | M459: 45889 | N459: =TEXT(LANÇAMENTO[[#This Row],[DATA PEDIDO]],"MMM")&"-"&TEXT(M459,"AAAA") -> ago-2025 | O459: 28/35/42 | P459: BOLETO | Q459: RETIRA | R459: 2 | S459: =IF(LANÇAMENTO[[#This Row],[DATA PEDIDO]]="","",LANÇAMENTO[[#This Row],[DATA PEDIDO]]+LANÇAMENTO[[#This Row],[PRAZO]]) -> 45891 | T459: =IF(LANÇAMENTO[[#This Row],[OBRA COM MATERIAL]]="OK","ENTREGUE",IF(LANÇAMENTO[[#This Row],[PRAZO]]="","",LANÇAMENTO[[#This Row],[PREVISÃO ENTREGA OBRA]]-$E$1)) -> ENTREGUE | U459: ok
A460: 45889 | B460: JD ALINE | C460: INTERIORANA | D460: OUTROS | E460: FITA TELADA FIBATAPE ROLO 90M | F460: 1 | G460: UNID. | H460: 7442 | I460: ARTESANA | J460: FITA TELADA FIBATAPE ROLO 90M | K460: 28.47 | L460: =LANÇAMENTO[[#This Row],[VALOR UNITARIO]]*LANÇAMENTO[[#This Row],[QTDADE]] -> 28.47 | M460: 45889 | N460: =TEXT(LANÇAMENTO[[#This Row],[DATA PEDIDO]],"MMM")&"-"&TEXT(M460,"AAAA") -> ago-2025 | O460: 28/35/42 | P460: BOLETO | Q460: RETIRA | R460: 2 | S460: =IF(LANÇAMENTO[[#This Row],[DATA PEDIDO]]="","",LANÇAMENTO[[#This Row],[DATA PEDIDO]]+LANÇAMENTO[[#This Row],[PRAZO]]) -> 45891 | T460: =IF(LANÇAMENTO[[#This Row],[OBRA COM MATERIAL]]="OK","ENTREGUE",IF(LANÇAMENTO[[#This Row],[PRAZO]]="","",LANÇAMENTO[[#This Row],[PREVISÃO ENTREGA OBRA]]-$E$1)) -> ENTREGUE | U460: ok
A461: 45889 | B461: JD ALINE | C461: INTERIORANA | D461: OUTROS | E461: PAR AFUSO GN25 ANCORA | F461: 5 | G461: UNID. | H461: 7442 | I461: ARTESANA | J461: PAR AFUSO GN25 ANCORA | K461: 4.43 | L461: =LANÇAMENTO[[#This Row],[VALOR UNITARIO]]*LANÇAMENTO[[#This Row],[QTDADE]] -> 22.15 | M461: 45889 | N461: =TEXT(LANÇAMENTO[[#This Row],[DATA PEDIDO]],"MMM")&"-"&TEXT(M461,"AAAA") -> ago-2025 | O461: 28/35/42 | P461: BOLETO | Q461: RETIRA | R461: 2 | S461: =IF(LANÇAMENTO[[#This Row],[DATA PEDIDO]]="","",LANÇAMENTO[[#This Row],[DATA PEDIDO]]+LANÇAMENTO[[#This Row],[PRAZO]]) -> 45891 | T461: =IF(LANÇAMENTO[[#This Row],[OBRA COM MATERIAL]]="OK","ENTREGUE",IF(LANÇAMENTO[[#This Row],[PRAZO]]="","",LANÇAMENTO[[#This Row],[PREVISÃO ENTREGA OBRA]]-$E$1)) -> ENTREGUE | U461: ok
A462: 45889 | B462: JD ALINE | C462: INTERIORANA | D462: OUTROS | E462: KIT PORTA PRONTA P/ DRYWALL 82CMX95MM ESQUERDO | F462: 1 | G462: UNID. | H462: 7442 | I462: ARTESANA | J462: KIT PORTA PRONTA P/ DRYWALL 82CMX95MM ESQUERDO | K462: 426.47 | L462: =LANÇAMENTO[[#This Row],[VALOR UNITARIO]]*LANÇAMENTO[[#This Row],[QTDADE]] -> 426.47 | M462: 45889 | N462: =TEXT(LANÇAMENTO[[#This Row],[DATA PEDIDO]],"MMM")&"-"&TEXT(M462,"AAAA") -> ago-2025 | O462: 28/35/42 | P462: BOLETO | Q462: RETIRA | R462: 2 | S462: =IF(LANÇAMENTO[[#This Row],[DATA PEDIDO]]="","",LANÇAMENTO[[#This Row],[DATA PEDIDO]]+LANÇAMENTO[[#This Row],[PRAZO]]) -> 45891 | T462: =IF(LANÇAMENTO[[#This Row],[OBRA COM MATERIAL]]="OK","ENTREGUE",IF(LANÇAMENTO[[#This Row],[PRAZO]]="","",LANÇAMENTO[[#This Row],[PREVISÃO ENTREGA OBRA]]-$E$1)) -> ENTREGUE | U462: ok
A463: 45889 | B463: MARIA CÉLIA | C463: INTERIORANA | D463: OUTROS | E463: AMANCO JOELHO 45 ESG. 150MM | F463: 10 | G463: UNID. | H463: 7443 | I463: CASA MIMOSA | J463: AMANCO JOELHO 45 ESG. 150MM | K463: 33.95 | L463: =LANÇAMENTO[[#This Row],[VALOR UNITARIO]]*LANÇAMENTO[[#This Row],[QTDADE]] -> 339.5 | M463: 45889 | N463: =TEXT(LANÇAMENTO[[#This Row],[DATA PEDIDO]],"MMM")&"-"&TEXT(M463,"AAAA") -> ago-2025 | O463: 28 | P463: BOLETO | Q463: RETIRA | R463: 0 | S463: =IF(LANÇAMENTO[[#This Row],[DATA PEDIDO]]="","",LANÇAMENTO[[#This Row],[DATA PEDIDO]]+LANÇAMENTO[[#This Row],[PRAZO]]) -> 45889 | T463: =IF(LANÇAMENTO[[#This Row],[OBRA COM MATERIAL]]="OK","ENTREGUE",IF(LANÇAMENTO[[#This Row],[PRAZO]]="","",LANÇAMENTO[[#This Row],[PREVISÃO ENTREGA OBRA]]-$E$1)) -> ENTREGUE | U463: ok
A464: 45889 | B464: WANDA FÉLIX | C464: INTERIORANA | D464: OUTROS | E464: VIDRO INCOLOR 3MM COMUM – SÓ CORTADO | F464: 1 | G464: UNID. | H464: 7444 | I464: ART VIDROS | J464: VIDRO INCOLOR 3MM COMUM – SÓ CORTADO | K464: 608 | L464: =LANÇAMENTO[[#This Row],[VALOR UNITARIO]]*LANÇAMENTO[[#This Row],[QTDADE]] -> 608 | M464: 45889 | N464: =TEXT(LANÇAMENTO[[#This Row],[DATA PEDIDO]],"MMM")&"-"&TEXT(M464,"AAAA") -> ago-2025 | O464: 30 | P464: BOLETO | Q464: RETIRA | R464: 2 | S464: =IF(LANÇAMENTO[[#This Row],[DATA PEDIDO]]="","",LANÇAMENTO[[#This Row],[DATA PEDIDO]]+LANÇAMENTO[[#This Row],[PRAZO]]) -> 45891 | T464: =IF(LANÇAMENTO[[#This Row],[OBRA COM MATERIAL]]="OK","ENTREGUE",IF(LANÇAMENTO[[#This Row],[PRAZO]]="","",LANÇAMENTO[[#This Row],[PREVISÃO ENTREGA OBRA]]-$E$1)) -> ENTREGUE | U464: ok
A465: 45889 | B465: WANDA FÉLIX | C465: INTERIORANA | D465: OUTROS | E465: 0,690 x 0,120 | F465: 30 | G465: UNID. | H465: 7444 | I465: ART VIDROS | J465: 0,690 x 0,120 | K465: 0 | L465: =LANÇAMENTO[[#This Row],[VALOR UNITARIO]]*LANÇAMENTO[[#This Row],[QTDADE]] -> 0 | M465: 45889 | N465: =TEXT(LANÇAMENTO[[#This Row],[DATA PEDIDO]],"MMM")&"-"&TEXT(M465,"AAAA") -> ago-2025 | O465: 30 | P465: BOLETO | Q465: RETIRA | R465: 2 | S465: =IF(LANÇAMENTO[[#This Row],[DATA PEDIDO]]="","",LANÇAMENTO[[#This Row],[DATA PEDIDO]]+LANÇAMENTO[[#This Row],[PRAZO]]) -> 45891 | T465: =IF(LANÇAMENTO[[#This Row],[OBRA COM MATERIAL]]="OK","ENTREGUE",IF(LANÇAMENTO[[#This Row],[PRAZO]]="","",LANÇAMENTO[[#This Row],[PREVISÃO ENTREGA OBRA]]-$E$1)) -> ENTREGUE | U465: ok
A466: 45889 | B466: WANDA FÉLIX | C466: INTERIORANA | D466: OUTROS | E466: 0,705 x 0,120 | F466: 18 | G466: UNID. | H466: 7444 | I466: ART VIDROS | J466: 0,705 x 0,120 | K466: 0 | L466: =LANÇAMENTO[[#This Row],[VALOR UNITARIO]]*LANÇAMENTO[[#This Row],[QTDADE]] -> 0 | M466: 45889 | N466: =TEXT(LANÇAMENTO[[#This Row],[DATA PEDIDO]],"MMM")&"-"&TEXT(M466,"AAAA") -> ago-2025 | O466: 30 | P466: BOLETO | Q466: RETIRA | R466: 2 | S466: =IF(LANÇAMENTO[[#This Row],[DATA PEDIDO]]="","",LANÇAMENTO[[#This Row],[DATA PEDIDO]]+LANÇAMENTO[[#This Row],[PRAZO]]) -> 45891 | T466: =IF(LANÇAMENTO[[#This Row],[OBRA COM MATERIAL]]="OK","ENTREGUE",IF(LANÇAMENTO[[#This Row],[PRAZO]]="","",LANÇAMENTO[[#This Row],[PREVISÃO ENTREGA OBRA]]-$E$1)) -> ENTREGUE | U466: ok
A467: 45889 | B467: WANDA FÉLIX | C467: INTERIORANA | D467: OUTROS | E467: 0,690 x 0,300 | F467: 4 | G467: UNID. | H467: 7444 | I467: ART VIDROS | J467: 0,690 x 0,300 | K467: 0 | L467: =LANÇAMENTO[[#This Row],[VALOR UNITARIO]]*LANÇAMENTO[[#This Row],[QTDADE]] -> 0 | M467: 45889 | N467: =TEXT(LANÇAMENTO[[#This Row],[DATA PEDIDO]],"MMM")&"-"&TEXT(M467,"AAAA") -> ago-2025 | O467: 30 | P467: BOLETO | Q467: RETIRA | R467: 2 | S467: =IF(LANÇAMENTO[[#This Row],[DATA PEDIDO]]="","",LANÇAMENTO[[#This Row],[DATA PEDIDO]]+LANÇAMENTO[[#This Row],[PRAZO]]) -> 45891 | T467: =IF(LANÇAMENTO[[#This Row],[OBRA COM MATERIAL]]="OK","ENTREGUE",IF(LANÇAMENTO[[#This Row],[PRAZO]]="","",LANÇAMENTO[[#This Row],[PREVISÃO ENTREGA OBRA]]-$E$1)) -> ENTREGUE | U467: ok
A468: 45889 | B468: WANDA FÉLIX | C468: INTERIORANA | D468: OUTROS | E468: MASSA CINZA | F468: 20 | G468: KG | H468: 7444 | I468: ART VIDROS | J468: MASSA CINZA | K468: 8 | L468: =LANÇAMENTO[[#This Row],[VALOR UNITARIO]]*LANÇAMENTO[[#This Row],[QTDADE]] -> 160 | M468: 45889 | N468: =TEXT(LANÇAMENTO[[#This Row],[DATA PEDIDO]],"MMM")&"-"&TEXT(M468,"AAAA") -> ago-2025 | O468: 30 | P468: BOLETO | Q468: RETIRA | R468: 2 | S468: =IF(LANÇAMENTO[[#This Row],[DATA PEDIDO]]="","",LANÇAMENTO[[#This Row],[DATA PEDIDO]]+LANÇAMENTO[[#This Row],[PRAZO]]) -> 45891 | T468: =IF(LANÇAMENTO[[#This Row],[OBRA COM MATERIAL]]="OK","ENTREGUE",IF(LANÇAMENTO[[#This Row],[PRAZO]]="","",LANÇAMENTO[[#This Row],[PREVISÃO ENTREGA OBRA]]-$E$1)) -> ENTREGUE | U468: ok
A469: 45889 | B469: PRÉDIO VAGO | C469: B&B | D469: OUTROS | E469: CAÇAMBA | F469: 1 | G469: UNID. | H469: 7445 | I469: SOS CAÇAMBAS | J469: CAÇAMBA | K469: 200 | L469: =LANÇAMENTO[[#This Row],[VALOR UNITARIO]]*LANÇAMENTO[[#This Row],[QTDADE]] -> 200 | M469: 45889 | N469: =TEXT(LANÇAMENTO[[#This Row],[DATA PEDIDO]],"MMM")&"-"&TEXT(M469,"AAAA") -> ago-2025 | O469: 7 | P469: BOLETO | Q469: ENTREGA | R469: 0 | S469: =IF(LANÇAMENTO[[#This Row],[DATA PEDIDO]]="","",LANÇAMENTO[[#This Row],[DATA PEDIDO]]+LANÇAMENTO[[#This Row],[PRAZO]]) -> 45889 | T469: =IF(LANÇAMENTO[[#This Row],[OBRA COM MATERIAL]]="OK","ENTREGUE",IF(LANÇAMENTO[[#This Row],[PRAZO]]="","",LANÇAMENTO[[#This Row],[PREVISÃO ENTREGA OBRA]]-$E$1)) -> ENTREGUE | U469: ok
A470: 45889 | B470: MARIA DE LOURDES | C470: INTERIORANA | D470: OUTROS | E470: blocos 14x19x39 | F470: 520 | G470: UNID. | H470: 7446 | I470: CONCREBLOCO | J470: blocos 14x19x39 | K470: 3.55 | L470: =LANÇAMENTO[[#This Row],[VALOR UNITARIO]]*LANÇAMENTO[[#This Row],[QTDADE]] -> 1846 | M470: 45889 | N470: =TEXT(LANÇAMENTO[[#This Row],[DATA PEDIDO]],"MMM")&"-"&TEXT(M470,"AAAA") -> ago-2025 | O470: 20 | P470: BOLETO | Q470: ENTREGA | R470: 6 | S470: =IF(LANÇAMENTO[[#This Row],[DATA PEDIDO]]="","",LANÇAMENTO[[#This Row],[DATA PEDIDO]]+LANÇAMENTO[[#This Row],[PRAZO]]) -> 45895 | T470: =IF(LANÇAMENTO[[#This Row],[OBRA COM MATERIAL]]="OK","ENTREGUE",IF(LANÇAMENTO[[#This Row],[PRAZO]]="","",LANÇAMENTO[[#This Row],[PREVISÃO ENTREGA OBRA]]-$E$1)) -> ENTREGUE | U470: ok
...

Sheet Planilha1

Sheet Planilha2

Sheet Planilha3

Sheet PEDIDOS EMITIDOS
A1: DATA PEDIDO | B1: 46128 | E1: COMPRADORA | F1: THAMYRES
A3: PEDIDO | B3: FORNECEDOR | C3: OBRA | D3: CONDIÇÃO PAGAMENTO | E3: FORMA DE PAGAMENTO | F3: Soma de VALOR TOTAL
A4: 8344 | B4: ITA AÇOS | C4: AGENOR DE CAMPOS | D4: 28 | E4: BOLETO | F4: 323.68
A5: 8345 | B5: OLD RIVER | C5: PAULINA ROSA | D5: 28 | E5: BOLETO | F5: 573.56
A6: 8346 | B6: ARTESANA | C6: JULIO SECCO | D6: 0 | E6: CARTÃO | F6: 87.55
A7: 8347 | B7: AREA ELETRICOS | C7: OMAR DONATO | D7: 28 | E7: BOLETO | F7: 1313.4
A8: Total Geral | F8: 2298.19

Sheet BASE PEDIDO
A1: PEDIDO | B1: 8347
A3: DATA PEDIDO | B3: PRAZO | C3: RETIRA OU ENTREGA | D3: ESCOLA | E3: FORNECEDOR | F3: CONDIÇÃO PAGAMENTO | G3: FORMA DE PAGAMENTO | H3: DESCRIÇÃO MATERIAL | I3: UNID | J3: QTDADE | K3: VALOR UNITARIO | L3: FATURAMENTO | M3: Soma de VALOR TOTAL
A4: 46128 | B4: 0 | C4: RETIRA | D4: OMAR DONATO | E4: AREA ELETRICOS | F4: 28 | G4: BOLETO | H4: CABO FLEX750V 1,5MM2 PT | I4: ROLO | J4: 2 | K4: 150 | L4: BRASUL | M4: 300
A5: 46128 | B5: 0 | C5: RETIRA | D5: OMAR DONATO | E5: AREA ELETRICOS | F5: 28 | G5: BOLETO | H5: CABO FLEX750V 1,5MM2 MR | I5: ROLO | J5: 2 | K5: 150 | L5: BRASUL | M5: 300
A6: 46128 | B6: 0 | C6: RETIRA | D6: OMAR DONATO | E6: AREA ELETRICOS | F6: 28 | G6: BOLETO | H6: CABO FLEX750V 1,5MM2 VD | I6: ROLO | J6: 2 | K6: 150 | L6: BRASUL | M6: 300
A7: 46128 | B7: 0 | C7: RETIRA | D7: OMAR DONATO | E7: AREA ELETRICOS | F7: 28 | G7: BOLETO | H7: BOTOEIRA BOMBA LIGA/DESLIGA C/MARTELO | I7: UNID. | J7: 6 | K7: 68.9 | L7: BRASUL | M7: 413.4

Sheet JB IMPRIMIR
M1: JB CONSTRUÇÕES E EMPREENDIMENTOS LTDA
M2: Av luis dummount vilares 2078, São Paulo, Brazil 02239-000
M3: Telefone: (11) 3313-8220
M4: e-mail: thamyres@brasulconstrutora.com.br
C6: DATA: | D6: ='BASE PEDIDO'!A4 -> 46128 | H6: PEDIDO DE COMPRA | K6: Nº | L6: ='BASE PEDIDO'!B1 -> 8347
L7: ='BASE PEDIDO'!D4 -> OMAR DONATO
B9: Razão Social: | E9: =VLOOKUP(E10,FORNECEDOR[#All],2,FALSE) -> AEA DISTRIBUIDORA DE MAT. ELETRICOS LTDA
B10: Fornecedor: | E10: ='BASE PEDIDO'!E4 -> AREA ELETRICOS | J10: Vendedor: | K10: =VLOOKUP(E10,FORNECEDOR[#All],4,FALSE) -> Wellison
B11: E-mail: | E11: =VLOOKUP(E10,FORNECEDOR[#All],3,FALSE) -> 0 | J11: Telefone: | K11: =VLOOKUP(E10,FORNECEDOR[#All],5,FALSE) -> 1133931842
B13: Endereço de Cobrança: Rua Coronel Jordão, 440 /450 | I13: Bairro: Vila Paiva | L13: CEP: 02075-030
B14: Cidade: São Paulo | I14: UF: SP | L14: Comprador: Thamyres
B16: Faturamento: | E16: 14 | F16: =IF(E16="","","dias") -> dias | G16: ='BASE PEDIDO'!G4 -> BOLETO | H16: =IF(G16="PIX",VLOOKUP(E10,FORNECEDOR[#All],6,FALSE),"") | K16: Estimativa de vencimento: | L16: =$L$21+E16 -> 46142
B17: ='BASE PEDIDO'!F4 -> 28 | E17: =MID(B17,4,2) | F17: =IF(E17="","","dias") | H17: =IF(G16="PIX",VLOOKUP(E10,FORNECEDOR[#All],7,FALSE),"") | L17: =IF(E17=""," ",$L$21+E17)
C18: OBS: CONTAR FATURAMENTO A PARTIR DO DIA 27/12/24 PARA MANTER OS FATURAMENTOS ANTERIORES DA JB | E18: =MID(B17,7,2) | F18: =IF(E18="","","dias") | L18: =IF(E18=""," ",$L$21+E18)
B19: OBSERVAÇÃO: | E19: NOTA FISCAL DEVE SER FATURADA EM NOME DA EMPRESA | I19: =IF('BASE PEDIDO'!L4="JB","JB CONSTRUÇÕES E EMPREENDIMENTOS LTDA",IF('BASE PEDIDO'!L4="JB CONSTRUÇÕES E EMPREENDIMENTOS LTDA","JB CONSTRUÇÕES E EMPREENDIMENTOS LTDA","JB CONSTRUÇÕES E EMPREENDIMENTOS LTDA")) -> JB CONSTRUÇÕES E EMPREENDIMENTOS LTDA
B21: PRAZO | D21: ='BASE PEDIDO'!C4 -> RETIRA | F21: ='BASE PEDIDO'!B4 -> 0 | G21: dias | K21: ="DATA PREVISTA DA "&'BASE PEDIDO'!C4 -> DATA PREVISTA DA RETIRA | L21: =F21+D6 -> 46128
B23: Local de Entrega: | E23: =VLOOKUP(L7,OBRAS[#All],4,FALSE) -> Estr. Ernesto Zabeu, 253 | H23: Bairro: | I23: =VLOOKUP(L7,OBRAS[#All],5,FALSE) -> Tatetos
B24: OBRA: | D24: =VLOOKUP(L7,OBRAS[#All],3,FALSE) -> ​Escola Estadual Omar Donato Bassani | H24: Contrato Obra: | I24: =VLOOKUP(L7,OBRAS[#All],7,FALSE) -> 0
B25: CEP: | D25: =VLOOKUP(L7,OBRAS[#All],6,FALSE) -> 09837-150 | H25: Cidade: | I25: =VLOOKUP(L7,OBRAS[#All],8,FALSE) -> São Bernardo | K25: UF: | L25: =VLOOKUP(L7,OBRAS[#All],9,FALSE) -> SP
C28: ITEM | D28: DESCRIÇÃO | I28: QTDADE | J28: UNID. | K28: VALOR UNITÁRIO | L28: VALOR TOTAL
C30: 1 | D30: ='BASE PEDIDO'!H4 -> CABO FLEX750V 1,5MM2 PT | I30: ='BASE PEDIDO'!J4 -> 2 | J30: ='BASE PEDIDO'!I4 -> ROLO | K30: ='BASE PEDIDO'!K4 -> 150 | L30: =I30*K30 -> 300
C31: 2 | D31: ='BASE PEDIDO'!H5 -> CABO FLEX750V 1,5MM2 MR | I31: ='BASE PEDIDO'!J5 -> 2 | J31: ='BASE PEDIDO'!I5 -> ROLO | K31: ='BASE PEDIDO'!K5 -> 150 | L31: =I31*K31 -> 300
C32: 3 | D32: ='BASE PEDIDO'!H6 -> CABO FLEX750V 1,5MM2 VD | I32: ='BASE PEDIDO'!J6 -> 2 | J32: ='BASE PEDIDO'!I6 -> ROLO | K32: ='BASE PEDIDO'!K6 -> 150 | L32: =I32*K32 -> 300
C33: 4 | D33: ='BASE PEDIDO'!H7 -> BOTOEIRA BOMBA LIGA/DESLIGA C/MARTELO | I33: ='BASE PEDIDO'!J7 -> 6 | J33: ='BASE PEDIDO'!I7 -> UNID. | K33: ='BASE PEDIDO'!K7 -> 68.9 | L33: =I33*K33 -> 413.4
C34: 5 | D34: ='BASE PEDIDO'!H8 -> 0 | I34: ='BASE PEDIDO'!J8 -> 0 | J34: ='BASE PEDIDO'!I8 -> 0 | K34: ='BASE PEDIDO'!K8 -> 0 | L34: =I34*K34 -> 0
C35: 6 | D35: ='BASE PEDIDO'!H9 -> 0 | I35: ='BASE PEDIDO'!J9 -> 0 | J35: ='BASE PEDIDO'!I9 -> 0 | K35: ='BASE PEDIDO'!K9 -> 0 | L35: =I35*K35 -> 0
C36: 7 | D36: ='BASE PEDIDO'!H10 -> 0 | I36: ='BASE PEDIDO'!J10 -> 0 | J36: ='BASE PEDIDO'!I10 -> 0 | K36: ='BASE PEDIDO'!K10 -> 0 | L36: =I36*K36 -> 0
C37: 8 | D37: ='BASE PEDIDO'!H11 -> 0 | I37: ='BASE PEDIDO'!J11 -> 0 | J37: ='BASE PEDIDO'!I11 -> 0 | K37: ='BASE PEDIDO'!K11 -> 0 | L37: =I37*K37 -> 0
C38: 9 | D38: ='BASE PEDIDO'!H12 -> 0 | I38: ='BASE PEDIDO'!J12 -> 0 | J38: ='BASE PEDIDO'!I12 -> 0 | K38: ='BASE PEDIDO'!K12 -> 0 | L38: =I38*K38 -> 0
C39: 10 | D39: ='BASE PEDIDO'!H13 -> 0 | I39: ='BASE PEDIDO'!J13 -> 0 | J39: ='BASE PEDIDO'!I13 -> 0 | K39: ='BASE PEDIDO'!K13 -> 0 | L39: =I39*K39 -> 0
C40: 11 | D40: ='BASE PEDIDO'!H14 -> 0 | I40: ='BASE PEDIDO'!J14 -> 0 | J40: ='BASE PEDIDO'!I14 -> 0 | K40: ='BASE PEDIDO'!K14 -> 0 | L40: =I40*K40 -> 0
C41: 12 | D41: ='BASE PEDIDO'!H15 -> 0 | I41: ='BASE PEDIDO'!J15 -> 0 | J41: ='BASE PEDIDO'!I15 -> 0 | K41: ='BASE PEDIDO'!K15 -> 0 | L41: =I41*K41 -> 0
... C59: 30 | D59: ='BASE PEDIDO'!H33 -> 0 | I59: ='BASE PEDIDO'!J33 -> 0 | J59: ='BASE PEDIDO'!I33 -> 0 | K59: ='BASE PEDIDO'!K33 -> 0 | L59: =I59*K59 -> 0
K60: SUB TOTAL | L60: =SUM(L30:L59)-L61 -> 1313.4
K61: DESCONTO | L61: =SUMIF(D30:D57,"DESCONTO",L30:L57) -> 0
K62: TOTAL | L62: =L60+L61 -> 1313.4
L64: Horario de RECEBIMENTO NA OBRA
L65: Segunda a Quinta-feira das 07:30h às 11:30h e das 13:00h as 15:30h
L66: Sexta-feira das 07:30h às 11:30h e das 13:00h as 14:30h

Sheet BRASUL IMPRIMIR
M1: BRASUL CONSTRUTORA LTDA
M2: Rua Coronel Jordão, 440, Vila Paiva - São Paulo, SP - CEP 02075-030
M3: Telefone: (11) 3313-8220
M4: e-mail: thamyres@brasulconstrutora.com.br
C6: DATA: | D6: ='BASE PEDIDO'!A4 -> 46128 | H6: PEDIDO DE COMPRA | K6: Nº | L6: ='BASE PEDIDO'!B1 -> 8347
L7: ='BASE PEDIDO'!D4 -> OMAR DONATO
B9: Razão Social: | E9: =VLOOKUP(E10,FORNECEDOR[#All],2,FALSE) -> AEA DISTRIBUIDORA DE MAT. ELETRICOS LTDA
B10: Fornecedor: | E10: ='BASE PEDIDO'!E4 -> AREA ELETRICOS | J10: Vendedor: | K10: =VLOOKUP(E10,FORNECEDOR[#All],4,FALSE) -> Wellison
B11: E-mail: | J11: Telefone: | K11: =VLOOKUP(E10,FORNECEDOR[#All],5,FALSE) -> 1133931842
B13: Endereço de Cobrança: Rua Coronel Jordão, 440 /450 | I13: Bairro: Vila Paiva | L13: CEP: 02075-030
B14: Cidade: São Paulo | I14: UF: SP | L14: Comprador: Thamyres
B16: Faturamento: | E16: 0 | F16: =IF(E16="","","dias") -> dias | G16: ='BASE PEDIDO'!G4 -> BOLETO | H16: =IF(G16="PIX",VLOOKUP(E10,FORNECEDOR[#All],6,FALSE),"") | K16: Estimativa de vencimento: | L16: =$L$23+E16 -> 46128
B17: ='BASE PEDIDO'!F4 -> 28 | E17: 45 | F17: dias | H17: =IF(G16="PIX",VLOOKUP(E10,FORNECEDOR[#All],7,FALSE),"") | L17: =$L$23+E17 -> 46173
E18: 28 | F18: =IF(E18="","","dias") -> dias | L18: =$L$23+E18 -> 46156
E19: 60 | F19: =IF(E19="","","dias") -> dias | L19: =$L$23+E19 -> 46188
E20: 90 | F20: dias | L20: =$L$23+E20 -> 46218
B21: OBSERVAÇÃO: | E21: NOTA FISCAL DEVE SER FATURADA EM NOME DA EMPRESA | I21: =IF('BASE PEDIDO'!L4="JB","JB CONSTRUÇÕES E EMPREENDIMENTOS LTDA",IF('BASE PEDIDO'!L4="BRASUL","BRASUL CONSTRUTORA LTDA","BRASUL CONSTRUTORA LTDA")) -> BRASUL CONSTRUTORA LTDA
B23: PRAZO | D23: ='BASE PEDIDO'!C4 -> RETIRA | F23: ='BASE PEDIDO'!B4 -> 0 | G23: dias | K23: ="DATA PREVISTA DA "&'BASE PEDIDO'!C4 -> DATA PREVISTA DA RETIRA | L23: =D6+F23 -> 46128
B25: Local de Entrega: | E25: =VLOOKUP(L7,OBRAS[#All],4,FALSE) -> Estr. Ernesto Zabeu, 253 | H25: Bairro: | I25: =VLOOKUP(L7,OBRAS[#All],5,FALSE) -> Tatetos
B26: OBRA: | D26: =VLOOKUP(L7,OBRAS[#All],3,FALSE) -> ​Escola Estadual Omar Donato Bassani | H26: Contrato Obra: | I26: =VLOOKUP(L7,OBRAS[#All],7,FALSE) -> 0
B27: CEP: | D27: =VLOOKUP(L7,OBRAS[#All],6,FALSE) -> 09837-150 | H27: Cidade: | I27: =VLOOKUP(L7,OBRAS[#All],8,FALSE) -> São Bernardo | K27: UF: | L27: =VLOOKUP(L7,OBRAS[#All],9,FALSE) -> SP
C30: ITEM | D30: DESCRIÇÃO | I30: QTDADE | J30: UNID. | K30: VALOR UNITÁRIO | L30: VALOR TOTAL
C32: 1 | D32: ='BASE PEDIDO'!H4 -> CABO FLEX750V 1,5MM2 PT | I32: ='BASE PEDIDO'!J4 -> 2 | J32: ='BASE PEDIDO'!I4 -> ROLO | K32: ='BASE PEDIDO'!K4 -> 150 | L32: =I32*K32 -> 300
C33: 2 | D33: ='BASE PEDIDO'!H5 -> CABO FLEX750V 1,5MM2 MR | I33: ='BASE PEDIDO'!J5 -> 2 | J33: ='BASE PEDIDO'!I5 -> ROLO | K33: ='BASE PEDIDO'!K5 -> 150 | L33: =I33*K33 -> 300
C34: 3 | D34: ='BASE PEDIDO'!H6 -> CABO FLEX750V 1,5MM2 VD | I34: ='BASE PEDIDO'!J6 -> 2 | J34: ='BASE PEDIDO'!I6 -> ROLO | K34: ='BASE PEDIDO'!K6 -> 150 | L34: =I34*K34 -> 300
C35: 4 | D35: ='BASE PEDIDO'!H7 -> BOTOEIRA BOMBA LIGA/DESLIGA C/MARTELO | I35: ='BASE PEDIDO'!J7 -> 6 | J35: ='BASE PEDIDO'!I7 -> UNID. | K35: ='BASE PEDIDO'!K7 -> 68.9 | L35: =I35*K35 -> 413.4
C36: 5 | D36: ='BASE PEDIDO'!H8 -> 0 | I36: ='BASE PEDIDO'!J8 -> 0 | J36: ='BASE PEDIDO'!I8 -> 0 | K36: ='BASE PEDIDO'!K8 -> 0 | L36: =I36*K36 -> 0
C37: 6 | D37: ='BASE PEDIDO'!H9 -> 0 | I37: ='BASE PEDIDO'!J9 -> 0 | J37: ='BASE PEDIDO'!I9 -> 0 | K37: ='BASE PEDIDO'!K9 -> 0 | L37: =I37*K37 -> 0
C38: 7 | D38: ='BASE PEDIDO'!H10 -> 0 | I38: ='BASE PEDIDO'!J10 -> 0 | J38: ='BASE PEDIDO'!I10 -> 0 | K38: ='BASE PEDIDO'!K10 -> 0 | L38: =I38*K38 -> 0
C39: 8 | D39: ='BASE PEDIDO'!H11 -> 0 | I39: ='BASE PEDIDO'!J11 -> 0 | J39: ='BASE PEDIDO'!I11 -> 0 | K39: ='BASE PEDIDO'!K11 -> 0 | L39: =I39*K39 -> 0
C40: 9 | D40: ='BASE PEDIDO'!H12 -> 0 | I40: ='BASE PEDIDO'!J12 -> 0 | J40: ='BASE PEDIDO'!I12 -> 0 | K40: ='BASE PEDIDO'!K12 -> 0 | L40: =I40*K40 -> 0
C41: 10 | D41: ='BASE PEDIDO'!H13 -> 0 | I41: ='BASE PEDIDO'!J13 -> 0 | J41: ='BASE PEDIDO'!I13 -> 0 | K41: ='BASE PEDIDO'!K13 -> 0 | L41: =I41*K41 -> 0
C42: 11 | D42: ='BASE PEDIDO'!H14 -> 0 | I42: ='BASE PEDIDO'!J14 -> 0 | J42: ='BASE PEDIDO'!I14 -> 0 | K42: ='BASE PEDIDO'!K14 -> 0 | L42: =I42*K42 -> 0
C43: 12 | D43: ='BASE PEDIDO'!H15 -> 0 | I43: ='BASE PEDIDO'!J15 -> 0 | J43: ='BASE PEDIDO'!I15 -> 0 | K43: ='BASE PEDIDO'!K15 -> 0 | L43: =I43*K43 -> 0
... C64: 33 | D64: ='BASE PEDIDO'!H36 -> 0 | I64: ='BASE PEDIDO'!J36 -> 0 | J64: ='BASE PEDIDO'!I36 -> 0 | K64: ='BASE PEDIDO'!K36 -> 0 | L64: =I64*K64 -> 0
C65: 51 | D65: ='BASE PEDIDO'!H54 -> 0 | I65: ='BASE PEDIDO'!J54 -> 0 | J65: ='BASE PEDIDO'!I54 -> 0 | K65: ='BASE PEDIDO'!K54 -> 0 | L65: =I65*K65 -> 0
K66: SUB TOTAL | L66: =SUM(L30:L65)-L96 -> 1313.4
K67: DESCONTO | L67: =SUMIF(D32:D65,"DESCONTO",L32:L65) -> 0
K68: TOTAL | L68: =L95+L66 -> 1313.4
L70: Horario de RECEBIMENTO NA OBRA
L71: Segunda a Quinta-feira das 07:30h às 11:30h e das 13:00h as 15:30h
L72: Sexta-feira das 07:30h às 11:30h e das 13:00h as 14:30h

Sheet B&B
M1: B & B Engenharia e Construções LTDA
M2: Rua itamonte 33, 440 , Vila Medeiros - São Paulo, SP - CEP 02220-000
M3: Telefone: (11) 3313-8220
M4: e-mail: thamyres@brasulconstrutora.com.br
C6: DATA: | D6: ='BASE PEDIDO'!A4 -> 46128 | H6: PEDIDO DE COMPRA | K6: Nº | L6: ='BASE PEDIDO'!B1 -> 8347
L7: ='BASE PEDIDO'!D4 -> OMAR DONATO
B9: Razão Social: | E9: =VLOOKUP(E10,FORNECEDOR[#All],2,FALSE) -> AEA DISTRIBUIDORA DE MAT. ELETRICOS LTDA
B10: Fornecedor: | E10: ='BASE PEDIDO'!E4 -> AREA ELETRICOS | J10: Vendedor: | K10: =VLOOKUP(E10,FORNECEDOR[#All],4,FALSE) -> Wellison
B11: E-mail: | E11: =VLOOKUP(E10,FORNECEDOR[#All],3,FALSE) -> 0 | J11: Telefone: | K11: =VLOOKUP(E10,FORNECEDOR[#All],5,FALSE) -> 1133931842
B13: Endereço de Cobrança: Rua Coronel Jordão, 440 /450 | I13: Bairro: Vila Paiva | L13: CEP: 02075-030
B14: Cidade: São Paulo | I14: UF: SP | L14: Comprador: Thamyres
B16: Faturamento: | E16: 28 | F16: =IF(E16="","","dias") -> dias | G16: ='BASE PEDIDO'!G4 -> BOLETO | H16: =IF(G16="PIX",VLOOKUP(E10,FORNECEDOR[#All],6,FALSE),"") | K16: Estimativa de vencimento: | L16: =IF(E16=""," ",$L$22+E16) -> 46156
B17: ='BASE PEDIDO'!F4 -> 28 | E17: =MID(B17,4,2) | F17: =IF(E17="","","dias") | H17: =IF(G16="PIX",VLOOKUP(E10,FORNECEDOR[#All],7,FALSE),"") | L17: =IF(E17=""," ",$L$22+E17)
E18: 35 | F18: dias | L18: =IF(E18=""," ",$L$22+E18) -> 46163
E19: 42 | F19: =IF(E19="","","dias") -> dias | L19: =IF(E19=""," ",$L$22+E19) -> 46170
B20: OBSERVAÇÃO: | E20: NOTA FISCAL DEVE SER FATURADA EM NOME DA EMPRESA | I20: =IF('BASE PEDIDO'!L4="B&B","B&B Engenharia e Construções LTDA",IF('BASE PEDIDO'!L4="B&B Engenharia e Construções LTDA","B&B Engenharia e Construções LTDA","B&B Engenharia e Construções LTDA")) -> B&B Engenharia e Construções LTDA
B22: PRAZO | D22: ='BASE PEDIDO'!C4 -> RETIRA | F22: ='BASE PEDIDO'!B4 -> 0 | G22: dias | K22: ="DATA PREVISTA DA "&'BASE PEDIDO'!C4 -> DATA PREVISTA DA RETIRA | L22: =D6+F22 -> 46128
B24: Local de Entrega: | E24: =VLOOKUP(L7,OBRAS[#All],4,FALSE) -> Estr. Ernesto Zabeu, 253 | H24: Bairro: | I24: =VLOOKUP(L7,OBRAS[#All],5,FALSE) -> Tatetos
B25: OBRA: | D25: =VLOOKUP(L7,OBRAS[#All],3,FALSE) -> ​Escola Estadual Omar Donato Bassani | H25: Contrato Obra: | I25: =VLOOKUP(L7,OBRAS[#All],7,FALSE) -> 0
B26: CEP: | D26: =VLOOKUP(L7,OBRAS[#All],6,FALSE) -> 09837-150 | H26: Cidade: | I26: =VLOOKUP(L7,OBRAS[#All],8,FALSE) -> São Bernardo | K26: UF: | L26: =VLOOKUP(L7,OBRAS[#All],9,FALSE) -> SP
C29: ITEM | D29: DESCRIÇÃO | I29: QTDADE | J29: UNID. | K29: VALOR UNITÁRIO | L29: VALOR TOTAL
C31: 1 | D31: ='BASE PEDIDO'!H4 -> CABO FLEX750V 1,5MM2 PT | I31: ='BASE PEDIDO'!J4 -> 2 | J31: ='BASE PEDIDO'!I4 -> ROLO | K31: ='BASE PEDIDO'!K4 -> 150 | L31: =I31*K31 -> 300
C32: 2 | D32: ='BASE PEDIDO'!H5 -> CABO FLEX750V 1,5MM2 MR | I32: ='BASE PEDIDO'!J5 -> 2 | J32: ='BASE PEDIDO'!I5 -> ROLO | K32: ='BASE PEDIDO'!K5 -> 150 | L32: =I32*K32 -> 300
C33: 3 | D33: ='BASE PEDIDO'!H6 -> CABO FLEX750V 1,5MM2 VD | I33: ='BASE PEDIDO'!J6 -> 2 | J33: ='BASE PEDIDO'!I6 -> ROLO | K33: ='BASE PEDIDO'!K6 -> 150 | L33: =I33*K33 -> 300
C34: 4 | D34: ='BASE PEDIDO'!H7 -> BOTOEIRA BOMBA LIGA/DESLIGA C/MARTELO | I34: ='BASE PEDIDO'!J7 -> 6 | J34: ='BASE PEDIDO'!I7 -> UNID. | K34: ='BASE PEDIDO'!K7 -> 68.9 | L34: =I34*K34 -> 413.4
C35: 5 | D35: ='BASE PEDIDO'!H8 -> 0 | I35: ='BASE PEDIDO'!J8 -> 0 | J35: ='BASE PEDIDO'!I8 -> 0 | K35: ='BASE PEDIDO'!K8 -> 0 | L35: =I35*K35 -> 0
C36: 6 | D36: ='BASE PEDIDO'!H9 -> 0 | I36: ='BASE PEDIDO'!J9 -> 0 | J36: ='BASE PEDIDO'!I9 -> 0 | K36: ='BASE PEDIDO'!K9 -> 0 | L36: =I36*K36 -> 0
C37: 7 | D37: ='BASE PEDIDO'!H10 -> 0 | I37: ='BASE PEDIDO'!J10 -> 0 | J37: ='BASE PEDIDO'!I10 -> 0 | K37: ='BASE PEDIDO'!K10 -> 0 | L37: =I37*K37 -> 0
C38: 8 | D38: ='BASE PEDIDO'!H11 -> 0 | I38: ='BASE PEDIDO'!J11 -> 0 | J38: ='BASE PEDIDO'!I11 -> 0 | K38: ='BASE PEDIDO'!K11 -> 0 | L38: =I38*K38 -> 0
C39: 9 | D39: ='BASE PEDIDO'!H12 -> 0 | I39: ='BASE PEDIDO'!J12 -> 0 | J39: ='BASE PEDIDO'!I12 -> 0 | K39: ='BASE PEDIDO'!K12 -> 0 | L39: =I39*K39 -> 0
C40: 10 | D40: ='BASE PEDIDO'!H13 -> 0 | I40: ='BASE PEDIDO'!J13 -> 0 | J40: ='BASE PEDIDO'!I13 -> 0 | K40: ='BASE PEDIDO'!K13 -> 0 | L40: =I40*K40 -> 0
C41: 11 | D41: ='BASE PEDIDO'!H14 -> 0 | I41: ='BASE PEDIDO'!J14 -> 0 | J41: ='BASE PEDIDO'!I14 -> 0 | K41: ='BASE PEDIDO'!K14 -> 0 | L41: =I41*K41 -> 0
C42: 12 | D42: ='BASE PEDIDO'!H15 -> 0 | I42: ='BASE PEDIDO'!J15 -> 0 | J42: ='BASE PEDIDO'!I15 -> 0 | K42: ='BASE PEDIDO'!K15 -> 0 | L42: =I42*K42 -> 0
... C95: 65 | D95: ='BASE PEDIDO'!H68 -> 0 | I95: ='BASE PEDIDO'!J68 -> 0 | J95: ='BASE PEDIDO'!I68 -> 0 | K95: ='BASE PEDIDO'!K68 -> 0 | L95: =I95*K95 -> 0
K96: SUB TOTAL | L96: =SUM(L31:L95)-L97 -> 1313.4
K97: DESCONTO | L97: =SUMIF(D31:D88,"DESCONTO",L31:L88) -> 0
K98: TOTAL | L98: =L96+L97 -> 1313.4
L100: Horario de RECEBIMENTO NA OBRA
L101: Segunda a Quinta-feira das 07:30h às 11:30h e das 13:00h as 15:30h
L102: Sexta-feira das 07:30h às 11:30h e das 13:00h as 14:30h

Sheet INTERIORANA IMPRIMIR
M1: INTERIORANA CONSTRUTORA LTDA
M2: Avª Mofarrej, 348 – Sala 703 – Vila Leopoldina – São Paulo/SP
M3: Telefone: (11) 2892.8916
M4: e-mail: thamyres@brasulconstrutora.com.br
C6: DATA: | D6: ='BASE PEDIDO'!A4 -> 46128 | H6: PEDIDO DE COMPRA | K6: Nº | L6: ='BASE PEDIDO'!B1 -> 8347
L7: ='BASE PEDIDO'!D4 -> OMAR DONATO
B9: Razão Social: | E9: =VLOOKUP(E10,FORNECEDOR[#All],2,FALSE) -> AEA DISTRIBUIDORA DE MAT. ELETRICOS LTDA
B10: Fornecedor: | E10: ='BASE PEDIDO'!E4 -> AREA ELETRICOS | J10: Vendedor: | K10: =VLOOKUP(E10,FORNECEDOR[#All],4,FALSE) -> Wellison
B11: E-mail: | J11: Telefone: | K11: =VLOOKUP(E10,FORNECEDOR[#All],5,FALSE) -> 1133931842
B13: Endereço de Cobrança: Rua Coronel Jordão, 440 /450 | I13: Bairro: Vila Paiva | L13: CEP: 02075-030
B14: Cidade: São Paulo | I14: UF: SP | L14: Comprador: Thamyres
B16: Faturamento: | E16: 28 | F16: =IF(E16="","","dias") -> dias | G16: ='BASE PEDIDO'!G4 -> BOLETO | H16: =IF(G16="PIX",VLOOKUP(E10,FORNECEDOR[#All],6,FALSE),"") | K16: Estimativa de vencimento: | L16: =$L$24+E16 -> 46156
B17: ='BASE PEDIDO'!F4 -> 28 | E17: 60 | F17: dias | L17: =$L$24+E17 -> 46188
E18: 90 | F18: dias | H18: =IF(G16="PIX",VLOOKUP(E10,FORNECEDOR[#All],7,FALSE),"") | L18: =IF(E18=""," ",$D$6+E18) -> 46218
E19: 35 | F19: =IF(E19="","","dias") -> dias | L19: =IF(E19=""," ",$D$6+E19) -> 46163
E20: 60 | F20: =IF(E20="","","dias") -> dias | L20: =IF(E20=""," ",$L$24+E20) -> 46188
E21: 60 | F21: =IF(E21="","","dias") -> dias | L21: =IF(E21=""," ",$L$24+E21) -> 46188
B22: OBSERVAÇÃO: | E22: NOTA FISCAL DEVE SER FATURADA EM NOME DA EMPRESA | I22: =IF('BASE PEDIDO'!L4="JB","JB CONSTRUÇÕES E EMPREENDIMENTOS LTDA",IF('BASE PEDIDO'!L4="BRASUL","BRASUL CONSTRUTORA LTDA","INTERIORANA CONSTRUTORA LTDA")) -> BRASUL CONSTRUTORA LTDA
B24: PRAZO | D24: ='BASE PEDIDO'!C4 -> RETIRA | F24: ='BASE PEDIDO'!B4 -> 0 | G24: dias | K24: ="DATA PREVISTA DA "&'BASE PEDIDO'!C4 -> DATA PREVISTA DA RETIRA | L24: =D6+F24 -> 46128
B26: Local de Entrega: | E26: =VLOOKUP(L7,OBRAS[#All],4,FALSE) -> Estr. Ernesto Zabeu, 253 | H26: Bairro: | I26: =VLOOKUP(L7,OBRAS[#All],5,FALSE) -> Tatetos
B27: OBRA: | D27: =VLOOKUP(L7,OBRAS[#All],3,FALSE) -> ​Escola Estadual Omar Donato Bassani | H27: Contrato Obra: | I27: =VLOOKUP(L7,OBRAS[#All],7,FALSE) -> 0
B28: CEP: | H28: Cidade: | I28: =VLOOKUP(L7,OBRAS[#All],8,FALSE) -> São Bernardo | K28: UF: | L28: =VLOOKUP(L7,OBRAS[#All],9,FALSE) -> SP
C31: ITEM | D31: DESCRIÇÃO | I31: QTDADE | J31: UNID. | K31: VALOR UNITÁRIO | L31: VALOR TOTAL
C33: 1 | D33: ='BASE PEDIDO'!H4 -> CABO FLEX750V 1,5MM2 PT | I33: ='BASE PEDIDO'!J4 -> 2 | J33: ='BASE PEDIDO'!I4 -> ROLO | K33: ='BASE PEDIDO'!K4 -> 150 | L33: =I33*K33 -> 300
C34: 2 | D34: ='BASE PEDIDO'!H5 -> CABO FLEX750V 1,5MM2 MR | I34: ='BASE PEDIDO'!J5 -> 2 | J34: ='BASE PEDIDO'!I5 -> ROLO | K34: ='BASE PEDIDO'!K5 -> 150 | L34: =I34*K34 -> 300
C35: 3 | D35: ='BASE PEDIDO'!H6 -> CABO FLEX750V 1,5MM2 VD | I35: ='BASE PEDIDO'!J6 -> 2 | J35: ='BASE PEDIDO'!I6 -> ROLO | K35: ='BASE PEDIDO'!K6 -> 150 | L35: =I35*K35 -> 300
C36: 4 | D36: ='BASE PEDIDO'!H7 -> BOTOEIRA BOMBA LIGA/DESLIGA C/MARTELO | I36: ='BASE PEDIDO'!J7 -> 6 | J36: ='BASE PEDIDO'!I7 -> UNID. | K36: ='BASE PEDIDO'!K7 -> 68.9 | L36: =I36*K36 -> 413.4
C37: 5 | D37: ='BASE PEDIDO'!H8 -> 0 | I37: ='BASE PEDIDO'!J8 -> 0 | J37: ='BASE PEDIDO'!I8 -> 0 | K37: ='BASE PEDIDO'!K8 -> 0 | L37: =I37*K37 -> 0
C38: 6 | D38: ='BASE PEDIDO'!H9 -> 0 | I38: ='BASE PEDIDO'!J9 -> 0 | J38: ='BASE PEDIDO'!I9 -> 0 | K38: ='BASE PEDIDO'!K9 -> 0 | L38: =I38*K38 -> 0
C39: 7 | D39: ='BASE PEDIDO'!H10 -> 0 | I39: ='BASE PEDIDO'!J10 -> 0 | J39: ='BASE PEDIDO'!I10 -> 0 | K39: ='BASE PEDIDO'!K10 -> 0 | L39: =I39*K39 -> 0
C40: 8 | D40: ='BASE PEDIDO'!H11 -> 0 | I40: ='BASE PEDIDO'!J11 -> 0 | J40: ='BASE PEDIDO'!I11 -> 0 | K40: ='BASE PEDIDO'!K11 -> 0 | L40: =I40*K40 -> 0
C41: 9 | D41: ='BASE PEDIDO'!H12 -> 0 | I41: ='BASE PEDIDO'!J12 -> 0 | J41: ='BASE PEDIDO'!I12 -> 0 | K41: ='BASE PEDIDO'!K12 -> 0 | L41: =I41*K41 -> 0
C42: 10 | D42: ='BASE PEDIDO'!H13 -> 0 | I42: ='BASE PEDIDO'!J13 -> 0 | J42: ='BASE PEDIDO'!I13 -> 0 | K42: ='BASE PEDIDO'!K13 -> 0 | L42: =I42*K42 -> 0
C43: 11 | D43: ='BASE PEDIDO'!H14 -> 0 | I43: ='BASE PEDIDO'!J14 -> 0 | J43: ='BASE PEDIDO'!I14 -> 0 | K43: ='BASE PEDIDO'!K14 -> 0 | L43: =I43*K43 -> 0
C44: 12 | D44: ='BASE PEDIDO'!H15 -> 0 | I44: ='BASE PEDIDO'!J15 -> 0 | J44: ='BASE PEDIDO'!I15 -> 0 | K44: ='BASE PEDIDO'!K15 -> 0 | L44: =I44*K44 -> 0
... C63: 31 | D63: ='BASE PEDIDO'!H34 -> 0 | I63: ='BASE PEDIDO'!J34 -> 0 | J63: ='BASE PEDIDO'!I34 -> 0 | K63: ='BASE PEDIDO'!K34 -> 0 | L63: =I63*K63 -> 0
C64: 32 | D64: ='BASE PEDIDO'!H35 -> 0 | I64: ='BASE PEDIDO'!J35 -> 0 | J64: ='BASE PEDIDO'!I34 -> 0 | K64: ='BASE PEDIDO'!K35 -> 0 | L64: =I64*K64 -> 0
C65: 33 | D65: ='BASE PEDIDO'!H36 -> 0 | I65: ='BASE PEDIDO'!J36 -> 0 | J65: ='BASE PEDIDO'!I35 -> 0 | K65: ='BASE PEDIDO'!K36 -> 0 | L65: =I65*K65 -> 0
C66: 34 | D66: ='BASE PEDIDO'!H37 -> 0 | I66: ='BASE PEDIDO'!J37 -> 0 | J66: ='BASE PEDIDO'!I36 -> 0 | K66: ='BASE PEDIDO'!K37 -> 0 | L66: =I66*K66 -> 0
C67: 35 | D67: ='BASE PEDIDO'!H38 -> 0 | I67: ='BASE PEDIDO'!J38 -> 0 | J67: ='BASE PEDIDO'!I37 -> 0 | K67: ='BASE PEDIDO'!K38 -> 0 | L67: =I67*K67 -> 0
C68: 36 | D68: ='BASE PEDIDO'!H39 -> 0 | I68: ='BASE PEDIDO'!J39 -> 0 | J68: ='BASE PEDIDO'!I38 -> 0 | K68: ='BASE PEDIDO'!K39 -> 0 | L68: =I68*K68 -> 0
C69: 37 | D69: ='BASE PEDIDO'!H40 -> 0 | I69: ='BASE PEDIDO'!J40 -> 0 | J69: ='BASE PEDIDO'!I39 -> 0 | K69: ='BASE PEDIDO'!K40 -> 0 | L69: =I69*K69 -> 0
C70: 38 | D70: ='BASE PEDIDO'!H41 -> 0 | I70: ='BASE PEDIDO'!J41 -> 0 | J70: ='BASE PEDIDO'!I40 -> 0 | K70: ='BASE PEDIDO'!K41 -> 0 | L70: =I70*K70 -> 0
C71: 39 | D71: ='BASE PEDIDO'!H42 -> 0 | I71: ='BASE PEDIDO'!J42 -> 0 | J71: ='BASE PEDIDO'!I41 -> 0 | K71: ='BASE PEDIDO'!K42 -> 0 | L71: =I71*K71 -> 0
C72: 40 | D72: ='BASE PEDIDO'!H43 -> 0 | I72: ='BASE PEDIDO'!J43 -> 0 | J72: ='BASE PEDIDO'!I42 -> 0 | K72: ='BASE PEDIDO'!K43 -> 0 | L72: =I72*K72 -> 0
C73: 41 | D73: ='BASE PEDIDO'!H44 -> 0 | I73: ='BASE PEDIDO'!J44 -> 0 | J73: ='BASE PEDIDO'!I43 -> 0 | K73: ='BASE PEDIDO'!K44 -> 0 | L73: =I73*K73 -> 0
C74: 42 | D74: ='BASE PEDIDO'!H45 -> 0 | I74: ='BASE PEDIDO'!J45 -> 0 | J74: ='BASE PEDIDO'!I44 -> 0 | K74: ='BASE PEDIDO'!K45 -> 0 | L74: =I74*K74 -> 0
C75: 43 | D75: ='BASE PEDIDO'!H46 -> 0 | I75: ='BASE PEDIDO'!J46 -> 0 | J75: ='BASE PEDIDO'!I45 -> 0 | K75: ='BASE PEDIDO'!K46 -> 0 | L75: =I75*K75 -> 0
... C104: 72 | D104: ='BASE PEDIDO'!H75 -> 0 | I104: ='BASE PEDIDO'!J75 -> 0 | J104: ='BASE PEDIDO'!I74 -> 0 | K104: ='BASE PEDIDO'!K75 -> 0 | L104: =I104*K104 -> 0
K105: SUB TOTAL | L105: =SUM(L33:L104)-L106 -> 1313.4
K106: DESCONTO | L106: =SUMIF(D33:D60,"DESCONTO",L33:L60) -> 0
K107: TOTAL | L107: =L105+L106 -> 1313.4
L109: Horario de RECEBIMENTO NA OBRA
L110: Segunda a Quinta-feira das 07:30h às 11:30h e das 13:00h as 15:30h
L111: Sexta-feira das 07:30h às 11:30h e das 13:00h as 14:30h

Sheet DADOS DAS OBRAS
A1: OBRA | B1: FATURAMENTO | C1: ESCOLA | D1: Local de Entrega: | E1: Bairro: | F1: CEP: | G1: Contrato Obra: | H1: Cidade: | I1: UF: | J1: Empreiteiro | K1: Contato
A2: FCO MIGNONE | B2: BRASUL | C2: EE FRANCISCO MIGNONE | D2: Rua Rio Birigui nº 01 | E2: Gleba do Pessego - Parque do Carmo | F2: 08265-290 | G2: 70/00146/23/01 | H2: São Paulo | I2: SP | J2: BERNARDO | K2: (11) 9.8506-0719
A3: KEIZO - JB | B3: JB | C3: EE KEIZO ISHIHARA | D3: Rua Mário Gessulho, 60 | E3: Conj. Res. Butanta | F3: 05540-130 | G3: 10/00005/23-01-051 | H3: São Paulo | I3: SP | J3: GEORGE | K3: (11) 9.8033-4770
A4: SOLON BORGES - JB | B4: JB | C4: EE/CEL SOLON BORGES DOS REIS | D4: Av. José Joaquim Seabra, 1187 | E4: Rio Pequeno | F4: 05364-000 | G4: 10/00005/23-01-051 | H4: São Paulo | I4: SP | J4: GEORGE | K4: (11) 9.8033-4770
A5: PEDRO COSTA - JB | B5: JB | C5: EE DEP PEDRO COSTA | D5: Rua Nilo Luís Mazzei, 378 | E5: Vila Isolina Mazzei | F5: 02081-070 | G5: 10/00005/23-01-051 | H5: São Paulo | I5: SP | J5: BERNARDO | K5: (11) 9.8506-0719
A6: BENEDITO TOLOSA - JB | B6: JB | C6: EE PROF BENEDITO TOLOSA | D6: Rua Jaguarete, 617 | E6: Casa Verde | F6: 02515-010 | G6: 10/00005/23-01-051 | H6: São Paulo | I6: SP | J6: KERLISON | K6: (11) 9.8570-2178
A7: THEREZA | B7: BRASUL | C7: EE THEREZA SILVEIRA | D7: Rua: Santo Antonio, 41 | E7: Jd. São Miguel | F7: 11440-080 | H7: Guaruja | I7: SP
A8: PE NILDO | B8: BRASUL | C8: EE Padre Nildo do Amaral Junior | D8: R. da Tropicália, s/n | E8: Jardim Pedro José Nunes | F8: 08061-010 | H8: São Paulo | I8: SP
A9: ALDEIA CAPOEIRÃO | B9: BRASUL | C9: EEI ALDEIA CAPOEIRAO | D9: ALDEIA CAPOEIRAO | E9: KM 93 | F9: 11760 - 000 | H9: Itariri | I9: SP | J9: SANDOVAL | K9: (11) 9.7792-3909
A10: ARY BARROSO | B10: BRASUL
A11: ANTONIO FERNANDES | B11: BRASUL | C11: EE PROF ANTONIO FERNANDES | D11: Rua Prof Antonio Fernandes 74 | E11: Vila Tupy | F11: 11900-000 | G11: 69/00811/23/01 | H11: Registro | I11: SP
A12: WALDEMAR RIGOTO - B&B | B12: B&B | C12: E. E. Prof. Waldemar da Silva Rigotto | D12: R. Primeiro de Maio, S/N | E12: Sítio Paecara (Vicente de Carvalho) | F12: 11460-000 | H12: Guaruja | I12: SP
A13: PEDRO BARROS | B13: BRASUL | C13: EE/EMEF PEDRO BARROS | D13: Rod. Régis Bittencourt, 384 | E13: Pedro Barros | F13: 11850-00 | G13: 69/00077/24-001-001 | H13: Miracatu | I13: SP
A14: EE ITARIRI | B14: BRASUL | C14: EE PEI ITARIRI | D14: Rua Benedito Calixto, 306 | E14: Centro Itariri | F14: 11760-000 | G14: 70/00158/23/01 | H14: Itariri | I14: SP
A15: EE WALDOMIRO MARIANI | B15: B&B | C15: EE Prof. Waldomiro Marian | D15: R. Orlando Terras, s/n | E15: Jardim Rea | F15: 11534-870 | H15: Cubatão | I15: SP | K15: (13) 3323-6265
A16: THEREZINHA ARANHA | B16: BRASUL | C16: EE Therezinha A Mantelli | D16: Rua Profº Antonio de Castro Lopes, 930 | E16: PQ Boturussu/Ermelindo Matarazzo | F16: 03805-080 | G16: 70/00146/23/01 | H16: São Paulo | I16: SP
A17: MARIO CORADIN | B17: BRASUL | C17: MARIO CORADIN | D17: Rod. Regis Bittencourt, Km 555 | E17: Rio Vermelho | F17: 11955-000 | G17: 69/01135/23/01 | H17: Barra do Turco | I17: SP
A18: EE GODOFREDO FURTADO - JB | B18: JB | C18: GODOFREDO FURTADO - JB | D18: R. João Moura, 727 - Jardim Paulista, São Paulo | E18: São Paulo | F18: 05412-001 | H18: São Paulo | I18: SP
A19: ALAY CORREA | B19: BRASUL | C19: ALAY JOSE CORREA VEREADOR | D19: R. Serra da Juréia, 130 - Jardim Valeri | E19: Registro | F19: 11900-000 | H19: São Paulo | I19: SP
A20: FDE | B20: BRASUL | C20: Fundação para o Desenvolvimento da Educação | D20: Av. São Luís, 99 - Centro Historico de São Paulo | E20: São Paulo | F20: 01046-001 | H20: São Paulo | I20: SP
A21: JOSE VICENTE BERTOLI | B21: BRASUL | C21: EE Prof. José Vicente Bertoli | D21: Estrada Municipal do Bairro Angatuba, S/N | E21: Angatuba | F21: 11930-000 | H21: Pariquera-Açu | I21: SP
A22: DARWIN FELIX | B22: BRASUL | C22: Escola Estadual Professor Darwin Felix | D22: Rua Quintino Bocaiúva, 406 - V Esperanca | E22: Piquete | F22: 12620-000 | H22: São Paulo | I22: SP
A23: WILSON SIMONINI | B23: BRASUL | C23: EE Wilson Roberto Simonini | D23: Rua João correa magalhães 200 | E23: Pq D João Neri | F23: 08151-260 | G23: 70/00553/22-01 | H23: São Paulo | I23: SP
A24: POETA DOMINGUES | B24: BRASUL | C24: EE POETA DOMINGUES | D24: EE Poeta Domingos Bauer Leite | E24: Miracatu | F24: 11850-000 | H24: Miracatu | I24: SP
A25: CLAY PRESGRAVE | B25: BRASUL | C25: EE Engenheiro Clay Presgrave do Amaral | D25: Av. Engº Clay P. do Amaral, 386 | E25: Ana Dias | F25: 11760-000 | H25: Itariri | I25: SP
A26: ANA ROSA DE ARAUJO | B26: JB | C26: E.E. Dona Ana Rosa De Araújo | D26: R. Eden, 100 | E26: Vila Inah | F26: 05619-000 | H26: São Paulo | I26: SP
A27: FERNANDO ABBUD | B27: BRASUL | C27: E.E Prof. José Fernando Abbud | D27: Av. Afonso Monteiro da Cruz, 261 | E27: Serraria | F27: 09980-550 | H27: Diadema | I27: SP
A28: DE CENTRO | B28: JB | C28: DE CENTRO | D28: Avenida Olavo Fontoura, 2.222 | E28: Casa Verde | F28: 02510-110 | H28: São Paulo | I28: SP
A29: ANTONIO PRADO | B29: JB | C29: EE CONS ANTÔNIO PRADO - JB | D29: R. Vitorino Carmilo, 621 | E29: Barra Funda | F29: 01153-000 | H29: São Paulo | I29: SP
A30: MARIA AP VIANA MUNIZ | B30: BRASUL | C30: MARIA APARECIDA VIANA MUNIZ PROFESSORA | D30: RUA 9 DE JULHO , 112 | E30: CENTRO | H30: Eldorado Registro | I30: SP
A31: ARLINDO BETIO | B31: BRASUL | C31: EE ARLINDO BETIO | D31: R. Vítor Brecheret, 31 | E31: Jardim Casa Grande | H31: Diadema | I31: SP
A32: OROSIMBO MAIA | B32: JB | C32: EE OROSIMBO MAIA | D32: Av. Andrade Neves, 214 | E32: Centro | F32: 13013-160 | H32: Campinas | I32: SP
A33: JOAQUIM FERREIRA | B33: JB | C33: EE JOAQUIM FERREIRA LIMA PROFESSOR | D33: RUA JOAO NOGUEIRA FERRAZ FILHO | E33: Vila Trinta e um de março | F33: 13091-558 | H33: Campinas | I33: SP
A34: MSN LUIS GONZAGA | B34: JB | C34: EE MNS LUIS GONZAGA DE MOURA | D34: R. Carlos Francheu 100 - Centro | E34: Centro | F34: 13023-610 | H34: Campinas | I34: SP
A35: DE MIRACATU | B35: BRASUL | C35: DIRETORIA DE ENSINO MIRACATU | D35: Av. Doná Evarista de Castro Ferreira | E35: Centro | F35: 11850-000 | H35: Miracatu | I35: SP
A36: JOAQUIM LEME PRADO | B36: JB | C36: Escola Estadual Joaquim Leme do Prado | D36: Av. Imirim, 2113 | E36: Imirim | F36: 02465-200 | H36: São Paulo | I36: SP
A37: MARIA MONTESSORI | B37: BRASUL | C37: EE MARIA MONTESSORI | D37: Av. Conceição, 2288 | E37: Vila Maria Alta | F37: 02072-002 | H37: São Paulo | I37: SP
A38: MARIA JOSE MORAIS | B38: BRASUL | C38: EE. Professora Maria José Morais de Carvalho | D38: Estrada dos Moraes, BR-116 | E38: Miracatu | F38: 11850-000 | H38: Miracatu | I38: SP
A39: ANA RITA GODINHO | B39: JB | C39: Escola Estadual Professora Ana Rita Godinho Pousa | D39: R. Benedita Franco Gomes, 165 | E39: Vila Esmeralda | F39: 13077-066 | H39: Campinas | I39: SP
A40: EE Fabio Farias | B40: JB | C40: Escola Estadual Fabio Farias | D40: AV. BRIGADEIRO RAFAEL TOBIAS DE AGUIAR 501 | E40: Jardim Aurelia | F40: 13033-010 | H40: Campinas | I40: SP
A41: PEI RAPOSO TAVARES | B41: BRASUL | C41: E. E. PEI Raposo Tavares | D41: Rua Anízio Pedro Oliveira, 22 | E41: Raposo Tavares | F41: 11760-000 | H41: Itariri | I41: SP
A42: DE REGISTRO | B42: BRASUL | C42: DIRETORIA DE ENSINO REGISTRO | D42: R. Vitória, 465 | E42: Jardim America | F42: 11900-000 | H42: Registro | I42: SP
A43: JOSE BARTOCCI | B43: BRASUL | C43: EE PROFESSOR JOSE BARTOCCI | D43: R. São Serapião, 396 | E43: Vila Ré | F43: 03664-000 | H43: São Paulo | I43: SP
... A56: DJALMA OCTAVIANO | B56: JB | C56: EE Djalma Octaviano | D56: Rua Willian Booth | E56: Jardim Pauliceia | F56: 13034-685 | H56: Campinas | I56: SP
A57: CASTINAUTA DE BARROS | B57: JB | C57: EE Prof Castinauta de Barros Mello e Albuquerque | D57: Rua Orlando de Oliveira 700 | E57: Jardim Campineiro | H57: Campinas | I57: SP
A58: FRANCISCO ALVARES | B58: JB | C58: EE Prof Francisco Álvares | D58: Estrada da Rhodia KM 15 N | E58: Vila Holandia | H58: Campinas | I58: SP
A59: MARIA MATOSINHO | B59: JB | C59: E.E José Maria Matosinho | D59: Praça Professsor Paulo José Otaviano, s/n | E59: São Bernardo | F59: 13030-571 | H59: Campinas | I59: SP
A60: SERRA NEGRA | B60: BRASUL | C60: SERRA NEGRA
A61: OMAR DONATO | B61: BRASUL | C61: ​Escola Estadual Omar Donato Bassani | D61: Estr. Ernesto Zabeu, 253 | E61: Tatetos | F61: 09837-150 | H61: São Bernardo | I61: SP
A62: MIGUEL ABU-YAGHI | B62: BRASUL | C62: Escola Miguel Abu-Yaghi | D62: R. Sete de Setembro, 2-58 | F62: 11940-000 | H62: Jacupiranga | I62: SP
A63: ADALBERTO NASCIMENTO | B63: BRASUL | C63: E. E. Adalberto Nascimento | D63: R. Adalberto Maia, 235 | E63: Taquaral | F63: 13076-007 | H63: Campinas | I63: SP
A64: ALBINO LUIZ CALDAS | B64: B&B | C64: Escola Estadual Albino Luiz Caldas | D64: Rua Irma Maria Rita de Souza Brito Lopes (Irma Dulce) | E64: Conjunto Residencial Humaitá | F64: 11349-330 | H64: São Vicente | I64: SP
A66: CARMELA CHIARA | B66: INTERIORANA | C66: E.E CARMELA CHIARA GINEFRA | D66: CENTRO | E66: CENTRO | F66: 13190-000 | H66: MONTE MOR | I66: SP
A67: CRISTIANE CHAVES | B67: INTERIORANA | C67: PEI CRISTIANE CHAVES MOREIRA | D67: R. Fabiano Pinheiro da Silva, 40 | E67: Jardim Santana | F67: 13184-547 | H67: Hortolandia | I67: SP
A68: JOSE DE ALMEIDA PINHEIRO | B68: B&B | C68: JOSE DE ALMEIDA PINHEIRO JUNIOR PROFESSOR | D68: RUA DOUTOR JOSE BENEDITO ALMEIDA RIBEIRO , SN | E68: PARQUE DAS BANDEIRAS | F68: 11346-030 | H68: São Vicente | I68: SP
A69: DONA ARACY | B69: INTERIORANA | C69: E.E DONA ARACY | D69: TRAVESSA FRANCISCO PARROTA SN | E69: VILA MONTE CARLO | F69: 13572-410 | H69: SÃO CARLOS | I69: SP
A70: ATTILIA PRADO | B70: INTERIORANA | C70: EE ATTILIA PRADO | D70: RUA JOAQUIM AUGUSTO RIBEIRO DE SOUZA SN | E70: PLANALTO PARAISO | F70: 13563-330 | H70: SÃO CARLOS | I70: SP
A71: PEDRO CELESTINO | B71: INTERIORANA | C71: EE PEDRO CELESTINO | D71: RUA DAS ARAPONGAS, SN | E71: JARDIM SÃO JOAQUIM | F71: 13615-600 | H71: LEME | I71: SP
A72: ELOI CHAVES | B72: INTERIORANA | C72: EE ELOI CHAVES | D72: AVENIDA ROSA SENHORINI ZERO 100 | E72: CACHOEIRA DE EMAS | F72: 13641-002 | H72: PIRASSUNUNGA | I72: SP
A73: ESTERINA PLACO | B73: INTERIORANA | C73: EE ESTERINA PLACO | D73: AVENIDA ARARAQUARA 451 | E73: VILA BRASILIA | F73: 13566-770 | H73: SÃO CARLOS | I73: SP
A74: JESUINO DE ARRUDA | B74: INTERIORANA | C74: EE JESUINO DE ARRUDA | D74: PRAÇA DONA MARIA GERTRUDES DE ARRUDA, SN | E74: VILA SONIA | F74: 13572-215 | H74: SÃO CARLOS | I74: SP
A75: LAURO BARREIRA | B75: INTERIORANA | C75: EE LAURO BARREIRA | D75: RUA PRUDENTE DE MORAES 318 | E75: CENTRO | F75: 13650-000 | H75: SANTA CRUZ DAS PALMEIRAS | I75: SP
... A101: ELVIRA SILVA | B101: BRASUL | C101: E.E Elvira Silva | D101: R. Vitorino Antonio Da Silva, SN | E101: Iguape | F101: 11920-000 | H101: Miracatu | I101: SP
A102: VIRGILIO SILVEIRA | B102: INTERIORANA | C102: E.E VIRGILIO SILVEIRA | D102: R. João Galdino de Camargo, 203 | E102: Rechan | F102: 18217000 | H102: ITAPETININGA | I102: SP
A103: EURINY DE SOUZA | B103: INTERIORANA | C103: E.E PROFA EURINY DE SOUZA VIEIRA | D103: Estr. Mun. José Corrêa de Morães, 225 | E103: Chapadinha | F103: 18206-800 | H103: Itapetininga | I103: SP
A104: JOSÉ DE CAMPOS | B104: INTERIORANA | C104: E.E Prof. José de Campos | D104: R. João Batista Nunes Beccari, 166 | E104: Jardim Morada do Sol | F104: 13346-430 | H104: Indaiatuba | I104: SP
A105: LUIZ CAMPO | B105: INTERIORANA | C105: E.E luiz campo dallorto | D105: R. Goianésia, 299 | E105: Jardim Dal'orto | F105: 13178-030 | H105: Sumaré | I105: SP
A106: DER SUMARÉ | B106: INTERIORANA | C106: Diretoria de Ensino Sumaré | D106: Rua Luiz José Duarte, 333 | E106: Jardim Sao Carlos | F106: 13170-023 | H106: Sumaré | I106: SP
A107: RENATO DE AZEVEDO | B107: INTERIORANA | C107: E.E Renato de Azevedo | D107: Av. Santana, 3905 | E107: Nova Gardênia | F107: 12946-706 | H107: Atibaia | I107: SP
A108: APARECIDA DE FATIMA | B108: INTERIORANA | C108: E.E Aparecida de Fatima | D108: Av. Pres. Tancredo de Almeida Neves, 85 | E108: Conj. Hab. Pres. Castelo Branco | F108: 06329-350 | H108: Carapicuíba | I108: SP
A109: MARIA CÉLIA | B109: INTERIORANA | C109: E.E Maria Célia Falcão Rodrigues | D109: RUA ARACY VALENTE , 159 | E109: PARQUE MIKAIL | F109: 7142390 | H109: GUARULHOS | I109: SP
A110: NEUSA DE FATIMA | B110: INTERIORANA | C110: E.E NEUSA DE FATIMA MARIN BERNADI | D110: RUA BARAO DE MAUA , 5875 | E110: JARDIM ITAPEVA | F110: 09330-150 | H110: MAUA | I110: SP
A111: MARIA THEREZINHA | B111: INTERIORANA | C111: E.E Maria Therezinha | D111: R MARIO DE ANDRADE , 186 | E111: JARDIM MIRANDA D'AVIZ | F111: 09330-500 | H111: MAUA | I111: SP
A112: REVERENDO AUGUSTO | B112: B&B | C112: E.E Reverendo Augusto Paes | D112: R. Dr. Júlio de Mesquita Filho, 729 | E112: Aviação, Praia Grande | F112: 11702-350 | H112: Aviação | I112: SP
A113: JOSÉ ROBERTO | B113: BRASUL | C113: E.E José Roberto Friebolin | D113: Rua: Bahia, 392 | E113: Vila Rosália | F113: 07072-200 | H113: Guarulhos | I113: SP
A114: JD ALINE | B114: INTERIORANA | C114: E.E JD ALINE | D114: R. Benedita Teodoro da Silva, 286 | E114: Jardim Santiago | F114: 13185-828 | H114: Hortolândia | I114: SP
A115: MARIA DE LOURDES | B115: INTERIORANA | C115: EE MARIA DE LOURDES STIPP STEFFEN | D115: R. Antônio Benedito Jesus Mte., 174 | E115: Jardim Marina | F115: 13343-56 | H115: Indaiatuba | I115: SP
A116: PAULO CAMILLO | B116: INTERIORANA | C116: EE PAULO CAMILO DE CAMARGO | D116: R. Catulo da Paixão Cearense, 110 | E116: Jardim Sao Bento | F116: 13187-112 | H116: Hortolândia | I116: SP
A117: JULIO SECCO | B117: B&B | C117: E. E. Júlio Secco de Carvalho | D117: R. Amelletto Franceschelli, 286 | E117: Solemar | F117: 11709-140 | H117: Praia Grande | I117: SP
A118: BENEDITO CALIXTO | B118: B&B | C118: EE Benedito calixto | D118: Av. Rui Barbosa, 180 | E118: Centro | F118: 11740-000 | H118: Itanhaém | I118: SP
A119: BAIRRO JAIRE | B119: BRASUL | C119: E E Bairro Jaire | D119: Estrada Municipal Iguape Pariquera Acu | E119: Avenida Jaire | F119: 11920-000 | H119: Iguape | I119: SP
A120: MARGARIDA PINHO | B120: B&B | C120: E.E Margarida Pinho Rodrigues | D120: R: Drº - R. Dr. Polydoro de Oliveira Bittencourt, 300 | E120: Vila Margarida | F120: 11330-570 | H120: São Vicente | I120: SP
A121: JULIO PARDO | B121: B&B | C121: E.E Julio pardo | D121: Av. Júlio Prestes de Albuquerque, 934 | E121: Nova Mirim | F121: 11717-110 | H121: Praia Grande | I121: SP
... A124: LAURINDO GOMES | B124: INTERIORANA | C124: EE Laurindo Gomes | D124: R. Natal Albino Leme, 200 | E124: JARDIM SAN REMO | F124: 13190-000 | H124: Monte Mor | I124: SP
A125: LAUDELINO FERNANDES | B125: B&B | C125: EE Prof Laudelino Fernandes dos Santos | D125: RUA SAO BENEDITO , 762 | E125: VILA CAICARA | F125: 11706250 | H125: PRAIA GRANDE | I125: SP
A126: CARMEM MIRANDA | B126: B&B | C126: EE Carmem Miranda | D126: R. Profa. Teresinha Rodrigues Kalil, 1221 | E126: Jardim Brasil | F126: 11750-000 | H126: Peruíbe | I126: SP
A127: ESCRITÓRIO | B127: BRASUL | C127: ESCRITÓRIO
A128: DOM DUARTE | B128: BRASUL | C128: EE Dom Duarte | D128: Av. de Pinedo, 577 | E128: Socorro | F128: 04764-001 | H128: São Paulo | I128: SP
A129: FATEC CATANDUVA | B129: BRASUL | C129: FATEC CATANDUVA | D129: Rua Maranhão, 898 | E129: Centro | F129: 15800-020 | H129: Catanduva | I129: SP
A130: HERCY MORAES | B130: JB | C130: EE HERCY MORAES | D130: Av. Paulo Provenza Sobrinho, 1450 | E130: Vila Perseu Leite de Barros | H130: Campinas | I130: SP
A131: VITALINO BERNINI | B131: B&B | C131: EE PROF. VITALINO BERNINI | D131: R. Dr. Itatiba, 510 | E131: Jd Caraminguava | F131: 11750-000 | H131: Peruíbe | I131: SP
A132: ABRAHÃO JACOB | B132: B&B | C132: E.E. Dr. Abrahão Jacob Lafer | D132: R. Claudino Pacheco, 9562 | E132: Guilhermina | F132: 11701-475 | H132: Praia Grande | I132: SP
A133: ALDEIA RIO BRANCO | B133: B&B | C133: E.E Aldeia Rio Branco | D133: Rio Branco Itanhaém | E133: Emburá | F133: 11740-000 | H133: Itanhaem | I133: SP
A134: JOAQUIM PEDROSO | B134: INTERIORANA | C134: EE Joaquim Pedroso de Alvarenga | D134: Alameda José Boldrini, 187 | E134: Itaici | F134: 13341-700 | H134: Indaiatuba | I134: SP
A135: BARTHOLOMEU | B135: BRASUL | C135: EE Bartholomeu de Carlos | D135: R. Aracajú, 490 | E135: Jardim Leblon | F135: 07272-090 | H135: Guarulhos | I135: SP
A136: GENNY PIMAZZONY | B136: INTERIORANA | C136: E.E Genny Pimazzoni | D136: R. São José, 305 | E136: Cardeal | F136: 13350-000 | H136: Elias Fausto | I136: SP
A137: VILA TUPI | B137: B&B | C137: E.E Vila Tupi | D137: R. Bororós, 26904 | E137: Vila Tupi | F137: 11703-390 | H137: Praia Grande | I137: SP
A138: AGENOR DE CAMPOS | B138: B&B | C138: E.E Agenor de Campos | D138: Avenida Agenor de Campos, R. Aimorés, S/N | E138: Mongaguá | F138: 11730-000 | H138: Mongaguá | I138: SP
A139: OTTONIEL JUNQUEIRA | B139: B&B | C139: E.E Prof Ottoniel Junqueira | D139: R. Alfredo Gomes, 185 | E139: Centro | F139: 11750-000 | H139: Peruíbe | I139: SP
A140: FLEURIDES CAVALINI | B140: BRASUL | C140: E.E Fleurides Cavalini | D140: Av. Vitório Romanini | E140: Vila Cicma | F140: 17800-000 | H140: Adamantina | I140: SP
...

Sheet FORNECEDORES
A1: FORNECEDOR | B1: Razão Social | C1: E-mail | D1: Vendedor | E1: Telefone | F1: PIX | G1: FAVORECIDO
A2: F PINHEIRO | B2: F Pinheiro Comercio de Mat. p/ Construção LTDA | C2: beatriz@fpinheiro.com.br | D2: Beatriz | E2: (11) 96591-4597 | F2: 54.773.338/0001-05 | G2: F. PINHEIRO COMERCIO DE MATERIAL PARA CONSTRUCAO SLU LTDA
A3: BIG TELHAS | B3: BIG TELHAS CNPJ: 05.167.149/0001-83 | C3: marcos.paulo@telhasmp.com.br | D3: Marcos Paulo | E3: 19 99806-7474
A4: C&C | B4: C&C CASA E CONSTRUÇÃO LTDA | D4: Luciane | E4: (11) 94778-9353
A5: OLD RIVER | B5: PRO LIMA - COMERCIAL E DISTRIBUIDORA LTDA | C5: cotacao@oldriver.com.br | D5: Rudy | E5: 94015-2734
A6: CORANTE | B6: OZ MATERIAIS PARA CONSTRUCAO LTDA - MATRIZ | C6: aretusa@corantetintas.com.br | D6: Aretusa | E6: 11 98269-0417
A7: OBRAMESTRE | B7: OBRAMESTRE DEP MAT CONST LTDA | C7: adm01@obramestre.com | D7: Mayra | E7: 11 93950-6104
A8: CIMENTOFORT | B8: CimentoFort Distribuidora | C8: silvia@cimentofort.com.br | D8: Silvia | E8: (11)97514-9578
A9: ECO AMBIENTAL | B9: ECO AMBIENTAL CACAMBAS ESTACIONARIAS LTDA | C9: rodrigo@ecoambientalcacambas.com.br | D9: Rodrigo | E9: 11 97697-2621
A10: INOVABAN | B10: INOVABAN COMERCIO, LOCAÇÃO E MANUTENÇÃO DE EQUIPAMENTOS LTDA | C10: priscila@inovaban.com.br | D10: Priscila | E10: 11 98908-1735
A11: UEHARA ELETRICA | B11: UEHARA COM.DE MATS ELETRLTDA | C11: fernando@ueharaeletrica.com.br | D11: Fernando | E11: 11 3856-7501 | F11: 53.934.626.0001-31
A12: THIAGO ELETRICA | B12: 31.191.128 THIAGO DOS SANTOS SOUZA | C12: tseletricargt@hotmail.com | D12: Thiago | E12: 13 99746-9888 | F12: 31.391.128/0001-57 | G12: 31.391.128 Thiago dos Santos Souza Banco: BTG Pactual
A13: CATEL | B13: CATEL HIDRAULICOS LOUCAS E METAIS | C13: alan@catelhlm.com.br | D13: Alan | E13: 11 3313-8220
A14: CASA MIMOSA | B14: CASA MIMOSA HIDRAULICA E ACABAMENTOS LTDA | C14: vendas@casamimosa.com.br | D14: Rodrigo | E14: (11) 27825500 | F14: 62.978.978/0001-80 | G14: Casa Mimosa Hidráulica e Acabamentos Ltd
A15: PORTUGUÊS CAÇAMBAS | B15: JOYCE MARION ZORGDRAGER GUARUJÁ | C15: jmzcacamba@gmail.com | D15: Andrade | E15: 13 97812-3658
A16: PARADA DA LIMPEZA | B16: PARADA DA LIMPEZA 16.657.550/0001-18
A17: BECO GÁS | B17: TERMOGAS AQUECIMENTO E CONTROLE LTDA 02.793.273/0001-66 | D17: JOSÉ | E17: 11 2692-6150 | F17: CNPJ 57.288.482/0001-44 | G17: BECO DOS FOGÕES PEÇAS E ACESSÓRIOS LTDA
A18: ANDAIMES ZONA LESTE | B18: ZONA LESTE ANDAIMES | D18: Amanda | E18: (11) 2765-8733
A19: CONSTRUSILVA | B19: ADRIANA PINA SILVEIRA E SILVA ME | D19: Ana Clara | E19: 11) 9 8599-5296 | F19: CNPJ: 03.533.447/0001-14 | G19: ADRIANA PINA DA SILVEIRA E SILVA
A20: LESTE SÃO PAULO | B20: LESTE SÃO PAULO MATERIAIS DE CONSTRUÇÃO LTDA | C20: leticia@futuramadeiras.com.br | D20: Leticia | E20: 11 2254-8764
A21: DEPOSITO PADRÃO | B21: DEPOSITO E COMERCIO PADRAO LOJA 2 LTDA | C21: viviane@brasulconstrutora.com.br | D21: Melissa | E21: 11963310257 | F21: CNPJ 53.198.573/0001-38 | G21: Deposito e COmercio Padrao - loja 02
A22: AREA ELETRICOS | B22: AEA DISTRIBUIDORA DE MAT. ELETRICOS LTDA | D22: Wellison | E22: 1133931842
A23: ITA AÇOS | B23: AÇOS ITAPETININGA LTDA | C23: sebachvocal@gmail.com | D23: Erik Maluf | E23: (15) 3259-8333
A24: ART VIDROS | B24: ART VIDROS VIDRAÇARIA | C24: artvidros@vidracariaartvidros.com.br | D24: Beth | E24: (11) 2905-5804 | F24: CNPJ 43.479.500/0001-60 | G24: ART VIDROS LTDA BANCO ITAU
A25: GFENDS ESQUADRIAS | B25: GFENDS ESQUADRIAS DE ALUMINIO LTDA | D25: Geraldo | E25: (11) 94784-5189
A26: GUARUJÁ EXTINTORES | B26: GUARUJA EXTINTORES CNPJ: 17338751000115 | E26: (13) 3323-6265
A27: DIRECT BORRACHAS | B27: DIRECT BORRACHAS CNPJ: 23.447.624/0001-57 | D27: GISELE | E27: (11)2011-9058 | F27: 234476240001-57 | G27: DIRECT B I C PLASTICOS
A28: DEPOSITO ZONA NORTE | B28: DEPÓSITO ZONA NORTE | C28: vendas@depositozonanorte.com.br | D28: JOÃO | E28: 11) 2638-2438
A29: CS EXTINTORES | B29: CS EXTINTORES REPRESENTAÇÕES | D29: BRUNO | E29: 11 96359-7115
A30: CM MARMORE E GRANITO | B30: CM MARMORES E GRANITOS | C30: cm.marmore@hotmail.com | D30: ANGELO | E30: (11) 99677-8779 | F30: CNPJ: 42.794.567/0001-27 | G30: C E M ALVENARIA E COMERCIO LTDA
A31: BARRACAO ANDAIMES | B31: BARRACAO DO CONSTRUTOR PERUÍBE CNPJ: 46.387.169/0001-47 | D31: PEDRO | E31: (13) 99645-1016 | F31: CNPJ: 46387169000147 | G31: Barracao do Construtor Peruíbe
A32: MAD VERDE | B32: Concretex Com. Madeiras LTDA | C32: roseli.madverde@hotmail.com | D32: Roseli | E32: 11 95967-8300
A33: ITATERRA | B33: Itaterra Transportes LTDA 43.223.981/0001-49 | C33: contato@itaterraentulho.com.br | D33: Aline | E33: 11 94012-5563
A34: HAMAN BLOCOS | B34: HAMAN BLOCOS INDUSTRIA E COMERCIO LTDA | C34: financeiro_hamanblocos@hotmail.com | D34: Nilton | E34: (11) 4656-1096
A35: CASA DA LOCAÇÃO | B35: CASA DA LOCAÇÃO EIRELI-ME | C35: casadalocacao2018@hotmail.com | E35: 13 3821-2007
A36: WRC | B36: WRC HIDRAULICA LOUÇAS E METAIS LTDA | C36: gabriel@wrchidrulica.com | D36: Gabriel | E36: 11 2254-8764
A37: NSA | B37: N.S.A COMERCIO DE PARAFUSOS LTDA | C37: vendas@gruponsa.com.br | D37: Cosme | E37: 11 3976-2869
A38: RV PLASTIC | B38: RV PLASTIC FORROS E DIVISORIAS LTDA | C38: rvplastic@rvplastic.com.br | D38: Junior | E38: 11 3326-2994
A39: TELHA NORTE | B39: SAINT-GOBAIN DISTRIBUIÇÃO BRASUL LTDA | C39: augusto.endes@saint-gobain.com | D39: Augusto | E39: 11 9.8510-6170
A40: INFINITY MADEIRAS
A41: RICARDO FRETE VIDROS | B41: RICARDO FRETE DE VIDROS | D41: Ricardo | E41: 11 99965-2665 | F41: CPF :116.776.968-69 | G41: Ricardo Julio
A42: SIRO MATERIAIS ELETRICO | B42: Siro Materiais Elétricos Ltda | C42: luciana.soares@siro.com.br | D42: Luciana | E42: 11 3879-6102 | F42: 44.019.149/0001-98 | G42: Siro Materiais Eletricos
A43: SANTA ROSA | B43: H A C MATERIAIS PARA CONTRUÇÃO LTDA - SANTA ROSA
A44: NAKA | B44: NAKA GRANILITE | C44: nakagranilite@gmail.com | D44: Silvia | E44: 11 98378-6009
A45: TELHADÃO | B45: Telhadão Comercial Ltda. 02.470.293/0002-87 | C45: leonardo@telhadao.com.br | D45: Leonardo | E45: 11 97668-4346
A46: JMD | B46: JMD COMERCIO DE MATERIAIS ELETRICOS LTDA - EPP | D46: Junior | E46: 11 97562-8201
A47: N TINTAS | B47: N TINTAS COMERCIO DE TINTAS LTDA | D47: Gabriela | E47: 11 2950-5070 | F47: 00.152.006/0001-84 | G47: N TINTAS COMERCIO DE TINTAS LTDA
A48: LITOS LOCAÇÃO | B48: LITO ENTULHOS - BRUNO CEZAR CREPALDI - ME | C48: crepaldi.bruno@hotmail.com | D48: Nadja | E48: 11 94735-3954
A49: JD ONIX | B49: JD ONIX FECHADURAS E SERVIÇOS PARA ESCOLA | D49: Julio Rodrigues | E49: 11 98598-3967
A50: POLIBRA | B50: POLIBRA REPRESENTAÇÕES LTDA | D50: Percival
A51: ALTISSIMO | B51: ALTISSIMO EQUIPAMENTOS PARA CONSTRUÇÃO LTDA | D51: Fernanda | E51: 11 3526-5777
A52: ANDAIMENORTE | B52: ANDAIMENORTE LOCAÇÃO DE EQUIPAMENTO PARA CONSTRUÇÃO CIVIL LTDA | D52: Ygor
A53: BRN | B53: BRN INDUSTRIA DE QUIMICOS PARA CONSTRUÇÃO LTDA | C53: maria.santos@grupobarone.com.br | D53: Maria | E53: 11 97816-3074
A54: RISATEC | B54: RISATEC DISTRIBUIDORA DE FERRO E AÇO LTDA | C54: francisca.cavalcante@risatec.com.br | D54: Francisca | E54: 11 91315-0876
A55: LONGAMETRAGEM | B55: LONGAMETRAGEM FERRAGENS LTDA | D55: REINALDO | E55: 11 97336-0474
A56: JOSE CARLOS | B56: JOSE CARLOS DE LMEIDA M.E | C56: jc1232106@gmail.com | D56: Zeca | E56: 13 99701-2267
A57: ALFA MAQUINAS | B57: Alfa maquinas locação e serviços | C57: pablodantas@alfamaquinas.com | D57: Pablo | E57: 11 94703-7896
A58: LAJE GODEK | B58: GODEK MATERIAIS PARA CONSTRUÇÃO | C58: materiais.godek2930@gmail.com | D58: Amanda | E58: 13 99641-0608 | F58: 17.955.910.0004-73 | G58: Domingos Ramos da Silva Filho
A59: GAMELINHA | B59: GAMELINHA MATERIAIS P/ CONSTRUÇÃO LTDA ME | C59: gamelinha@terra.com.br | D59: Maria Paula | E59: 11 3313-8220
A60: DUTRA MAQUINAS | B60: DUTRA MAQUINAS | D60: Alisson
A61: TRANSLINO | B61: Translino Comercio de Areia e Pedra | C61: translinotransporte@hotmail.com | D61: Athos | E61: 11 94128-1161
A62: MAD MAIS | B62: MAD MAIS MADEIRAS LTDA | C62: NFE@MADMAIS.COM.BR | D62: Thais | E62: 11 2902-0505 | F62: CNPJ: 10785708000159 | G62: MAD MAIS MADEIRAS EM
A63: BRASIL NOVO | B63: Concreto e Lajes Brasil Novo 08408532000174 | C63: rafarocha25@hotmail.com | D63: Leandro | E63: 11 95477-5297
A64: CASA DO LOJISTA | B64: Casa do lojista atacadista de materiais para construção | C64: eduardo.silva@casadolojista.com.br | D64: Daniela | E64: 11 95839-1541
A65: GOLDONI | B65: IND. DE TELAS E ARAMES N GOLDONI LTDA | C65: comercial@telasgoldoni.com.br | D65: Priscila | E65: 11 3313-8220
A66: MITSUNARI | B66: TELAS METALICAS TELMETAL LTDA 61.217.188/0001-19 | C66: anamitsunarivendas@hotmail.com | D66: Ana Mitsunari | E66: 11 98771-7367
A67: IMPERIO AÇO | B67: IMPÉRIO COMÉRCIO DE PERFIS E TUBOS | C67: anamitsunarivendas@hotmail.com | D67: Ana Mitsunari | E67: 11 98771-7367
A68: SOUZA GÁS | B68: LF Souza Comercio de Gás - 43316169000168 | C68: van.gas2013@gmail.com | D68: LF Souza | E68: 11 91318-9870 | F68: 11984971323 | G68: LUIS FELIPE SOUZA SILVA GAS
A69: DEPOSITO ZONA SUL | B69: DEPOSITO ZONA SUL | C69: we.vendas@dzs.com.br | D69: Wellington | E69: 11 3501-1014
A70: THAMES DEEP CLEAN | B70: JLARA IND DE MAQUINAS E PRODS LIMPEZA LTDA. | C70: VENDAS@THAMESJLARA.COM.BR | D70: Thames | E70: 11 2207-7820
A71: LUMICENTER LIGHTING | B71: LUMICENTER LIGHTING | C71: lucineia.nascimento@lumicenter.com | D71: Lucineia | E71: 41 2103-2750 Ramal 2820 | F71: CNPJ: 78.331.899/0001-12
A72: CONSIGAZ MIRACATU | B72: CONSIGAZ MIRACATU CNPJ: 22.921.038/0005-63 | C72: consigazmiracatu@hotmail.com | D72: Ivan | E72: 13 99799-5103 | F72: CNPJ : 22.921.038/0005-63 | G72: Itaú Empresas MH Distribuidora
A73: ANDAIME NORTE | B73: 09.525.694/0001-55 - ANDAIMENORTE LOCACAO DE EQUIPAMENTOS | C73: Juan@andaimenorte.com.br | D73: Juan | E73: 11 93074-6369
A74: CSA AUTOMATAÇÃO | B74: CPF/CNPJ: 20.297.280/0001-59 | C74: vendas@csaautomacao.com.br | D74: Juliana | E74: 11 4200-1320 | F74: CNPJ: 20297280000159 | G74: CSA Centro de Serviços e Automação Ltda
A75: DRYKO IMPERMEABILIZANTES | B75: Indústria Dryko Ltda. CNPJ: 03.081.895/0005-58 | C75: RONALDO.AMIN1705@GMAIL.COM | D75: Ronaldo | E75: 11 99106-5488
A76: CEARÁ | B76: CEARÁ MATERIAIS P/ CONSTRUÇÃO | D76: Reginaldo | E76: 13 99195-2746
A77: CASA DA BETONEIRA | B77: 49.842.041 KARINE LARA DA SILVA | C77: adm@acasadabetoneira.com.br | D77: Karina | E77: 13 98135-1437 | F77: 49.842.041/0001-14 | G77: KARINE LARA DA SILVA
A78: ZECA | B78: José Carlos de Almeida ME CNPJ 179366170001-16 | C78: CNPJ 179366170001-16 | D78: Zeca | E78: 13 99701-2267 | F78: CNPJ 179366170001-16 | G78: José Carlos de Almeida ME
A79: ARTESANA | B79: ARTESANA DIVISÓRIAS E FORROS LTDA | C79: CNPJ: 55.010.060/0009-34 | D79: Amanda | E79: 11 2797-7444 | F79: CNPJ 55.010.060/0001-87 | G79: ARTESANA DIVISORIAS E FORROS
A80: OBRAMAX | B80: BMB Material de Construcao S.A. - CNPJ: 23.476.033/0001-08 | C80: lastolpho@obramax.com.br | D80: Lucia | E80: 11 94210-4263
A81: GRAMA VERDE | B81: JOSE ALEXANDRE PONTES COSTA E OUTROS CNPJ : 27.255.936/0003-81 | C81: grama4357@gmail.com | D81: Alexandre | E81: 15 99742-4670
A82: CRISTAL ATACADO | B82: Cristal Atacado de Ferramentas CNPJ: 02.054.258/0001-04 | C82: cristal.atafer@gmail.com | D82: Edmilson | E82: 11 93450-3167
A83: ELETRICA FUSÃO | B83: ELETRICA FUSÃO LTDA CNPJ: 29.719.702/0001-01 | C83: contato@eletricafusao.com.br | D83: Bruno | E83: 11 98690-3513
A84: SODIMAC | B84: Construdecor S.A - Cumbica CD | D84: Otilio | E84: 11 94006-9257
A85: BRASCON | B85: DF INDUSTRIA E COMERCIO DE CONDUTORES ELETRICOS LTDA | D85: Luciani | E85: 11 94778-9353
A86: GARCEZ | B86: Garcez Locação de Caçambas CNPJ : 16.863.500/0001-97 | C86: garcezlocacao@outlook.com | D86: Elaine | E86: 11 94032-3919
A87: CIMEMPRIMO | B87: CIMEMPRIMO DISTRIBUIDORA DE MATERIAIS DE CONSTRUÇÃO LTDA | D87: Isabel | E87: 11 2782-2004
A88: RARIDADE PISOS & AZULEJOS | B88: ROBERTO CESAR CORREA PISOS | D88: Cleide | E88: 11 97155-7219 | F88: 11 96060-7199 | G88: Cleide Tavares Ramalho
A89: PASQUETTI HIDRAULICA | B89: PASQUETTI COM MAT HIDR LTDA | C89: Marcelo@pasquetti.com.br | D89: Marcelo | E89: 11 98562-0246
A90: PRESIDENTE PARAFUSO | B90: PRESIDENTE COMERCIO DE PARAFUSOS FERRAGENS E FERRAMENTAS SOC | D90: Renato | E90: 11 99952-9490
A91: MULTI SOLUÇOES | B91: MULTI SOLUÇÕES MATERIAIS PARA CONSTRUÇÃO E SERVIÇOS | C91: adm.multisolucoes@gmail.com | D91: Bismarck | E91: (11) 940352683 | F91: CNPJ 05867073000107 | G91: LUCI MARIA CAETANO CONSTRUÇÃO
A92: DIMIBU | B92: DIMIBU INDUSTRIA DE ARTEFATOS DE PAPEL E PAPELÃO TLDA | C92: dimibu@dimibu.com.br | D92: Tainá | E92: 11 94028-2822 | F92: CNPJ: 60.810.611/0001-27 | G92: Dimibu industria de artefatos de papel e Papelão ltda
A93: ENNOVE | B93: E.N.V COMPONETES PLASTICOS E FERRAMENTARIA LTDA | C93: financeiro@ennove.ind.br | D93: Priscila | E93: (16) 3413-7235
A94: SANTA ODILA | B94: PLACHE E PLACHE LTDA | C94: staodila@uol.com.br | D94: Bianca | E94: 19 98742-6560
A95: METROPOLIS | B95: UBERTI - COMERCIO DE MATERIAIS PARA CONSTRUÇÃO LTDA | C95: compras@webmetropolis.com.br | D95: Leticia | E95: 19 2138-3519
A96: LEDMOURA | B96: LED MOURA COMERCIAL ELETRICA E HIDRAULICA LTDA EPP | C96: luccas@ledmoura.com.br | D96: Luccas | E96: 19 99191-0025
A97: ARTEX | B97: GESSO ARTEX DECOR 53.875.813/0001-91 | D97: Artex | E97: 13 3458-3922 | F97: contato@gessoartexdecor.com | G97: GESSO ARTEX DECOR COMÉRCIO E PRESTAÇÃO DE SERVIÇOS LTDA
A98: RW SOLUÇÃO AMBIENTAL | B98: RW SOLUÇÃO AMBIENTAL LTDA | C98: rwcacambas@hotmail.com | D98: Valquiria | E98: 19 98116-8363
A99: CALHAS ENGENHEIRO | B99: C. FERREIRA DOS SANTOS COMÉRCIO E SERVIÇO | D99: Cirlene | E99: 11 95803-1004
A100: FERRONOR | B100: FERRONOR COMERCIO DE FERRO E ACO LTDA | C100: ferronor@ferronor.com.br | D100: Vivian | E100: 11 2223-3913
...

Sheet UNIDADES + ITENS
A1: ITEM | C1: UNID. | E1: FORMA DE PAGAMENTO
A2: FUNDAÇÃO / ESTRUTURA | C2: UNID. | E2: PIX
A3: COBERTURA / FORRO | C3: PEÇA | E3: BOLETO
A4: HIDRAULICA | C4: LATA | E4: CARTÃO
A5: ELETRICA | C5: GALÃO
A6: REVESTMENTO / PISO | C6: M
A7: VIDRO / CAIXILHARIA | C7: M2
A8: PINTURA | C8: JOGO
A9: INCENDIO | C9: CONJ.
A10: LOCAÇÃO | C10: VERBA
A11: OUTROS | C11: KG
C12: SACO
C13: ROLO
C14: PACOTE
C15: BARRICA
C16: BALDE
C17: M3
C18: BARRA

Sheet TOTAL GERAL
A1: OBRA | B1: ITEM | C1: TOTAL | D1: 45444 | E1: 45474 | F1: 45505 | G1: 45536 | H1: 45566 | I1: 45597 | J1: 45627 | K1: 45658
A2: =A3&"-"&"TOTAL" -> WALDEMAR RIGOTO - B&B-TOTAL | C2: =SUM(D2:L2) -> 0 | D2: =SUM(D3:D12) -> 0 | E2: =SUM(E3:E12) -> 0 | F2: =SUM(F3:F12) -> 0 | G2: =SUM(G3:G12) -> 0 | H2: =SUM(H3:H12) -> 0 | I2: =SUM(I3:I12) -> 0 | J2: =SUM(J3:J12) -> 0 | K2: =SUM(K3:K12) -> 0 | L2: =SUM(L3:L12) -> 0 | M2: OBRA FINALIZADA
A3: WALDEMAR RIGOTO - B&B | B3: FUNDAÇÃO / ESTRUTURA | D3: =SUMIFS(LANÇAMENTO!$L:$L,LANÇAMENTO!$B:$B,'TOTAL GERAL'!$A$3,LANÇAMENTO!$N:$N,'TOTAL GERAL'!$D$1,LANÇAMENTO!$D:$D,'TOTAL GERAL'!$B3) -> 0 | E3: =SUMIFS(LANÇAMENTO!$L:$L,LANÇAMENTO!$B:$B,'TOTAL GERAL'!$A$3,LANÇAMENTO!$N:$N,'TOTAL GERAL'!$E$1,LANÇAMENTO!$D:$D,'TOTAL GERAL'!$B3) -> 0 | F3: =SUMIFS(LANÇAMENTO!$L:$L,LANÇAMENTO!$B:$B,'TOTAL GERAL'!$A$3,LANÇAMENTO!$N:$N,'TOTAL GERAL'!$F$1,LANÇAMENTO!$D:$D,'TOTAL GERAL'!$B3) -> 0
B4: COBERTURA / FORRO | D4: =SUMIFS(LANÇAMENTO!$L:$L,LANÇAMENTO!$B:$B,'TOTAL GERAL'!$A$3,LANÇAMENTO!$N:$N,'TOTAL GERAL'!$D$1,LANÇAMENTO!$D:$D,'TOTAL GERAL'!$B4) -> 0 | E4: =SUMIFS(LANÇAMENTO!$L:$L,LANÇAMENTO!$B:$B,'TOTAL GERAL'!$A$3,LANÇAMENTO!$N:$N,'TOTAL GERAL'!$E$1,LANÇAMENTO!$D:$D,'TOTAL GERAL'!$B4) -> 0 | F4: =SUMIFS(LANÇAMENTO!$L:$L,LANÇAMENTO!$B:$B,'TOTAL GERAL'!$A$3,LANÇAMENTO!$N:$N,'TOTAL GERAL'!$F$1,LANÇAMENTO!$D:$D,'TOTAL GERAL'!$B4) -> 0
B5: HIDRAULICA | D5: =SUMIFS(LANÇAMENTO!$L:$L,LANÇAMENTO!$B:$B,'TOTAL GERAL'!$A$3,LANÇAMENTO!$N:$N,'TOTAL GERAL'!$D$1,LANÇAMENTO!$D:$D,'TOTAL GERAL'!$B5) -> 0 | E5: =SUMIFS(LANÇAMENTO!$L:$L,LANÇAMENTO!$B:$B,'TOTAL GERAL'!$A$3,LANÇAMENTO!$N:$N,'TOTAL GERAL'!$E$1,LANÇAMENTO!$D:$D,'TOTAL GERAL'!$B5) -> 0 | F5: =SUMIFS(LANÇAMENTO!$L:$L,LANÇAMENTO!$B:$B,'TOTAL GERAL'!$A$3,LANÇAMENTO!$N:$N,'TOTAL GERAL'!$F$1,LANÇAMENTO!$D:$D,'TOTAL GERAL'!$B5) -> 0
B6: ELETRICA | D6: =SUMIFS(LANÇAMENTO!$L:$L,LANÇAMENTO!$B:$B,'TOTAL GERAL'!$A$3,LANÇAMENTO!$N:$N,'TOTAL GERAL'!$D$1,LANÇAMENTO!$D:$D,'TOTAL GERAL'!$B6) -> 0 | E6: =SUMIFS(LANÇAMENTO!$L:$L,LANÇAMENTO!$B:$B,'TOTAL GERAL'!$A$3,LANÇAMENTO!$N:$N,'TOTAL GERAL'!$E$1,LANÇAMENTO!$D:$D,'TOTAL GERAL'!$B6) -> 0 | F6: =SUMIFS(LANÇAMENTO!$L:$L,LANÇAMENTO!$B:$B,'TOTAL GERAL'!$A$3,LANÇAMENTO!$N:$N,'TOTAL GERAL'!$F$1,LANÇAMENTO!$D:$D,'TOTAL GERAL'!$B6) -> 0
B7: REVESTMENTO / PISO | D7: =SUMIFS(LANÇAMENTO!$L:$L,LANÇAMENTO!$B:$B,'TOTAL GERAL'!$A$3,LANÇAMENTO!$N:$N,'TOTAL GERAL'!$D$1,LANÇAMENTO!$D:$D,'TOTAL GERAL'!$B7) -> 0 | E7: =SUMIFS(LANÇAMENTO!$L:$L,LANÇAMENTO!$B:$B,'TOTAL GERAL'!$A$3,LANÇAMENTO!$N:$N,'TOTAL GERAL'!$E$1,LANÇAMENTO!$D:$D,'TOTAL GERAL'!$B7) -> 0 | F7: =SUMIFS(LANÇAMENTO!$L:$L,LANÇAMENTO!$B:$B,'TOTAL GERAL'!$A$3,LANÇAMENTO!$N:$N,'TOTAL GERAL'!$F$1,LANÇAMENTO!$D:$D,'TOTAL GERAL'!$B7) -> 0
B8: VIDRO / CAIXILHARIA | D8: =SUMIFS(LANÇAMENTO!$L:$L,LANÇAMENTO!$B:$B,'TOTAL GERAL'!$A$3,LANÇAMENTO!$N:$N,'TOTAL GERAL'!$D$1,LANÇAMENTO!$D:$D,'TOTAL GERAL'!$B8) -> 0 | E8: =SUMIFS(LANÇAMENTO!$L:$L,LANÇAMENTO!$B:$B,'TOTAL GERAL'!$A$3,LANÇAMENTO!$N:$N,'TOTAL GERAL'!$E$1,LANÇAMENTO!$D:$D,'TOTAL GERAL'!$B8) -> 0 | F8: =SUMIFS(LANÇAMENTO!$L:$L,LANÇAMENTO!$B:$B,'TOTAL GERAL'!$A$3,LANÇAMENTO!$N:$N,'TOTAL GERAL'!$F$1,LANÇAMENTO!$D:$D,'TOTAL GERAL'!$B8) -> 0
B9: PINTURA | D9: =SUMIFS(LANÇAMENTO!$L:$L,LANÇAMENTO!$B:$B,'TOTAL GERAL'!$A$3,LANÇAMENTO!$N:$N,'TOTAL GERAL'!$D$1,LANÇAMENTO!$D:$D,'TOTAL GERAL'!$B9) -> 0 | E9: =SUMIFS(LANÇAMENTO!$L:$L,LANÇAMENTO!$B:$B,'TOTAL GERAL'!$A$3,LANÇAMENTO!$N:$N,'TOTAL GERAL'!$E$1,LANÇAMENTO!$D:$D,'TOTAL GERAL'!$B9) -> 0 | F9: =SUMIFS(LANÇAMENTO!$L:$L,LANÇAMENTO!$B:$B,'TOTAL GERAL'!$A$3,LANÇAMENTO!$N:$N,'TOTAL GERAL'!$F$1,LANÇAMENTO!$D:$D,'TOTAL GERAL'!$B9) -> 0
B10: INCENDIO | D10: =SUMIFS(LANÇAMENTO!$L:$L,LANÇAMENTO!$B:$B,'TOTAL GERAL'!$A$3,LANÇAMENTO!$N:$N,'TOTAL GERAL'!$D$1,LANÇAMENTO!$D:$D,'TOTAL GERAL'!$B10) -> 0 | E10: =SUMIFS(LANÇAMENTO!$L:$L,LANÇAMENTO!$B:$B,'TOTAL GERAL'!$A$3,LANÇAMENTO!$N:$N,'TOTAL GERAL'!$E$1,LANÇAMENTO!$D:$D,'TOTAL GERAL'!$B10) -> 0 | F10: =SUMIFS(LANÇAMENTO!$L:$L,LANÇAMENTO!$B:$B,'TOTAL GERAL'!$A$3,LANÇAMENTO!$N:$N,'TOTAL GERAL'!$F$1,LANÇAMENTO!$D:$D,'TOTAL GERAL'!$B10) -> 0
B11: LOCAÇÃO | D11: =SUMIFS(LANÇAMENTO!$L:$L,LANÇAMENTO!$B:$B,'TOTAL GERAL'!$A$3,LANÇAMENTO!$N:$N,'TOTAL GERAL'!$D$1,LANÇAMENTO!$D:$D,'TOTAL GERAL'!$B11) -> 0 | E11: =SUMIFS(LANÇAMENTO!$L:$L,LANÇAMENTO!$B:$B,'TOTAL GERAL'!$A$3,LANÇAMENTO!$N:$N,'TOTAL GERAL'!$E$1,LANÇAMENTO!$D:$D,'TOTAL GERAL'!$B11) -> 0 | F11: =SUMIFS(LANÇAMENTO!$L:$L,LANÇAMENTO!$B:$B,'TOTAL GERAL'!$A$3,LANÇAMENTO!$N:$N,'TOTAL GERAL'!$F$1,LANÇAMENTO!$D:$D,'TOTAL GERAL'!$B11) -> 0
B12: OUTROS | D12: =SUMIFS(LANÇAMENTO!$L:$L,LANÇAMENTO!$B:$B,'TOTAL GERAL'!$A$3,LANÇAMENTO!$N:$N,'TOTAL GERAL'!$D$1,LANÇAMENTO!$D:$D,'TOTAL GERAL'!$B12) -> 0 | E12: =SUMIFS(LANÇAMENTO!$L:$L,LANÇAMENTO!$B:$B,'TOTAL GERAL'!$A$3,LANÇAMENTO!$N:$N,'TOTAL GERAL'!$E$1,LANÇAMENTO!$D:$D,'TOTAL GERAL'!$B12) -> 0 | F12: =SUMIFS(LANÇAMENTO!$L:$L,LANÇAMENTO!$B:$B,'TOTAL GERAL'!$A$3,LANÇAMENTO!$N:$N,'TOTAL GERAL'!$F$1,LANÇAMENTO!$D:$D,'TOTAL GERAL'!$B12) -> 0
A13: =A14&"-"&"TOTAL" -> PEDRO COSTA - JB-TOTAL | C13: =SUM(F13:L13) -> 0 | F13: =SUM(F14:F23) -> 0 | G13: =SUM(G14:G23) -> 0 | H13: =SUM(H14:H23) -> 0 | I13: =SUM(I14:I23) -> 0 | J13: =SUM(J14:J23) -> 0 | K13: =SUM(K14:K23) -> 0 | L13: =SUM(L14:L23) -> 0 | N13: OK
A14: PEDRO COSTA - JB | B14: FUNDAÇÃO / ESTRUTURA | F14: =SUMIFS(LANÇAMENTO!$L:$L,LANÇAMENTO!$B:$B,'TOTAL GERAL'!$A$14,LANÇAMENTO!$N:$N,'TOTAL GERAL'!$F$1,LANÇAMENTO!$D:$D,'TOTAL GERAL'!$B14) -> 0 | G14: =SUMIFS(LANÇAMENTO!$L:$L,LANÇAMENTO!$B:$B,'TOTAL GERAL'!$A$14,LANÇAMENTO!$N:$N,'TOTAL GERAL'!$G$1,LANÇAMENTO!$D:$D,'TOTAL GERAL'!$B14) -> 0 | H14: =SUMIFS(LANÇAMENTO!$L:$L,LANÇAMENTO!$B:$B,'TOTAL GERAL'!$A$14,LANÇAMENTO!$N:$N,'TOTAL GERAL'!$H$1,LANÇAMENTO!$D:$D,'TOTAL GERAL'!$B14) -> 0
B15: COBERTURA / FORRO | F15: =SUMIFS(LANÇAMENTO!$L:$L,LANÇAMENTO!$B:$B,'TOTAL GERAL'!$A$14,LANÇAMENTO!$N:$N,'TOTAL GERAL'!$F$1,LANÇAMENTO!$D:$D,'TOTAL GERAL'!$B15) -> 0 | G15: =SUMIFS(LANÇAMENTO!$L:$L,LANÇAMENTO!$B:$B,'TOTAL GERAL'!$A$14,LANÇAMENTO!$N:$N,'TOTAL GERAL'!$G$1,LANÇAMENTO!$D:$D,'TOTAL GERAL'!$B15) -> 0 | H15: =SUMIFS(LANÇAMENTO!$L:$L,LANÇAMENTO!$B:$B,'TOTAL GERAL'!$A$14,LANÇAMENTO!$N:$N,'TOTAL GERAL'!$H$1,LANÇAMENTO!$D:$D,'TOTAL GERAL'!$B15) -> 0
B16: HIDRAULICA | F16: =SUMIFS(LANÇAMENTO!$L:$L,LANÇAMENTO!$B:$B,'TOTAL GERAL'!$A$14,LANÇAMENTO!$N:$N,'TOTAL GERAL'!$F$1,LANÇAMENTO!$D:$D,'TOTAL GERAL'!$B16) -> 0 | G16: =SUMIFS(LANÇAMENTO!$L:$L,LANÇAMENTO!$B:$B,'TOTAL GERAL'!$A$14,LANÇAMENTO!$N:$N,'TOTAL GERAL'!$G$1,LANÇAMENTO!$D:$D,'TOTAL GERAL'!$B16) -> 0 | H16: =SUMIFS(LANÇAMENTO!$L:$L,LANÇAMENTO!$B:$B,'TOTAL GERAL'!$A$14,LANÇAMENTO!$N:$N,'TOTAL GERAL'!$H$1,LANÇAMENTO!$D:$D,'TOTAL GERAL'!$B16) -> 0
B17: ELETRICA | F17: =SUMIFS(LANÇAMENTO!$L:$L,LANÇAMENTO!$B:$B,'TOTAL GERAL'!$A$14,LANÇAMENTO!$N:$N,'TOTAL GERAL'!$F$1,LANÇAMENTO!$D:$D,'TOTAL GERAL'!$B17) -> 0 | G17: =SUMIFS(LANÇAMENTO!$L:$L,LANÇAMENTO!$B:$B,'TOTAL GERAL'!$A$14,LANÇAMENTO!$N:$N,'TOTAL GERAL'!$G$1,LANÇAMENTO!$D:$D,'TOTAL GERAL'!$B17) -> 0 | H17: =SUMIFS(LANÇAMENTO!$L:$L,LANÇAMENTO!$B:$B,'TOTAL GERAL'!$A$14,LANÇAMENTO!$N:$N,'TOTAL GERAL'!$H$1,LANÇAMENTO!$D:$D,'TOTAL GERAL'!$B17) -> 0
B18: REVESTMENTO / PISO | F18: =SUMIFS(LANÇAMENTO!$L:$L,LANÇAMENTO!$B:$B,'TOTAL GERAL'!$A$14,LANÇAMENTO!$N:$N,'TOTAL GERAL'!$F$1,LANÇAMENTO!$D:$D,'TOTAL GERAL'!$B18) -> 0 | G18: =SUMIFS(LANÇAMENTO!$L:$L,LANÇAMENTO!$B:$B,'TOTAL GERAL'!$A$14,LANÇAMENTO!$N:$N,'TOTAL GERAL'!$G$1,LANÇAMENTO!$D:$D,'TOTAL GERAL'!$B18) -> 0 | H18: =SUMIFS(LANÇAMENTO!$L:$L,LANÇAMENTO!$B:$B,'TOTAL GERAL'!$A$14,LANÇAMENTO!$N:$N,'TOTAL GERAL'!$H$1,LANÇAMENTO!$D:$D,'TOTAL GERAL'!$B18) -> 0
B19: VIDRO / CAIXILHARIA | F19: =SUMIFS(LANÇAMENTO!$L:$L,LANÇAMENTO!$B:$B,'TOTAL GERAL'!$A$14,LANÇAMENTO!$N:$N,'TOTAL GERAL'!$F$1,LANÇAMENTO!$D:$D,'TOTAL GERAL'!$B19) -> 0 | G19: =SUMIFS(LANÇAMENTO!$L:$L,LANÇAMENTO!$B:$B,'TOTAL GERAL'!$A$14,LANÇAMENTO!$N:$N,'TOTAL GERAL'!$G$1,LANÇAMENTO!$D:$D,'TOTAL GERAL'!$B19) -> 0 | H19: =SUMIFS(LANÇAMENTO!$L:$L,LANÇAMENTO!$B:$B,'TOTAL GERAL'!$A$14,LANÇAMENTO!$N:$N,'TOTAL GERAL'!$H$1,LANÇAMENTO!$D:$D,'TOTAL GERAL'!$B19) -> 0
B20: PINTURA | F20: =SUMIFS(LANÇAMENTO!$L:$L,LANÇAMENTO!$B:$B,'TOTAL GERAL'!$A$14,LANÇAMENTO!$N:$N,'TOTAL GERAL'!$F$1,LANÇAMENTO!$D:$D,'TOTAL GERAL'!$B20) -> 0 | G20: =SUMIFS(LANÇAMENTO!$L:$L,LANÇAMENTO!$B:$B,'TOTAL GERAL'!$A$14,LANÇAMENTO!$N:$N,'TOTAL GERAL'!$G$1,LANÇAMENTO!$D:$D,'TOTAL GERAL'!$B20) -> 0 | H20: =SUMIFS(LANÇAMENTO!$L:$L,LANÇAMENTO!$B:$B,'TOTAL GERAL'!$A$14,LANÇAMENTO!$N:$N,'TOTAL GERAL'!$H$1,LANÇAMENTO!$D:$D,'TOTAL GERAL'!$B20) -> 0
B21: INCENDIO | F21: =SUMIFS(LANÇAMENTO!$L:$L,LANÇAMENTO!$B:$B,'TOTAL GERAL'!$A$14,LANÇAMENTO!$N:$N,'TOTAL GERAL'!$F$1,LANÇAMENTO!$D:$D,'TOTAL GERAL'!$B21) -> 0 | G21: =SUMIFS(LANÇAMENTO!$L:$L,LANÇAMENTO!$B:$B,'TOTAL GERAL'!$A$14,LANÇAMENTO!$N:$N,'TOTAL GERAL'!$G$1,LANÇAMENTO!$D:$D,'TOTAL GERAL'!$B21) -> 0 | H21: =SUMIFS(LANÇAMENTO!$L:$L,LANÇAMENTO!$B:$B,'TOTAL GERAL'!$A$14,LANÇAMENTO!$N:$N,'TOTAL GERAL'!$H$1,LANÇAMENTO!$D:$D,'TOTAL GERAL'!$B21) -> 0
B22: LOCAÇÃO | F22: =SUMIFS(LANÇAMENTO!$L:$L,LANÇAMENTO!$B:$B,'TOTAL GERAL'!$A$14,LANÇAMENTO!$N:$N,'TOTAL GERAL'!$F$1,LANÇAMENTO!$D:$D,'TOTAL GERAL'!$B22) -> 0 | G22: =SUMIFS(LANÇAMENTO!$L:$L,LANÇAMENTO!$B:$B,'TOTAL GERAL'!$A$14,LANÇAMENTO!$N:$N,'TOTAL GERAL'!$G$1,LANÇAMENTO!$D:$D,'TOTAL GERAL'!$B22) -> 0 | H22: =SUMIFS(LANÇAMENTO!$L:$L,LANÇAMENTO!$B:$B,'TOTAL GERAL'!$A$14,LANÇAMENTO!$N:$N,'TOTAL GERAL'!$H$1,LANÇAMENTO!$D:$D,'TOTAL GERAL'!$B22) -> 0
B23: OUTROS | F23: =SUMIFS(LANÇAMENTO!$L:$L,LANÇAMENTO!$B:$B,'TOTAL GERAL'!$A$14,LANÇAMENTO!$N:$N,'TOTAL GERAL'!$F$1,LANÇAMENTO!$D:$D,'TOTAL GERAL'!$B23) -> 0 | G23: =SUMIFS(LANÇAMENTO!$L:$L,LANÇAMENTO!$B:$B,'TOTAL GERAL'!$A$14,LANÇAMENTO!$N:$N,'TOTAL GERAL'!$G$1,LANÇAMENTO!$D:$D,'TOTAL GERAL'!$B23) -> 0 | H23: =SUMIFS(LANÇAMENTO!$L:$L,LANÇAMENTO!$B:$B,'TOTAL GERAL'!$A$14,LANÇAMENTO!$N:$N,'TOTAL GERAL'!$H$1,LANÇAMENTO!$D:$D,'TOTAL GERAL'!$B23) -> 0
A24: =A25&"-"&"TOTAL" -> BENEDITO TOLOSA - JB-TOTAL | C24: =SUM(F24:L24) -> 0 | F24: =SUM(F25:F34) -> 0 | G24: =SUM(G25:G34) -> 0 | H24: =SUM(H25:H34) -> 0 | I24: =SUM(I25:I34) -> 0 | J24: =SUM(J25:J34) -> 0 | K24: =SUM(K25:K34) -> 0 | L24: =SUM(L25:L34) -> 0 | N24: OK
A25: BENEDITO TOLOSA - JB | B25: FUNDAÇÃO / ESTRUTURA | F25: =SUMIFS(LANÇAMENTO!$L:$L,LANÇAMENTO!$B:$B,'TOTAL GERAL'!$A$25,LANÇAMENTO!$N:$N,'TOTAL GERAL'!$F$1,LANÇAMENTO!$D:$D,'TOTAL GERAL'!$B25) -> 0 | G25: =SUMIFS(LANÇAMENTO!$L:$L,LANÇAMENTO!$B:$B,'TOTAL GERAL'!$A$25,LANÇAMENTO!$N:$N,'TOTAL GERAL'!$G$1,LANÇAMENTO!$D:$D,'TOTAL GERAL'!$B25) -> 0 | H25: =SUMIFS(LANÇAMENTO!$L:$L,LANÇAMENTO!$B:$B,'TOTAL GERAL'!$A$25,LANÇAMENTO!$N:$N,'TOTAL GERAL'!$H$1,LANÇAMENTO!$D:$D,'TOTAL GERAL'!$B25) -> 0
B26: COBERTURA / FORRO | F26: =SUMIFS(LANÇAMENTO!$L:$L,LANÇAMENTO!$B:$B,'TOTAL GERAL'!$A$25,LANÇAMENTO!$N:$N,'TOTAL GERAL'!$F$1,LANÇAMENTO!$D:$D,'TOTAL GERAL'!$B26) -> 0 | G26: =SUMIFS(LANÇAMENTO!$L:$L,LANÇAMENTO!$B:$B,'TOTAL GERAL'!$A$25,LANÇAMENTO!$N:$N,'TOTAL GERAL'!$G$1,LANÇAMENTO!$D:$D,'TOTAL GERAL'!$B26) -> 0 | H26: =SUMIFS(LANÇAMENTO!$L:$L,LANÇAMENTO!$B:$B,'TOTAL GERAL'!$A$25,LANÇAMENTO!$N:$N,'TOTAL GERAL'!$H$1,LANÇAMENTO!$D:$D,'TOTAL GERAL'!$B26) -> 0
B27: HIDRAULICA | F27: =SUMIFS(LANÇAMENTO!$L:$L,LANÇAMENTO!$B:$B,'TOTAL GERAL'!$A$25,LANÇAMENTO!$N:$N,'TOTAL GERAL'!$F$1,LANÇAMENTO!$D:$D,'TOTAL GERAL'!$B27) -> 0 | G27: =SUMIFS(LANÇAMENTO!$L:$L,LANÇAMENTO!$B:$B,'TOTAL GERAL'!$A$25,LANÇAMENTO!$N:$N,'TOTAL GERAL'!G$1,LANÇAMENTO!$D:$D,'TOTAL GERAL'!$B27) -> 0 | H27: =SUMIFS(LANÇAMENTO!$L:$L,LANÇAMENTO!$B:$B,'TOTAL GERAL'!$A$25,LANÇAMENTO!$N:$N,'TOTAL GERAL'!H$1,LANÇAMENTO!$D:$D,'TOTAL GERAL'!$B27) -> 0
B28: ELETRICA | F28: =SUMIFS(LANÇAMENTO!$L:$L,LANÇAMENTO!$B:$B,'TOTAL GERAL'!$A$25,LANÇAMENTO!$N:$N,'TOTAL GERAL'!$F$1,LANÇAMENTO!$D:$D,'TOTAL GERAL'!$B28) -> 0 | G28: =SUMIFS(LANÇAMENTO!$L:$L,LANÇAMENTO!$B:$B,'TOTAL GERAL'!$A$25,LANÇAMENTO!$N:$N,'TOTAL GERAL'!$G$1,LANÇAMENTO!$D:$D,'TOTAL GERAL'!$B28) -> 0 | H28: =SUMIFS(LANÇAMENTO!$L:$L,LANÇAMENTO!$B:$B,'TOTAL GERAL'!$A$25,LANÇAMENTO!$N:$N,'TOTAL GERAL'!$H$1,LANÇAMENTO!$D:$D,'TOTAL GERAL'!$B28) -> 0
B29: REVESTMENTO / PISO | F29: =SUMIFS(LANÇAMENTO!$L:$L,LANÇAMENTO!$B:$B,'TOTAL GERAL'!$A$25,LANÇAMENTO!$N:$N,'TOTAL GERAL'!$F$1,LANÇAMENTO!$D:$D,'TOTAL GERAL'!$B29) -> 0 | G29: =SUMIFS(LANÇAMENTO!$L:$L,LANÇAMENTO!$B:$B,'TOTAL GERAL'!$A$25,LANÇAMENTO!$N:$N,'TOTAL GERAL'!$G$1,LANÇAMENTO!$D:$D,'TOTAL GERAL'!$B29) -> 0 | H29: =SUMIFS(LANÇAMENTO!$L:$L,LANÇAMENTO!$B:$B,'TOTAL GERAL'!$A$25,LANÇAMENTO!$N:$N,'TOTAL GERAL'!$H$1,LANÇAMENTO!$D:$D,'TOTAL GERAL'!$B29) -> 0
B30: VIDRO / CAIXILHARIA | F30: =SUMIFS(LANÇAMENTO!$L:$L,LANÇAMENTO!$B:$B,'TOTAL GERAL'!$A$25,LANÇAMENTO!$N:$N,'TOTAL GERAL'!$F$1,LANÇAMENTO!$D:$D,'TOTAL GERAL'!$B30) -> 0 | G30: =SUMIFS(LANÇAMENTO!$L:$L,LANÇAMENTO!$B:$B,'TOTAL GERAL'!$A$25,LANÇAMENTO!$N:$N,'TOTAL GERAL'!$G$1,LANÇAMENTO!$D:$D,'TOTAL GERAL'!$B30) -> 0 | H30: =SUMIFS(LANÇAMENTO!$L:$L,LANÇAMENTO!$B:$B,'TOTAL GERAL'!$A$25,LANÇAMENTO!$N:$N,'TOTAL GERAL'!$H$1,LANÇAMENTO!$D:$D,'TOTAL GERAL'!$B30) -> 0
B31: PINTURA | F31: =SUMIFS(LANÇAMENTO!$L:$L,LANÇAMENTO!$B:$B,'TOTAL GERAL'!$A$25,LANÇAMENTO!$N:$N,'TOTAL GERAL'!$F$1,LANÇAMENTO!$D:$D,'TOTAL GERAL'!$B31) -> 0 | G31: =SUMIFS(LANÇAMENTO!$L:$L,LANÇAMENTO!$B:$B,'TOTAL GERAL'!$A$25,LANÇAMENTO!$N:$N,'TOTAL GERAL'!$G$1,LANÇAMENTO!$D:$D,'TOTAL GERAL'!$B31) -> 0 | H31: =SUMIFS(LANÇAMENTO!$L:$L,LANÇAMENTO!$B:$B,'TOTAL GERAL'!$A$25,LANÇAMENTO!$N:$N,'TOTAL GERAL'!$H$1,LANÇAMENTO!$D:$D,'TOTAL GERAL'!$B31) -> 0
B32: INCENDIO | F32: =SUMIFS(LANÇAMENTO!$L:$L,LANÇAMENTO!$B:$B,'TOTAL GERAL'!$A$25,LANÇAMENTO!$N:$N,'TOTAL GERAL'!$F$1,LANÇAMENTO!$D:$D,'TOTAL GERAL'!$B32) -> 0 | G32: =SUMIFS(LANÇAMENTO!$L:$L,LANÇAMENTO!$B:$B,'TOTAL GERAL'!$A$25,LANÇAMENTO!$N:$N,'TOTAL GERAL'!$G$1,LANÇAMENTO!$D:$D,'TOTAL GERAL'!$B32) -> 0 | H32: =SUMIFS(LANÇAMENTO!$L:$L,LANÇAMENTO!$B:$B,'TOTAL GERAL'!$A$25,LANÇAMENTO!$N:$N,'TOTAL GERAL'!$H$1,LANÇAMENTO!$D:$D,'TOTAL GERAL'!$B32) -> 0
B33: LOCAÇÃO | F33: =SUMIFS(LANÇAMENTO!$L:$L,LANÇAMENTO!$B:$B,'TOTAL GERAL'!$A$25,LANÇAMENTO!$N:$N,'TOTAL GERAL'!$F$1,LANÇAMENTO!$D:$D,'TOTAL GERAL'!$B33) -> 0 | G33: =SUMIFS(LANÇAMENTO!$L:$L,LANÇAMENTO!$B:$B,'TOTAL GERAL'!$A$25,LANÇAMENTO!$N:$N,'TOTAL GERAL'!$G$1,LANÇAMENTO!$D:$D,'TOTAL GERAL'!$B33) -> 0 | H33: =SUMIFS(LANÇAMENTO!$L:$L,LANÇAMENTO!$B:$B,'TOTAL GERAL'!$A$25,LANÇAMENTO!$N:$N,'TOTAL GERAL'!$H$1,LANÇAMENTO!$D:$D,'TOTAL GERAL'!$B33) -> 0
B34: OUTROS | F34: =SUMIFS(LANÇAMENTO!$L:$L,LANÇAMENTO!$B:$B,'TOTAL GERAL'!$A$25,LANÇAMENTO!$N:$N,'TOTAL GERAL'!$F$1,LANÇAMENTO!$D:$D,'TOTAL GERAL'!$B34) -> 0 | G34: =SUMIFS(LANÇAMENTO!$L:$L,LANÇAMENTO!$B:$B,'TOTAL GERAL'!$A$25,LANÇAMENTO!$N:$N,'TOTAL GERAL'!$G$1,LANÇAMENTO!$D:$D,'TOTAL GERAL'!$B34) -> 0 | H34: =SUMIFS(LANÇAMENTO!$L:$L,LANÇAMENTO!$B:$B,'TOTAL GERAL'!$A$25,LANÇAMENTO!$N:$N,'TOTAL GERAL'!$H$1,LANÇAMENTO!$D:$D,'TOTAL GERAL'!$B34) -> 0
A35: =A36&"-"&"TOTAL" -> PEDRO BARROS-TOTAL | C35: =SUM(F35:L35) -> 0 | F35: =SUM(F36:F45) -> 0 | G35: =SUM(G36:G45) -> 0 | H35: =SUM(H36:H45) -> 0 | I35: =SUM(I36:I45) -> 0 | J35: =SUM(J36:J45) -> 0 | K35: =SUM(K36:K45) -> 0 | L35: =SUM(L36:L45) -> 0 | N35: OK
A36: PEDRO BARROS | B36: FUNDAÇÃO / ESTRUTURA | F36: =SUMIFS(LANÇAMENTO!$L:$L,LANÇAMENTO!$B:$B,'TOTAL GERAL'!$A$36,LANÇAMENTO!$N:$N,'TOTAL GERAL'!$F$1,LANÇAMENTO!$D:$D,'TOTAL GERAL'!$B36) -> 0 | G36: =SUMIFS(LANÇAMENTO!$L:$L,LANÇAMENTO!$B:$B,'TOTAL GERAL'!$A$36,LANÇAMENTO!$N:$N,'TOTAL GERAL'!$G$1,LANÇAMENTO!$D:$D,'TOTAL GERAL'!$B36) -> 0 | H36: =SUMIFS(LANÇAMENTO!$L:$L,LANÇAMENTO!$B:$B,'TOTAL GERAL'!$A$36,LANÇAMENTO!$N:$N,'TOTAL GERAL'!$H$1,LANÇAMENTO!$D:$D,'TOTAL GERAL'!$B36) -> 0
B37: COBERTURA / FORRO | F37: =SUMIFS(LANÇAMENTO!$L:$L,LANÇAMENTO!$B:$B,'TOTAL GERAL'!$A$36,LANÇAMENTO!$N:$N,'TOTAL GERAL'!$F$1,LANÇAMENTO!$D:$D,'TOTAL GERAL'!$B37) -> 0 | G37: =SUMIFS(LANÇAMENTO!$L:$L,LANÇAMENTO!$B:$B,'TOTAL GERAL'!$A$36,LANÇAMENTO!$N:$N,'TOTAL GERAL'!$G$1,LANÇAMENTO!$D:$D,'TOTAL GERAL'!$B37) -> 0 | H37: =SUMIFS(LANÇAMENTO!$L:$L,LANÇAMENTO!$B:$B,'TOTAL GERAL'!$A$36,LANÇAMENTO!$N:$N,'TOTAL GERAL'!$H$1,LANÇAMENTO!$D:$D,'TOTAL GERAL'!$B37) -> 0
B38: HIDRAULICA | F38: =SUMIFS(LANÇAMENTO!$L:$L,LANÇAMENTO!$B:$B,'TOTAL GERAL'!$A$36,LANÇAMENTO!$N:$N,'TOTAL GERAL'!$F$1,LANÇAMENTO!$D:$D,'TOTAL GERAL'!$B38) -> 0 | G38: =SUMIFS(LANÇAMENTO!$L:$L,LANÇAMENTO!$B:$B,'TOTAL GERAL'!$A$36,LANÇAMENTO!$N:$N,'TOTAL GERAL'!$G$1,LANÇAMENTO!$D:$D,'TOTAL GERAL'!$B38) -> 0 | H38: =SUMIFS(LANÇAMENTO!$L:$L,LANÇAMENTO!$B:$B,'TOTAL GERAL'!$A$36,LANÇAMENTO!$N:$N,'TOTAL GERAL'!$H$1,LANÇAMENTO!$D:$D,'TOTAL GERAL'!$B38) -> 0
B39: ELETRICA | F39: =SUMIFS(LANÇAMENTO!$L:$L,LANÇAMENTO!$B:$B,'TOTAL GERAL'!$A$36,LANÇAMENTO!$N:$N,'TOTAL GERAL'!$F$1,LANÇAMENTO!$D:$D,'TOTAL GERAL'!$B39) -> 0 | G39: =SUMIFS(LANÇAMENTO!$L:$L,LANÇAMENTO!$B:$B,'TOTAL GERAL'!$A$36,LANÇAMENTO!$N:$N,'TOTAL GERAL'!$G$1,LANÇAMENTO!$D:$D,'TOTAL GERAL'!$B39) -> 0 | H39: =SUMIFS(LANÇAMENTO!$L:$L,LANÇAMENTO!$B:$B,'TOTAL GERAL'!$A$36,LANÇAMENTO!$N:$N,'TOTAL GERAL'!$H$1,LANÇAMENTO!$D:$D,'TOTAL GERAL'!$B39) -> 0
B40: REVESTMENTO / PISO | F40: =SUMIFS(LANÇAMENTO!$L:$L,LANÇAMENTO!$B:$B,'TOTAL GERAL'!$A$36,LANÇAMENTO!$N:$N,'TOTAL GERAL'!$F$1,LANÇAMENTO!$D:$D,'TOTAL GERAL'!$B40) -> 0 | G40: =SUMIFS(LANÇAMENTO!$L:$L,LANÇAMENTO!$B:$B,'TOTAL GERAL'!$A$36,LANÇAMENTO!$N:$N,'TOTAL GERAL'!$G$1,LANÇAMENTO!$D:$D,'TOTAL GERAL'!$B40) -> 0 | H40: =SUMIFS(LANÇAMENTO!$L:$L,LANÇAMENTO!$B:$B,'TOTAL GERAL'!$A$36,LANÇAMENTO!$N:$N,'TOTAL GERAL'!$H$1,LANÇAMENTO!$D:$D,'TOTAL GERAL'!$B40) -> 0
B41: VIDRO / CAIXILHARIA | F41: =SUMIFS(LANÇAMENTO!$L:$L,LANÇAMENTO!$B:$B,'TOTAL GERAL'!$A$36,LANÇAMENTO!$N:$N,'TOTAL GERAL'!$F$1,LANÇAMENTO!$D:$D,'TOTAL GERAL'!$B41) -> 0 | G41: =SUMIFS(LANÇAMENTO!$L:$L,LANÇAMENTO!$B:$B,'TOTAL GERAL'!$A$36,LANÇAMENTO!$N:$N,'TOTAL GERAL'!$G$1,LANÇAMENTO!$D:$D,'TOTAL GERAL'!$B41) -> 0 | H41: =SUMIFS(LANÇAMENTO!$L:$L,LANÇAMENTO!$B:$B,'TOTAL GERAL'!$A$36,LANÇAMENTO!$N:$N,'TOTAL GERAL'!$H$1,LANÇAMENTO!$D:$D,'TOTAL GERAL'!$B41) -> 0
B42: PINTURA | F42: =SUMIFS(LANÇAMENTO!$L:$L,LANÇAMENTO!$B:$B,'TOTAL GERAL'!$A$36,LANÇAMENTO!$N:$N,'TOTAL GERAL'!$F$1,LANÇAMENTO!$D:$D,'TOTAL GERAL'!$B42) -> 0 | G42: =SUMIFS(LANÇAMENTO!$L:$L,LANÇAMENTO!$B:$B,'TOTAL GERAL'!$A$36,LANÇAMENTO!$N:$N,'TOTAL GERAL'!$G$1,LANÇAMENTO!$D:$D,'TOTAL GERAL'!$B42) -> 0 | H42: =SUMIFS(LANÇAMENTO!$L:$L,LANÇAMENTO!$B:$B,'TOTAL GERAL'!$A$36,LANÇAMENTO!$N:$N,'TOTAL GERAL'!$H$1,LANÇAMENTO!$D:$D,'TOTAL GERAL'!$B42) -> 0
B43: INCENDIO | F43: =SUMIFS(LANÇAMENTO!$L:$L,LANÇAMENTO!$B:$B,'TOTAL GERAL'!$A$36,LANÇAMENTO!$N:$N,'TOTAL GERAL'!$F$1,LANÇAMENTO!$D:$D,'TOTAL GERAL'!$B43) -> 0 | G43: =SUMIFS(LANÇAMENTO!$L:$L,LANÇAMENTO!$B:$B,'TOTAL GERAL'!$A$36,LANÇAMENTO!$N:$N,'TOTAL GERAL'!$G$1,LANÇAMENTO!$D:$D,'TOTAL GERAL'!$B43) -> 0 | H43: =SUMIFS(LANÇAMENTO!$L:$L,LANÇAMENTO!$B:$B,'TOTAL GERAL'!$A$36,LANÇAMENTO!$N:$N,'TOTAL GERAL'!$H$1,LANÇAMENTO!$D:$D,'TOTAL GERAL'!$B43) -> 0
B44: LOCAÇÃO | F44: =SUMIFS(LANÇAMENTO!$L:$L,LANÇAMENTO!$B:$B,'TOTAL GERAL'!$A$36,LANÇAMENTO!$N:$N,'TOTAL GERAL'!$F$1,LANÇAMENTO!$D:$D,'TOTAL GERAL'!$B44) -> 0 | G44: =SUMIFS(LANÇAMENTO!$L:$L,LANÇAMENTO!$B:$B,'TOTAL GERAL'!$A$36,LANÇAMENTO!$N:$N,'TOTAL GERAL'!$G$1,LANÇAMENTO!$D:$D,'TOTAL GERAL'!$B44) -> 0 | H44: =SUMIFS(LANÇAMENTO!$L:$L,LANÇAMENTO!$B:$B,'TOTAL GERAL'!$A$36,LANÇAMENTO!$N:$N,'TOTAL GERAL'!$H$1,LANÇAMENTO!$D:$D,'TOTAL GERAL'!$B44) -> 0
B45: OUTROS | F45: =SUMIFS(LANÇAMENTO!$L:$L,LANÇAMENTO!$B:$B,'TOTAL GERAL'!$A$36,LANÇAMENTO!$N:$N,'TOTAL GERAL'!$F$1,LANÇAMENTO!$D:$D,'TOTAL GERAL'!$B45) -> 0 | G45: =SUMIFS(LANÇAMENTO!$L:$L,LANÇAMENTO!$B:$B,'TOTAL GERAL'!$A$36,LANÇAMENTO!$N:$N,'TOTAL GERAL'!$G$1,LANÇAMENTO!$D:$D,'TOTAL GERAL'!$B45) -> 0 | H45: =SUMIFS(LANÇAMENTO!$L:$L,LANÇAMENTO!$B:$B,'TOTAL GERAL'!$A$36,LANÇAMENTO!$N:$N,'TOTAL GERAL'!$H$1,LANÇAMENTO!$D:$D,'TOTAL GERAL'!$B45) -> 0
A46: =A47&"-"&"TOTAL" -> ALDEIA CAPOEIRÃO-TOTAL | C46: =SUM(F46:L46) -> 0 | F46: =SUM(F47:F56) -> 0 | G46: =SUM(G47:G56) -> 0 | H46: =SUM(H47:H56) -> 0 | I46: =SUM(I47:I56) -> 0 | J46: =SUM(J47:J56) -> 0 | K46: =SUM(K47:K56) -> 0 | L46: =SUM(L47:L56) -> 0 | N46: OK
A47: ALDEIA CAPOEIRÃO | B47: FUNDAÇÃO / ESTRUTURA | F47: =SUMIFS(LANÇAMENTO!$L:$L,LANÇAMENTO!$B:$B,'TOTAL GERAL'!$A$47,LANÇAMENTO!$N:$N,'TOTAL GERAL'!$F$1,LANÇAMENTO!$D:$D,'TOTAL GERAL'!$B47) -> 0 | G47: =SUMIFS(LANÇAMENTO!$L:$L,LANÇAMENTO!$B:$B,'TOTAL GERAL'!$A$47,LANÇAMENTO!$N:$N,'TOTAL GERAL'!$G$1,LANÇAMENTO!$D:$D,'TOTAL GERAL'!$B47) -> 0 | H47: =SUMIFS(LANÇAMENTO!$L:$L,LANÇAMENTO!$B:$B,'TOTAL GERAL'!$A$47,LANÇAMENTO!$N:$N,'TOTAL GERAL'!$H$1,LANÇAMENTO!$D:$D,'TOTAL GERAL'!$B47) -> 0
B48: COBERTURA / FORRO | F48: =SUMIFS(LANÇAMENTO!$L:$L,LANÇAMENTO!$B:$B,'TOTAL GERAL'!$A$47,LANÇAMENTO!$N:$N,'TOTAL GERAL'!$F$1,LANÇAMENTO!$D:$D,'TOTAL GERAL'!$B48) -> 0 | G48: =SUMIFS(LANÇAMENTO!$L:$L,LANÇAMENTO!$B:$B,'TOTAL GERAL'!$A$47,LANÇAMENTO!$N:$N,'TOTAL GERAL'!$G$1,LANÇAMENTO!$D:$D,'TOTAL GERAL'!$B48) -> 0 | H48: =SUMIFS(LANÇAMENTO!$L:$L,LANÇAMENTO!$B:$B,'TOTAL GERAL'!$A$47,LANÇAMENTO!$N:$N,'TOTAL GERAL'!$H$1,LANÇAMENTO!$D:$D,'TOTAL GERAL'!$B48) -> 0
B49: HIDRAULICA | F49: =SUMIFS(LANÇAMENTO!$L:$L,LANÇAMENTO!$B:$B,'TOTAL GERAL'!$A$47,LANÇAMENTO!$N:$N,'TOTAL GERAL'!$F$1,LANÇAMENTO!$D:$D,'TOTAL GERAL'!$B49) -> 0 | G49: =SUMIFS(LANÇAMENTO!$L:$L,LANÇAMENTO!$B:$B,'TOTAL GERAL'!$A$47,LANÇAMENTO!$N:$N,'TOTAL GERAL'!$G$1,LANÇAMENTO!$D:$D,'TOTAL GERAL'!$B49) -> 0 | H49: =SUMIFS(LANÇAMENTO!$L:$L,LANÇAMENTO!$B:$B,'TOTAL GERAL'!$A$47,LANÇAMENTO!$N:$N,'TOTAL GERAL'!$H$1,LANÇAMENTO!$D:$D,'TOTAL GERAL'!$B49) -> 0
B50: ELETRICA | F50: =SUMIFS(LANÇAMENTO!$L:$L,LANÇAMENTO!$B:$B,'TOTAL GERAL'!$A$47,LANÇAMENTO!$N:$N,'TOTAL GERAL'!$F$1,LANÇAMENTO!$D:$D,'TOTAL GERAL'!$B50) -> 0 | G50: =SUMIFS(LANÇAMENTO!$L:$L,LANÇAMENTO!$B:$B,'TOTAL GERAL'!$A$47,LANÇAMENTO!$N:$N,'TOTAL GERAL'!$G$1,LANÇAMENTO!$D:$D,'TOTAL GERAL'!$B50) -> 0 | H50: =SUMIFS(LANÇAMENTO!$L:$L,LANÇAMENTO!$B:$B,'TOTAL GERAL'!$A$47,LANÇAMENTO!$N:$N,'TOTAL GERAL'!$H$1,LANÇAMENTO!$D:$D,'TOTAL GERAL'!$B50) -> 0
B51: REVESTMENTO / PISO | F51: =SUMIFS(LANÇAMENTO!$L:$L,LANÇAMENTO!$B:$B,'TOTAL GERAL'!$A$47,LANÇAMENTO!$N:$N,'TOTAL GERAL'!$F$1,LANÇAMENTO!$D:$D,'TOTAL GERAL'!$B51) -> 0 | G51: =SUMIFS(LANÇAMENTO!$L:$L,LANÇAMENTO!$B:$B,'TOTAL GERAL'!$A$47,LANÇAMENTO!$N:$N,'TOTAL GERAL'!$G$1,LANÇAMENTO!$D:$D,'TOTAL GERAL'!$B51) -> 0 | H51: =SUMIFS(LANÇAMENTO!$L:$L,LANÇAMENTO!$B:$B,'TOTAL GERAL'!$A$47,LANÇAMENTO!$N:$N,'TOTAL GERAL'!$H$1,LANÇAMENTO!$D:$D,'TOTAL GERAL'!$B51) -> 0
B52: VIDRO / CAIXILHARIA | F52: =SUMIFS(LANÇAMENTO!$L:$L,LANÇAMENTO!$B:$B,'TOTAL GERAL'!$A$47,LANÇAMENTO!$N:$N,'TOTAL GERAL'!$F$1,LANÇAMENTO!$D:$D,'TOTAL GERAL'!$B52) -> 0 | G52: =SUMIFS(LANÇAMENTO!$L:$L,LANÇAMENTO!$B:$B,'TOTAL GERAL'!$A$47,LANÇAMENTO!$N:$N,'TOTAL GERAL'!$G$1,LANÇAMENTO!$D:$D,'TOTAL GERAL'!$B52) -> 0 | H52: =SUMIFS(LANÇAMENTO!$L:$L,LANÇAMENTO!$B:$B,'TOTAL GERAL'!$A$47,LANÇAMENTO!$N:$N,'TOTAL GERAL'!$H$1,LANÇAMENTO!$D:$D,'TOTAL GERAL'!$B52) -> 0
B53: PINTURA | F53: =SUMIFS(LANÇAMENTO!$L:$L,LANÇAMENTO!$B:$B,'TOTAL GERAL'!$A$47,LANÇAMENTO!$N:$N,'TOTAL GERAL'!$F$1,LANÇAMENTO!$D:$D,'TOTAL GERAL'!$B53) -> 0 | G53: =SUMIFS(LANÇAMENTO!$L:$L,LANÇAMENTO!$B:$B,'TOTAL GERAL'!$A$47,LANÇAMENTO!$N:$N,'TOTAL GERAL'!$G$1,LANÇAMENTO!$D:$D,'TOTAL GERAL'!$B53) -> 0 | H53: =SUMIFS(LANÇAMENTO!$L:$L,LANÇAMENTO!$B:$B,'TOTAL GERAL'!$A$47,LANÇAMENTO!$N:$N,'TOTAL GERAL'!$H$1,LANÇAMENTO!$D:$D,'TOTAL GERAL'!$B53) -> 0
B54: INCENDIO | F54: =SUMIFS(LANÇAMENTO!$L:$L,LANÇAMENTO!$B:$B,'TOTAL GERAL'!$A$47,LANÇAMENTO!$N:$N,'TOTAL GERAL'!$F$1,LANÇAMENTO!$D:$D,'TOTAL GERAL'!$B54) -> 0 | G54: =SUMIFS(LANÇAMENTO!$L:$L,LANÇAMENTO!$B:$B,'TOTAL GERAL'!$A$47,LANÇAMENTO!$N:$N,'TOTAL GERAL'!$G$1,LANÇAMENTO!$D:$D,'TOTAL GERAL'!$B54) -> 0 | H54: =SUMIFS(LANÇAMENTO!$L:$L,LANÇAMENTO!$B:$B,'TOTAL GERAL'!$A$47,LANÇAMENTO!$N:$N,'TOTAL GERAL'!$H$1,LANÇAMENTO!$D:$D,'TOTAL GERAL'!$B54) -> 0
B55: LOCAÇÃO | F55: =SUMIFS(LANÇAMENTO!$L:$L,LANÇAMENTO!$B:$B,'TOTAL GERAL'!$A$47,LANÇAMENTO!$N:$N,'TOTAL GERAL'!$F$1,LANÇAMENTO!$D:$D,'TOTAL GERAL'!$B55) -> 0 | G55: =SUMIFS(LANÇAMENTO!$L:$L,LANÇAMENTO!$B:$B,'TOTAL GERAL'!$A$47,LANÇAMENTO!$N:$N,'TOTAL GERAL'!$G$1,LANÇAMENTO!$D:$D,'TOTAL GERAL'!$B55) -> 0 | H55: =SUMIFS(LANÇAMENTO!$L:$L,LANÇAMENTO!$B:$B,'TOTAL GERAL'!$A$47,LANÇAMENTO!$N:$N,'TOTAL GERAL'!$H$1,LANÇAMENTO!$D:$D,'TOTAL GERAL'!$B55) -> 0
B56: OUTROS | F56: =SUMIFS(LANÇAMENTO!$L:$L,LANÇAMENTO!$B:$B,'TOTAL GERAL'!$A$47,LANÇAMENTO!$N:$N,'TOTAL GERAL'!$F$1,LANÇAMENTO!$D:$D,'TOTAL GERAL'!$B56) -> 0 | G56: =SUMIFS(LANÇAMENTO!$L:$L,LANÇAMENTO!$B:$B,'TOTAL GERAL'!$A$47,LANÇAMENTO!$N:$N,'TOTAL GERAL'!$G$1,LANÇAMENTO!$D:$D,'TOTAL GERAL'!$B56) -> 0 | H56: =SUMIFS(LANÇAMENTO!$L:$L,LANÇAMENTO!$B:$B,'TOTAL GERAL'!$A$47,LANÇAMENTO!$N:$N,'TOTAL GERAL'!$H$1,LANÇAMENTO!$D:$D,'TOTAL GERAL'!$B56) -> 0
A57: =A58&"-"&"TOTAL" -> EE ITARIRI-TOTAL | C57: =SUM(D57:L57) -> 0 | D57: =SUM(D58:D67) -> 0 | E57: =SUM(E58:E67) -> 0 | F57: =SUM(F58:F67) -> 0 | G57: =SUM(G58:G67) -> 0 | H57: =SUM(H58:H67) -> 0 | I57: =SUM(I58:I67) -> 0 | J57: =SUM(J58:J67) -> 0 | K57: =SUM(K58:K67) -> 0 | L57: =SUM(L58:L67) -> 0
A58: EE ITARIRI | B58: FUNDAÇÃO / ESTRUTURA | D58: =SUMIFS(LANÇAMENTO!$L:$L,LANÇAMENTO!$B:$B,'TOTAL GERAL'!$A$58,LANÇAMENTO!$N:$N,'TOTAL GERAL'!$D$1,LANÇAMENTO!$D:$D,'TOTAL GERAL'!$B58) -> 0 | E58: =SUMIFS(LANÇAMENTO!$L:$L,LANÇAMENTO!$B:$B,'TOTAL GERAL'!$A$58,LANÇAMENTO!$N:$N,'TOTAL GERAL'!$E$1,LANÇAMENTO!$D:$D,'TOTAL GERAL'!$B58) -> 0 | F58: =SUMIFS(LANÇAMENTO!$L:$L,LANÇAMENTO!$B:$B,'TOTAL GERAL'!$A$58,LANÇAMENTO!$N:$N,'TOTAL GERAL'!$F$1,LANÇAMENTO!$D:$D,'TOTAL GERAL'!$B58) -> 0 | G58: =SUMIFS(LANÇAMENTO!$L:$L,LANÇAMENTO!$B:$B,'TOTAL GERAL'!$A$58,LANÇAMENTO!$N:$N,'TOTAL GERAL'!$G$1,LANÇAMENTO!$D:$D,'TOTAL GERAL'!$B58) -> 0 | H58: =SUMIFS(LANÇAMENTO!$L:$L,LANÇAMENTO!$B:$B,'TOTAL GERAL'!$A$58,LANÇAMENTO!$N:$N,'TOTAL GERAL'!$H$1,LANÇAMENTO!$D:$D,'TOTAL GERAL'!$B58) -> 0
B59: COBERTURA / FORRO | D59: =SUMIFS(LANÇAMENTO!$L:$L,LANÇAMENTO!$B:$B,'TOTAL GERAL'!$A$58,LANÇAMENTO!$N:$N,'TOTAL GERAL'!$D$1,LANÇAMENTO!$D:$D,'TOTAL GERAL'!$B59) -> 0 | E59: =SUMIFS(LANÇAMENTO!$L:$L,LANÇAMENTO!$B:$B,'TOTAL GERAL'!$A$58,LANÇAMENTO!$N:$N,'TOTAL GERAL'!$E$1,LANÇAMENTO!$D:$D,'TOTAL GERAL'!$B59) -> 0 | F59: =SUMIFS(LANÇAMENTO!$L:$L,LANÇAMENTO!$B:$B,'TOTAL GERAL'!$A$58,LANÇAMENTO!$N:$N,'TOTAL GERAL'!$F$1,LANÇAMENTO!$D:$D,'TOTAL GERAL'!$B59) -> 0 | G59: =SUMIFS(LANÇAMENTO!$L:$L,LANÇAMENTO!$B:$B,'TOTAL GERAL'!$A$58,LANÇAMENTO!$N:$N,'TOTAL GERAL'!$G$1,LANÇAMENTO!$D:$D,'TOTAL GERAL'!$B59) -> 0 | H59: =SUMIFS(LANÇAMENTO!$L:$L,LANÇAMENTO!$B:$B,'TOTAL GERAL'!$A$58,LANÇAMENTO!$N:$N,'TOTAL GERAL'!$H$1,LANÇAMENTO!$D:$D,'TOTAL GERAL'!$B59) -> 0
B60: HIDRAULICA | D60: =SUMIFS(LANÇAMENTO!$L:$L,LANÇAMENTO!$B:$B,'TOTAL GERAL'!$A$58,LANÇAMENTO!$N:$N,'TOTAL GERAL'!$D$1,LANÇAMENTO!$D:$D,'TOTAL GERAL'!$B60) -> 0 | E60: =SUMIFS(LANÇAMENTO!$L:$L,LANÇAMENTO!$B:$B,'TOTAL GERAL'!$A$58,LANÇAMENTO!$N:$N,'TOTAL GERAL'!$E$1,LANÇAMENTO!$D:$D,'TOTAL GERAL'!$B60) -> 0 | F60: =SUMIFS(LANÇAMENTO!$L:$L,LANÇAMENTO!$B:$B,'TOTAL GERAL'!$A$58,LANÇAMENTO!$N:$N,'TOTAL GERAL'!$F$1,LANÇAMENTO!$D:$D,'TOTAL GERAL'!$B60) -> 0 | G60: =SUMIFS(LANÇAMENTO!$L:$L,LANÇAMENTO!$B:$B,'TOTAL GERAL'!$A$58,LANÇAMENTO!$N:$N,'TOTAL GERAL'!$G$1,LANÇAMENTO!$D:$D,'TOTAL GERAL'!$B60) -> 0 | H60: =SUMIFS(LANÇAMENTO!$L:$L,LANÇAMENTO!$B:$B,'TOTAL GERAL'!$A$58,LANÇAMENTO!$N:$N,'TOTAL GERAL'!$H$1,LANÇAMENTO!$D:$D,'TOTAL GERAL'!$B60) -> 0
B61: ELETRICA | D61: =SUMIFS(LANÇAMENTO!$L:$L,LANÇAMENTO!$B:$B,'TOTAL GERAL'!$A$58,LANÇAMENTO!$N:$N,'TOTAL GERAL'!$D$1,LANÇAMENTO!$D:$D,'TOTAL GERAL'!$B61) -> 0 | E61: =SUMIFS(LANÇAMENTO!$L:$L,LANÇAMENTO!$B:$B,'TOTAL GERAL'!$A$58,LANÇAMENTO!$N:$N,'TOTAL GERAL'!$E$1,LANÇAMENTO!$D:$D,'TOTAL GERAL'!$B61) -> 0 | F61: =SUMIFS(LANÇAMENTO!$L:$L,LANÇAMENTO!$B:$B,'TOTAL GERAL'!$A$58,LANÇAMENTO!$N:$N,'TOTAL GERAL'!$F$1,LANÇAMENTO!$D:$D,'TOTAL GERAL'!$B61) -> 0 | G61: =SUMIFS(LANÇAMENTO!$L:$L,LANÇAMENTO!$B:$B,'TOTAL GERAL'!$A$58,LANÇAMENTO!$N:$N,'TOTAL GERAL'!$G$1,LANÇAMENTO!$D:$D,'TOTAL GERAL'!$B61) -> 0 | H61: =SUMIFS(LANÇAMENTO!$L:$L,LANÇAMENTO!$B:$B,'TOTAL GERAL'!$A$58,LANÇAMENTO!$N:$N,'TOTAL GERAL'!$H$1,LANÇAMENTO!$D:$D,'TOTAL GERAL'!$B61) -> 0
B62: REVESTMENTO / PISO | D62: =SUMIFS(LANÇAMENTO!$L:$L,LANÇAMENTO!$B:$B,'TOTAL GERAL'!$A$58,LANÇAMENTO!$N:$N,'TOTAL GERAL'!$D$1,LANÇAMENTO!$D:$D,'TOTAL GERAL'!$B62) -> 0 | E62: =SUMIFS(LANÇAMENTO!$L:$L,LANÇAMENTO!$B:$B,'TOTAL GERAL'!$A$58,LANÇAMENTO!$N:$N,'TOTAL GERAL'!$E$1,LANÇAMENTO!$D:$D,'TOTAL GERAL'!$B62) -> 0 | F62: =SUMIFS(LANÇAMENTO!$L:$L,LANÇAMENTO!$B:$B,'TOTAL GERAL'!$A$58,LANÇAMENTO!$N:$N,'TOTAL GERAL'!$F$1,LANÇAMENTO!$D:$D,'TOTAL GERAL'!$B62) -> 0 | G62: =SUMIFS(LANÇAMENTO!$L:$L,LANÇAMENTO!$B:$B,'TOTAL GERAL'!$A$58,LANÇAMENTO!$N:$N,'TOTAL GERAL'!$G$1,LANÇAMENTO!$D:$D,'TOTAL GERAL'!$B62) -> 0 | H62: =SUMIFS(LANÇAMENTO!$L:$L,LANÇAMENTO!$B:$B,'TOTAL GERAL'!$A$58,LANÇAMENTO!$N:$N,'TOTAL GERAL'!$H$1,LANÇAMENTO!$D:$D,'TOTAL GERAL'!$B62) -> 0
B63: VIDRO / CAIXILHARIA | D63: =SUMIFS(LANÇAMENTO!$L:$L,LANÇAMENTO!$B:$B,'TOTAL GERAL'!$A$58,LANÇAMENTO!$N:$N,'TOTAL GERAL'!$D$1,LANÇAMENTO!$D:$D,'TOTAL GERAL'!$B63) -> 0 | E63: =SUMIFS(LANÇAMENTO!$L:$L,LANÇAMENTO!$B:$B,'TOTAL GERAL'!$A$58,LANÇAMENTO!$N:$N,'TOTAL GERAL'!$E$1,LANÇAMENTO!$D:$D,'TOTAL GERAL'!$B63) -> 0 | F63: =SUMIFS(LANÇAMENTO!$L:$L,LANÇAMENTO!$B:$B,'TOTAL GERAL'!$A$58,LANÇAMENTO!$N:$N,'TOTAL GERAL'!$F$1,LANÇAMENTO!$D:$D,'TOTAL GERAL'!$B63) -> 0 | G63: =SUMIFS(LANÇAMENTO!$L:$L,LANÇAMENTO!$B:$B,'TOTAL GERAL'!$A$58,LANÇAMENTO!$N:$N,'TOTAL GERAL'!$G$1,LANÇAMENTO!$D:$D,'TOTAL GERAL'!$B63) -> 0 | H63: =SUMIFS(LANÇAMENTO!$L:$L,LANÇAMENTO!$B:$B,'TOTAL GERAL'!$A$58,LANÇAMENTO!$N:$N,'TOTAL GERAL'!$H$1,LANÇAMENTO!$D:$D,'TOTAL GERAL'!$B63) -> 0
B64: PINTURA | D64: =SUMIFS(LANÇAMENTO!$L:$L,LANÇAMENTO!$B:$B,'TOTAL GERAL'!$A$58,LANÇAMENTO!$N:$N,'TOTAL GERAL'!$D$1,LANÇAMENTO!$D:$D,'TOTAL GERAL'!$B64) -> 0 | E64: =SUMIFS(LANÇAMENTO!$L:$L,LANÇAMENTO!$B:$B,'TOTAL GERAL'!$A$58,LANÇAMENTO!$N:$N,'TOTAL GERAL'!$E$1,LANÇAMENTO!$D:$D,'TOTAL GERAL'!$B64) -> 0 | F64: =SUMIFS(LANÇAMENTO!$L:$L,LANÇAMENTO!$B:$B,'TOTAL GERAL'!$A$58,LANÇAMENTO!$N:$N,'TOTAL GERAL'!$F$1,LANÇAMENTO!$D:$D,'TOTAL GERAL'!$B64) -> 0 | G64: =SUMIFS(LANÇAMENTO!$L:$L,LANÇAMENTO!$B:$B,'TOTAL GERAL'!$A$58,LANÇAMENTO!$N:$N,'TOTAL GERAL'!$G$1,LANÇAMENTO!$D:$D,'TOTAL GERAL'!$B64) -> 0 | H64: =SUMIFS(LANÇAMENTO!$L:$L,LANÇAMENTO!$B:$B,'TOTAL GERAL'!$A$58,LANÇAMENTO!$N:$N,'TOTAL GERAL'!$H$1,LANÇAMENTO!$D:$D,'TOTAL GERAL'!$B64) -> 0
B65: INCENDIO | D65: =SUMIFS(LANÇAMENTO!$L:$L,LANÇAMENTO!$B:$B,'TOTAL GERAL'!$A$58,LANÇAMENTO!$N:$N,'TOTAL GERAL'!$D$1,LANÇAMENTO!$D:$D,'TOTAL GERAL'!$B65) -> 0 | E65: =SUMIFS(LANÇAMENTO!$L:$L,LANÇAMENTO!$B:$B,'TOTAL GERAL'!$A$58,LANÇAMENTO!$N:$N,'TOTAL GERAL'!$E$1,LANÇAMENTO!$D:$D,'TOTAL GERAL'!$B65) -> 0 | F65: =SUMIFS(LANÇAMENTO!$L:$L,LANÇAMENTO!$B:$B,'TOTAL GERAL'!$A$58,LANÇAMENTO!$N:$N,'TOTAL GERAL'!$F$1,LANÇAMENTO!$D:$D,'TOTAL GERAL'!$B65) -> 0 | G65: =SUMIFS(LANÇAMENTO!$L:$L,LANÇAMENTO!$B:$B,'TOTAL GERAL'!$A$58,LANÇAMENTO!$N:$N,'TOTAL GERAL'!$G$1,LANÇAMENTO!$D:$D,'TOTAL GERAL'!$B65) -> 0 | H65: =SUMIFS(LANÇAMENTO!$L:$L,LANÇAMENTO!$B:$B,'TOTAL GERAL'!$A$58,LANÇAMENTO!$N:$N,'TOTAL GERAL'!$H$1,LANÇAMENTO!$D:$D,'TOTAL GERAL'!$B65) -> 0
B66: LOCAÇÃO | D66: =SUMIFS(LANÇAMENTO!$L:$L,LANÇAMENTO!$B:$B,'TOTAL GERAL'!$A$58,LANÇAMENTO!$N:$N,'TOTAL GERAL'!$D$1,LANÇAMENTO!$D:$D,'TOTAL GERAL'!$B66) -> 0 | E66: =SUMIFS(LANÇAMENTO!$L:$L,LANÇAMENTO!$B:$B,'TOTAL GERAL'!$A$58,LANÇAMENTO!$N:$N,'TOTAL GERAL'!$E$1,LANÇAMENTO!$D:$D,'TOTAL GERAL'!$B66) -> 0 | F66: =SUMIFS(LANÇAMENTO!$L:$L,LANÇAMENTO!$B:$B,'TOTAL GERAL'!$A$58,LANÇAMENTO!$N:$N,'TOTAL GERAL'!$F$1,LANÇAMENTO!$D:$D,'TOTAL GERAL'!$B66) -> 0 | G66: =SUMIFS(LANÇAMENTO!$L:$L,LANÇAMENTO!$B:$B,'TOTAL GERAL'!$A$58,LANÇAMENTO!$N:$N,'TOTAL GERAL'!$G$1,LANÇAMENTO!$D:$D,'TOTAL GERAL'!$B66) -> 0 | H66: =SUMIFS(LANÇAMENTO!$L:$L,LANÇAMENTO!$B:$B,'TOTAL GERAL'!$A$58,LANÇAMENTO!$N:$N,'TOTAL GERAL'!$H$1,LANÇAMENTO!$D:$D,'TOTAL GERAL'!$B66) -> 0
B67: OUTROS | D67: =SUMIFS(LANÇAMENTO!$L:$L,LANÇAMENTO!$B:$B,'TOTAL GERAL'!$A$58,LANÇAMENTO!$N:$N,'TOTAL GERAL'!$D$1,LANÇAMENTO!$D:$D,'TOTAL GERAL'!$B67) -> 0 | E67: =SUMIFS(LANÇAMENTO!$L:$L,LANÇAMENTO!$B:$B,'TOTAL GERAL'!$A$58,LANÇAMENTO!$N:$N,'TOTAL GERAL'!$E$1,LANÇAMENTO!$D:$D,'TOTAL GERAL'!$B67) -> 0 | F67: =SUMIFS(LANÇAMENTO!$L:$L,LANÇAMENTO!$B:$B,'TOTAL GERAL'!$A$58,LANÇAMENTO!$N:$N,'TOTAL GERAL'!$F$1,LANÇAMENTO!$D:$D,'TOTAL GERAL'!$B67) -> 0 | G67: =SUMIFS(LANÇAMENTO!$L:$L,LANÇAMENTO!$B:$B,'TOTAL GERAL'!$A$58,LANÇAMENTO!$N:$N,'TOTAL GERAL'!$G$1,LANÇAMENTO!$D:$D,'TOTAL GERAL'!$B67) -> 0 | H67: =SUMIFS(LANÇAMENTO!$L:$L,LANÇAMENTO!$B:$B,'TOTAL GERAL'!$A$58,LANÇAMENTO!$N:$N,'TOTAL GERAL'!$H$1,LANÇAMENTO!$D:$D,'TOTAL GERAL'!$B67) -> 0
A68: =A69&"-"&"TOTAL" -> EE GODOFREDO FURTADO - JB-TOTAL | C68: =SUM(D68:L68) -> 0 | D68: =SUM(D69:D78) -> 0 | E68: =SUM(E69:E78) -> 0 | F68: =SUM(F69:F78) -> 0 | G68: =SUM(G69:G78) -> 0 | H68: =SUM(H69:H78) -> 0 | I68: =SUM(I69:I78) -> 0 | J68: =SUM(J69:J78) -> 0 | K68: =SUM(K69:K78) -> 0 | L68: =SUM(L69:L78) -> 0
A69: EE GODOFREDO FURTADO - JB | B69: FUNDAÇÃO / ESTRUTURA | D69: =SUMIFS(LANÇAMENTO!$L:$L,LANÇAMENTO!$B:$B,'TOTAL GERAL'!$A$69,LANÇAMENTO!$N:$N,'TOTAL GERAL'!$D$1,LANÇAMENTO!$D:$D,'TOTAL GERAL'!$B69) -> 0 | E69: =SUMIFS(LANÇAMENTO!$L:$L,LANÇAMENTO!$B:$B,'TOTAL GERAL'!$A$69,LANÇAMENTO!$N:$N,'TOTAL GERAL'!$E$1,LANÇAMENTO!$D:$D,'TOTAL GERAL'!$B69) -> 0 | F69: =SUMIFS(LANÇAMENTO!$L:$L,LANÇAMENTO!$B:$B,'TOTAL GERAL'!$A$69,LANÇAMENTO!$N:$N,'TOTAL GERAL'!$F$1,LANÇAMENTO!$D:$D,'TOTAL GERAL'!$B69) -> 0 | G69: =SUMIFS(LANÇAMENTO!$L:$L,LANÇAMENTO!$B:$B,'TOTAL GERAL'!$A$69,LANÇAMENTO!$N:$N,'TOTAL GERAL'!$G$1,LANÇAMENTO!$D:$D,'TOTAL GERAL'!$B69) -> 0 | H69: =SUMIFS(LANÇAMENTO!$L:$L,LANÇAMENTO!$B:$B,'TOTAL GERAL'!$A$69,LANÇAMENTO!$N:$N,'TOTAL GERAL'!$H$1,LANÇAMENTO!$D:$D,'TOTAL GERAL'!$B69) -> 0
B70: COBERTURA / FORRO | D70: =SUMIFS(LANÇAMENTO!$L:$L,LANÇAMENTO!$B:$B,'TOTAL GERAL'!$A$69,LANÇAMENTO!$N:$N,'TOTAL GERAL'!$D$1,LANÇAMENTO!$D:$D,'TOTAL GERAL'!$B70) -> 0 | E70: =SUMIFS(LANÇAMENTO!$L:$L,LANÇAMENTO!$B:$B,'TOTAL GERAL'!$A$69,LANÇAMENTO!$N:$N,'TOTAL GERAL'!$E$1,LANÇAMENTO!$D:$D,'TOTAL GERAL'!$B70) -> 0 | F70: =SUMIFS(LANÇAMENTO!$L:$L,LANÇAMENTO!$B:$B,'TOTAL GERAL'!$A$69,LANÇAMENTO!$N:$N,'TOTAL GERAL'!$F$1,LANÇAMENTO!$D:$D,'TOTAL GERAL'!$B70) -> 0 | G70: =SUMIFS(LANÇAMENTO!$L:$L,LANÇAMENTO!$B:$B,'TOTAL GERAL'!$A$69,LANÇAMENTO!$N:$N,'TOTAL GERAL'!$G$1,LANÇAMENTO!$D:$D,'TOTAL GERAL'!$B70) -> 0 | H70: =SUMIFS(LANÇAMENTO!$L:$L,LANÇAMENTO!$B:$B,'TOTAL GERAL'!$A$69,LANÇAMENTO!$N:$N,'TOTAL GERAL'!$H$1,LANÇAMENTO!$D:$D,'TOTAL GERAL'!$B70) -> 0
B71: HIDRAULICA | D71: =SUMIFS(LANÇAMENTO!$L:$L,LANÇAMENTO!$B:$B,'TOTAL GERAL'!$A$69,LANÇAMENTO!$N:$N,'TOTAL GERAL'!$D$1,LANÇAMENTO!$D:$D,'TOTAL GERAL'!$B71) -> 0 | E71: =SUMIFS(LANÇAMENTO!$L:$L,LANÇAMENTO!$B:$B,'TOTAL GERAL'!$A$69,LANÇAMENTO!$N:$N,'TOTAL GERAL'!$E$1,LANÇAMENTO!$D:$D,'TOTAL GERAL'!$B71) -> 0 | F71: =SUMIFS(LANÇAMENTO!$L:$L,LANÇAMENTO!$B:$B,'TOTAL GERAL'!$A$69,LANÇAMENTO!$N:$N,'TOTAL GERAL'!$F$1,LANÇAMENTO!$D:$D,'TOTAL GERAL'!$B71) -> 0 | G71: =SUMIFS(LANÇAMENTO!$L:$L,LANÇAMENTO!$B:$B,'TOTAL GERAL'!$A$69,LANÇAMENTO!$N:$N,'TOTAL GERAL'!$G$1,LANÇAMENTO!$D:$D,'TOTAL GERAL'!$B71) -> 0 | H71: =SUMIFS(LANÇAMENTO!$L:$L,LANÇAMENTO!$B:$B,'TOTAL GERAL'!$A$69,LANÇAMENTO!$N:$N,'TOTAL GERAL'!$H$1,LANÇAMENTO!$D:$D,'TOTAL GERAL'!$B71) -> 0
B72: ELETRICA | D72: =SUMIFS(LANÇAMENTO!$L:$L,LANÇAMENTO!$B:$B,'TOTAL GERAL'!$A$69,LANÇAMENTO!$N:$N,'TOTAL GERAL'!$D$1,LANÇAMENTO!$D:$D,'TOTAL GERAL'!$B72) -> 0 | E72: =SUMIFS(LANÇAMENTO!$L:$L,LANÇAMENTO!$B:$B,'TOTAL GERAL'!$A$69,LANÇAMENTO!$N:$N,'TOTAL GERAL'!$E$1,LANÇAMENTO!$D:$D,'TOTAL GERAL'!$B72) -> 0 | F72: =SUMIFS(LANÇAMENTO!$L:$L,LANÇAMENTO!$B:$B,'TOTAL GERAL'!$A$69,LANÇAMENTO!$N:$N,'TOTAL GERAL'!$F$1,LANÇAMENTO!$D:$D,'TOTAL GERAL'!$B72) -> 0 | G72: =SUMIFS(LANÇAMENTO!$L:$L,LANÇAMENTO!$B:$B,'TOTAL GERAL'!$A$69,LANÇAMENTO!$N:$N,'TOTAL GERAL'!$G$1,LANÇAMENTO!$D:$D,'TOTAL GERAL'!$B72) -> 0 | H72: =SUMIFS(LANÇAMENTO!$L:$L,LANÇAMENTO!$B:$B,'TOTAL GERAL'!$A$69,LANÇAMENTO!$N:$N,'TOTAL GERAL'!$H$1,LANÇAMENTO!$D:$D,'TOTAL GERAL'!$B72) -> 0
B73: REVESTMENTO / PISO | D73: =SUMIFS(LANÇAMENTO!$L:$L,LANÇAMENTO!$B:$B,'TOTAL GERAL'!$A$69,LANÇAMENTO!$N:$N,'TOTAL GERAL'!$D$1,LANÇAMENTO!$D:$D,'TOTAL GERAL'!$B73) -> 0 | E73: =SUMIFS(LANÇAMENTO!$L:$L,LANÇAMENTO!$B:$B,'TOTAL GERAL'!$A$69,LANÇAMENTO!$N:$N,'TOTAL GERAL'!$E$1,LANÇAMENTO!$D:$D,'TOTAL GERAL'!$B73) -> 0 | F73: =SUMIFS(LANÇAMENTO!$L:$L,LANÇAMENTO!$B:$B,'TOTAL GERAL'!$A$69,LANÇAMENTO!$N:$N,'TOTAL GERAL'!$F$1,LANÇAMENTO!$D:$D,'TOTAL GERAL'!$B73) -> 0 | G73: =SUMIFS(LANÇAMENTO!$L:$L,LANÇAMENTO!$B:$B,'TOTAL GERAL'!$A$69,LANÇAMENTO!$N:$N,'TOTAL GERAL'!$G$1,LANÇAMENTO!$D:$D,'TOTAL GERAL'!$B73) -> 0 | H73: =SUMIFS(LANÇAMENTO!$L:$L,LANÇAMENTO!$B:$B,'TOTAL GERAL'!$A$69,LANÇAMENTO!$N:$N,'TOTAL GERAL'!$H$1,LANÇAMENTO!$D:$D,'TOTAL GERAL'!$B73) -> 0
B74: VIDRO / CAIXILHARIA | D74: =SUMIFS(LANÇAMENTO!$L:$L,LANÇAMENTO!$B:$B,'TOTAL GERAL'!$A$69,LANÇAMENTO!$N:$N,'TOTAL GERAL'!$D$1,LANÇAMENTO!$D:$D,'TOTAL GERAL'!$B74) -> 0 | E74: =SUMIFS(LANÇAMENTO!$L:$L,LANÇAMENTO!$B:$B,'TOTAL GERAL'!$A$69,LANÇAMENTO!$N:$N,'TOTAL GERAL'!$E$1,LANÇAMENTO!$D:$D,'TOTAL GERAL'!$B74) -> 0 | F74: =SUMIFS(LANÇAMENTO!$L:$L,LANÇAMENTO!$B:$B,'TOTAL GERAL'!$A$69,LANÇAMENTO!$N:$N,'TOTAL GERAL'!$F$1,LANÇAMENTO!$D:$D,'TOTAL GERAL'!$B74) -> 0 | G74: =SUMIFS(LANÇAMENTO!$L:$L,LANÇAMENTO!$B:$B,'TOTAL GERAL'!$A$69,LANÇAMENTO!$N:$N,'TOTAL GERAL'!$G$1,LANÇAMENTO!$D:$D,'TOTAL GERAL'!$B74) -> 0 | H74: =SUMIFS(LANÇAMENTO!$L:$L,LANÇAMENTO!$B:$B,'TOTAL GERAL'!$A$69,LANÇAMENTO!$N:$N,'TOTAL GERAL'!$H$1,LANÇAMENTO!$D:$D,'TOTAL GERAL'!$B74) -> 0
B75: PINTURA | D75: =SUMIFS(LANÇAMENTO!$L:$L,LANÇAMENTO!$B:$B,'TOTAL GERAL'!$A$69,LANÇAMENTO!$N:$N,'TOTAL GERAL'!$D$1,LANÇAMENTO!$D:$D,'TOTAL GERAL'!$B75) -> 0 | E75: =SUMIFS(LANÇAMENTO!$L:$L,LANÇAMENTO!$B:$B,'TOTAL GERAL'!$A$69,LANÇAMENTO!$N:$N,'TOTAL GERAL'!$E$1,LANÇAMENTO!$D:$D,'TOTAL GERAL'!$B75) -> 0 | F75: =SUMIFS(LANÇAMENTO!$L:$L,LANÇAMENTO!$B:$B,'TOTAL GERAL'!$A$69,LANÇAMENTO!$N:$N,'TOTAL GERAL'!$F$1,LANÇAMENTO!$D:$D,'TOTAL GERAL'!$B75) -> 0 | G75: =SUMIFS(LANÇAMENTO!$L:$L,LANÇAMENTO!$B:$B,'TOTAL GERAL'!$A$69,LANÇAMENTO!$N:$N,'TOTAL GERAL'!$G$1,LANÇAMENTO!$D:$D,'TOTAL GERAL'!$B75) -> 0 | H75: =SUMIFS(LANÇAMENTO!$L:$L,LANÇAMENTO!$B:$B,'TOTAL GERAL'!$A$69,LANÇAMENTO!$N:$N,'TOTAL GERAL'!$H$1,LANÇAMENTO!$D:$D,'TOTAL GERAL'!$B75) -> 0
B76: INCENDIO | D76: =SUMIFS(LANÇAMENTO!$L:$L,LANÇAMENTO!$B:$B,'TOTAL GERAL'!$A$69,LANÇAMENTO!$N:$N,'TOTAL GERAL'!$D$1,LANÇAMENTO!$D:$D,'TOTAL GERAL'!$B76) -> 0 | E76: =SUMIFS(LANÇAMENTO!$L:$L,LANÇAMENTO!$B:$B,'TOTAL GERAL'!$A$69,LANÇAMENTO!$N:$N,'TOTAL GERAL'!$E$1,LANÇAMENTO!$D:$D,'TOTAL GERAL'!$B76) -> 0 | F76: =SUMIFS(LANÇAMENTO!$L:$L,LANÇAMENTO!$B:$B,'TOTAL GERAL'!$A$69,LANÇAMENTO!$N:$N,'TOTAL GERAL'!$F$1,LANÇAMENTO!$D:$D,'TOTAL GERAL'!$B76) -> 0 | G76: =SUMIFS(LANÇAMENTO!$L:$L,LANÇAMENTO!$B:$B,'TOTAL GERAL'!$A$69,LANÇAMENTO!$N:$N,'TOTAL GERAL'!$G$1,LANÇAMENTO!$D:$D,'TOTAL GERAL'!$B76) -> 0 | H76: =SUMIFS(LANÇAMENTO!$L:$L,LANÇAMENTO!$B:$B,'TOTAL GERAL'!$A$69,LANÇAMENTO!$N:$N,'TOTAL GERAL'!$H$1,LANÇAMENTO!$D:$D,'TOTAL GERAL'!$B76) -> 0
B77: LOCAÇÃO | D77: =SUMIFS(LANÇAMENTO!$L:$L,LANÇAMENTO!$B:$B,'TOTAL GERAL'!$A$69,LANÇAMENTO!$N:$N,'TOTAL GERAL'!$D$1,LANÇAMENTO!$D:$D,'TOTAL GERAL'!$B77) -> 0 | E77: =SUMIFS(LANÇAMENTO!$L:$L,LANÇAMENTO!$B:$B,'TOTAL GERAL'!$A$69,LANÇAMENTO!$N:$N,'TOTAL GERAL'!$E$1,LANÇAMENTO!$D:$D,'TOTAL GERAL'!$B77) -> 0 | F77: =SUMIFS(LANÇAMENTO!$L:$L,LANÇAMENTO!$B:$B,'TOTAL GERAL'!$A$69,LANÇAMENTO!$N:$N,'TOTAL GERAL'!$F$1,LANÇAMENTO!$D:$D,'TOTAL GERAL'!$B77) -> 0 | G77: =SUMIFS(LANÇAMENTO!$L:$L,LANÇAMENTO!$B:$B,'TOTAL GERAL'!$A$69,LANÇAMENTO!$N:$N,'TOTAL GERAL'!$G$1,LANÇAMENTO!$D:$D,'TOTAL GERAL'!$B77) -> 0 | H77: =SUMIFS(LANÇAMENTO!$L:$L,LANÇAMENTO!$B:$B,'TOTAL GERAL'!$A$69,LANÇAMENTO!$N:$N,'TOTAL GERAL'!$H$1,LANÇAMENTO!$D:$D,'TOTAL GERAL'!$B77) -> 0
B78: OUTROS | D78: =SUMIFS(LANÇAMENTO!$L:$L,LANÇAMENTO!$B:$B,'TOTAL GERAL'!$A$69,LANÇAMENTO!$N:$N,'TOTAL GERAL'!$D$1,LANÇAMENTO!$D:$D,'TOTAL GERAL'!$B78) -> 0 | E78: =SUMIFS(LANÇAMENTO!$L:$L,LANÇAMENTO!$B:$B,'TOTAL GERAL'!$A$69,LANÇAMENTO!$N:$N,'TOTAL GERAL'!$E$1,LANÇAMENTO!$D:$D,'TOTAL GERAL'!$B78) -> 0 | F78: =SUMIFS(LANÇAMENTO!$L:$L,LANÇAMENTO!$B:$B,'TOTAL GERAL'!$A$69,LANÇAMENTO!$N:$N,'TOTAL GERAL'!$F$1,LANÇAMENTO!$D:$D,'TOTAL GERAL'!$B78) -> 0 | G78: =SUMIFS(LANÇAMENTO!$L:$L,LANÇAMENTO!$B:$B,'TOTAL GERAL'!$A$69,LANÇAMENTO!$N:$N,'TOTAL GERAL'!$G$1,LANÇAMENTO!$D:$D,'TOTAL GERAL'!$B78) -> 0 | H78: =SUMIFS(LANÇAMENTO!$L:$L,LANÇAMENTO!$B:$B,'TOTAL GERAL'!$A$69,LANÇAMENTO!$N:$N,'TOTAL GERAL'!$H$1,LANÇAMENTO!$D:$D,'TOTAL GERAL'!$B78) -> 0

Sheet PEDIDOS EMITIDOS + DESCRIÇÃO
A2: OBRA | B2: (Tudo)
A4: ITEM | B4: PEDIDO | C4: FORNECEDOR | D4: DESCRIÇÃO MATERIAL | E4: UNID | F4: Soma de QTDADE | G4: Soma de VALOR TOTAL
A5: Total Geral

Sheet PREV ENTREGA
A1: OBRA COM MATERIAL | B1: OK
A3: OBRA | B3: PREVISÃO ENTREGA OBRA | C3: FORNECEDOR | D3: DESCRIÇÃO MATERIAL | E3: UNID | F3: Soma de QTDADE
A4: THEREZA | B4: 45922 | C4: C&S CALHAS | D4: 5,50 metros rufo pingadeira corte 25cm 0.6mm | E4: UNID. | F4: 1
D5: 5,20 metros rufo capa corte 70cm 0.7mm | E5: UNID. | F5: 1
B6: 22/09/2025 Total | F6: 2
A7: THEREZA Total | F7: 2
A8: (vazio) | C8: (vazio) | D8: (vazio) | E8: (vazio)
B9: Total
A10: (vazio) Total
A11: WILSON SIMONINI | B11: 45925 | C11: DEPOSITO PADRÃO | D11: FITA ALUMINIO 10CMX10MT DRYKO | E11: UNID. | F11: 16
B12: 25/09/2025 Total | F12: 16
A13: WILSON SIMONINI Total | F13: 16
A14: SERRA NEGRA | B14: 46111 | C14: Marson Distribuição LTDA | D14: ADESIVO DE SILICONE INCOLOR | E14: UNID. | F14: 1
D15: REJUNTE | E15: UNID. | F15: 1
D16: ESPAÇADOR | E16: UNID. | F16: 1
D17: COLHER PEDREIRO | E17: UNID. | F17: 1
B18: 30/03/2026 Total | F18: 4
A19: SERRA NEGRA Total | F19: 4
A20: OMAR DONATO | B20: 45951 | C20: SILVA CAÇAMBAS | D20: CAÇAMBA | E20: UNID. | F20: 1
B21: 21/10/2025 Total | F21: 1
B22: 45950 | C22: DEPOSITO PADRÃO | D22: TABUA DE PINUS 30CMX3MTX2MM | E22: UNID. | F22: 3
D23: CARRINHO MAO 55 LITROS | E23: UNID. | F23: 1
D24: ENXADA LARGA FORJADA 1;5L | E24: UNID. | F24: 1
D25: ARAME RECOZIDO TORCIDO | E25: KG | F25: 1
D26: CIMENTOCNSENTREGACIMENTO CPII 50KG LIZ/ | E26: UNID. | F26: 10
D27: BLOCO DE CONCRETO VEDAÇÃO VAZADO - 19X19X39CM | E27: UNID. | F27: 50
D28: CANALETA DE CONCRETO 19X19X39 CM | E28: UNID. | F28: 10
D29: VERGALHAO CA50 10MM (3/8) | E29: UNID. | F29: 6
D30: VERGALHAO CA60 5MM (7/32) | E30: UNID. | F30: 5
D31: SARRAFO PINUS BRUTO 10CMX3MT | E31: UNID. | F31: 4
D32: PREGO POLIDO GERDAU C/C 18 X 27 | E32: KG | F32: 1
D33: MARRETA TENACE C/CABO | E33: UNID. | F33: 1
C34: N TINTAS | D34: TRINCHA TIGRE 500 2 1/2 | E34: UNID. | F34: 1
D35: FUTURIT ESM SINT FOSCO GL GRAFITE | E35: UNID. | F35: 1
D36: SAYERLACK AGUA RAZ LITRO | E36: UNID. | F36: 1
D37: ROLO ANTIRESPINGO TIGRE 1377/9CMS. | E37: UNID. | F37: 1
C38: ROCHA MATERIAIS | D38: AREIA ENSACADA 20KG | E38: SACO | F38: 60
D39: PEDRA N°1 - 20KG ENSACADA | E39: SACO | F39: 20
D40: DISCO DE SERRA MADEIRA 24D 110MM 60864 CORTAG | E40: UNID. | F40: 1
D41: DISCO DIAMA. SEGMENTADO PLUS 4.3/8" X 20MM 1558 FELSEN | E41: UNID. | F41: 2
B42: 20/10/2025 Total | F42: 180
B43: 45947 | C43: CASA MIMOSA | D43: AMANCO ADESIVO PVC 850G | E43: UNID. | F43: 1
D44: AMANCO TUBO 6M ESG. 100MM | E44: UNID. | F44: 1
D45: AMANCO TUBO 6M ESG. 40MM | E45: UNID. | F45: 1
D46: BLUKIT ACAB.ABS P/VALV.H.MAX/ASTR/DOC. CR | E46: UNID. | F46: 2
B47: 17/10/2025 Total | F47: 5
B48: 45959 | C48: TRIFASICA | D48: TERMINACAO POLIM A FRIO TFTO-4121 (8,7/15KV 12/20KV, 25 - 95MM) | E48: UNID. | F48: 12
D49: SUPORTE P/ MUFLA E CABO 20-30MM TCK-95 | E49: UNID. | F49: 3
D50: CONECTOR CUNHA CN-10 AZ S/ CARTUCHO | E50: UNID. | F50: 2
D51: MASSA CALAFETAR 1KG - CZ | E51: UNID. | F51: 5
D52: CINTA CIRCULAR 110MM GF (C/ PARAF E PORCA) | E52: UNID. | F52: 2
D53: CINTA CIRCULAR 360MM GF (C/ PARAF E PORCA) | E53: UNID. | F53: 2
D54: CURVA ACO G.F. 90 - 4" NBR-5624 | E54: UNID. | F54: 6
D55: LUVA ACO G.F. - 4" NBR-5624 | E55: UNID. | F55: 4
D56: CABO COBRE FLEX EPR 0,6/1KV 25MM AZ | E56: M | F56: 30
D57: CABO COBRE FLEX EPR 0,6/1KV 25MM VD | E57: M | F57: 6
D58: CABO COBRE FLEX EPR 0,6/1KV 70MM PT | E58: M | F58: 30
D59: CABO COBRE FLEX EPR 0,6/1KV 70MM AZ | E59: M | F59: 10
D60: ELETRODUTO CORRUGADO TIPO KANAFLEX - 4" | E60: M | F60: 25
... D85: ELETRODUTO ACO G.F. C/ 3MTS - 4" NBR-5624 | E85: UNID. | F85: 6
B86: 29/10/2025 Total | F86: 689
B87: 46098 | C87: AREA ELETRICOS | D87: CABO FLEX 750V 16MM PT | E87: M | F87: 140
D88: CABO FLEX HEPR 1KV 120MM PT | E88: M | F88: 60
D89: CABO FLEX HEPR ATOX 1KV 120MM AZ CL | E89: M | F89: 10
D90: CABO FLEX HEPR ATOX 1KV 50MM VD | E90: M | F90: 40
B91: 17/03/2026 Total | F91: 250
B92: 46125 | C92: OLD RIVER | D92: ROMA 301/005 TRINCHA CABO PRETO/CERDA GRIS 301 2" | E92: UNID. | F92: 2
D93: FUTURA FUTURIT ESM SINT.BRILHO VERMELHO 3,6L | E93: GALÃO | F93: 1
D94: FENIX 2001/15 ROLO ESPUMA POLIESTER 15CM PRETO | E94: UNID. | F94: 2
C95: AUGUSTO NEVES | D95: Chaves Storz | E95: UNID. | F95: 2
B96: 13/04/2026 Total | F96: 7
B97: 46126 | C97: SIRO MATERIAIS ELETRICO | D97: BOTOEIRA QUEBRA VIDRO (PORTA CHAVE) | E97: UNID. | F97: 1
C98: UEHARA ELETRICA | D98: LUZ EMERGENCIA 30 LEDS SEGURIMAX LITIOSLIM | E98: UNID. | F98: 12
D99: CABO FLEX COBRECOM 750V 6,00 MM PRETO MT | E99: M | F99: 10
D100: SIRENE P/ALARME DNI 115DB 12/24V P/INCENDIO | E100: UNID. | F100: 1
B101: 14/04/2026 Total | F101: 24
A102: OMAR DONATO Total | F102: 1156
A103: MARIA DE LOURDES | B103: 45889 | C103: DEPOSITO PADRÃO | D103: GIRICA CARRINHO DE MAO - 60 LITROS - EXTRA FORTE | E103: UNID. | F103: 1
B104: 20/08/2025 Total | F104: 1
B105: 45890 | C105: POSTE PADRÃO RANGEL | D105: CAÇAMBA | E105: UNID. | F105: 1
B106: 21/08/2025 Total | F106: 1
B107: 45888 | C107: DEPOSITO PADRÃO | D107: ESPACADOR NIVELADOR SLIM 2,0 MM C/1000 PCS | E107: UNID. | F107: 4
D108: CUNHA P/PISO/AZ NIVEL.SLIM CORTAG C/100 | E108: UNID. | F108: 10
B109: 19/08/2025 Total | F109: 14
B110: 45894 | C110: SODIMAC | D110: FRETE | E110: UNID. | F110: 1
D111: Argamassa para Porcelanato Interno 20kg Cinza Quartzolit, CINZA, 20KG | E111: SACO | F111: 55
D112: Porcelanato York WH 87,7x87,7cm Caixa 1,54m² Retificado Branco, BRANCO, ., 87,7X87,7 | E112: M2 | F112: 167.4
D113: Rejunte Flexível, Cinza Platina, 5kg, CINZA PLATINA, 5KG, | E113: SACO | F113: 6
C114: PAI & FILHOS | D114: DESCONTO | E114: SACO | F114: 1
D115: CIMENTO CPII 50KG | E115: SACO | F115: 15
C116: TRANS JZ | D116: AREIA MÉDIA | E116: M3 | F116: 3
B117: 25/08/2025 Total | F117: 248.4
B118: 45895 | C118: CONCREBLOCO | D118: FRETE | E118: UNID. | F118: 1
D119: blocos 14x19x39 | E119: UNID. | F119: 520
D120: meio bloco 14 | E120: UNID. | F120: 60
B121: 26/08/2025 Total | F121: 581
B122: 45901 | C122: MIL MÁQUINAS | D122: DIAGONAL | E122: UNID. | F122: 1
D123: PAINEL METALICO 1,5M | E123: UNID. | F123: 8
D124: PLATAFORMA P/ ANDAIMES 1.5M | E124: UNID. | F124: 6
B125: 01/09/2025 Total | F125: 15
...

Sheet SEM PEDIDO
A2: PEDIDO | B2: (Tudo)
A4: OBRA | B4: UNID | C4: Soma de QTDADE
A5: FCO MIGNONE | B5: SACO | C5: 20
A6: THEREZA | B6: UNID. | C6: 2
A7: (vazio) | B7: (vazio)
A8: WILSON SIMONINI | B8: UNID. | C8: 16
A9: SERRA NEGRA | B9: UNID. | C9: 4
A10: OMAR DONATO | B10: GALÃO | C10: 1
B11: KG | C11: 2
B12: M | C12: 556
B13: ROLO | C13: 6
B14: SACO | C14: 80
B15: UNID. | C15: 523
A16: MARIA DE LOURDES | B16: BALDE | C16: 2
B17: BARRA | C17: 30
B18: GALÃO | C18: 24
B19: KG | C19: 142
B20: LATA | C20: 3
B21: M | C21: 340
B22: M2 | C22: 167.4
B23: M3 | C23: 4
B24: PACOTE | C24: 1
B25: SACO | C25: 130
B26: UNID. | C26: 1492
A27: LAURO BARREIRA | B27: UNID. | C27: 14
A28: PEDRO CELESTINO | B28: M | C28: 12
B29: UNID. | C29: 26
A30: ANTONIO NUNES LOPES | B30: M | C30: 91
B31: UNID. | C31: 72
A32: GUIDO ROSOLÉN | B32: GALÃO | C32: 2
B33: M3 | C33: 33
B34: UNID. | C34: 18
A35: DEPUTADO ANTONIO | B35: BARRA | C35: 6
B36: KG | C36: 4
B37: M | C37: 146
B38: M2 | C38: 76
B39: UNID. | C39: 131
A40: ALEXANDRINA SANTIAGO | B40: LATA | C40: 5
B41: M | C41: 55
B42: M3 | C42: 2
B43: SACO | C43: 12
B44: UNID. | C44: 224
A45: PRÉDIO VAGO | B45: BARRA | C45: 185
B46: GALÃO | C46: 3
B47: KG | C47: 5
B48: LATA | C48: 8
B49: M | C49: 6348
B50: M2 | C50: 251.2
B51: SACO | C51: 39
B52: UNID. | C52: 1736.2
A53: ZILDA DOMINGOS | B53: LATA | C53: 2
B54: M3 | C54: 16
B55: PEÇA | C55: 16
B56: UNID. | C56: 8
B57: (vazio)
A58: WANDA FÉLIX | B58: BARRA | C58: 25
B59: GALÃO | C59: 9
B60: KG | C60: 34.21
B61: M | C61: 175
B62: M2 | C62: 51
B63: M3 | C63: 30
B64: PACOTE | C64: 6
B65: SACO | C65: 163
B66: UNID. | C66: 1046.5
B67: VERBA | C67: 1
A68: ELVIRA SILVA | B68: SACO | C68: 36
B69: UNID. | C69: 18
A70: VIRGILIO SILVEIRA | B70: BARRA | C70: 40
B71: GALÃO | C71: 7
B72: KG | C72: 23.5
B73: LATA | C73: 14
B74: M | C74: 1512.5
B75: M2 | C75: 390
B76: M3 | C76: 97
B77: PEÇA | C77: 55
B78: ROLO | C78: 5
B79: SACO | C79: 45
B80: UNID. | C80: 2298
B81: VERBA | C81: 1
B82: CONJ. | C82: 4
A83: EURINY DE SOUZA | B83: BARRA | C83: 9
B84: GALÃO | C84: 6
B85: JOGO | C85: 4
B86: KG | C86: 481
B87: LATA | C87: 4
B88: M | C88: 165.55
B89: M2 | C89: 100
B90: PACOTE | C90: 14
B91: ROLO | C91: 10
B92: UNID. | C92: 1184
B93: CONJ. | C93: 4
A94: JOSÉ DE CAMPOS | B94: UNID. | C94: 1
A95: LUIZ CAMPO | B95: BARRA | C95: 163
B96: GALÃO | C96: 26
B97: KG | C97: 2604.89
B98: LATA | C98: 11
B99: M | C99: 407
B100: M2 | C100: 1146.23
B101: M3 | C101: 81
B102: PACOTE | C102: 4
...
